Workbook

Sheet Read me
A1: RRG Website Shipping · Australia · proposed rates
A2: Prepared 20 October 2026 from Roof Racks Galore order and carrier data. Same layout as "RRG Website Shipping OCT 2025": one tab per delivery state, a table for each warehouse the order ships from, Standard and Priority, Metro / Metro Outer / Regional.
A4: Settings (change the yellow cells; every price in the workbook updates)
A5: Freight margin on top of expected cost | B5: 0 | C5: 0% = break-even: on average the Standard charge covers what the carrier charges us for that size, zone and warehouse. 10% adds 10% on top of expected cost.
A6: Minimum Priority uplift over Standard ($) | B6: 5 | C6: Priority is at least this much more than Standard.
A7: Round prices up to the next $x.50 up to ($) | B7: 30 | C7: Below this, prices end in .50 (e.g. $12.50). Above it they round up to the next $5.
A9: Priority ÷ Standard ratio by size
A10: Small | B10: 1.34 | C10: Median of Priority ÷ Standard across the 2025 sheet, kept between 1.20 and 1.35 (Large was 2.1 and XL 1.0 in 2025 because those Standard prices were far below cost). Applied to every cell. Change these if you want a different Priority premium.
A11: Medium | B11: 1.26
A12: Large | B12: 1.35
A13: XL | B13: 1.2
A14: XXL | B14: 1.2
A17: How the prices are set
A18: 1. Each order is sized the way the website does it: every product gets a 1–5 score from its longest side, cubic weight (250 kg/m³) and actual weight, and the order takes its biggest product's size. See the Freight SIZE RULES tab.
A19: 2. Expected cost = what carriers charged us (plus 10% GST) on 21,585 orders, July 2025 to August 2026, matched in the sales, freight and carrier reports (Orders_Matched_All_3), that went from one warehouse as one consignment. Cost is the carrier's estimated cost in that file.
A20: 3. Costs are averaged after dropping the top and bottom 10% of orders in each group, so one-off surcharges don't set the price.
A21: 4. Each size × zone gets a national figure, separately for same-state and interstate deliveries. Each warehouse-to-state lane then gets a factor from its own orders (for example WA to VIC costs about 25% more than the interstate average). Lanes with few orders lean on the national figure; lanes with no orders use distance.
A22: 4b. Lane factors are worked out separately for Small, Medium and Large-and-up, kept between 0.6× and 1.6×, and interstate lanes with few orders lean more on distance (for example QLD–WA, with 13 orders from Wangara to QLD). A warehouse's own state is never priced above the cheapest other warehouse into that state (this mainly lowers ACT from Fyshwick, whose local orders mostly went StarTrack and TNT).
A23: 5. Where a lane has its own orders for a size and zone, those orders are blended in. Prices never go down from a smaller size to a larger one, or from Metro to Outer to Regional.
A24: 6. Standard = expected cost × (1 + freight margin), rounded up. Priority = Standard × the Priority ratio for its size (above), at least the minimum uplift, rounded up. We don't yet have enough priority shipments to cost Priority separately.
A25: 7. Delivery time frames are copied from the 2025 sheet, except that there is no 0–1 day Priority any more: those 30 cells (all same-state Metro deliveries) are now Priority 1–2 days and Standard 1–3 days (was 1–2 days).
A26: 8. One rate for interstate XXL to Metro Outer and Regional: these have one price only: Standard, set at what Priority would have cost, with no Priority option (the Priority price and time are left blank). The Standard cells are grey in the state tabs, use the Priority delivery times, and are marked "One rate" on the Cost model tab.
A28: What else changed from the 2025 sheet
A29: • The TAS tab now has a From SA table and the WA tab a From TAS table (both were missing).
... A38: • The Impact tab re-prices the same 21,585 orders under these rates so you can see the effect before changing the website.

Sheet Summary
A1: Summary
A2: Re-pricing the 21,585 matched single-shipment orders (Impact tab) under the new rates. Updates when you change the settings on Read me.
B4: Orders | C4: We charged | D4: Cost us | E4: Charged − cost | F4: New rates would charge | G4: New − cost
A5: All orders | B5: =COUNTA(Impact!$A$2:$A$21586) -> 21585 | C5: =SUM(Impact!$G$2:$G$21586) -> 453660.59 | D5: =SUM(Impact!$H$2:$H$21586) -> 784190.19 | E5: =C5-D5 -> -330529.6 | F5: =SUM(Impact!$J$2:$J$21586) -> 781646.5 | G5: =F5-D5 -> -2543.69
A7: By size
A8: Small | B8: =COUNTIF(Impact!$D$2:$D$21586,"Small") -> 10698 | C8: =SUMIF(Impact!$D$2:$D$21586,"Small",Impact!$G$2:$G$21586) -> 154197.38 | D8: =SUMIF(Impact!$D$2:$D$21586,"Small",Impact!$H$2:$H$21586) -> 164358.85 | E8: =C8-D8 -> -10161.47 | F8: =SUMIF(Impact!$D$2:$D$21586,"Small",Impact!$J$2:$J$21586) -> 151295 | G8: =F8-D8 -> -13063.85
A9: Medium | B9: =COUNTIF(Impact!$D$2:$D$21586,"Medium") -> 8330 | C9: =SUMIF(Impact!$D$2:$D$21586,"Medium",Impact!$G$2:$G$21586) -> 158789.23 | D9: =SUMIF(Impact!$D$2:$D$21586,"Medium",Impact!$H$2:$H$21586) -> 324148.17 | E9: =C9-D9 -> -165358.94 | F9: =SUMIF(Impact!$D$2:$D$21586,"Medium",Impact!$J$2:$J$21586) -> 344448.5 | G9: =F9-D9 -> 20300.33
A10: Large | B10: =COUNTIF(Impact!$D$2:$D$21586,"Large") -> 1221 | C10: =SUMIF(Impact!$D$2:$D$21586,"Large",Impact!$G$2:$G$21586) -> 47138.03 | D10: =SUMIF(Impact!$D$2:$D$21586,"Large",Impact!$H$2:$H$21586) -> 100142.97 | E10: =C10-D10 -> -53004.94 | F10: =SUMIF(Impact!$D$2:$D$21586,"Large",Impact!$J$2:$J$21586) -> 96978 | G10: =F10-D10 -> -3164.97
A11: XL | B11: =COUNTIF(Impact!$D$2:$D$21586,"XL") -> 1062 | C11: =SUMIF(Impact!$D$2:$D$21586,"XL",Impact!$G$2:$G$21586) -> 67921.46 | D11: =SUMIF(Impact!$D$2:$D$21586,"XL",Impact!$H$2:$H$21586) -> 144957.79 | E11: =C11-D11 -> -77036.33 | F11: =SUMIF(Impact!$D$2:$D$21586,"XL",Impact!$J$2:$J$21586) -> 138820 | G11: =F11-D11 -> -6137.79
A12: XXL | B12: =COUNTIF(Impact!$D$2:$D$21586,"XXL") -> 274 | C12: =SUMIF(Impact!$D$2:$D$21586,"XXL",Impact!$G$2:$G$21586) -> 25614.49 | D12: =SUMIF(Impact!$D$2:$D$21586,"XXL",Impact!$H$2:$H$21586) -> 50582.41 | E12: =C12-D12 -> -24967.92 | F12: =SUMIF(Impact!$D$2:$D$21586,"XXL",Impact!$J$2:$J$21586) -> 50105 | G12: =F12-D12 -> -477.41
A14: By zone
A15: Metro | B15: =COUNTIF(Impact!$C$2:$C$21586,"Metro") -> 9973 | C15: =SUMIF(Impact!$C$2:$C$21586,"Metro",Impact!$G$2:$G$21586) -> 153909.4 | D15: =SUMIF(Impact!$C$2:$C$21586,"Metro",Impact!$H$2:$H$21586) -> 275798.06 | E15: =C15-D15 -> -121888.66 | F15: =SUMIF(Impact!$C$2:$C$21586,"Metro",Impact!$J$2:$J$21586) -> 272077.5 | G15: =F15-D15 -> -3720.56
A16: Metro Outer | B16: =COUNTIF(Impact!$C$2:$C$21586,"Metro Outer") -> 6495 | C16: =SUMIF(Impact!$C$2:$C$21586,"Metro Outer",Impact!$G$2:$G$21586) -> 132035.83 | D16: =SUMIF(Impact!$C$2:$C$21586,"Metro Outer",Impact!$H$2:$H$21586) -> 247958.21 | E16: =C16-D16 -> -115922.38 | F16: =SUMIF(Impact!$C$2:$C$21586,"Metro Outer",Impact!$J$2:$J$21586) -> 252989 | G16: =F16-D16 -> 5030.79
A17: Regional | B17: =COUNTIF(Impact!$C$2:$C$21586,"Regional") -> 5117 | C17: =SUMIF(Impact!$C$2:$C$21586,"Regional",Impact!$G$2:$G$21586) -> 167715.36 | D17: =SUMIF(Impact!$C$2:$C$21586,"Regional",Impact!$H$2:$H$21586) -> 260433.92 | E17: =C17-D17 -> -92718.56 | F17: =SUMIF(Impact!$C$2:$C$21586,"Regional",Impact!$J$2:$J$21586) -> 256580 | G17: =F17-D17 -> -3853.92
A19: By warehouse
A20: QLD · Brendale | B20: =COUNTIF(Impact!$B$2:$B$21586,"QLD") -> 6038 | C20: =SUMIF(Impact!$B$2:$B$21586,"QLD",Impact!$G$2:$G$21586) -> 123663.46 | D20: =SUMIF(Impact!$B$2:$B$21586,"QLD",Impact!$H$2:$H$21586) -> 223158.1 | E20: =C20-D20 -> -99494.64 | F20: =SUMIF(Impact!$B$2:$B$21586,"QLD",Impact!$J$2:$J$21586) -> 223463.5 | G20: =F20-D20 -> 305.4
A21: NSW · Moorebank | B21: =COUNTIF(Impact!$B$2:$B$21586,"NSW") -> 6243 | C21: =SUMIF(Impact!$B$2:$B$21586,"NSW",Impact!$G$2:$G$21586) -> 127256.18 | D21: =SUMIF(Impact!$B$2:$B$21586,"NSW",Impact!$H$2:$H$21586) -> 212864.15 | E21: =C21-D21 -> -85607.97 | F21: =SUMIF(Impact!$B$2:$B$21586,"NSW",Impact!$J$2:$J$21586) -> 214090.5 | G21: =F21-D21 -> 1226.35
A22: VIC · Campbellfield | B22: =COUNTIF(Impact!$B$2:$B$21586,"VIC") -> 4431 | C22: =SUMIF(Impact!$B$2:$B$21586,"VIC",Impact!$G$2:$G$21586) -> 90737.95 | D22: =SUMIF(Impact!$B$2:$B$21586,"VIC",Impact!$H$2:$H$21586) -> 153924.38 | E22: =C22-D22 -> -63186.43 | F22: =SUMIF(Impact!$B$2:$B$21586,"VIC",Impact!$J$2:$J$21586) -> 155774 | G22: =F22-D22 -> 1849.62
A23: SA · Adelaide | B23: =COUNTIF(Impact!$B$2:$B$21586,"SA") -> 1922 | C23: =SUMIF(Impact!$B$2:$B$21586,"SA",Impact!$G$2:$G$21586) -> 44535.35 | D23: =SUMIF(Impact!$B$2:$B$21586,"SA",Impact!$H$2:$H$21586) -> 67861.06 | E23: =C23-D23 -> -23325.71 | F23: =SUMIF(Impact!$B$2:$B$21586,"SA",Impact!$J$2:$J$21586) -> 67932 | G23: =F23-D23 -> 70.94
A24: WA · Wangara | B24: =COUNTIF(Impact!$B$2:$B$21586,"WA") -> 2467 | C24: =SUMIF(Impact!$B$2:$B$21586,"WA",Impact!$G$2:$G$21586) -> 56720.9 | D24: =SUMIF(Impact!$B$2:$B$21586,"WA",Impact!$H$2:$H$21586) -> 103369.45 | E24: =C24-D24 -> -46648.55 | F24: =SUMIF(Impact!$B$2:$B$21586,"WA",Impact!$J$2:$J$21586) -> 100341.5 | G24: =F24-D24 -> -3027.95
A25: TAS · Moonah | B25: =COUNTIF(Impact!$B$2:$B$21586,"TAS") -> 269 | C25: =SUMIF(Impact!$B$2:$B$21586,"TAS",Impact!$G$2:$G$21586) -> 6009.22 | D25: =SUMIF(Impact!$B$2:$B$21586,"TAS",Impact!$H$2:$H$21586) -> 13260.62 | E25: =C25-D25 -> -7251.4 | F25: =SUMIF(Impact!$B$2:$B$21586,"TAS",Impact!$J$2:$J$21586) -> 11407 | G25: =F25-D25 -> -1853.62
A26: ACT · Fyshwick | B26: =COUNTIF(Impact!$B$2:$B$21586,"ACT") -> 215 | C26: =SUMIF(Impact!$B$2:$B$21586,"ACT",Impact!$G$2:$G$21586) -> 4737.53 | D26: =SUMIF(Impact!$B$2:$B$21586,"ACT",Impact!$H$2:$H$21586) -> 9752.43 | E26: =C26-D26 -> -5014.9 | F26: =SUMIF(Impact!$B$2:$B$21586,"ACT",Impact!$J$2:$J$21586) -> 8638 | G26: =F26-D26 -> -1114.43
A28: Typical price per order, Standard (median of each tab's same-state table)
A29: Size | B29: Metro 2025 | C29: Metro new | D29: Outer 2025 | E29: Outer new | F29: Regional 2025 | G29: Regional new
A30: Small | B30: 9.5 | C30: =MEDIAN('Cost model'!M62,'Cost model'!M167,'Cost model'!M317,'Cost model'!M422,'Cost model'!M527,'Cost model'!M632,'Cost model'!M737) -> 9.5 | D30: 12.5 | E30: =MEDIAN('Cost model'!M63,'Cost model'!M168,'Cost model'!M318,'Cost model'!M423,'Cost model'!M528,'Cost model'!M633,'Cost model'!M738) -> 13.5 | F30: 17.5 | G30: =MEDIAN('Cost model'!M64,'Cost model'!M169,'Cost model'!M319,'Cost model'!M424,'Cost model'!M529,'Cost model'!M634,'Cost model'!M739) -> 16.5
A31: Medium | B31: 9.5 | C31: =MEDIAN('Cost model'!M65,'Cost model'!M170,'Cost model'!M320,'Cost model'!M425,'Cost model'!M530,'Cost model'!M635,'Cost model'!M740) -> 25.5 | D31: 12.5 | E31: =MEDIAN('Cost model'!M66,'Cost model'!M171,'Cost model'!M321,'Cost model'!M426,'Cost model'!M531,'Cost model'!M636,'Cost model'!M741) -> 40 | F31: 19.5 | G31: =MEDIAN('Cost model'!M67,'Cost model'!M172,'Cost model'!M322,'Cost model'!M427,'Cost model'!M532,'Cost model'!M637,'Cost model'!M742) -> 45
A32: Large | B32: 19 | C32: =MEDIAN('Cost model'!M68,'Cost model'!M173,'Cost model'!M323,'Cost model'!M428,'Cost model'!M533,'Cost model'!M638,'Cost model'!M743) -> 55 | D32: 24.5 | E32: =MEDIAN('Cost model'!M69,'Cost model'!M174,'Cost model'!M324,'Cost model'!M429,'Cost model'!M534,'Cost model'!M639,'Cost model'!M744) -> 70 | F32: 50 | G32: =MEDIAN('Cost model'!M70,'Cost model'!M175,'Cost model'!M325,'Cost model'!M430,'Cost model'!M535,'Cost model'!M640,'Cost model'!M745) -> 95
A33: XL | B33: 25 | C33: =MEDIAN('Cost model'!M71,'Cost model'!M176,'Cost model'!M326,'Cost model'!M431,'Cost model'!M536,'Cost model'!M641,'Cost model'!M746) -> 100 | D33: 45 | E33: =MEDIAN('Cost model'!M72,'Cost model'!M177,'Cost model'!M327,'Cost model'!M432,'Cost model'!M537,'Cost model'!M642,'Cost model'!M747) -> 130 | F33: 85 | G33: =MEDIAN('Cost model'!M73,'Cost model'!M178,'Cost model'!M328,'Cost model'!M433,'Cost model'!M538,'Cost model'!M643,'Cost model'!M748) -> 165
A34: XXL | B34: 45 | C34: =MEDIAN('Cost model'!M74,'Cost model'!M179,'Cost model'!M329,'Cost model'!M434,'Cost model'!M539,'Cost model'!M644,'Cost model'!M749) -> 135 | D34: 85 | E34: =MEDIAN('Cost model'!M75,'Cost model'!M180,'Cost model'!M330,'Cost model'!M435,'Cost model'!M540,'Cost model'!M645,'Cost model'!M750) -> 180 | F34: 250 | G34: =MEDIAN('Cost model'!M76,'Cost model'!M181,'Cost model'!M331,'Cost model'!M436,'Cost model'!M541,'Cost model'!M646,'Cost model'!M751) -> 230
A36: Option: split Medium at 1.05 m (what Medium orders actually cost us, incl. GST, trimmed average)
B37: Orders | C37: Metro | D37: Outer metro | E37: Regional
A38: Medium up to 1.05 m, same state | B38: 1887 | C38: 11.95 | D38: 20.92 | E38: 27.1
A39: Medium over 1.05 m, same state | B39: 4247 | C39: 30.64 | D39: 43.65 | E39: 50.85
A40: Medium up to 1.05 m, interstate | B40: 687 | C40: 22.85 | D40: 25.81 | E40: 35.17
A41: Medium over 1.05 m, interstate | B41: 1560 | C41: 49.42 | D41: 55.37 | E41: 61.01
A42: Most Medium orders under 1.05 m can go Australia Post. Splitting Medium would let the website keep a low price for those and charge the long ones what StarTrack costs. It needs a 6th size on the website, so it isn't applied in the state tabs.

Sheet ACT
A1: Freight Charges for ACT Orders
A3: Standard | B3: From QLD | F3: From VIC | J3: From SA | N3: From NSW | R3: From ACT | V3: From TAS | Z3: From WA
A4: Freight Size | B4: Metro | C4: Metro Outer | D4: Regional | F4: Metro | G4: Metro Outer | H4: Regional | J4: Metro | K4: Metro Outer | L4: Regional | N4: Metro | O4: Metro Outer | P4: Regional | R4: Metro | S4: Metro Outer | T4: Regional | V4: Metro | W4: Metro Outer | X4: Regional | Z4: Metro | AA4: Metro Outer | AB4: Regional
A5: Small | B5: ='Cost model'!M2 -> 14.5 | C5: ='Cost model'!M3 -> 16.5 | D5: ='Cost model'!M4 -> 20.5 | F5: ='Cost model'!M17 -> 12.5 | G5: ='Cost model'!M18 -> 13.5 | H5: ='Cost model'!M19 -> 16.5 | J5: ='Cost model'!M32 -> 15.5 | K5: ='Cost model'!M33 -> 18.5 | L5: ='Cost model'!M34 -> 22.5 | N5: ='Cost model'!M47 -> 12.5 | O5: ='Cost model'!M48 -> 14.5 | P5: ='Cost model'!M49 -> 17.5 | R5: ='Cost model'!M62 -> 12.5 | S5: ='Cost model'!M63 -> 13.5 | T5: ='Cost model'!M64 -> 16.5 | V5: ='Cost model'!M77 -> 13.5 | W5: ='Cost model'!M78 -> 15.5 | X5: ='Cost model'!M79 -> 19.5 | Z5: ='Cost model'!M92 -> 14.5 | AA5: ='Cost model'!M93 -> 17.5 | AB5: ='Cost model'!M94 -> 21.5
A6: Medium | B6: ='Cost model'!M5 -> 35 | C6: ='Cost model'!M6 -> 40 | D6: ='Cost model'!M7 -> 45 | F6: ='Cost model'!M20 -> 35 | G6: ='Cost model'!M21 -> 40 | H6: ='Cost model'!M22 -> 45 | J6: ='Cost model'!M35 -> 45 | K6: ='Cost model'!M36 -> 50 | L6: ='Cost model'!M37 -> 55 | N6: ='Cost model'!M50 -> 40 | O6: ='Cost model'!M51 -> 50 | P6: ='Cost model'!M52 -> 55 | R6: ='Cost model'!M65 -> 35 | S6: ='Cost model'!M66 -> 40 | T6: ='Cost model'!M67 -> 45 | V6: ='Cost model'!M80 -> 40 | W6: ='Cost model'!M81 -> 50 | X6: ='Cost model'!M82 -> 55 | Z6: ='Cost model'!M95 -> 50 | AA6: ='Cost model'!M96 -> 55 | AB6: ='Cost model'!M97 -> 60
A7: Large | B7: ='Cost model'!M8 -> 75 | C7: ='Cost model'!M9 -> 85 | D7: ='Cost model'!M10 -> 110 | F7: ='Cost model'!M23 -> 60 | G7: ='Cost model'!M24 -> 70 | H7: ='Cost model'!M25 -> 95 | J7: ='Cost model'!M38 -> 80 | K7: ='Cost model'!M39 -> 90 | L7: ='Cost model'!M40 -> 120 | N7: ='Cost model'!M53 -> 75 | O7: ='Cost model'!M54 -> 85 | P7: ='Cost model'!M55 -> 115 | R7: ='Cost model'!M68 -> 60 | S7: ='Cost model'!M69 -> 70 | T7: ='Cost model'!M70 -> 95 | V7: ='Cost model'!M83 -> 70 | W7: ='Cost model'!M84 -> 85 | X7: ='Cost model'!M85 -> 110 | Z7: ='Cost model'!M98 -> 75 | AA7: ='Cost model'!M99 -> 90 | AB7: ='Cost model'!M100 -> 120
A8: XL | B8: ='Cost model'!M11 -> 120 | C8: ='Cost model'!M12 -> 150 | D8: ='Cost model'!M13 -> 195 | F8: ='Cost model'!M26 -> 105 | G8: ='Cost model'!M27 -> 130 | H8: ='Cost model'!M28 -> 165 | J8: ='Cost model'!M41 -> 125 | K8: ='Cost model'!M42 -> 165 | L8: ='Cost model'!M43 -> 210 | N8: ='Cost model'!M56 -> 130 | O8: ='Cost model'!M57 -> 160 | P8: ='Cost model'!M58 -> 200 | R8: ='Cost model'!M71 -> 105 | S8: ='Cost model'!M72 -> 130 | T8: ='Cost model'!M73 -> 165 | V8: ='Cost model'!M86 -> 120 | W8: ='Cost model'!M87 -> 150 | X8: ='Cost model'!M88 -> 190 | Z8: ='Cost model'!M101 -> 130 | AA8: ='Cost model'!M102 -> 165 | AB8: ='Cost model'!M103 -> 210
A9: XXL | B9: ='Cost model'!M14 -> 160 | C9: ='Cost model'!M15 -> 265 | D9: ='Cost model'!M16 -> 320 | F9: ='Cost model'!M29 -> 135 | G9: ='Cost model'!M30 -> 230 | H9: ='Cost model'!M31 -> 280 | J9: ='Cost model'!M44 -> 170 | K9: ='Cost model'!M45 -> 290 | L9: ='Cost model'!M46 -> 345 | N9: ='Cost model'!M59 -> 170 | O9: ='Cost model'!M60 -> 280 | P9: ='Cost model'!M61 -> 330 | R9: ='Cost model'!M74 -> 135 | S9: ='Cost model'!M75 -> 190 | T9: ='Cost model'!M76 -> 230 | V9: ='Cost model'!M89 -> 160 | W9: ='Cost model'!M90 -> 265 | X9: ='Cost model'!M91 -> 320 | Z9: ='Cost model'!M104 -> 170 | AA9: ='Cost model'!M105 -> 290 | AB9: ='Cost model'!M106 -> 345
A11: Priority | B11: From QLD | F11: From VIC | J11: From SA | N11: From NSW | R11: From ACT | V11: From TAS | Z11: From WA
A12: Freight Size | B12: Metro | C12: Metro Outer | D12: Regional | F12: Metro | G12: Metro Outer | H12: Regional | J12: Metro | K12: Metro Outer | L12: Regional | N12: Metro | O12: Metro Outer | P12: Regional | R12: Metro | S12: Metro Outer | T12: Regional | V12: Metro | W12: Metro Outer | X12: Regional | Z12: Metro | AA12: Metro Outer | AB12: Regional
A13: Small | B13: ='Cost model'!N2 -> 19.5 | C13: ='Cost model'!N3 -> 22.5 | D13: ='Cost model'!N4 -> 27.5 | F13: ='Cost model'!N17 -> 17.5 | G13: ='Cost model'!N18 -> 18.5 | H13: ='Cost model'!N19 -> 22.5 | J13: ='Cost model'!N32 -> 21.5 | K13: ='Cost model'!N33 -> 25.5 | L13: ='Cost model'!N34 -> 35 | N13: ='Cost model'!N47 -> 17.5 | O13: ='Cost model'!N48 -> 19.5 | P13: ='Cost model'!N49 -> 23.5 | R13: ='Cost model'!N62 -> 17.5 | S13: ='Cost model'!N63 -> 18.5 | T13: ='Cost model'!N64 -> 22.5 | V13: ='Cost model'!N77 -> 18.5 | W13: ='Cost model'!N78 -> 21.5 | X13: ='Cost model'!N79 -> 26.5 | Z13: ='Cost model'!N92 -> 19.5 | AA13: ='Cost model'!N93 -> 23.5 | AB13: ='Cost model'!N94 -> 29.5
A14: Medium | B14: ='Cost model'!N5 -> 45 | C14: ='Cost model'!N6 -> 55 | D14: ='Cost model'!N7 -> 60 | F14: ='Cost model'!N20 -> 45 | G14: ='Cost model'!N21 -> 55 | H14: ='Cost model'!N22 -> 60 | J14: ='Cost model'!N35 -> 60 | K14: ='Cost model'!N36 -> 65 | L14: ='Cost model'!N37 -> 70 | N14: ='Cost model'!N50 -> 55 | O14: ='Cost model'!N51 -> 65 | P14: ='Cost model'!N52 -> 70 | R14: ='Cost model'!N65 -> 45 | S14: ='Cost model'!N66 -> 55 | T14: ='Cost model'!N67 -> 60 | V14: ='Cost model'!N80 -> 55 | W14: ='Cost model'!N81 -> 65 | X14: ='Cost model'!N82 -> 70 | Z14: ='Cost model'!N95 -> 65 | AA14: ='Cost model'!N96 -> 70 | AB14: ='Cost model'!N97 -> 80
A15: Large | B15: ='Cost model'!N8 -> 105 | C15: ='Cost model'!N9 -> 115 | D15: ='Cost model'!N10 -> 150 | F15: ='Cost model'!N23 -> 85 | G15: ='Cost model'!N24 -> 95 | H15: ='Cost model'!N25 -> 130 | J15: ='Cost model'!N38 -> 110 | K15: ='Cost model'!N39 -> 125 | L15: ='Cost model'!N40 -> 165 | N15: ='Cost model'!N53 -> 105 | O15: ='Cost model'!N54 -> 115 | P15: ='Cost model'!N55 -> 160 | R15: ='Cost model'!N68 -> 85 | S15: ='Cost model'!N69 -> 95 | T15: ='Cost model'!N70 -> 130 | V15: ='Cost model'!N83 -> 95 | W15: ='Cost model'!N84 -> 115 | X15: ='Cost model'!N85 -> 150 | Z15: ='Cost model'!N98 -> 105 | AA15: ='Cost model'!N99 -> 125 | AB15: ='Cost model'!N100 -> 165
A16: XL | B16: ='Cost model'!N11 -> 145 | C16: ='Cost model'!N12 -> 180 | D16: ='Cost model'!N13 -> 235 | F16: ='Cost model'!N26 -> 130 | G16: ='Cost model'!N27 -> 160 | H16: ='Cost model'!N28 -> 200 | J16: ='Cost model'!N41 -> 150 | K16: ='Cost model'!N42 -> 200 | L16: ='Cost model'!N43 -> 255 | N16: ='Cost model'!N56 -> 160 | O16: ='Cost model'!N57 -> 195 | P16: ='Cost model'!N58 -> 240 | R16: ='Cost model'!N71 -> 130 | S16: ='Cost model'!N72 -> 160 | T16: ='Cost model'!N73 -> 200 | V16: ='Cost model'!N86 -> 145 | W16: ='Cost model'!N87 -> 180 | X16: ='Cost model'!N88 -> 230 | Z16: ='Cost model'!N101 -> 160 | AA16: ='Cost model'!N102 -> 200 | AB16: ='Cost model'!N103 -> 255
A17: XXL | B17: ='Cost model'!N14 -> 195 | F17: ='Cost model'!N29 -> 165 | J17: ='Cost model'!N44 -> 205 | N17: ='Cost model'!N59 -> 205 | R17: ='Cost model'!N74 -> 165 | S17: ='Cost model'!N75 -> 230 | T17: ='Cost model'!N76 -> 280 | V17: ='Cost model'!N89 -> 195 | Z17: ='Cost model'!N104 -> 205
A19: Delivery time frames for ACT Orders
A21: Standard | B21: From QLD | F21: From VIC | J21: From SA | N21: From NSW | R21: From ACT | V21: From TAS | Z21: From WA
A22: Freight Size | B22: Metro | C22: Metro Outer | D22: Regional | F22: Metro | G22: Metro Outer | H22: Regional | J22: Metro | K22: Metro Outer | L22: Regional | N22: Metro | O22: Metro Outer | P22: Regional | R22: Metro | S22: Metro Outer | T22: Regional | V22: Metro | W22: Metro Outer | X22: Regional | Z22: Metro | AA22: Metro Outer | AB22: Regional
A23: Small | B23: 2-5 Days | C23: 2-5 Days | D23: 3-7 Days | F23: 2-5 Days | G23: 2-5 Days | H23: 2-5 Days | J23: 2-5 Days | K23: 2-5 Days | L23: 2-5 Days | N23: 2-5 Days | O23: 2-5 Days | P23: 3-7 Days | R23: 1-3 Days | S23: 1-3 Days | T23: 2-5 Days | V23: 7-14 Days | W23: 7-14 Days | X23: 7-14 Days | Z23: 7-14 Days | AA23: 7-14 Days | AB23: 7-14 Days
A24: Medium | B24: 2-5 Days | C24: 2-5 Days | D24: 3-7 Days | F24: 2-5 Days | G24: 2-5 Days | H24: 2-5 Days | J24: 2-5 Days | K24: 2-5 Days | L24: 2-5 Days | N24: 2-5 Days | O24: 2-5 Days | P24: 3-7 Days | R24: 1-3 Days | S24: 1-3 Days | T24: 2-5 Days | V24: 7-14 Days | W24: 7-14 Days | X24: 7-14 Days | Z24: 7-14 Days | AA24: 7-14 Days | AB24: 7-14 Days
A25: Large | B25: 3-7 Days | C25: 3-7 Days | D25: 5-10 Days | F25: 3-7 Days | G25: 3-7 Days | H25: 5-10 Days | J25: 3-7 Days | K25: 3-7 Days | L25: 5-10 Days | N25: 3-7 Days | O25: 3-7 Days | P25: 5-10 Days | R25: 1-3 Days | S25: 1-3 Days | T25: 3-7 Days | V25: 7-14 Days | W25: 7-14 Days | X25: 7-14 Days | Z25: 7-14 Days | AA25: 7-14 Days | AB25: 7-14 Days
A26: XL | B26: 5-10 Days | C26: 5-10 Days | D26: 5-10 Days | F26: 5-10 Days | G26: 5-10 Days | H26: 5-10 Days | J26: 5-10 Days | K26: 5-10 Days | L26: 5-10 Days | N26: 5-10 Days | O26: 5-10 Days | P26: 5-10 Days | R26: 1-3 Days | S26: 1-3 Days | T26: 5-10 Days | V26: 7-14 Days | W26: 7-14 Days | X26: 7-14 Days | Z26: 7-14 Days | AA26: 7-14 Days | AB26: 7-14 Days
A27: XXL | B27: 5-10 Days | C27: 3-7 Days | D27: 5-10 Days | F27: 5-10 Days | G27: 3-7 Days | H27: 5-10 Days | J27: 5-10 Days | K27: 3-7 Days | L27: 5-10 Days | N27: 5-10 Days | O27: 3-7 Days | P27: 5-10 Days | R27: 1-3 Days | S27: 1-3 Days | T27: 5-10 Days | V27: 7-14 Days | W27: 7-14 Days | X27: 7-14 Days | Z27: 7-14 Days | AA27: 7-14 Days | AB27: 7-14 Days
A29: Priority | B29: From QLD | F29: From VIC | J29: From SA | N29: From NSW | R29: From ACT | V29: From TAS | Z29: From WA
A30: Freight Size | B30: Metro | C30: Metro Outer | D30: Regional | F30: Metro | G30: Metro Outer | H30: Regional | J30: Metro | K30: Metro Outer | L30: Regional | N30: Metro | O30: Metro Outer | P30: Regional | R30: Metro | S30: Metro Outer | T30: Regional | V30: Metro | W30: Metro Outer | X30: Regional | Z30: Metro | AA30: Metro Outer | AB30: Regional
A31: Small | B31: 1-2 Days | C31: 1-2 Days | D31: 2-5 Days | F31: 1-2 Days | G31: 1-2 Days | H31: 2-5 Days | J31: 1-2 Days | K31: 1-2 Days | L31: 2-5 Days | N31: 1-2 Days | O31: 1-2 Days | P31: 2-5 Days | R31: 1-2 Days | S31: 1-2 Days | T31: 1-3 Days | V31: 1-2 Days | W31: 1-2 Days | X31: 2-5 Days | Z31: 1-2 Days | AA31: 1-2 Days | AB31: 2-5 Days
A32: Medium | B32: 1-2 Days | C32: 1-2 Days | D32: 2-5 Days | F32: 1-2 Days | G32: 1-2 Days | H32: 2-5 Days | J32: 1-2 Days | K32: 1-2 Days | L32: 2-5 Days | N32: 1-2 Days | O32: 1-2 Days | P32: 2-5 Days | R32: 1-2 Days | S32: 1-2 Days | T32: 1-3 Days | V32: 1-2 Days | W32: 1-2 Days | X32: 2-5 Days | Z32: 1-2 Days | AA32: 1-2 Days | AB32: 2-5 Days
A33: Large | B33: 2-5 Days | C33: 2-5 Days | D33: 5-10 Days | F33: 2-5 Days | G33: 2-5 Days | H33: 5-10 Days | J33: 2-5 Days | K33: 2-5 Days | L33: 5-10 Days | N33: 2-5 Days | O33: 2-5 Days | P33: 5-10 Days | R33: 1-2 Days | S33: 1-2 Days | T33: 2-7 Days | V33: 7-14 Days | W33: 7-14 Days | X33: 7-14 Days | Z33: 7-14 Days | AA33: 7-14 Days | AB33: 7-14 Days
A34: XL | B34: 3-7 Days | C34: 3-7 Days | D34: 5-10 Days | F34: 3-7 Days | G34: 3-7 Days | H34: 5-10 Days | J34: 3-7 Days | K34: 3-7 Days | L34: 5-10 Days | N34: 3-7 Days | O34: 3-7 Days | P34: 5-10 Days | R34: 1-2 Days | S34: 1-2 Days | T34: 2-7 Days | V34: 7-14 Days | W34: 7-14 Days | X34: 7-14 Days | Z34: 7-14 Days | AA34: 7-14 Days | AB34: 7-14 Days
A35: XXL | B35: 3-7 Days | F35: 3-7 Days | J35: 3-7 Days | N35: 3-7 Days | R35: 1-2 Days | S35: 1-2 Days | T35: 2-7 Days | V35: 7-14 Days | Z35: 7-14 Days

Sheet NSW
A1: Freight Charges for NSW Orders
A3: Standard | B3: From QLD | F3: From VIC | J3: From SA | N3: From WA | R3: From NSW | V3: From TAS | Z3: From ACT
A4: Freight Size | B4: Metro | C4: Metro Outer | D4: Regional | F4: Metro | G4: Metro Outer | H4: Regional | J4: Metro | K4: Metro Outer | L4: Regional | N4: Metro | O4: Metro Outer | P4: Regional | R4: Metro | S4: Metro Outer | T4: Regional | V4: Metro | W4: Metro Outer | X4: Regional | Z4: Metro | AA4: Metro Outer | AB4: Regional
A5: Small | B5: ='Cost model'!M107 -> 12.5 | C5: ='Cost model'!M108 -> 15.5 | D5: ='Cost model'!M109 -> 18.5 | F5: ='Cost model'!M122 -> 13.5 | G5: ='Cost model'!M123 -> 16.5 | H5: ='Cost model'!M124 -> 21.5 | J5: ='Cost model'!M137 -> 13.5 | K5: ='Cost model'!M138 -> 16.5 | L5: ='Cost model'!M139 -> 19.5 | N5: ='Cost model'!M152 -> 13.5 | O5: ='Cost model'!M153 -> 15.5 | P5: ='Cost model'!M154 -> 20.5 | R5: ='Cost model'!M167 -> 8.5 | S5: ='Cost model'!M168 -> 13.5 | T5: ='Cost model'!M169 -> 18.5 | V5: ='Cost model'!M182 -> 14.5 | W5: ='Cost model'!M183 -> 17.5 | X5: ='Cost model'!M184 -> 24.5 | Z5: ='Cost model'!M197 -> 20.5 | AA5: ='Cost model'!M198 -> 20.5 | AB5: ='Cost model'!M199 -> 23.5
A6: Medium | B6: ='Cost model'!M110 -> 40 | C6: ='Cost model'!M111 -> 45 | D6: ='Cost model'!M112 -> 50 | F6: ='Cost model'!M125 -> 40 | G6: ='Cost model'!M126 -> 45 | H6: ='Cost model'!M127 -> 50 | J6: ='Cost model'!M140 -> 40 | K6: ='Cost model'!M141 -> 50 | L6: ='Cost model'!M142 -> 55 | N6: ='Cost model'!M155 -> 50 | O6: ='Cost model'!M156 -> 60 | P6: ='Cost model'!M157 -> 65 | R6: ='Cost model'!M170 -> 25.5 | S6: ='Cost model'!M171 -> 40 | T6: ='Cost model'!M172 -> 45 | V6: ='Cost model'!M185 -> 50 | W6: ='Cost model'!M186 -> 60 | X6: ='Cost model'!M187 -> 65 | Z6: ='Cost model'!M200 -> 45 | AA6: ='Cost model'!M201 -> 55 | AB6: ='Cost model'!M202 -> 65
A7: Large | B7: ='Cost model'!M113 -> 65 | C7: ='Cost model'!M114 -> 80 | D7: ='Cost model'!M115 -> 105 | F7: ='Cost model'!M128 -> 65 | G7: ='Cost model'!M129 -> 75 | H7: ='Cost model'!M130 -> 100 | J7: ='Cost model'!M143 -> 70 | K7: ='Cost model'!M144 -> 85 | L7: ='Cost model'!M145 -> 115 | N7: ='Cost model'!M158 -> 90 | O7: ='Cost model'!M159 -> 100 | P7: ='Cost model'!M160 -> 135 | R7: ='Cost model'!M173 -> 60 | S7: ='Cost model'!M174 -> 70 | T7: ='Cost model'!M175 -> 75 | V7: ='Cost model'!M188 -> 80 | W7: ='Cost model'!M189 -> 85 | X7: ='Cost model'!M190 -> 125 | Z7: ='Cost model'!M203 -> 65 | AA7: ='Cost model'!M204 -> 75 | AB7: ='Cost model'!M205 -> 105
A8: XL | B8: ='Cost model'!M116 -> 120 | C8: ='Cost model'!M117 -> 135 | D8: ='Cost model'!M118 -> 180 | F8: ='Cost model'!M131 -> 95 | G8: ='Cost model'!M132 -> 145 | H8: ='Cost model'!M133 -> 160 | J8: ='Cost model'!M146 -> 115 | K8: ='Cost model'!M147 -> 150 | L8: ='Cost model'!M148 -> 190 | N8: ='Cost model'!M161 -> 145 | O8: ='Cost model'!M162 -> 185 | P8: ='Cost model'!M163 -> 240 | R8: ='Cost model'!M176 -> 95 | S8: ='Cost model'!M177 -> 110 | T8: ='Cost model'!M178 -> 145 | V8: ='Cost model'!M191 -> 130 | W8: ='Cost model'!M192 -> 170 | X8: ='Cost model'!M193 -> 210 | Z8: ='Cost model'!M206 -> 110 | AA8: ='Cost model'!M207 -> 140 | AB8: ='Cost model'!M208 -> 170
A9: XXL | B9: ='Cost model'!M119 -> 145 | C9: ='Cost model'!M120 -> 235 | D9: ='Cost model'!M121 -> 285 | F9: ='Cost model'!M134 -> 135 | G9: ='Cost model'!M135 -> 240 | H9: ='Cost model'!M136 -> 280 | J9: ='Cost model'!M149 -> 155 | K9: ='Cost model'!M150 -> 265 | L9: ='Cost model'!M151 -> 320 | N9: ='Cost model'!M164 -> 195 | O9: ='Cost model'!M165 -> 325 | P9: ='Cost model'!M166 -> 390 | R9: ='Cost model'!M179 -> 135 | S9: ='Cost model'!M180 -> 150 | T9: ='Cost model'!M181 -> 230 | V9: ='Cost model'!M194 -> 170 | W9: ='Cost model'!M195 -> 285 | X9: ='Cost model'!M196 -> 345 | Z9: ='Cost model'!M209 -> 145 | AA9: ='Cost model'!M210 -> 240 | AB9: ='Cost model'!M211 -> 295
A11: Priority | B11: From QLD | F11: From VIC | J11: From SA | N11: From WA | R11: From NSW | V11: From TAS | Z11: From ACT
A12: Freight Size | B12: Metro | C12: Metro Outer | D12: Regional | F12: Metro | G12: Metro Outer | H12: Regional | J12: Metro | K12: Metro Outer | L12: Regional | N12: Metro | O12: Metro Outer | P12: Regional | R12: Metro | S12: Metro Outer | T12: Regional | V12: Metro | W12: Metro Outer | X12: Regional | Z12: Metro | AA12: Metro Outer | AB12: Regional
A13: Small | B13: ='Cost model'!N107 -> 17.5 | C13: ='Cost model'!N108 -> 21.5 | D13: ='Cost model'!N109 -> 25.5 | F13: ='Cost model'!N122 -> 18.5 | G13: ='Cost model'!N123 -> 22.5 | H13: ='Cost model'!N124 -> 29.5 | J13: ='Cost model'!N137 -> 18.5 | K13: ='Cost model'!N138 -> 22.5 | L13: ='Cost model'!N139 -> 26.5 | N13: ='Cost model'!N152 -> 18.5 | O13: ='Cost model'!N153 -> 21.5 | P13: ='Cost model'!N154 -> 27.5 | R13: ='Cost model'!N167 -> 13.5 | S13: ='Cost model'!N168 -> 18.5 | T13: ='Cost model'!N169 -> 25.5 | V13: ='Cost model'!N182 -> 19.5 | W13: ='Cost model'!N183 -> 23.5 | X13: ='Cost model'!N184 -> 35 | Z13: ='Cost model'!N197 -> 27.5 | AA13: ='Cost model'!N198 -> 27.5 | AB13: ='Cost model'!N199 -> 35
A14: Medium | B14: ='Cost model'!N110 -> 55 | C14: ='Cost model'!N111 -> 60 | D14: ='Cost model'!N112 -> 65 | F14: ='Cost model'!N125 -> 55 | G14: ='Cost model'!N126 -> 60 | H14: ='Cost model'!N127 -> 65 | J14: ='Cost model'!N140 -> 55 | K14: ='Cost model'!N141 -> 65 | L14: ='Cost model'!N142 -> 70 | N14: ='Cost model'!N155 -> 65 | O14: ='Cost model'!N156 -> 80 | P14: ='Cost model'!N157 -> 85 | R14: ='Cost model'!N170 -> 35 | S14: ='Cost model'!N171 -> 55 | T14: ='Cost model'!N172 -> 60 | V14: ='Cost model'!N185 -> 65 | W14: ='Cost model'!N186 -> 80 | X14: ='Cost model'!N187 -> 85 | Z14: ='Cost model'!N200 -> 60 | AA14: ='Cost model'!N201 -> 70 | AB14: ='Cost model'!N202 -> 85
A15: Large | B15: ='Cost model'!N113 -> 90 | C15: ='Cost model'!N114 -> 110 | D15: ='Cost model'!N115 -> 145 | F15: ='Cost model'!N128 -> 90 | G15: ='Cost model'!N129 -> 105 | H15: ='Cost model'!N130 -> 135 | J15: ='Cost model'!N143 -> 95 | K15: ='Cost model'!N144 -> 115 | L15: ='Cost model'!N145 -> 160 | N15: ='Cost model'!N158 -> 125 | O15: ='Cost model'!N159 -> 135 | P15: ='Cost model'!N160 -> 185 | R15: ='Cost model'!N173 -> 85 | S15: ='Cost model'!N174 -> 95 | T15: ='Cost model'!N175 -> 105 | V15: ='Cost model'!N188 -> 110 | W15: ='Cost model'!N189 -> 115 | X15: ='Cost model'!N190 -> 170 | Z15: ='Cost model'!N203 -> 90 | AA15: ='Cost model'!N204 -> 105 | AB15: ='Cost model'!N205 -> 145
A16: XL | B16: ='Cost model'!N116 -> 145 | C16: ='Cost model'!N117 -> 165 | D16: ='Cost model'!N118 -> 220 | F16: ='Cost model'!N131 -> 115 | G16: ='Cost model'!N132 -> 175 | H16: ='Cost model'!N133 -> 195 | J16: ='Cost model'!N146 -> 140 | K16: ='Cost model'!N147 -> 180 | L16: ='Cost model'!N148 -> 230 | N16: ='Cost model'!N161 -> 175 | O16: ='Cost model'!N162 -> 225 | P16: ='Cost model'!N163 -> 290 | R16: ='Cost model'!N176 -> 115 | S16: ='Cost model'!N177 -> 135 | T16: ='Cost model'!N178 -> 175 | V16: ='Cost model'!N191 -> 160 | W16: ='Cost model'!N192 -> 205 | X16: ='Cost model'!N193 -> 255 | Z16: ='Cost model'!N206 -> 135 | AA16: ='Cost model'!N207 -> 170 | AB16: ='Cost model'!N208 -> 205
A17: XXL | B17: ='Cost model'!N119 -> 175 | F17: ='Cost model'!N134 -> 165 | J17: ='Cost model'!N149 -> 190 | N17: ='Cost model'!N164 -> 235 | R17: ='Cost model'!N179 -> 165 | S17: ='Cost model'!N180 -> 180 | T17: ='Cost model'!N181 -> 280 | V17: ='Cost model'!N194 -> 205 | Z17: ='Cost model'!N209 -> 175
A19: Delivery time frames for NSW Orders
A21: Standard | B21: From QLD | F21: From VIC | J21: From SA | N21: From WA | R21: From NSW | V21: From TAS | Z21: From ACT
A22: Freight Size | B22: Metro | C22: Metro Outer | D22: Regional | F22: Metro | G22: Metro Outer | H22: Regional | J22: Metro | K22: Metro Outer | L22: Regional | N22: Metro | O22: Metro Outer | P22: Regional | R22: Metro | S22: Metro Outer | T22: Regional | V22: Metro | W22: Metro Outer | X22: Regional | Z22: Metro | AA22: Metro Outer | AB22: Regional
A23: Small | B23: 1-2 Days | C23: 1-3 Days | D23: 2-5 Days | F23: 1-2 Days | G23: 1-3 Days | H23: 2-5 Days | J23: 2-5 Days | K23: 2-5 Days | L23: 2-5 Days | N23: 7-10 Days | O23: 7-10 Days | P23: 7-10 Days | R23: 1-2 Days | S23: 1-3 Days | T23: 2-5 Days | V23: 7-14 Days | W23: 7-14 Days | X23: 7-14 Days | Z23: 7-14 Days | AA23: 7-14 Days | AB23: 7-14 Days
A24: Medium | B24: 1-2 Days | C24: 1-3 Days | D24: 2-5 Days | F24: 1-2 Days | G24: 1-3 Days | H24: 2-5 Days | J24: 2-5 Days | K24: 2-5 Days | L24: 2-5 Days | N24: 7-10 Days | O24: 7-10 Days | P24: 7-10 Days | R24: 1-2 Days | S24: 1-3 Days | T24: 2-5 Days | V24: 7-14 Days | W24: 7-14 Days | X24: 7-14 Days | Z24: 7-14 Days | AA24: 7-14 Days | AB24: 7-14 Days
A25: Large | B25: 1-2 Days | C25: 1-3 Days | D25: 3-7 Days | F25: 1-2 Days | G25: 1-3 Days | H25: 3-7 Days | J25: 3-7 Days | K25: 3-7 Days | L25: 5-10 Days | N25: 7-10 Days | O25: 7-10 Days | P25: 7-10 Days | R25: 1-2 Days | S25: 1-3 Days | T25: 3-7 Days | V25: 7-14 Days | W25: 7-14 Days | X25: 7-14 Days | Z25: 7-14 Days | AA25: 7-14 Days | AB25: 7-14 Days
A26: XL | B26: 2-5 Days | C26: 2-5 Days | D26: 5-10 Days | F26: 2-5 Days | G26: 2-5 Days | H26: 5-10 Days | J26: 5-10 Days | K26: 5-10 Days | L26: 5-10 Days | N26: 7-10 Days | O26: 7-10 Days | P26: 7-10 Days | R26: 2-5 Days | S26: 2-5 Days | T26: 5-10 Days | V26: 7-14 Days | W26: 7-14 Days | X26: 7-14 Days | Z26: 7-14 Days | AA26: 7-14 Days | AB26: 7-14 Days
A27: XXL | B27: 2-5 Days | C27: 1-3 Days | D27: 2-7 Days | F27: 2-5 Days | G27: 1-3 Days | H27: 2-7 Days | J27: 5-10 Days | K27: 3-7 Days | L27: 5-10 Days | N27: 7-10 Days | O27: 7-10 Days | P27: 7-14 Days | R27: 2-5 Days | S27: 2-5 Days | T27: 5-10 Days | V27: 7-14 Days | W27: 7-14 Days | X27: 7-14 Days | Z27: 7-14 Days | AA27: 7-14 Days | AB27: 7-14 Days
A29: Priority | B29: From QLD | F29: From VIC | J29: From SA | N29: From WA | R29: From NSW | V29: From TAS | Z29: From ACT
A30: Freight Size | B30: Metro | C30: Metro Outer | D30: Regional | F30: Metro | G30: Metro Outer | H30: Regional | J30: Metro | K30: Metro Outer | L30: Regional | N30: Metro | O30: Metro Outer | P30: Regional | R30: Metro | S30: Metro Outer | T30: Regional | V30: Metro | W30: Metro Outer | X30: Regional | Z30: Metro | AA30: Metro Outer | AB30: Regional
A31: Small | B31: 1-2 Days | C31: 1-2 Days | D31: 1-3 Days | F31: 1-2 Days | G31: 1-2 Days | H31: 1-3 Days | J31: 1-2 Days | K31: 1-2 Days | L31: 2-5 Days | N31: 1-2 Days | O31: 1-2 Days | P31: 2-5 Days | R31: 1-2 Days | S31: 1-2 Days | T31: 1-3 Days | V31: 1-2 Days | W31: 1-2 Days | X31: 2-5 Days | Z31: 1-2 Days | AA31: 1-2 Days | AB31: 2-5 Days
A32: Medium | B32: 1-2 Days | C32: 1-2 Days | D32: 1-3 Days | F32: 1-2 Days | G32: 1-2 Days | H32: 1-3 Days | J32: 1-2 Days | K32: 1-2 Days | L32: 2-5 Days | N32: 1-2 Days | O32: 1-2 Days | P32: 2-5 Days | R32: 1-2 Days | S32: 1-2 Days | T32: 1-3 Days | V32: 1-2 Days | W32: 1-2 Days | X32: 2-5 Days | Z32: 1-2 Days | AA32: 1-2 Days | AB32: 2-5 Days
A33: Large | B33: 1-2 Days | C33: 1-2 Days | D33: 2-7 Days | F33: 1-2 Days | G33: 1-2 Days | H33: 2-7 Days | J33: 2-5 Days | K33: 2-5 Days | L33: 5-10 Days | N33: 7-10 Days | O33: 7-10 Days | P33: 7-14 Days | R33: 1-2 Days | S33: 1-2 Days | T33: 2-7 Days | V33: 7-14 Days | W33: 7-14 Days | X33: 7-14 Days | Z33: 7-14 Days | AA33: 7-14 Days | AB33: 7-14 Days
A34: XL | B34: 1-3 Days | C34: 1-3 Days | D34: 2-7 Days | F34: 1-3 Days | G34: 1-3 Days | H34: 2-7 Days | J34: 3-7 Days | K34: 3-7 Days | L34: 5-10 Days | N34: 7-10 Days | O34: 7-10 Days | P34: 7-14 Days | R34: 1-3 Days | S34: 1-3 Days | T34: 2-7 Days | V34: 7-14 Days | W34: 7-14 Days | X34: 7-14 Days | Z34: 7-14 Days | AA34: 7-14 Days | AB34: 7-14 Days
A35: XXL | B35: 1-3 Days | F35: 1-3 Days | J35: 3-7 Days | N35: 7-10 Days | R35: 1-3 Days | S35: 1-3 Days | T35: 2-7 Days | V35: 7-14 Days | Z35: 7-14 Days

Sheet NT
A1: Freight Charges for NT Orders
A3: Standard | B3: From SA | F3: From VIC | J3: From WA | N3: From QLD | R3: From NSW | V3: From TAS | Z3: From ACT
A4: Freight Size | B4: Metro | C4: Metro Outer | D4: Regional | F4: Metro | G4: Metro Outer | H4: Regional | J4: Metro | K4: Metro Outer | L4: Regional | N4: Metro | O4: Metro Outer | P4: Regional | R4: Metro | S4: Metro Outer | T4: Regional | V4: Metro | W4: Metro Outer | X4: Regional | Z4: Metro | AA4: Metro Outer | AB4: Regional
A5: Small | B5: ='Cost model'!M212 -> 20.5 | C5: ='Cost model'!M213 -> 22.5 | D5: ='Cost model'!M214 -> 24.5 | F5: ='Cost model'!M227 -> 19.5 | G5: ='Cost model'!M228 -> 21.5 | H5: ='Cost model'!M229 -> 27.5 | J5: ='Cost model'!M242 -> 21.5 | K5: ='Cost model'!M243 -> 21.5 | L5: ='Cost model'!M244 -> 27.5 | N5: ='Cost model'!M257 -> 20.5 | O5: ='Cost model'!M258 -> 21.5 | P5: ='Cost model'!M259 -> 26.5 | R5: ='Cost model'!M272 -> 16.5 | S5: ='Cost model'!M273 -> 20.5 | T5: ='Cost model'!M274 -> 27.5 | V5: ='Cost model'!M287 -> 14.5 | W5: ='Cost model'!M288 -> 17.5 | X5: ='Cost model'!M289 -> 21.5 | Z5: ='Cost model'!M302 -> 14.5 | AA5: ='Cost model'!M303 -> 17.5 | AB5: ='Cost model'!M304 -> 21.5
A6: Medium | B6: ='Cost model'!M215 -> 60 | C6: ='Cost model'!M216 -> 65 | D6: ='Cost model'!M217 -> 70 | F6: ='Cost model'!M230 -> 55 | G6: ='Cost model'!M231 -> 65 | H6: ='Cost model'!M232 -> 80 | J6: ='Cost model'!M245 -> 60 | K6: ='Cost model'!M246 -> 65 | L6: ='Cost model'!M247 -> 75 | N6: ='Cost model'!M260 -> 55 | O6: ='Cost model'!M261 -> 60 | P6: ='Cost model'!M262 -> 70 | R6: ='Cost model'!M275 -> 70 | S6: ='Cost model'!M276 -> 70 | T6: ='Cost model'!M277 -> 80 | V6: ='Cost model'!M290 -> 45 | W6: ='Cost model'!M291 -> 55 | X6: ='Cost model'!M292 -> 60 | Z6: ='Cost model'!M305 -> 45 | AA6: ='Cost model'!M306 -> 55 | AB6: ='Cost model'!M307 -> 60
A7: Large | B7: ='Cost model'!M218 -> 95 | C7: ='Cost model'!M219 -> 100 | D7: ='Cost model'!M220 -> 135 | F7: ='Cost model'!M233 -> 95 | G7: ='Cost model'!M234 -> 105 | H7: ='Cost model'!M235 -> 145 | J7: ='Cost model'!M248 -> 100 | K7: ='Cost model'!M249 -> 110 | L7: ='Cost model'!M250 -> 150 | N7: ='Cost model'!M263 -> 90 | O7: ='Cost model'!M264 -> 105 | P7: ='Cost model'!M265 -> 140 | R7: ='Cost model'!M278 -> 90 | S7: ='Cost model'!M279 -> 105 | T7: ='Cost model'!M280 -> 145 | V7: ='Cost model'!M293 -> 85 | W7: ='Cost model'!M294 -> 95 | X7: ='Cost model'!M295 -> 130 | Z7: ='Cost model'!M308 -> 80 | AA7: ='Cost model'!M309 -> 95 | AB7: ='Cost model'!M310 -> 125
A8: XL | B8: ='Cost model'!M221 -> 150 | C8: ='Cost model'!M222 -> 185 | D8: ='Cost model'!M223 -> 225 | F8: ='Cost model'!M236 -> 155 | G8: ='Cost model'!M237 -> 195 | H8: ='Cost model'!M238 -> 250 | J8: ='Cost model'!M251 -> 165 | K8: ='Cost model'!M252 -> 205 | L8: ='Cost model'!M253 -> 255 | N8: ='Cost model'!M266 -> 150 | O8: ='Cost model'!M267 -> 190 | P8: ='Cost model'!M268 -> 240 | R8: ='Cost model'!M281 -> 155 | S8: ='Cost model'!M282 -> 195 | T8: ='Cost model'!M283 -> 245 | V8: ='Cost model'!M296 -> 135 | W8: ='Cost model'!M297 -> 175 | X8: ='Cost model'!M298 -> 220 | Z8: ='Cost model'!M311 -> 135 | AA8: ='Cost model'!M312 -> 175 | AB8: ='Cost model'!M313 -> 220
A9: XXL | B9: ='Cost model'!M224 -> 190 | C9: ='Cost model'!M225 -> 325 | D9: ='Cost model'!M226 -> 405 | F9: ='Cost model'!M239 -> 205 | G9: ='Cost model'!M240 -> 345 | H9: ='Cost model'!M241 -> 410 | J9: ='Cost model'!M254 -> 215 | K9: ='Cost model'!M255 -> 360 | L9: ='Cost model'!M256 -> 435 | N9: ='Cost model'!M269 -> 200 | O9: ='Cost model'!M270 -> 340 | P9: ='Cost model'!M271 -> 400 | R9: ='Cost model'!M284 -> 205 | S9: ='Cost model'!M285 -> 345 | T9: ='Cost model'!M286 -> 415 | V9: ='Cost model'!M299 -> 185 | W9: ='Cost model'!M300 -> 310 | X9: ='Cost model'!M301 -> 370 | Z9: ='Cost model'!M314 -> 180 | AA9: ='Cost model'!M315 -> 300 | AB9: ='Cost model'!M316 -> 360
A11: Priority | B11: From SA | F11: From VIC | J11: From WA | N11: From QLD | R11: From NSW | V11: From TAS | Z11: From ACT
A12: Freight Size | B12: Metro | C12: Metro Outer | D12: Regional | F12: Metro | G12: Metro Outer | H12: Regional | J12: Metro | K12: Metro Outer | L12: Regional | N12: Metro | O12: Metro Outer | P12: Regional | R12: Metro | S12: Metro Outer | T12: Regional | V12: Metro | W12: Metro Outer | X12: Regional | Z12: Metro | AA12: Metro Outer | AB12: Regional
A13: Small | B13: ='Cost model'!N212 -> 27.5 | C13: ='Cost model'!N213 -> 35 | D13: ='Cost model'!N214 -> 35 | F13: ='Cost model'!N227 -> 26.5 | G13: ='Cost model'!N228 -> 29.5 | H13: ='Cost model'!N229 -> 40 | J13: ='Cost model'!N242 -> 29.5 | K13: ='Cost model'!N243 -> 29.5 | L13: ='Cost model'!N244 -> 40 | N13: ='Cost model'!N257 -> 27.5 | O13: ='Cost model'!N258 -> 29.5 | P13: ='Cost model'!N259 -> 40 | R13: ='Cost model'!N272 -> 22.5 | S13: ='Cost model'!N273 -> 27.5 | T13: ='Cost model'!N274 -> 40 | V13: ='Cost model'!N287 -> 19.5 | W13: ='Cost model'!N288 -> 23.5 | X13: ='Cost model'!N289 -> 29.5 | Z13: ='Cost model'!N302 -> 19.5 | AA13: ='Cost model'!N303 -> 23.5 | AB13: ='Cost model'!N304 -> 29.5
A14: Medium | B14: ='Cost model'!N215 -> 80 | C14: ='Cost model'!N216 -> 85 | D14: ='Cost model'!N217 -> 90 | F14: ='Cost model'!N230 -> 70 | G14: ='Cost model'!N231 -> 85 | H14: ='Cost model'!N232 -> 105 | J14: ='Cost model'!N245 -> 80 | K14: ='Cost model'!N246 -> 85 | L14: ='Cost model'!N247 -> 95 | N14: ='Cost model'!N260 -> 70 | O14: ='Cost model'!N261 -> 80 | P14: ='Cost model'!N262 -> 90 | R14: ='Cost model'!N275 -> 90 | S14: ='Cost model'!N276 -> 90 | T14: ='Cost model'!N277 -> 105 | V14: ='Cost model'!N290 -> 60 | W14: ='Cost model'!N291 -> 70 | X14: ='Cost model'!N292 -> 80 | Z14: ='Cost model'!N305 -> 60 | AA14: ='Cost model'!N306 -> 70 | AB14: ='Cost model'!N307 -> 80
A15: Large | B15: ='Cost model'!N218 -> 130 | C15: ='Cost model'!N219 -> 135 | D15: ='Cost model'!N220 -> 185 | F15: ='Cost model'!N233 -> 130 | G15: ='Cost model'!N234 -> 145 | H15: ='Cost model'!N235 -> 200 | J15: ='Cost model'!N248 -> 135 | K15: ='Cost model'!N249 -> 150 | L15: ='Cost model'!N250 -> 205 | N15: ='Cost model'!N263 -> 125 | O15: ='Cost model'!N264 -> 145 | P15: ='Cost model'!N265 -> 190 | R15: ='Cost model'!N278 -> 125 | S15: ='Cost model'!N279 -> 145 | T15: ='Cost model'!N280 -> 200 | V15: ='Cost model'!N293 -> 115 | W15: ='Cost model'!N294 -> 130 | X15: ='Cost model'!N295 -> 180 | Z15: ='Cost model'!N308 -> 110 | AA15: ='Cost model'!N309 -> 130 | AB15: ='Cost model'!N310 -> 170
A16: XL | B16: ='Cost model'!N221 -> 180 | C16: ='Cost model'!N222 -> 225 | D16: ='Cost model'!N223 -> 270 | F16: ='Cost model'!N236 -> 190 | G16: ='Cost model'!N237 -> 235 | H16: ='Cost model'!N238 -> 300 | J16: ='Cost model'!N251 -> 200 | K16: ='Cost model'!N252 -> 250 | L16: ='Cost model'!N253 -> 310 | N16: ='Cost model'!N266 -> 180 | O16: ='Cost model'!N267 -> 230 | P16: ='Cost model'!N268 -> 290 | R16: ='Cost model'!N281 -> 190 | S16: ='Cost model'!N282 -> 235 | T16: ='Cost model'!N283 -> 295 | V16: ='Cost model'!N296 -> 165 | W16: ='Cost model'!N297 -> 210 | X16: ='Cost model'!N298 -> 265 | Z16: ='Cost model'!N311 -> 165 | AA16: ='Cost model'!N312 -> 210 | AB16: ='Cost model'!N313 -> 265
A17: XXL | B17: ='Cost model'!N224 -> 230 | F17: ='Cost model'!N239 -> 250 | J17: ='Cost model'!N254 -> 260 | N17: ='Cost model'!N269 -> 240 | R17: ='Cost model'!N284 -> 250 | V17: ='Cost model'!N299 -> 225 | Z17: ='Cost model'!N314 -> 220
A19: Delivery time frames for NT Orders
A21: Standard | B21: From SA | F21: From VIC | J21: From WA | N21: From QLD | R21: From NSW | V21: From TAS | Z21: From ACT
A22: Freight Size | B22: Metro | C22: Metro Outer | D22: Regional | F22: Metro | G22: Metro Outer | H22: Regional | J22: Metro | K22: Metro Outer | L22: Regional | N22: Metro | O22: Metro Outer | P22: Regional | R22: Metro | S22: Metro Outer | T22: Regional | V22: Metro | W22: Metro Outer | X22: Regional | Z22: Metro | AA22: Metro Outer | AB22: Regional
A23: Small | B23: 1-2 Days | C23: 1-3 Days | D23: 2-5 Days | F23: 2-5 Days | G23: 3-7 Days | H23: 5-10 Days | J23: 2-5 Days | K23: 2-5 Days | L23: 3-7 Days | N23: 2-5 Days | O23: 2-5 Days | P23: 3-7 Days | R23: 2-5 Days | S23: 2-5 Days | T23: 3-7 Days | V23: 7-14 Days | W23: 7-14 Days | X23: 7-14 Days | Z23: 7-14 Days | AA23: 7-14 Days | AB23: 7-14 Days
A24: Medium | B24: 1-2 Days | C24: 1-3 Days | D24: 2-5 Days | F24: 2-5 Days | G24: 3-7 Days | H24: 5-10 Days | J24: 2-5 Days | K24: 2-5 Days | L24: 3-7 Days | N24: 2-5 Days | O24: 2-5 Days | P24: 3-7 Days | R24: 2-5 Days | S24: 2-5 Days | T24: 3-7 Days | V24: 7-14 Days | W24: 7-14 Days | X24: 7-14 Days | Z24: 7-14 Days | AA24: 7-14 Days | AB24: 7-14 Days
A25: Large | B25: 1-2 Days | C25: 1-3 Days | D25: 3-7 Days | F25: 3-7 Days | G25: 3-7 Days | H25: 5-10 Days | J25: 5-10 Days | K25: 5-10 Days | L25: 5-10 Days | N25: 5-10 Days | O25: 5-10 Days | P25: 5-10 Days | R25: 5-10 Days | S25: 5-10 Days | T25: 5-10 Days | V25: 7-14 Days | W25: 7-14 Days | X25: 7-14 Days | Z25: 7-14 Days | AA25: 7-14 Days | AB25: 7-14 Days
A26: XL | B26: 1-2 Days | C26: 1-3 Days | D26: 5-10 Days | F26: 5-10 Days | G26: 5-10 Days | H26: 5-10 Days | J26: 5-10 Days | K26: 5-10 Days | L26: 5-10 Days | N26: 5-10 Days | O26: 5-10 Days | P26: 5-10 Days | R26: 5-10 Days | S26: 5-10 Days | T26: 5-10 Days | V26: 7-14 Days | W26: 7-14 Days | X26: 7-14 Days | Z26: 7-14 Days | AA26: 7-14 Days | AB26: 7-14 Days
A27: XXL | B27: 1-2 Days | F27: 5-10 Days | J27: 5-10 Days | N27: 5-10 Days | R27: 5-10 Days | V27: 7-14 Days | W27: 7-14 Days | X27: 7-14 Days | Z27: 7-14 Days | AA27: 7-14 Days | AB27: 7-14 Days
A29: Priority | B29: From SA | F29: From VIC | J29: From WA | N29: From QLD | R29: From NSW | V29: From TAS | Z29: From ACT
A30: Freight Size | B30: Metro | C30: Metro Outer | D30: Regional | F30: Metro | G30: Metro Outer | H30: Regional | J30: Metro | K30: Metro Outer | L30: Regional | N30: Metro | O30: Metro Outer | P30: Regional | R30: Metro | S30: Metro Outer | T30: Regional | V30: Metro | W30: Metro Outer | X30: Regional | Z30: Metro | AA30: Metro Outer | AB30: Regional
A31: Small | B31: 1-3 Days | C31: 2-5 Days | D31: 3-7 Days | F31: 1-3 Days | G31: 2-5 Days | H31: 3-7 Days | J31: 1-3 Days | K31: 3-7 Days | L31: 3-7 Days | N31: 1-2 Days | O31: 1-2 Days | P31: 2-5 Days | R31: 1-2 Days | S31: 1-2 Days | T31: 2-5 Days | V31: 1-2 Days | W31: 1-2 Days | X31: 2-5 Days | Z31: 1-2 Days | AA31: 1-2 Days | AB31: 2-5 Days
A32: Medium | B32: 1-3 Days | C32: 2-5 Days | D32: 3-7 Days | F32: 1-3 Days | G32: 2-5 Days | H32: 3-7 Days | J32: 1-3 Days | K32: 3-7 Days | L32: 3-7 Days | N32: 1-2 Days | O32: 1-2 Days | P32: 2-5 Days | R32: 1-2 Days | S32: 1-2 Days | T32: 2-5 Days | V32: 1-2 Days | W32: 1-2 Days | X32: 2-5 Days | Z32: 1-2 Days | AA32: 1-2 Days | AB32: 2-5 Days
A33: Large | B33: 1-3 Days | C33: 2-5 Days | D33: 3-7 Days | F33: 1-3 Days | G33: 2-5 Days | H33: 3-7 Days | J33: 3-7 Days | K33: 3-7 Days | L33: 5-10 Days | N33: 7-14 Days | O33: 7-14 Days | P33: 7-14 Days | R33: 7-14 Days | S33: 7-14 Days | T33: 7-14 Days | V33: 7-14 Days | W33: 7-14 Days | X33: 7-14 Days | Z33: 7-14 Days | AA33: 7-14 Days | AB33: 7-14 Days
A34: XL | V34: 7-14 Days | W34: 7-14 Days | X34: 7-14 Days | Z34: 7-14 Days | AA34: 7-14 Days | AB34: 7-14 Days
A35: XXL | V35: 7-14 Days | Z35: 7-14 Days

Sheet QLD
A1: Freight Charges for QLD Orders
A3: Standard | B3: From QLD | F3: From VIC | J3: From SA | N3: From NSW | R3: From TAS | V3: From ACT | Z3: From WA
A4: Freight Size | B4: Metro | C4: Metro Outer | D4: Regional | F4: Metro | G4: Metro Outer | H4: Regional | J4: Metro | K4: Metro Outer | L4: Regional | N4: Metro | O4: Metro Outer | P4: Regional | R4: Metro | S4: Metro Outer | T4: Regional | V4: Metro | W4: Metro Outer | X4: Regional | Z4: Metro | AA4: Metro Outer | AB4: Regional
A5: Small | B5: ='Cost model'!M317 -> 10.5 | C5: ='Cost model'!M318 -> 14.5 | D5: ='Cost model'!M319 -> 16.5 | F5: ='Cost model'!M332 -> 16.5 | G5: ='Cost model'!M333 -> 18.5 | H5: ='Cost model'!M334 -> 20.5 | J5: ='Cost model'!M347 -> 13.5 | K5: ='Cost model'!M348 -> 17.5 | L5: ='Cost model'!M349 -> 20.5 | N5: ='Cost model'!M362 -> 10.5 | O5: ='Cost model'!M363 -> 15.5 | P5: ='Cost model'!M364 -> 16.5 | R5: ='Cost model'!M377 -> 15.5 | S5: ='Cost model'!M378 -> 18.5 | T5: ='Cost model'!M379 -> 23.5 | V5: ='Cost model'!M392 -> 13.5 | W5: ='Cost model'!M393 -> 18.5 | X5: ='Cost model'!M394 -> 20.5 | Z5: ='Cost model'!M407 -> 12.5 | AA5: ='Cost model'!M408 -> 21.5 | AB5: ='Cost model'!M409 -> 21.5
A6: Medium | B6: ='Cost model'!M320 -> 24.5 | C6: ='Cost model'!M321 -> 40 | D6: ='Cost model'!M322 -> 50 | F6: ='Cost model'!M335 -> 45 | G6: ='Cost model'!M336 -> 50 | H6: ='Cost model'!M337 -> 60 | J6: ='Cost model'!M350 -> 50 | K6: ='Cost model'!M351 -> 55 | L6: ='Cost model'!M352 -> 60 | N6: ='Cost model'!M365 -> 45 | O6: ='Cost model'!M366 -> 55 | P6: ='Cost model'!M367 -> 60 | R6: ='Cost model'!M380 -> 55 | S6: ='Cost model'!M381 -> 65 | T6: ='Cost model'!M382 -> 90 | V6: ='Cost model'!M395 -> 50 | W6: ='Cost model'!M396 -> 60 | X6: ='Cost model'!M397 -> 60 | Z6: ='Cost model'!M410 -> 45 | AA6: ='Cost model'!M411 -> 50 | AB6: ='Cost model'!M412 -> 60
A7: Large | B7: ='Cost model'!M323 -> 60 | C7: ='Cost model'!M324 -> 85 | D7: ='Cost model'!M325 -> 110 | F7: ='Cost model'!M338 -> 85 | G7: ='Cost model'!M339 -> 85 | H7: ='Cost model'!M340 -> 125 | J7: ='Cost model'!M353 -> 75 | K7: ='Cost model'!M354 -> 90 | L7: ='Cost model'!M355 -> 120 | N7: ='Cost model'!M368 -> 75 | O7: ='Cost model'!M369 -> 100 | P7: ='Cost model'!M370 -> 120 | R7: ='Cost model'!M383 -> 85 | S7: ='Cost model'!M384 -> 105 | T7: ='Cost model'!M385 -> 140 | V7: ='Cost model'!M398 -> 80 | W7: ='Cost model'!M399 -> 90 | X7: ='Cost model'!M400 -> 120 | Z7: ='Cost model'!M413 -> 80 | AA7: ='Cost model'!M414 -> 90 | AB7: ='Cost model'!M415 -> 125
A8: XL | B8: ='Cost model'!M326 -> 110 | C8: ='Cost model'!M327 -> 130 | D8: ='Cost model'!M328 -> 175 | F8: ='Cost model'!M341 -> 130 | G8: ='Cost model'!M342 -> 155 | H8: ='Cost model'!M343 -> 205 | J8: ='Cost model'!M356 -> 125 | K8: ='Cost model'!M357 -> 175 | L8: ='Cost model'!M358 -> 210 | N8: ='Cost model'!M371 -> 130 | O8: ='Cost model'!M372 -> 165 | P8: ='Cost model'!M373 -> 215 | R8: ='Cost model'!M386 -> 150 | S8: ='Cost model'!M387 -> 195 | T8: ='Cost model'!M388 -> 255 | V8: ='Cost model'!M401 -> 130 | W8: ='Cost model'!M402 -> 165 | X8: ='Cost model'!M403 -> 210 | Z8: ='Cost model'!M416 -> 130 | AA8: ='Cost model'!M417 -> 165 | AB8: ='Cost model'!M418 -> 210
A9: XXL | B9: ='Cost model'!M329 -> 135 | C9: ='Cost model'!M330 -> 180 | D9: ='Cost model'!M331 -> 280 | F9: ='Cost model'!M344 -> 170 | G9: ='Cost model'!M345 -> 280 | H9: ='Cost model'!M346 -> 340 | J9: ='Cost model'!M359 -> 175 | K9: ='Cost model'!M360 -> 290 | L9: ='Cost model'!M361 -> 345 | N9: ='Cost model'!M374 -> 180 | O9: ='Cost model'!M375 -> 285 | P9: ='Cost model'!M376 -> 350 | R9: ='Cost model'!M389 -> 200 | S9: ='Cost model'!M390 -> 330 | T9: ='Cost model'!M391 -> 400 | V9: ='Cost model'!M404 -> 175 | W9: ='Cost model'!M405 -> 295 | X9: ='Cost model'!M406 -> 350 | Z9: ='Cost model'!M419 -> 175 | AA9: ='Cost model'!M420 -> 290 | AB9: ='Cost model'!M421 -> 350
A11: Priority | B11: From QLD | F11: From VIC | J11: From SA | N11: From NSW | R11: From TAS | V11: From ACT | Z11: From WA
A12: Freight Size | B12: Metro | C12: Metro Outer | D12: Regional | F12: Metro | G12: Metro Outer | H12: Regional | J12: Metro | K12: Metro Outer | L12: Regional | N12: Metro | O12: Metro Outer | P12: Regional | R12: Metro | S12: Metro Outer | T12: Regional | V12: Metro | W12: Metro Outer | X12: Regional | Z12: Metro | AA12: Metro Outer | AB12: Regional
A13: Small | B13: ='Cost model'!N317 -> 15.5 | C13: ='Cost model'!N318 -> 19.5 | D13: ='Cost model'!N319 -> 22.5 | F13: ='Cost model'!N332 -> 22.5 | G13: ='Cost model'!N333 -> 25.5 | H13: ='Cost model'!N334 -> 27.5 | J13: ='Cost model'!N347 -> 18.5 | K13: ='Cost model'!N348 -> 23.5 | L13: ='Cost model'!N349 -> 27.5 | N13: ='Cost model'!N362 -> 15.5 | O13: ='Cost model'!N363 -> 21.5 | P13: ='Cost model'!N364 -> 22.5 | R13: ='Cost model'!N377 -> 21.5 | S13: ='Cost model'!N378 -> 25.5 | T13: ='Cost model'!N379 -> 35 | V13: ='Cost model'!N392 -> 18.5 | W13: ='Cost model'!N393 -> 25.5 | X13: ='Cost model'!N394 -> 27.5 | Z13: ='Cost model'!N407 -> 17.5 | AA13: ='Cost model'!N408 -> 29.5 | AB13: ='Cost model'!N409 -> 29.5
A14: Medium | B14: ='Cost model'!N320 -> 35 | C14: ='Cost model'!N321 -> 55 | D14: ='Cost model'!N322 -> 65 | F14: ='Cost model'!N335 -> 60 | G14: ='Cost model'!N336 -> 65 | H14: ='Cost model'!N337 -> 80 | J14: ='Cost model'!N350 -> 65 | K14: ='Cost model'!N351 -> 70 | L14: ='Cost model'!N352 -> 80 | N14: ='Cost model'!N365 -> 60 | O14: ='Cost model'!N366 -> 70 | P14: ='Cost model'!N367 -> 80 | R14: ='Cost model'!N380 -> 70 | S14: ='Cost model'!N381 -> 85 | T14: ='Cost model'!N382 -> 115 | V14: ='Cost model'!N395 -> 65 | W14: ='Cost model'!N396 -> 80 | X14: ='Cost model'!N397 -> 80 | Z14: ='Cost model'!N410 -> 60 | AA14: ='Cost model'!N411 -> 65 | AB14: ='Cost model'!N412 -> 80
A15: Large | B15: ='Cost model'!N323 -> 85 | C15: ='Cost model'!N324 -> 115 | D15: ='Cost model'!N325 -> 150 | F15: ='Cost model'!N338 -> 115 | G15: ='Cost model'!N339 -> 115 | H15: ='Cost model'!N340 -> 170 | J15: ='Cost model'!N353 -> 105 | K15: ='Cost model'!N354 -> 125 | L15: ='Cost model'!N355 -> 165 | N15: ='Cost model'!N368 -> 105 | O15: ='Cost model'!N369 -> 135 | P15: ='Cost model'!N370 -> 165 | R15: ='Cost model'!N383 -> 115 | S15: ='Cost model'!N384 -> 145 | T15: ='Cost model'!N385 -> 190 | V15: ='Cost model'!N398 -> 110 | W15: ='Cost model'!N399 -> 125 | X15: ='Cost model'!N400 -> 165 | Z15: ='Cost model'!N413 -> 110 | AA15: ='Cost model'!N414 -> 125 | AB15: ='Cost model'!N415 -> 170
A16: XL | B16: ='Cost model'!N326 -> 135 | C16: ='Cost model'!N327 -> 160 | D16: ='Cost model'!N328 -> 210 | F16: ='Cost model'!N341 -> 160 | G16: ='Cost model'!N342 -> 190 | H16: ='Cost model'!N343 -> 250 | J16: ='Cost model'!N356 -> 150 | K16: ='Cost model'!N357 -> 210 | L16: ='Cost model'!N358 -> 255 | N16: ='Cost model'!N371 -> 160 | O16: ='Cost model'!N372 -> 200 | P16: ='Cost model'!N373 -> 260 | R16: ='Cost model'!N386 -> 180 | S16: ='Cost model'!N387 -> 235 | T16: ='Cost model'!N388 -> 310 | V16: ='Cost model'!N401 -> 160 | W16: ='Cost model'!N402 -> 200 | X16: ='Cost model'!N403 -> 255 | Z16: ='Cost model'!N416 -> 160 | AA16: ='Cost model'!N417 -> 200 | AB16: ='Cost model'!N418 -> 255
A17: XXL | B17: ='Cost model'!N329 -> 165 | C17: ='Cost model'!N330 -> 220 | D17: ='Cost model'!N331 -> 340 | F17: ='Cost model'!N344 -> 205 | J17: ='Cost model'!N359 -> 210 | N17: ='Cost model'!N374 -> 220 | R17: ='Cost model'!N389 -> 240 | V17: ='Cost model'!N404 -> 210 | Z17: ='Cost model'!N419 -> 210
A19: Delivery time frames for QLD Orders
A21: Standard | B21: From QLD | F21: From VIC | J21: From SA | N21: From NSW | R21: From TAS | V21: From ACT | Z21: From WA
A22: Freight Size | B22: Metro | C22: Metro Outer | D22: Regional | F22: Metro | G22: Metro Outer | H22: Regional | J22: Metro | K22: Metro Outer | L22: Regional | N22: Metro | O22: Metro Outer | P22: Regional | R22: Metro | S22: Metro Outer | T22: Regional | V22: Metro | W22: Metro Outer | X22: Regional | Z22: Metro | AA22: Metro Outer | AB22: Regional
A23: Small | B23: 1-3 Days | C23: 1-3 Days | D23: 2-5 Days | F23: 2-5 Days | G23: 2-5 Days | H23: 3-7 Days | J23: 2-5 Days | K23: 2-5 Days | L23: 2-5 Days | N23: 2-5 Days | O23: 2-5 Days | P23: 3-7 Days | R23: 7-14 Days | S23: 7-14 Days | T23: 7-14 Days | V23: 7-14 Days | W23: 7-14 Days | X23: 7-14 Days | Z23: 7-14 Days | AA23: 7-14 Days | AB23: 7-14 Days
A24: Medium | B24: 1-3 Days | C24: 1-3 Days | D24: 2-5 Days | F24: 2-5 Days | G24: 2-5 Days | H24: 3-7 Days | J24: 2-5 Days | K24: 2-5 Days | L24: 2-5 Days | N24: 2-5 Days | O24: 2-5 Days | P24: 3-7 Days | R24: 7-14 Days | S24: 7-14 Days | T24: 7-14 Days | V24: 7-14 Days | W24: 7-14 Days | X24: 7-14 Days | Z24: 7-14 Days | AA24: 7-14 Days | AB24: 7-14 Days
A25: Large | B25: 1-3 Days | C25: 1-3 Days | D25: 3-7 Days | F25: 3-7 Days | G25: 3-7 Days | H25: 5-10 Days | J25: 3-7 Days | K25: 3-7 Days | L25: 5-10 Days | N25: 3-7 Days | O25: 3-7 Days | P25: 5-10 Days | R25: 7-14 Days | S25: 7-14 Days | T25: 7-14 Days | V25: 7-14 Days | W25: 7-14 Days | X25: 7-14 Days | Z25: 7-14 Days | AA25: 7-14 Days | AB25: 7-14 Days
A26: XL | B26: 1-3 Days | C26: 1-3 Days | D26: 5-10 Days | F26: 5-10 Days | G26: 5-10 Days | H26: 5-10 Days | J26: 5-10 Days | K26: 5-10 Days | L26: 5-10 Days | N26: 5-10 Days | O26: 5-10 Days | P26: 5-10 Days | R26: 7-14 Days | S26: 7-14 Days | T26: 7-14 Days | V26: 7-14 Days | W26: 7-14 Days | X26: 7-14 Days | Z26: 7-14 Days | AA26: 7-14 Days | AB26: 7-14 Days
A27: XXL | B27: 1-3 Days | C27: 1-3 Days | D27: 5-10 Days | F27: 5-10 Days | G27: 3-7 Days | H27: 5-10 Days | J27: 5-10 Days | K27: 3-7 Days | L27: 5-10 Days | N27: 5-10 Days | O27: 3-7 Days | P27: 5-10 Days | R27: 7-14 Days | S27: 7-14 Days | T27: 7-14 Days | V27: 7-14 Days | W27: 7-14 Days | X27: 7-14 Days | Z27: 7-14 Days | AA27: 7-14 Days | AB27: 7-14 Days
A29: Priority | B29: From QLD | F29: From VIC | J29: From SA | N29: From NSW | R29: From TAS | V29: From ACT | Z29: From WA
A30: Freight Size | B30: Metro | C30: Metro Outer | D30: Regional | F30: Metro | G30: Metro Outer | H30: Regional | J30: Metro | K30: Metro Outer | L30: Regional | N30: Metro | O30: Metro Outer | P30: Regional | R30: Metro | S30: Metro Outer | T30: Regional | V30: Metro | W30: Metro Outer | X30: Regional | Z30: Metro | AA30: Metro Outer | AB30: Regional
A31: Small | B31: 1-2 Days | C31: 1-2 Days | D31: 1-3 Days | F31: 1-2 Days | G31: 1-2 Days | H31: 2-5 Days | J31: 1-2 Days | K31: 1-2 Days | L31: 2-5 Days | N31: 1-2 Days | O31: 1-2 Days | P31: 2-5 Days | R31: 1-2 Days | S31: 1-2 Days | T31: 2-5 Days | V31: 1-2 Days | W31: 1-2 Days | X31: 2-5 Days | Z31: 1-2 Days | AA31: 1-2 Days | AB31: 2-5 Days
A32: Medium | B32: 1-2 Days | C32: 1-2 Days | D32: 1-3 Days | F32: 1-2 Days | G32: 1-2 Days | H32: 2-5 Days | J32: 1-2 Days | K32: 1-2 Days | L32: 2-5 Days | N32: 1-2 Days | O32: 1-2 Days | P32: 2-5 Days | R32: 1-2 Days | S32: 1-2 Days | T32: 2-5 Days | V32: 1-2 Days | W32: 1-2 Days | X32: 2-5 Days | Z32: 1-2 Days | AA32: 1-2 Days | AB32: 2-5 Days
A33: Large | B33: 1-2 Days | C33: 1-2 Days | D33: 2-7 Days | F33: 2-5 Days | G33: 2-5 Days | H33: 5-10 Days | J33: 2-5 Days | K33: 2-5 Days | L33: 5-10 Days | N33: 2-5 Days | O33: 2-5 Days | P33: 5-10 Days | R33: 7-14 Days | S33: 7-14 Days | T33: 7-14 Days | V33: 7-14 Days | W33: 7-14 Days | X33: 7-14 Days | Z33: 7-14 Days | AA33: 7-14 Days | AB33: 7-14 Days
A34: XL | B34: 1-2 Days | C34: 1-2 Days | D34: 2-7 Days | F34: 3-7 Days | G34: 3-7 Days | H34: 5-10 Days | J34: 3-7 Days | K34: 3-7 Days | L34: 5-10 Days | N34: 3-7 Days | O34: 3-7 Days | P34: 5-10 Days | R34: 7-14 Days | S34: 7-14 Days | T34: 7-14 Days | V34: 7-14 Days | W34: 7-14 Days | X34: 7-14 Days | Z34: 7-14 Days | AA34: 7-14 Days | AB34: 7-14 Days
A35: XXL | B35: 1-2 Days | C35: 1-2 Days | D35: 2-7 Days | F35: 3-7 Days | J35: 3-7 Days | N35: 3-7 Days | R35: 7-14 Days | V35: 7-14 Days | Z35: 7-14 Days

Sheet SA
A1: Freight Charges for SA Orders
A3: Standard | B3: From SA | F3: From VIC | J3: From QLD | N3: From WA | R3: From NSW | V3: From TAS | Z3: From ACT
A4: Freight Size | B4: Metro | C4: Metro Outer | D4: Regional | F4: Metro | G4: Metro Outer | H4: Regional | J4: Metro | K4: Metro Outer | L4: Regional | N4: Metro | O4: Metro Outer | P4: Regional | R4: Metro | S4: Metro Outer | T4: Regional | V4: Metro | W4: Metro Outer | X4: Regional | Z4: Metro | AA4: Metro Outer | AB4: Regional
A5: Small | B5: ='Cost model'!M422 -> 8.5 | C5: ='Cost model'!M423 -> 11.5 | D5: ='Cost model'!M424 -> 16.5 | F5: ='Cost model'!M437 -> 13.5 | G5: ='Cost model'!M438 -> 17.5 | H5: ='Cost model'!M439 -> 20.5 | J5: ='Cost model'!M452 -> 13.5 | K5: ='Cost model'!M453 -> 16.5 | L5: ='Cost model'!M454 -> 19.5 | N5: ='Cost model'!M467 -> 15.5 | O5: ='Cost model'!M468 -> 16.5 | P5: ='Cost model'!M469 -> 20.5 | R5: ='Cost model'!M482 -> 8.5 | S5: ='Cost model'!M483 -> 11.5 | T5: ='Cost model'!M484 -> 16.5 | V5: ='Cost model'!M497 -> 17.5 | W5: ='Cost model'!M498 -> 20.5 | X5: ='Cost model'!M499 -> 25.5 | Z5: ='Cost model'!M512 -> 11.5 | AA5: ='Cost model'!M513 -> 14.5 | AB5: ='Cost model'!M514 -> 17.5
A6: Medium | B6: ='Cost model'!M425 -> 14.5 | C6: ='Cost model'!M426 -> 21.5 | D6: ='Cost model'!M427 -> 28.5 | F6: ='Cost model'!M440 -> 45 | G6: ='Cost model'!M441 -> 55 | H6: ='Cost model'!M442 -> 60 | J6: ='Cost model'!M455 -> 45 | K6: ='Cost model'!M456 -> 50 | L6: ='Cost model'!M457 -> 55 | N6: ='Cost model'!M470 -> 45 | O6: ='Cost model'!M471 -> 55 | P6: ='Cost model'!M472 -> 60 | R6: ='Cost model'!M485 -> 40 | S6: ='Cost model'!M486 -> 45 | T6: ='Cost model'!M487 -> 55 | V6: ='Cost model'!M500 -> 55 | W6: ='Cost model'!M501 -> 60 | X6: ='Cost model'!M502 -> 70 | Z6: ='Cost model'!M515 -> 40 | AA6: ='Cost model'!M516 -> 45 | AB6: ='Cost model'!M517 -> 50
A7: Large | B7: ='Cost model'!M428 -> 23.5 | C7: ='Cost model'!M429 -> 40 | D7: ='Cost model'!M430 -> 50 | F7: ='Cost model'!M443 -> 70 | G7: ='Cost model'!M444 -> 85 | H7: ='Cost model'!M445 -> 115 | J7: ='Cost model'!M458 -> 75 | K7: ='Cost model'!M459 -> 90 | L7: ='Cost model'!M460 -> 135 | N7: ='Cost model'!M473 -> 80 | O7: ='Cost model'!M474 -> 90 | P7: ='Cost model'!M475 -> 125 | R7: ='Cost model'!M488 -> 60 | S7: ='Cost model'!M489 -> 70 | T7: ='Cost model'!M490 -> 100 | V7: ='Cost model'!M503 -> 105 | W7: ='Cost model'!M504 -> 115 | X7: ='Cost model'!M505 -> 155 | Z7: ='Cost model'!M518 -> 65 | AA7: ='Cost model'!M519 -> 75 | AB7: ='Cost model'!M520 -> 100
A8: XL | B8: ='Cost model'!M431 -> 45 | C8: ='Cost model'!M432 -> 60 | D8: ='Cost model'!M433 -> 75 | F8: ='Cost model'!M446 -> 120 | G8: ='Cost model'!M447 -> 155 | H8: ='Cost model'!M448 -> 195 | J8: ='Cost model'!M461 -> 130 | K8: ='Cost model'!M462 -> 165 | L8: ='Cost model'!M463 -> 205 | N8: ='Cost model'!M476 -> 130 | O8: ='Cost model'!M477 -> 165 | P8: ='Cost model'!M478 -> 210 | R8: ='Cost model'!M491 -> 105 | S8: ='Cost model'!M492 -> 130 | T8: ='Cost model'!M493 -> 165 | V8: ='Cost model'!M506 -> 170 | W8: ='Cost model'!M507 -> 210 | X8: ='Cost model'!M508 -> 265 | Z8: ='Cost model'!M521 -> 105 | AA8: ='Cost model'!M522 -> 135 | AB8: ='Cost model'!M523 -> 170
A9: XXL | B9: ='Cost model'!M434 -> 80 | C9: ='Cost model'!M435 -> 105 | D9: ='Cost model'!M436 -> 155 | F9: ='Cost model'!M449 -> 160 | G9: ='Cost model'!M450 -> 270 | H9: ='Cost model'!M451 -> 350 | J9: ='Cost model'!M464 -> 190 | K9: ='Cost model'!M465 -> 285 | L9: ='Cost model'!M466 -> 345 | N9: ='Cost model'!M479 -> 175 | O9: ='Cost model'!M480 -> 290 | P9: ='Cost model'!M481 -> 350 | R9: ='Cost model'!M494 -> 135 | S9: ='Cost model'!M495 -> 230 | T9: ='Cost model'!M496 -> 280 | V9: ='Cost model'!M509 -> 220 | W9: ='Cost model'!M510 -> 370 | X9: ='Cost model'!M511 -> 440 | Z9: ='Cost model'!M524 -> 140 | AA9: ='Cost model'!M525 -> 235 | AB9: ='Cost model'!M526 -> 285
A11: Priority | B11: From SA | F11: From VIC | J11: From QLD | N11: From WA | R11: From NSW | V11: From TAS | Z11: From ACT
A12: Freight Size | B12: Metro | C12: Metro Outer | D12: Regional | F12: Metro | G12: Metro Outer | H12: Regional | J12: Metro | K12: Metro Outer | L12: Regional | N12: Metro | O12: Metro Outer | P12: Regional | R12: Metro | S12: Metro Outer | T12: Regional | V12: Metro | W12: Metro Outer | X12: Regional | Z12: Metro | AA12: Metro Outer | AB12: Regional
A13: Small | B13: ='Cost model'!N422 -> 13.5 | C13: ='Cost model'!N423 -> 16.5 | D13: ='Cost model'!N424 -> 22.5 | F13: ='Cost model'!N437 -> 18.5 | G13: ='Cost model'!N438 -> 23.5 | H13: ='Cost model'!N439 -> 27.5 | J13: ='Cost model'!N452 -> 18.5 | K13: ='Cost model'!N453 -> 22.5 | L13: ='Cost model'!N454 -> 26.5 | N13: ='Cost model'!N467 -> 21.5 | O13: ='Cost model'!N468 -> 22.5 | P13: ='Cost model'!N469 -> 27.5 | R13: ='Cost model'!N482 -> 13.5 | S13: ='Cost model'!N483 -> 16.5 | T13: ='Cost model'!N484 -> 22.5 | V13: ='Cost model'!N497 -> 23.5 | W13: ='Cost model'!N498 -> 27.5 | X13: ='Cost model'!N499 -> 35 | Z13: ='Cost model'!N512 -> 16.5 | AA13: ='Cost model'!N513 -> 19.5 | AB13: ='Cost model'!N514 -> 23.5
A14: Medium | B14: ='Cost model'!N425 -> 19.5 | C14: ='Cost model'!N426 -> 27.5 | D14: ='Cost model'!N427 -> 40 | F14: ='Cost model'!N440 -> 60 | G14: ='Cost model'!N441 -> 70 | H14: ='Cost model'!N442 -> 80 | J14: ='Cost model'!N455 -> 60 | K14: ='Cost model'!N456 -> 65 | L14: ='Cost model'!N457 -> 70 | N14: ='Cost model'!N470 -> 60 | O14: ='Cost model'!N471 -> 70 | P14: ='Cost model'!N472 -> 80 | R14: ='Cost model'!N485 -> 55 | S14: ='Cost model'!N486 -> 60 | T14: ='Cost model'!N487 -> 70 | V14: ='Cost model'!N500 -> 70 | W14: ='Cost model'!N501 -> 80 | X14: ='Cost model'!N502 -> 90 | Z14: ='Cost model'!N515 -> 55 | AA14: ='Cost model'!N516 -> 60 | AB14: ='Cost model'!N517 -> 65
A15: Large | B15: ='Cost model'!N428 -> 35 | C15: ='Cost model'!N429 -> 55 | D15: ='Cost model'!N430 -> 70 | F15: ='Cost model'!N443 -> 95 | G15: ='Cost model'!N444 -> 115 | H15: ='Cost model'!N445 -> 160 | J15: ='Cost model'!N458 -> 105 | K15: ='Cost model'!N459 -> 125 | L15: ='Cost model'!N460 -> 185 | N15: ='Cost model'!N473 -> 110 | O15: ='Cost model'!N474 -> 125 | P15: ='Cost model'!N475 -> 170 | R15: ='Cost model'!N488 -> 85 | S15: ='Cost model'!N489 -> 95 | T15: ='Cost model'!N490 -> 135 | V15: ='Cost model'!N503 -> 145 | W15: ='Cost model'!N504 -> 160 | X15: ='Cost model'!N505 -> 210 | Z15: ='Cost model'!N518 -> 90 | AA15: ='Cost model'!N519 -> 105 | AB15: ='Cost model'!N520 -> 135
A16: XL | B16: ='Cost model'!N431 -> 55 | C16: ='Cost model'!N432 -> 75 | D16: ='Cost model'!N433 -> 90 | F16: ='Cost model'!N446 -> 145 | G16: ='Cost model'!N447 -> 190 | H16: ='Cost model'!N448 -> 235 | J16: ='Cost model'!N461 -> 160 | K16: ='Cost model'!N462 -> 200 | L16: ='Cost model'!N463 -> 250 | N16: ='Cost model'!N476 -> 160 | O16: ='Cost model'!N477 -> 200 | P16: ='Cost model'!N478 -> 255 | R16: ='Cost model'!N491 -> 130 | S16: ='Cost model'!N492 -> 160 | T16: ='Cost model'!N493 -> 200 | V16: ='Cost model'!N506 -> 205 | W16: ='Cost model'!N507 -> 255 | X16: ='Cost model'!N508 -> 320 | Z16: ='Cost model'!N521 -> 130 | AA16: ='Cost model'!N522 -> 165 | AB16: ='Cost model'!N523 -> 205
A17: XXL | B17: ='Cost model'!N434 -> 100 | C17: ='Cost model'!N435 -> 130 | D17: ='Cost model'!N436 -> 190 | F17: ='Cost model'!N449 -> 195 | J17: ='Cost model'!N464 -> 230 | N17: ='Cost model'!N479 -> 210 | R17: ='Cost model'!N494 -> 165 | V17: ='Cost model'!N509 -> 265 | Z17: ='Cost model'!N524 -> 170
A19: Delivery time frames for SA Orders
A21: Standard | B21: From SA | F21: From VIC | J21: From QLD | N21: From WA | R21: From NSW | V21: From TAS | Z21: From ACT
A22: Freight Size | B22: Metro | C22: Metro Outer | D22: Regional | F22: Metro | G22: Metro Outer | H22: Regional | J22: Metro | K22: Metro Outer | L22: Regional | N22: Metro | O22: Metro Outer | P22: Regional | R22: Metro | S22: Metro Outer | T22: Regional | V22: Metro | W22: Metro Outer | X22: Regional | Z22: Metro | AA22: Metro Outer | AB22: Regional
A23: Small | B23: 1-3 Days | C23: 1-3 Days | D23: 2-5 Days | F23: 2-5 Days | G23: 2-5 Days | H23: 3-7 Days | J23: 2-5 Days | K23: 2-5 Days | L23: 2-5 Days | N23: 7-14 Days | O23: 7-14 Days | P23: 7-14 Days | R23: 2-5 Days | S23: 2-5 Days | T23: 3-7 Days | V23: 7-14 Days | W23: 7-14 Days | X23: 7-14 Days | Z23: 7-14 Days | AA23: 7-14 Days | AB23: 7-14 Days
A24: Medium | B24: 1-3 Days | C24: 1-3 Days | D24: 2-5 Days | F24: 2-5 Days | G24: 2-5 Days | H24: 3-7 Days | J24: 2-5 Days | K24: 2-5 Days | L24: 2-5 Days | N24: 7-14 Days | O24: 7-14 Days | P24: 7-14 Days | R24: 2-5 Days | S24: 2-5 Days | T24: 3-7 Days | V24: 7-14 Days | W24: 7-14 Days | X24: 7-14 Days | Z24: 7-14 Days | AA24: 7-14 Days | AB24: 7-14 Days
A25: Large | B25: 1-3 Days | C25: 1-3 Days | D25: 3-7 Days | F25: 3-7 Days | G25: 3-7 Days | H25: 5-10 Days | J25: 3-7 Days | K25: 3-7 Days | L25: 5-10 Days | N25: 7-14 Days | O25: 7-14 Days | P25: 7-14 Days | R25: 3-7 Days | S25: 3-7 Days | T25: 5-10 Days | V25: 7-14 Days | W25: 7-14 Days | X25: 7-14 Days | Z25: 7-14 Days | AA25: 7-14 Days | AB25: 7-14 Days
A26: XL | B26: 1-3 Days | C26: 1-3 Days | D26: 5-10 Days | F26: 5-10 Days | G26: 5-10 Days | H26: 5-10 Days | J26: 5-10 Days | K26: 5-10 Days | L26: 5-10 Days | N26: 7-14 Days | O26: 7-14 Days | P26: 7-14 Days | R26: 5-10 Days | S26: 5-10 Days | T26: 5-10 Days | V26: 7-14 Days | W26: 7-14 Days | X26: 7-14 Days | Z26: 7-14 Days | AA26: 7-14 Days | AB26: 7-14 Days
A27: XXL | B27: 1-3 Days | C27: 1-3 Days | D27: 5-10 Days | F27: 5-10 Days | G27: 3-7 Days | H27: 5-10 Days | J27: 5-10 Days | K27: 3-7 Days | L27: 5-10 Days | N27: 7-14 Days | O27: 7-14 Days | P27: 7-14 Days | R27: 5-10 Days | S27: 3-7 Days | T27: 5-10 Days | V27: 7-14 Days | W27: 7-14 Days | X27: 7-14 Days | Z27: 7-14 Days | AA27: 7-14 Days | AB27: 7-14 Days
A29: Priority | B29: From SA | F29: From VIC | J29: From QLD | N29: From WA | R29: From NSW | V29: From TAS | Z29: From ACT
A30: Freight Size | B30: Metro | C30: Metro Outer | D30: Regional | F30: Metro | G30: Metro Outer | H30: Regional | J30: Metro | K30: Metro Outer | L30: Regional | N30: Metro | O30: Metro Outer | P30: Regional | R30: Metro | S30: Metro Outer | T30: Regional | V30: Metro | W30: Metro Outer | X30: Regional | Z30: Metro | AA30: Metro Outer | AB30: Regional
A31: Small | B31: 1-2 Days | C31: 1-2 Days | D31: 1-3 Days | F31: 1-2 Days | G31: 1-2 Days | H31: 2-5 Days | J31: 1-2 Days | K31: 1-2 Days | L31: 2-5 Days | N31: 1-2 Days | O31: 1-2 Days | P31: 2-5 Days | R31: 1-2 Days | S31: 1-2 Days | T31: 2-5 Days | V31: 1-2 Days | W31: 1-2 Days | X31: 2-5 Days | Z31: 1-2 Days | AA31: 1-2 Days | AB31: 2-5 Days
A32: Medium | B32: 1-2 Days | C32: 1-2 Days | D32: 1-3 Days | F32: 1-2 Days | G32: 1-2 Days | H32: 2-5 Days | J32: 1-2 Days | K32: 1-2 Days | L32: 2-5 Days | N32: 1-2 Days | O32: 1-2 Days | P32: 2-5 Days | R32: 1-2 Days | S32: 1-2 Days | T32: 2-5 Days | V32: 1-2 Days | W32: 1-2 Days | X32: 2-5 Days | Z32: 1-2 Days | AA32: 1-2 Days | AB32: 2-5 Days
A33: Large | B33: 1-2 Days | C33: 1-2 Days | D33: 2-7 Days | F33: 2-5 Days | G33: 2-5 Days | H33: 5-10 Days | J33: 2-5 Days | K33: 2-5 Days | L33: 5-10 Days | N33: 7-14 Days | O33: 7-14 Days | P33: 7-14 Days | R33: 2-5 Days | S33: 2-5 Days | T33: 5-10 Days | V33: 7-14 Days | W33: 7-14 Days | X33: 7-14 Days | Z33: 7-14 Days | AA33: 7-14 Days | AB33: 7-14 Days
A34: XL | B34: 1-2 Days | C34: 1-2 Days | D34: 2-7 Days | F34: 3-7 Days | G34: 3-7 Days | H34: 5-10 Days | J34: 3-7 Days | K34: 3-7 Days | L34: 5-10 Days | N34: 7-14 Days | O34: 7-14 Days | P34: 7-14 Days | R34: 3-7 Days | S34: 3-7 Days | T34: 5-10 Days | V34: 7-14 Days | W34: 7-14 Days | X34: 7-14 Days | Z34: 7-14 Days | AA34: 7-14 Days | AB34: 7-14 Days
A35: XXL | B35: 1-2 Days | C35: 1-2 Days | D35: 2-7 Days | F35: 3-7 Days | J35: 3-7 Days | N35: 7-14 Days | R35: 3-7 Days | V35: 7-14 Days | Z35: 7-14 Days

Sheet TAS
A1: Freight Charges for TAS Orders
A3: Standard | B3: From TAS | F3: From VIC | J3: From NSW | N3: From QLD | R3: From WA | V3: From ACT | Z3: From SA
A4: Freight Size | B4: Metro | C4: Metro Outer | D4: Regional | F4: Metro | G4: Metro Outer | H4: Regional | J4: Metro | K4: Metro Outer | L4: Regional | N4: Metro | O4: Metro Outer | P4: Regional | R4: Metro | S4: Metro Outer | T4: Regional | V4: Metro | W4: Metro Outer | X4: Regional | Z4: Metro | AA4: Metro Outer | AB4: Regional
A5: Small | B5: ='Cost model'!M527 -> 9.5 | C5: ='Cost model'!M528 -> 13.5 | D5: ='Cost model'!M529 -> 17.5 | F5: ='Cost model'!M542 -> 15.5 | G5: ='Cost model'!M543 -> 18.5 | H5: ='Cost model'!M544 -> 22.5 | J5: ='Cost model'!M557 -> 13.5 | K5: ='Cost model'!M558 -> 16.5 | L5: ='Cost model'!M559 -> 19.5 | N5: ='Cost model'!M572 -> 15.5 | O5: ='Cost model'!M573 -> 18.5 | P5: ='Cost model'!M574 -> 22.5 | R5: ='Cost model'!M587 -> 13.5 | S5: ='Cost model'!M588 -> 16.5 | T5: ='Cost model'!M589 -> 20.5 | V5: ='Cost model'!M602 -> 14.5 | W5: ='Cost model'!M603 -> 18.5 | X5: ='Cost model'!M604 -> 21.5 | Z5: ='Cost model'!M617 -> 14.5 | AA5: ='Cost model'!M618 -> 16.5 | AB5: ='Cost model'!M619 -> 20.5
A6: Medium | B6: ='Cost model'!M530 -> 28.5 | C6: ='Cost model'!M531 -> 50 | D6: ='Cost model'!M532 -> 55 | F6: ='Cost model'!M545 -> 55 | G6: ='Cost model'!M546 -> 60 | H6: ='Cost model'!M547 -> 65 | J6: ='Cost model'!M560 -> 45 | K6: ='Cost model'!M561 -> 55 | L6: ='Cost model'!M562 -> 60 | N6: ='Cost model'!M575 -> 60 | O6: ='Cost model'!M576 -> 70 | P6: ='Cost model'!M577 -> 75 | R6: ='Cost model'!M590 -> 45 | S6: ='Cost model'!M591 -> 55 | T6: ='Cost model'!M592 -> 60 | V6: ='Cost model'!M605 -> 40 | W6: ='Cost model'!M606 -> 50 | X6: ='Cost model'!M607 -> 55 | Z6: ='Cost model'!M620 -> 50 | AA6: ='Cost model'!M621 -> 60 | AB6: ='Cost model'!M622 -> 70
A7: Large | B7: ='Cost model'!M533 -> 55 | C7: ='Cost model'!M534 -> 85 | D7: ='Cost model'!M535 -> 105 | F7: ='Cost model'!M548 -> 80 | G7: ='Cost model'!M549 -> 100 | H7: ='Cost model'!M550 -> 125 | J7: ='Cost model'!M563 -> 75 | K7: ='Cost model'!M564 -> 85 | L7: ='Cost model'!M565 -> 120 | N7: ='Cost model'!M578 -> 80 | O7: ='Cost model'!M579 -> 90 | P7: ='Cost model'!M580 -> 125 | R7: ='Cost model'!M593 -> 80 | S7: ='Cost model'!M594 -> 90 | T7: ='Cost model'!M595 -> 125 | V7: ='Cost model'!M608 -> 75 | W7: ='Cost model'!M609 -> 85 | X7: ='Cost model'!M610 -> 115 | Z7: ='Cost model'!M623 -> 85 | AA7: ='Cost model'!M624 -> 100 | AB7: ='Cost model'!M625 -> 135
A8: XL | B8: ='Cost model'!M536 -> 110 | C8: ='Cost model'!M537 -> 155 | D8: ='Cost model'!M538 -> 185 | F8: ='Cost model'!M551 -> 130 | G8: ='Cost model'!M552 -> 160 | H8: ='Cost model'!M553 -> 215 | J8: ='Cost model'!M566 -> 125 | K8: ='Cost model'!M567 -> 160 | L8: ='Cost model'!M568 -> 205 | N8: ='Cost model'!M581 -> 135 | O8: ='Cost model'!M582 -> 170 | P8: ='Cost model'!M583 -> 215 | R8: ='Cost model'!M596 -> 130 | S8: ='Cost model'!M597 -> 170 | T8: ='Cost model'!M598 -> 215 | V8: ='Cost model'!M611 -> 125 | W8: ='Cost model'!M612 -> 160 | X8: ='Cost model'!M613 -> 200 | Z8: ='Cost model'!M626 -> 140 | AA8: ='Cost model'!M627 -> 190 | AB8: ='Cost model'!M628 -> 230
A9: XXL | B9: ='Cost model'!M539 -> 145 | C9: ='Cost model'!M540 -> 195 | D9: ='Cost model'!M541 -> 275 | F9: ='Cost model'!M554 -> 175 | G9: ='Cost model'!M555 -> 310 | H9: ='Cost model'!M556 -> 350 | J9: ='Cost model'!M569 -> 170 | K9: ='Cost model'!M570 -> 285 | L9: ='Cost model'!M571 -> 340 | N9: ='Cost model'!M584 -> 180 | O9: ='Cost model'!M585 -> 300 | P9: ='Cost model'!M586 -> 360 | R9: ='Cost model'!M599 -> 175 | S9: ='Cost model'!M600 -> 295 | T9: ='Cost model'!M601 -> 355 | V9: ='Cost model'!M614 -> 165 | W9: ='Cost model'!M615 -> 280 | X9: ='Cost model'!M616 -> 330 | Z9: ='Cost model'!M629 -> 190 | AA9: ='Cost model'!M630 -> 320 | AB9: ='Cost model'!M631 -> 380
A11: Priority | B11: From TAS | F11: From VIC | J11: From NSW | N11: From QLD | R11: From WA | V11: From ACT | Z11: From SA
A12: Freight Size | B12: Metro | C12: Metro Outer | D12: Regional | F12: Metro | G12: Metro Outer | H12: Regional | J12: Metro | K12: Metro Outer | L12: Regional | N12: Metro | O12: Metro Outer | P12: Regional | R12: Metro | S12: Metro Outer | T12: Regional | V12: Metro | W12: Metro Outer | X12: Regional | Z12: Metro | AA12: Metro Outer | AB12: Regional
A13: Small | B13: ='Cost model'!N527 -> 14.5 | C13: ='Cost model'!N528 -> 18.5 | D13: ='Cost model'!N529 -> 23.5 | F13: ='Cost model'!N542 -> 21.5 | G13: ='Cost model'!N543 -> 25.5 | H13: ='Cost model'!N544 -> 35 | J13: ='Cost model'!N557 -> 18.5 | K13: ='Cost model'!N558 -> 22.5 | L13: ='Cost model'!N559 -> 26.5 | N13: ='Cost model'!N572 -> 21.5 | O13: ='Cost model'!N573 -> 25.5 | P13: ='Cost model'!N574 -> 35 | R13: ='Cost model'!N587 -> 18.5 | S13: ='Cost model'!N588 -> 22.5 | T13: ='Cost model'!N589 -> 27.5 | V13: ='Cost model'!N602 -> 19.5 | W13: ='Cost model'!N603 -> 25.5 | X13: ='Cost model'!N604 -> 29.5 | Z13: ='Cost model'!N617 -> 19.5 | AA13: ='Cost model'!N618 -> 22.5 | AB13: ='Cost model'!N619 -> 27.5
A14: Medium | B14: ='Cost model'!N530 -> 40 | C14: ='Cost model'!N531 -> 65 | D14: ='Cost model'!N532 -> 70 | F14: ='Cost model'!N545 -> 70 | G14: ='Cost model'!N546 -> 80 | H14: ='Cost model'!N547 -> 85 | J14: ='Cost model'!N560 -> 60 | K14: ='Cost model'!N561 -> 70 | L14: ='Cost model'!N562 -> 80 | N14: ='Cost model'!N575 -> 80 | O14: ='Cost model'!N576 -> 90 | P14: ='Cost model'!N577 -> 95 | R14: ='Cost model'!N590 -> 60 | S14: ='Cost model'!N591 -> 70 | T14: ='Cost model'!N592 -> 80 | V14: ='Cost model'!N605 -> 55 | W14: ='Cost model'!N606 -> 65 | X14: ='Cost model'!N607 -> 70 | Z14: ='Cost model'!N620 -> 65 | AA14: ='Cost model'!N621 -> 80 | AB14: ='Cost model'!N622 -> 90
A15: Large | B15: ='Cost model'!N533 -> 75 | C15: ='Cost model'!N534 -> 115 | D15: ='Cost model'!N535 -> 145 | F15: ='Cost model'!N548 -> 110 | G15: ='Cost model'!N549 -> 135 | H15: ='Cost model'!N550 -> 170 | J15: ='Cost model'!N563 -> 105 | K15: ='Cost model'!N564 -> 115 | L15: ='Cost model'!N565 -> 165 | N15: ='Cost model'!N578 -> 110 | O15: ='Cost model'!N579 -> 125 | P15: ='Cost model'!N580 -> 170 | R15: ='Cost model'!N593 -> 110 | S15: ='Cost model'!N594 -> 125 | T15: ='Cost model'!N595 -> 170 | V15: ='Cost model'!N608 -> 105 | W15: ='Cost model'!N609 -> 115 | X15: ='Cost model'!N610 -> 160 | Z15: ='Cost model'!N623 -> 115 | AA15: ='Cost model'!N624 -> 135 | AB15: ='Cost model'!N625 -> 185
A16: XL | B16: ='Cost model'!N536 -> 135 | C16: ='Cost model'!N537 -> 190 | D16: ='Cost model'!N538 -> 225 | F16: ='Cost model'!N551 -> 160 | G16: ='Cost model'!N552 -> 195 | H16: ='Cost model'!N553 -> 260 | J16: ='Cost model'!N566 -> 150 | K16: ='Cost model'!N567 -> 195 | L16: ='Cost model'!N568 -> 250 | N16: ='Cost model'!N581 -> 165 | O16: ='Cost model'!N582 -> 205 | P16: ='Cost model'!N583 -> 260 | R16: ='Cost model'!N596 -> 160 | S16: ='Cost model'!N597 -> 205 | T16: ='Cost model'!N598 -> 260 | V16: ='Cost model'!N611 -> 150 | W16: ='Cost model'!N612 -> 195 | X16: ='Cost model'!N613 -> 240 | Z16: ='Cost model'!N626 -> 170 | AA16: ='Cost model'!N627 -> 230 | AB16: ='Cost model'!N628 -> 280
A17: XXL | B17: ='Cost model'!N539 -> 175 | C17: ='Cost model'!N540 -> 235 | D17: ='Cost model'!N541 -> 330 | F17: ='Cost model'!N554 -> 210 | J17: ='Cost model'!N569 -> 205 | N17: ='Cost model'!N584 -> 220 | R17: ='Cost model'!N599 -> 210 | V17: ='Cost model'!N614 -> 200 | Z17: ='Cost model'!N629 -> 230
A19: Delivery time frames for TAS Orders
A21: Standard | B21: From TAS | F21: From VIC | J21: From NSW | N21: From QLD | R21: From WA | V21: From ACT | Z21: From SA
A22: Freight Size | B22: Metro | C22: Metro Outer | D22: Regional | F22: Metro | G22: Metro Outer | H22: Regional | J22: Metro | K22: Metro Outer | L22: Regional | N22: Metro | O22: Metro Outer | P22: Regional | R22: Metro | S22: Metro Outer | T22: Regional | V22: Metro | W22: Metro Outer | X22: Regional | Z22: Metro | AA22: Metro Outer | AB22: Regional
A23: Small | B23: 1-3 Days | C23: 1-3 Days | D23: 2-5 Days | F23: 2-5 Days | G23: 2-5 Days | H23: 3-7 Days | J23: 2-5 Days | K23: 2-5 Days | L23: 2-5 Days | N23: 7-14 Days | O23: 7-14 Days | P23: 7-14 Days | R23: 2-5 Days | S23: 2-5 Days | T23: 3-7 Days | V23: 2-5 Days | W23: 2-5 Days | X23: 3-7 Days | Z23: 2-5 Days | AA23: 2-5 Days | AB23: 3-7 Days
A24: Medium | B24: 1-3 Days | C24: 1-3 Days | D24: 2-5 Days | F24: 2-5 Days | G24: 2-5 Days | H24: 3-7 Days | J24: 2-5 Days | K24: 2-5 Days | L24: 2-5 Days | N24: 7-14 Days | O24: 7-14 Days | P24: 7-14 Days | R24: 2-5 Days | S24: 2-5 Days | T24: 3-7 Days | V24: 2-5 Days | W24: 2-5 Days | X24: 3-7 Days | Z24: 2-5 Days | AA24: 2-5 Days | AB24: 3-7 Days
A25: Large | B25: 1-3 Days | C25: 1-3 Days | D25: 3-7 Days | F25: 3-7 Days | G25: 3-7 Days | H25: 5-10 Days | J25: 3-7 Days | K25: 3-7 Days | L25: 5-10 Days | N25: 7-14 Days | O25: 7-14 Days | P25: 7-14 Days | R25: 3-7 Days | S25: 3-7 Days | T25: 5-10 Days | V25: 3-7 Days | W25: 3-7 Days | X25: 5-10 Days | Z25: 3-7 Days | AA25: 3-7 Days | AB25: 5-10 Days
A26: XL | B26: 1-3 Days | C26: 1-3 Days | D26: 5-10 Days | F26: 5-10 Days | G26: 5-10 Days | H26: 5-10 Days | J26: 5-10 Days | K26: 5-10 Days | L26: 5-10 Days | N26: 7-14 Days | O26: 7-14 Days | P26: 7-14 Days | R26: 5-10 Days | S26: 5-10 Days | T26: 5-10 Days | V26: 5-10 Days | W26: 5-10 Days | X26: 5-10 Days | Z26: 5-10 Days | AA26: 5-10 Days | AB26: 5-10 Days
A27: XXL | B27: 1-3 Days | C27: 1-3 Days | D27: 5-10 Days | F27: 5-10 Days | G27: 3-7 Days | H27: 5-10 Days | J27: 5-10 Days | K27: 3-7 Days | L27: 5-10 Days | N27: 7-14 Days | O27: 7-14 Days | P27: 7-14 Days | R27: 5-10 Days | S27: 3-7 Days | T27: 5-10 Days | V27: 5-10 Days | W27: 3-7 Days | X27: 5-10 Days | Z27: 5-10 Days | AA27: 3-7 Days | AB27: 5-10 Days
A29: Priority | B29: From TAS | F29: From VIC | J29: From NSW | N29: From QLD | R29: From WA | V29: From ACT | Z29: From SA
A30: Freight Size | B30: Metro | C30: Metro Outer | D30: Regional | F30: Metro | G30: Metro Outer | H30: Regional | J30: Metro | K30: Metro Outer | L30: Regional | N30: Metro | O30: Metro Outer | P30: Regional | R30: Metro | S30: Metro Outer | T30: Regional | V30: Metro | W30: Metro Outer | X30: Regional | Z30: Metro | AA30: Metro Outer | AB30: Regional
A31: Small | B31: 1-2 Days | C31: 1-2 Days | D31: 1-3 Days | F31: 1-2 Days | G31: 1-2 Days | H31: 2-5 Days | J31: 1-2 Days | K31: 1-2 Days | L31: 2-5 Days | N31: 1-2 Days | O31: 1-2 Days | P31: 2-5 Days | R31: 1-2 Days | S31: 1-2 Days | T31: 2-5 Days | V31: 1-2 Days | W31: 1-2 Days | X31: 2-5 Days | Z31: 1-2 Days | AA31: 1-2 Days | AB31: 2-5 Days
A32: Medium | B32: 1-2 Days | C32: 1-2 Days | D32: 1-3 Days | F32: 1-2 Days | G32: 1-2 Days | H32: 2-5 Days | J32: 1-2 Days | K32: 1-2 Days | L32: 2-5 Days | N32: 1-2 Days | O32: 1-2 Days | P32: 2-5 Days | R32: 1-2 Days | S32: 1-2 Days | T32: 2-5 Days | V32: 1-2 Days | W32: 1-2 Days | X32: 2-5 Days | Z32: 1-2 Days | AA32: 1-2 Days | AB32: 2-5 Days
A33: Large | B33: 1-2 Days | C33: 1-2 Days | D33: 2-7 Days | F33: 2-5 Days | G33: 2-5 Days | H33: 5-10 Days | J33: 2-5 Days | K33: 2-5 Days | L33: 5-10 Days | N33: 7-14 Days | O33: 7-14 Days | P33: 7-14 Days | R33: 2-5 Days | S33: 2-5 Days | T33: 5-10 Days | V33: 2-5 Days | W33: 2-5 Days | X33: 5-10 Days | Z33: 2-5 Days | AA33: 2-5 Days | AB33: 5-10 Days
A34: XL | B34: 1-2 Days | C34: 1-2 Days | D34: 2-7 Days | F34: 3-7 Days | G34: 3-7 Days | H34: 5-10 Days | J34: 3-7 Days | K34: 3-7 Days | L34: 5-10 Days | N34: 7-14 Days | O34: 7-14 Days | P34: 7-14 Days | R34: 3-7 Days | S34: 3-7 Days | T34: 5-10 Days | V34: 3-7 Days | W34: 3-7 Days | X34: 5-10 Days | Z34: 3-7 Days | AA34: 3-7 Days | AB34: 5-10 Days
A35: XXL | B35: 1-2 Days | C35: 1-2 Days | D35: 2-7 Days | F35: 3-7 Days | J35: 3-7 Days | N35: 7-14 Days | R35: 3-7 Days | V35: 3-7 Days | Z35: 3-7 Days

Sheet VIC
A1: Freight Charges for VIC Orders
A3: Standard | B3: From VIC | F3: From SA | J3: From QLD | N3: From WA | R3: From NSW | V3: From TAS | Z3: From ACT
A4: Freight Size | B4: Metro | C4: Metro Outer | D4: Regional | F4: Metro | G4: Metro Outer | H4: Regional | J4: Metro | K4: Metro Outer | L4: Regional | N4: Metro | O4: Metro Outer | P4: Regional | R4: Metro | S4: Metro Outer | T4: Regional | V4: Metro | W4: Metro Outer | X4: Regional | Z4: Metro | AA4: Metro Outer | AB4: Regional
A5: Small | B5: ='Cost model'!M632 -> 9.5 | C5: ='Cost model'!M633 -> 11.5 | D5: ='Cost model'!M634 -> 15.5 | F5: ='Cost model'!M647 -> 13.5 | G5: ='Cost model'!M648 -> 13.5 | H5: ='Cost model'!M649 -> 19.5 | J5: ='Cost model'!M662 -> 13.5 | K5: ='Cost model'!M663 -> 18.5 | L5: ='Cost model'!M664 -> 19.5 | N5: ='Cost model'!M677 -> 13.5 | O5: ='Cost model'!M678 -> 16.5 | P5: ='Cost model'!M679 -> 19.5 | R5: ='Cost model'!M692 -> 9.5 | S5: ='Cost model'!M693 -> 11.5 | T5: ='Cost model'!M694 -> 17.5 | V5: ='Cost model'!M707 -> 11.5 | W5: ='Cost model'!M708 -> 15.5 | X5: ='Cost model'!M709 -> 15.5 | Z5: ='Cost model'!M722 -> 12.5 | AA5: ='Cost model'!M723 -> 15.5 | AB5: ='Cost model'!M724 -> 18.5
A6: Medium | B6: ='Cost model'!M635 -> 30.5 | C6: ='Cost model'!M636 -> 40 | D6: ='Cost model'!M637 -> 45 | F6: ='Cost model'!M650 -> 40 | G6: ='Cost model'!M651 -> 45 | H6: ='Cost model'!M652 -> 55 | J6: ='Cost model'!M665 -> 40 | K6: ='Cost model'!M666 -> 45 | L6: ='Cost model'!M667 -> 55 | N6: ='Cost model'!M680 -> 50 | O6: ='Cost model'!M681 -> 60 | P6: ='Cost model'!M682 -> 65 | R6: ='Cost model'!M695 -> 40 | S6: ='Cost model'!M696 -> 45 | T6: ='Cost model'!M697 -> 55 | V6: ='Cost model'!M710 -> 45 | W6: ='Cost model'!M711 -> 50 | X6: ='Cost model'!M712 -> 50 | Z6: ='Cost model'!M725 -> 40 | AA6: ='Cost model'!M726 -> 45 | AB6: ='Cost model'!M727 -> 50
A7: Large | B7: ='Cost model'!M638 -> 50 | C7: ='Cost model'!M639 -> 60 | D7: ='Cost model'!M640 -> 65 | F7: ='Cost model'!M653 -> 70 | G7: ='Cost model'!M654 -> 70 | H7: ='Cost model'!M655 -> 95 | J7: ='Cost model'!M668 -> 75 | K7: ='Cost model'!M669 -> 85 | L7: ='Cost model'!M670 -> 120 | N7: ='Cost model'!M683 -> 85 | O7: ='Cost model'!M684 -> 95 | P7: ='Cost model'!M685 -> 130 | R7: ='Cost model'!M698 -> 70 | S7: ='Cost model'!M699 -> 85 | T7: ='Cost model'!M700 -> 100 | V7: ='Cost model'!M713 -> 70 | W7: ='Cost model'!M714 -> 85 | X7: ='Cost model'!M715 -> 110 | Z7: ='Cost model'!M728 -> 65 | AA7: ='Cost model'!M729 -> 75 | AB7: ='Cost model'!M730 -> 105
A8: XL | B8: ='Cost model'!M641 -> 75 | C8: ='Cost model'!M642 -> 90 | D8: ='Cost model'!M643 -> 110 | F8: ='Cost model'!M656 -> 100 | G8: ='Cost model'!M657 -> 140 | H8: ='Cost model'!M658 -> 165 | J8: ='Cost model'!M671 -> 125 | K8: ='Cost model'!M672 -> 155 | L8: ='Cost model'!M673 -> 180 | N8: ='Cost model'!M686 -> 140 | O8: ='Cost model'!M687 -> 175 | P8: ='Cost model'!M688 -> 220 | R8: ='Cost model'!M701 -> 110 | S8: ='Cost model'!M702 -> 130 | T8: ='Cost model'!M703 -> 175 | V8: ='Cost model'!M716 -> 120 | W8: ='Cost model'!M717 -> 150 | X8: ='Cost model'!M718 -> 195 | Z8: ='Cost model'!M731 -> 110 | AA8: ='Cost model'!M732 -> 155 | AB8: ='Cost model'!M733 -> 180
A9: XXL | B9: ='Cost model'!M644 -> 105 | C9: ='Cost model'!M645 -> 135 | D9: ='Cost model'!M646 -> 185 | F9: ='Cost model'!M659 -> 140 | G9: ='Cost model'!M660 -> 240 | H9: ='Cost model'!M661 -> 285 | J9: ='Cost model'!M674 -> 155 | K9: ='Cost model'!M675 -> 295 | L9: ='Cost model'!M676 -> 320 | N9: ='Cost model'!M689 -> 185 | O9: ='Cost model'!M690 -> 310 | P9: ='Cost model'!M691 -> 370 | R9: ='Cost model'!M704 -> 150 | S9: ='Cost model'!M705 -> 235 | T9: ='Cost model'!M706 -> 280 | V9: ='Cost model'!M719 -> 180 | W9: ='Cost model'!M720 -> 265 | X9: ='Cost model'!M721 -> 320 | Z9: ='Cost model'!M734 -> 145 | AA9: ='Cost model'!M735 -> 240 | AB9: ='Cost model'!M736 -> 290
A11: Priority | B11: From VIC | F11: From SA | J11: From QLD | N11: From WA | R11: From NSW | V11: From TAS | Z11: From ACT
A12: Freight Size | B12: Metro | C12: Metro Outer | D12: Regional | F12: Metro | G12: Metro Outer | H12: Regional | J12: Metro | K12: Metro Outer | L12: Regional | N12: Metro | O12: Metro Outer | P12: Regional | R12: Metro | S12: Metro Outer | T12: Regional | V12: Metro | W12: Metro Outer | X12: Regional | Z12: Metro | AA12: Metro Outer | AB12: Regional
A13: Small | B13: ='Cost model'!N632 -> 14.5 | C13: ='Cost model'!N633 -> 16.5 | D13: ='Cost model'!N634 -> 21.5 | F13: ='Cost model'!N647 -> 18.5 | G13: ='Cost model'!N648 -> 18.5 | H13: ='Cost model'!N649 -> 26.5 | J13: ='Cost model'!N662 -> 18.5 | K13: ='Cost model'!N663 -> 25.5 | L13: ='Cost model'!N664 -> 26.5 | N13: ='Cost model'!N677 -> 18.5 | O13: ='Cost model'!N678 -> 22.5 | P13: ='Cost model'!N679 -> 26.5 | R13: ='Cost model'!N692 -> 14.5 | S13: ='Cost model'!N693 -> 16.5 | T13: ='Cost model'!N694 -> 23.5 | V13: ='Cost model'!N707 -> 16.5 | W13: ='Cost model'!N708 -> 21.5 | X13: ='Cost model'!N709 -> 21.5 | Z13: ='Cost model'!N722 -> 17.5 | AA13: ='Cost model'!N723 -> 21.5 | AB13: ='Cost model'!N724 -> 25.5
A14: Medium | B14: ='Cost model'!N635 -> 40 | C14: ='Cost model'!N636 -> 55 | D14: ='Cost model'!N637 -> 60 | F14: ='Cost model'!N650 -> 55 | G14: ='Cost model'!N651 -> 60 | H14: ='Cost model'!N652 -> 70 | J14: ='Cost model'!N665 -> 55 | K14: ='Cost model'!N666 -> 60 | L14: ='Cost model'!N667 -> 70 | N14: ='Cost model'!N680 -> 65 | O14: ='Cost model'!N681 -> 80 | P14: ='Cost model'!N682 -> 85 | R14: ='Cost model'!N695 -> 55 | S14: ='Cost model'!N696 -> 60 | T14: ='Cost model'!N697 -> 70 | V14: ='Cost model'!N710 -> 60 | W14: ='Cost model'!N711 -> 65 | X14: ='Cost model'!N712 -> 65 | Z14: ='Cost model'!N725 -> 55 | AA14: ='Cost model'!N726 -> 60 | AB14: ='Cost model'!N727 -> 65
A15: Large | B15: ='Cost model'!N638 -> 70 | C15: ='Cost model'!N639 -> 85 | D15: ='Cost model'!N640 -> 90 | F15: ='Cost model'!N653 -> 95 | G15: ='Cost model'!N654 -> 95 | H15: ='Cost model'!N655 -> 130 | J15: ='Cost model'!N668 -> 105 | K15: ='Cost model'!N669 -> 115 | L15: ='Cost model'!N670 -> 165 | N15: ='Cost model'!N683 -> 115 | O15: ='Cost model'!N684 -> 130 | P15: ='Cost model'!N685 -> 180 | R15: ='Cost model'!N698 -> 95 | S15: ='Cost model'!N699 -> 115 | T15: ='Cost model'!N700 -> 135 | V15: ='Cost model'!N713 -> 95 | W15: ='Cost model'!N714 -> 115 | X15: ='Cost model'!N715 -> 150 | Z15: ='Cost model'!N728 -> 90 | AA15: ='Cost model'!N729 -> 105 | AB15: ='Cost model'!N730 -> 145
A16: XL | B16: ='Cost model'!N641 -> 90 | C16: ='Cost model'!N642 -> 110 | D16: ='Cost model'!N643 -> 135 | F16: ='Cost model'!N656 -> 120 | G16: ='Cost model'!N657 -> 170 | H16: ='Cost model'!N658 -> 200 | J16: ='Cost model'!N671 -> 150 | K16: ='Cost model'!N672 -> 190 | L16: ='Cost model'!N673 -> 220 | N16: ='Cost model'!N686 -> 170 | O16: ='Cost model'!N687 -> 210 | P16: ='Cost model'!N688 -> 265 | R16: ='Cost model'!N701 -> 135 | S16: ='Cost model'!N702 -> 160 | T16: ='Cost model'!N703 -> 210 | V16: ='Cost model'!N716 -> 145 | W16: ='Cost model'!N717 -> 180 | X16: ='Cost model'!N718 -> 235 | Z16: ='Cost model'!N731 -> 135 | AA16: ='Cost model'!N732 -> 190 | AB16: ='Cost model'!N733 -> 220
A17: XXL | B17: ='Cost model'!N644 -> 130 | C17: ='Cost model'!N645 -> 165 | D17: ='Cost model'!N646 -> 225 | F17: ='Cost model'!N659 -> 170 | J17: ='Cost model'!N674 -> 190 | N17: ='Cost model'!N689 -> 225 | R17: ='Cost model'!N704 -> 180 | V17: ='Cost model'!N719 -> 220 | Z17: ='Cost model'!N734 -> 175
A19: Delivery time frames for VIC Orders
A21: Standard | B21: From VIC | F21: From SA | J21: From QLD | N21: From WA | R21: From NSW | V21: From TAS | Z21: From ACT
A22: Freight Size | B22: Metro | C22: Metro Outer | D22: Regional | F22: Metro | G22: Metro Outer | H22: Regional | J22: Metro | K22: Metro Outer | L22: Regional | N22: Metro | O22: Metro Outer | P22: Regional | R22: Metro | S22: Metro Outer | T22: Regional | V22: Metro | W22: Metro Outer | X22: Regional | Z22: Metro | AA22: Metro Outer | AB22: Regional
A23: Small | B23: 1-3 Days | C23: 1-3 Days | D23: 2-5 Days | F23: 2-5 Days | G23: 2-5 Days | H23: 3-7 Days | J23: 2-5 Days | K23: 2-5 Days | L23: 2-5 Days | N23: 7-14 Days | O23: 7-14 Days | P23: 7-14 Days | R23: 2-5 Days | S23: 2-5 Days | T23: 2-5 Days | V23: 7-14 Days | W23: 7-14 Days | X23: 7-14 Days | Z23: 7-14 Days | AA23: 7-14 Days | AB23: 7-14 Days
A24: Medium | B24: 1-3 Days | C24: 1-3 Days | D24: 2-5 Days | F24: 2-5 Days | G24: 2-5 Days | H24: 3-7 Days | J24: 2-5 Days | K24: 2-5 Days | L24: 2-5 Days | N24: 7-14 Days | O24: 7-14 Days | P24: 7-14 Days | R24: 2-5 Days | S24: 2-5 Days | T24: 2-5 Days | V24: 7-14 Days | W24: 7-14 Days | X24: 7-14 Days | Z24: 7-14 Days | AA24: 7-14 Days | AB24: 7-14 Days
A25: Large | B25: 1-3 Days | C25: 1-3 Days | D25: 3-7 Days | F25: 3-7 Days | G25: 3-7 Days | H25: 5-10 Days | J25: 3-7 Days | K25: 3-7 Days | L25: 5-10 Days | N25: 7-14 Days | O25: 7-14 Days | P25: 7-14 Days | R25: 3-7 Days | S25: 3-7 Days | T25: 5-10 Days | V25: 7-14 Days | W25: 7-14 Days | X25: 7-14 Days | Z25: 7-14 Days | AA25: 7-14 Days | AB25: 7-14 Days
A26: XL | B26: 1-3 Days | C26: 1-3 Days | D26: 5-10 Days | F26: 5-10 Days | G26: 5-10 Days | H26: 5-10 Days | J26: 5-10 Days | K26: 5-10 Days | L26: 5-10 Days | N26: 7-14 Days | O26: 7-14 Days | P26: 7-14 Days | R26: 5-10 Days | S26: 5-10 Days | T26: 5-10 Days | V26: 7-14 Days | W26: 7-14 Days | X26: 7-14 Days | Z26: 7-14 Days | AA26: 7-14 Days | AB26: 7-14 Days
A27: XXL | B27: 1-3 Days | C27: 1-3 Days | D27: 5-10 Days | F27: 5-10 Days | G27: 3-7 Days | H27: 5-10 Days | J27: 5-10 Days | K27: 3-7 Days | L27: 5-10 Days | N27: 7-14 Days | O27: 7-14 Days | P27: 7-14 Days | R27: 5-10 Days | S27: 3-7 Days | T27: 5-10 Days | V27: 7-14 Days | W27: 7-14 Days | X27: 7-14 Days | Z27: 7-14 Days | AA27: 7-14 Days | AB27: 7-14 Days
A29: Priority | B29: From VIC | F29: From SA | J29: From QLD | N29: From WA | R29: From NSW | V29: From TAS | Z29: From ACT
A30: Freight Size | B30: Metro | C30: Metro Outer | D30: Regional | F30: Metro | G30: Metro Outer | H30: Regional | J30: Metro | K30: Metro Outer | L30: Regional | N30: Metro | O30: Metro Outer | P30: Regional | R30: Metro | S30: Metro Outer | T30: Regional | V30: Metro | W30: Metro Outer | X30: Regional | Z30: Metro | AA30: Metro Outer | AB30: Regional
A31: Small | B31: 1-2 Days | C31: 1-2 Days | D31: 1-3 Days | F31: 1-2 Days | G31: 1-2 Days | H31: 2-5 Days | J31: 1-2 Days | K31: 1-2 Days | L31: 2-5 Days | N31: 1-2 Days | O31: 1-2 Days | P31: 2-5 Days | R31: 1-2 Days | S31: 1-2 Days | T31: 2-5 Days | V31: 1-2 Days | W31: 1-2 Days | X31: 2-5 Days | Z31: 1-2 Days | AA31: 1-2 Days | AB31: 2-5 Days
A32: Medium | B32: 1-2 Days | C32: 1-2 Days | D32: 1-3 Days | F32: 1-2 Days | G32: 1-2 Days | H32: 2-5 Days | J32: 1-2 Days | K32: 1-2 Days | L32: 2-5 Days | N32: 1-2 Days | O32: 1-2 Days | P32: 2-5 Days | R32: 1-2 Days | S32: 1-2 Days | T32: 2-5 Days | V32: 1-2 Days | W32: 1-2 Days | X32: 2-5 Days | Z32: 1-2 Days | AA32: 1-2 Days | AB32: 2-5 Days
A33: Large | B33: 1-2 Days | C33: 1-2 Days | D33: 2-7 Days | F33: 2-5 Days | G33: 2-5 Days | H33: 5-10 Days | J33: 2-5 Days | K33: 2-5 Days | L33: 5-10 Days | N33: 7-14 Days | O33: 7-14 Days | P33: 7-14 Days | R33: 2-5 Days | S33: 2-5 Days | T33: 5-10 Days | V33: 7-14 Days | W33: 7-14 Days | X33: 7-14 Days | Z33: 7-14 Days | AA33: 7-14 Days | AB33: 7-14 Days
A34: XL | B34: 1-2 Days | C34: 1-2 Days | D34: 2-7 Days | F34: 3-7 Days | G34: 3-7 Days | H34: 5-10 Days | J34: 3-7 Days | K34: 3-7 Days | L34: 5-10 Days | N34: 7-14 Days | O34: 7-14 Days | P34: 7-14 Days | R34: 3-7 Days | S34: 3-7 Days | T34: 5-10 Days | V34: 7-14 Days | W34: 7-14 Days | X34: 7-14 Days | Z34: 7-14 Days | AA34: 7-14 Days | AB34: 7-14 Days
A35: XXL | B35: 1-2 Days | C35: 1-2 Days | D35: 2-7 Days | F35: 3-7 Days | J35: 3-7 Days | N35: 7-14 Days | R35: 3-7 Days | V35: 7-14 Days | Z35: 7-14 Days

Sheet WA
A1: Freight Charges for WA Orders
A3: Standard | B3: From WA | F3: From SA | J3: From VIC | N3: From NSW | R3: From QLD | V3: From ACT | Z3: From TAS
A4: Freight Size | B4: Metro | C4: Metro Outer | D4: Regional | F4: Metro | G4: Metro Outer | H4: Regional | J4: Metro | K4: Metro Outer | L4: Regional | N4: Metro | O4: Metro Outer | P4: Regional | R4: Metro | S4: Metro Outer | T4: Regional | V4: Metro | W4: Metro Outer | X4: Regional | Z4: Metro | AA4: Metro Outer | AB4: Regional
A5: Small | B5: ='Cost model'!M737 -> 8.5 | C5: ='Cost model'!M738 -> 11.5 | D5: ='Cost model'!M739 -> 17.5 | F5: ='Cost model'!M752 -> 12.5 | G5: ='Cost model'!M753 -> 23.5 | H5: ='Cost model'!M754 -> 23.5 | J5: ='Cost model'!M767 -> 15.5 | K5: ='Cost model'!M768 -> 19.5 | L5: ='Cost model'!M769 -> 24.5 | N5: ='Cost model'!M782 -> 11.5 | O5: ='Cost model'!M783 -> 12.5 | P5: ='Cost model'!M784 -> 19.5 | R5: ='Cost model'!M797 -> 14.5 | S5: ='Cost model'!M798 -> 20.5 | T5: ='Cost model'!M799 -> 20.5 | V5: ='Cost model'!M812 -> 25.5 | W5: ='Cost model'!M813 -> 25.5 | X5: ='Cost model'!M814 -> 27.5 | Z5: ='Cost model'!M827 -> 12.5 | AA5: ='Cost model'!M828 -> 16.5 | AB5: ='Cost model'!M829 -> 20.5
A6: Medium | B6: ='Cost model'!M740 -> 22.5 | C6: ='Cost model'!M741 -> 45 | D6: ='Cost model'!M742 -> 60 | F6: ='Cost model'!M755 -> 50 | G6: ='Cost model'!M756 -> 60 | H6: ='Cost model'!M757 -> 65 | J6: ='Cost model'!M770 -> 55 | K6: ='Cost model'!M771 -> 60 | L6: ='Cost model'!M772 -> 70 | N6: ='Cost model'!M785 -> 50 | O6: ='Cost model'!M786 -> 55 | P6: ='Cost model'!M787 -> 65 | R6: ='Cost model'!M800 -> 45 | S6: ='Cost model'!M801 -> 50 | T6: ='Cost model'!M802 -> 60 | V6: ='Cost model'!M815 -> 60 | W6: ='Cost model'!M816 -> 65 | X6: ='Cost model'!M817 -> 70 | Z6: ='Cost model'!M830 -> 60 | AA6: ='Cost model'!M831 -> 65 | AB6: ='Cost model'!M832 -> 70
A7: Large | B7: ='Cost model'!M743 -> 45 | C7: ='Cost model'!M744 -> 80 | D7: ='Cost model'!M745 -> 130 | F7: ='Cost model'!M758 -> 80 | G7: ='Cost model'!M759 -> 100 | H7: ='Cost model'!M760 -> 150 | J7: ='Cost model'!M773 -> 95 | K7: ='Cost model'!M774 -> 100 | L7: ='Cost model'!M775 -> 155 | N7: ='Cost model'!M788 -> 85 | O7: ='Cost model'!M789 -> 95 | P7: ='Cost model'!M790 -> 130 | R7: ='Cost model'!M803 -> 120 | S7: ='Cost model'!M804 -> 120 | T7: ='Cost model'!M805 -> 145 | V7: ='Cost model'!M818 -> 95 | W7: ='Cost model'!M819 -> 110 | X7: ='Cost model'!M820 -> 145 | Z7: ='Cost model'!M833 -> 90 | AA7: ='Cost model'!M834 -> 105 | AB7: ='Cost model'!M835 -> 145
A8: XL | B8: ='Cost model'!M746 -> 100 | C8: ='Cost model'!M747 -> 155 | D8: ='Cost model'!M748 -> 235 | F8: ='Cost model'!M761 -> 130 | G8: ='Cost model'!M762 -> 175 | H8: ='Cost model'!M763 -> 255 | J8: ='Cost model'!M776 -> 145 | K8: ='Cost model'!M777 -> 185 | L8: ='Cost model'!M778 -> 235 | N8: ='Cost model'!M791 -> 150 | O8: ='Cost model'!M792 -> 180 | P8: ='Cost model'!M793 -> 235 | R8: ='Cost model'!M806 -> 155 | S8: ='Cost model'!M807 -> 200 | T8: ='Cost model'!M808 -> 260 | V8: ='Cost model'!M821 -> 155 | W8: ='Cost model'!M822 -> 200 | X8: ='Cost model'!M823 -> 250 | Z8: ='Cost model'!M836 -> 160 | AA8: ='Cost model'!M837 -> 195 | AB8: ='Cost model'!M838 -> 245
A9: XXL | B9: ='Cost model'!M749 -> 110 | C9: ='Cost model'!M750 -> 210 | D9: ='Cost model'!M751 -> 305 | F9: ='Cost model'!M764 -> 195 | G9: ='Cost model'!M765 -> 315 | H9: ='Cost model'!M766 -> 370 | J9: ='Cost model'!M779 -> 190 | K9: ='Cost model'!M780 -> 350 | L9: ='Cost model'!M781 -> 385 | N9: ='Cost model'!M794 -> 185 | O9: ='Cost model'!M795 -> 315 | P9: ='Cost model'!M796 -> 375 | R9: ='Cost model'!M809 -> 210 | S9: ='Cost model'!M810 -> 350 | T9: ='Cost model'!M811 -> 415 | V9: ='Cost model'!M824 -> 210 | W9: ='Cost model'!M825 -> 350 | X9: ='Cost model'!M826 -> 415 | Z9: ='Cost model'!M839 -> 205 | AA9: ='Cost model'!M840 -> 345 | AB9: ='Cost model'!M841 -> 410
A11: Priority | B11: From WA | F11: From SA | J11: From VIC | N11: From NSW | R11: From QLD | V11: From ACT | Z11: From TAS
A12: Freight Size | B12: Metro | C12: Metro Outer | D12: Regional | F12: Metro | G12: Metro Outer | H12: Regional | J12: Metro | K12: Metro Outer | L12: Regional | N12: Metro | O12: Metro Outer | P12: Regional | R12: Metro | S12: Metro Outer | T12: Regional | V12: Metro | W12: Metro Outer | X12: Regional | Z12: Metro | AA12: Metro Outer | AB12: Regional
A13: Small | B13: ='Cost model'!N737 -> 13.5 | C13: ='Cost model'!N738 -> 16.5 | D13: ='Cost model'!N739 -> 23.5 | F13: ='Cost model'!N752 -> 17.5 | G13: ='Cost model'!N753 -> 35 | H13: ='Cost model'!N754 -> 35 | J13: ='Cost model'!N767 -> 21.5 | K13: ='Cost model'!N768 -> 26.5 | L13: ='Cost model'!N769 -> 35 | N13: ='Cost model'!N782 -> 16.5 | O13: ='Cost model'!N783 -> 17.5 | P13: ='Cost model'!N784 -> 26.5 | R13: ='Cost model'!N797 -> 19.5 | S13: ='Cost model'!N798 -> 27.5 | T13: ='Cost model'!N799 -> 27.5 | V13: ='Cost model'!N812 -> 35 | W13: ='Cost model'!N813 -> 35 | X13: ='Cost model'!N814 -> 40 | Z13: ='Cost model'!N827 -> 17.5 | AA13: ='Cost model'!N828 -> 22.5 | AB13: ='Cost model'!N829 -> 27.5
A14: Medium | B14: ='Cost model'!N740 -> 28.5 | C14: ='Cost model'!N741 -> 60 | D14: ='Cost model'!N742 -> 80 | F14: ='Cost model'!N755 -> 65 | G14: ='Cost model'!N756 -> 80 | H14: ='Cost model'!N757 -> 85 | J14: ='Cost model'!N770 -> 70 | K14: ='Cost model'!N771 -> 80 | L14: ='Cost model'!N772 -> 90 | N14: ='Cost model'!N785 -> 65 | O14: ='Cost model'!N786 -> 70 | P14: ='Cost model'!N787 -> 85 | R14: ='Cost model'!N800 -> 60 | S14: ='Cost model'!N801 -> 65 | T14: ='Cost model'!N802 -> 80 | V14: ='Cost model'!N815 -> 80 | W14: ='Cost model'!N816 -> 85 | X14: ='Cost model'!N817 -> 90 | Z14: ='Cost model'!N830 -> 80 | AA14: ='Cost model'!N831 -> 85 | AB14: ='Cost model'!N832 -> 90
A15: Large | B15: ='Cost model'!N743 -> 65 | C15: ='Cost model'!N744 -> 110 | D15: ='Cost model'!N745 -> 180 | F15: ='Cost model'!N758 -> 110 | G15: ='Cost model'!N759 -> 135 | H15: ='Cost model'!N760 -> 205 | J15: ='Cost model'!N773 -> 130 | K15: ='Cost model'!N774 -> 135 | L15: ='Cost model'!N775 -> 210 | N15: ='Cost model'!N788 -> 115 | O15: ='Cost model'!N789 -> 130 | P15: ='Cost model'!N790 -> 180 | R15: ='Cost model'!N803 -> 165 | S15: ='Cost model'!N804 -> 165 | T15: ='Cost model'!N805 -> 200 | V15: ='Cost model'!N818 -> 130 | W15: ='Cost model'!N819 -> 150 | X15: ='Cost model'!N820 -> 200 | Z15: ='Cost model'!N833 -> 125 | AA15: ='Cost model'!N834 -> 145 | AB15: ='Cost model'!N835 -> 200
A16: XL | B16: ='Cost model'!N746 -> 120 | C16: ='Cost model'!N747 -> 190 | D16: ='Cost model'!N748 -> 285 | F16: ='Cost model'!N761 -> 160 | G16: ='Cost model'!N762 -> 210 | H16: ='Cost model'!N763 -> 310 | J16: ='Cost model'!N776 -> 175 | K16: ='Cost model'!N777 -> 225 | L16: ='Cost model'!N778 -> 285 | N16: ='Cost model'!N791 -> 180 | O16: ='Cost model'!N792 -> 220 | P16: ='Cost model'!N793 -> 285 | R16: ='Cost model'!N806 -> 190 | S16: ='Cost model'!N807 -> 240 | T16: ='Cost model'!N808 -> 315 | V16: ='Cost model'!N821 -> 190 | W16: ='Cost model'!N822 -> 240 | X16: ='Cost model'!N823 -> 300 | Z16: ='Cost model'!N836 -> 195 | AA16: ='Cost model'!N837 -> 235 | AB16: ='Cost model'!N838 -> 295
A17: XXL | B17: ='Cost model'!N749 -> 135 | C17: ='Cost model'!N750 -> 255 | D17: ='Cost model'!N751 -> 370 | F17: ='Cost model'!N764 -> 235 | J17: ='Cost model'!N779 -> 230 | N17: ='Cost model'!N794 -> 225 | R17: ='Cost model'!N809 -> 255 | V17: ='Cost model'!N824 -> 255 | Z17: ='Cost model'!N839 -> 250
A19: Delivery time frames for WA Orders
A21: Standard | B21: From WA | F21: From SA | J21: From VIC | N21: From NSW | R21: From QLD | V21: From ACT | Z21: From TAS
A22: Freight Size | B22: Metro | C22: Metro Outer | D22: Regional | F22: Metro | G22: Metro Outer | H22: Regional | J22: Metro | K22: Metro Outer | L22: Regional | N22: Metro | O22: Metro Outer | P22: Regional | R22: Metro | S22: Metro Outer | T22: Regional | V22: Metro | W22: Metro Outer | X22: Regional | Z22: Metro | AA22: Metro Outer | AB22: Regional
A23: Small | B23: 1-3 Days | C23: 1-3 Days | D23: 2-5 Days | F23: 2-5 Days | G23: 2-5 Days | H23: 3-7 Days | J23: 2-5 Days | K23: 2-5 Days | L23: 2-5 Days | N23: 7-14 Days | O23: 7-14 Days | P23: 7-14 Days | R23: 7-14 Days | S23: 7-14 Days | T23: 7-14 Days | V23: 7-14 Days | W23: 7-14 Days | X23: 7-14 Days | Z23: 2-5 Days | AA23: 2-5 Days | AB23: 2-5 Days
A24: Medium | B24: 1-3 Days | C24: 1-3 Days | D24: 2-5 Days | F24: 2-5 Days | G24: 2-5 Days | H24: 3-7 Days | J24: 2-5 Days | K24: 2-5 Days | L24: 2-5 Days | N24: 7-14 Days | O24: 7-14 Days | P24: 7-14 Days | R24: 7-14 Days | S24: 7-14 Days | T24: 7-14 Days | V24: 7-14 Days | W24: 7-14 Days | X24: 7-14 Days | Z24: 2-5 Days | AA24: 2-5 Days | AB24: 2-5 Days
A25: Large | B25: 1-3 Days | C25: 1-3 Days | D25: 3-7 Days | F25: 3-7 Days | G25: 3-7 Days | H25: 5-10 Days | J25: 3-7 Days | K25: 3-7 Days | L25: 5-10 Days | N25: 7-14 Days | O25: 7-14 Days | P25: 7-14 Days | R25: 7-14 Days | S25: 7-14 Days | T25: 7-14 Days | V25: 7-14 Days | W25: 7-14 Days | X25: 7-14 Days | Z25: 3-7 Days | AA25: 3-7 Days | AB25: 5-10 Days
A26: XL | B26: 1-3 Days | C26: 1-3 Days | D26: 5-10 Days | F26: 5-10 Days | G26: 5-10 Days | H26: 5-10 Days | J26: 5-10 Days | K26: 5-10 Days | L26: 5-10 Days | N26: 7-14 Days | O26: 7-14 Days | P26: 7-14 Days | R26: 7-14 Days | S26: 7-14 Days | T26: 7-14 Days | V26: 7-14 Days | W26: 7-14 Days | X26: 7-14 Days | Z26: 5-10 Days | AA26: 5-10 Days | AB26: 5-10 Days
A27: XXL | B27: 1-3 Days | C27: 1-3 Days | D27: 5-10 Days | F27: 5-10 Days | G27: 3-7 Days | H27: 5-10 Days | J27: 5-10 Days | K27: 3-7 Days | L27: 5-10 Days | N27: 7-14 Days | O27: 7-14 Days | P27: 7-14 Days | R27: 7-14 Days | S27: 7-14 Days | T27: 7-14 Days | V27: 7-14 Days | W27: 7-14 Days | X27: 7-14 Days | Z27: 5-10 Days | AA27: 3-7 Days | AB27: 5-10 Days
A29: Priority | B29: From WA | F29: From SA | J29: From VIC | N29: From NSW | R29: From QLD | V29: From ACT | Z29: From TAS
A30: Freight Size | B30: Metro | C30: Metro Outer | D30: Regional | F30: Metro | G30: Metro Outer | H30: Regional | J30: Metro | K30: Metro Outer | L30: Regional | N30: Metro | O30: Metro Outer | P30: Regional | R30: Metro | S30: Metro Outer | T30: Regional | V30: Metro | W30: Metro Outer | X30: Regional | Z30: Metro | AA30: Metro Outer | AB30: Regional
A31: Small | B31: 1-2 Days | C31: 1-2 Days | D31: 1-3 Days | F31: 1-2 Days | G31: 1-2 Days | H31: 2-5 Days | J31: 1-2 Days | K31: 1-2 Days | L31: 2-5 Days | N31: 1-2 Days | O31: 1-2 Days | P31: 2-5 Days | R31: 1-2 Days | S31: 1-2 Days | T31: 2-5 Days | V31: 1-2 Days | W31: 1-2 Days | X31: 2-5 Days | Z31: 1-2 Days | AA31: 1-2 Days | AB31: 2-5 Days
A32: Medium | B32: 1-2 Days | C32: 1-2 Days | D32: 1-3 Days | F32: 1-2 Days | G32: 1-2 Days | H32: 2-5 Days | J32: 1-2 Days | K32: 1-2 Days | L32: 2-5 Days | N32: 1-2 Days | O32: 1-2 Days | P32: 2-5 Days | R32: 1-2 Days | S32: 1-2 Days | T32: 2-5 Days | V32: 1-2 Days | W32: 1-2 Days | X32: 2-5 Days | Z32: 1-2 Days | AA32: 1-2 Days | AB32: 2-5 Days
A33: Large | B33: 1-2 Days | C33: 1-2 Days | D33: 2-7 Days | F33: 2-5 Days | G33: 2-5 Days | H33: 5-10 Days | J33: 2-5 Days | K33: 2-5 Days | L33: 5-10 Days | N33: 7-14 Days | O33: 7-14 Days | P33: 7-14 Days | R33: 7-14 Days | S33: 7-14 Days | T33: 7-14 Days | V33: 7-14 Days | W33: 7-14 Days | X33: 7-14 Days | Z33: 2-5 Days | AA33: 2-5 Days | AB33: 5-10 Days
A34: XL | B34: 1-2 Days | C34: 1-2 Days | D34: 2-7 Days | F34: 3-7 Days | G34: 3-7 Days | H34: 5-10 Days | J34: 3-7 Days | K34: 3-7 Days | L34: 5-10 Days | N34: 7-14 Days | O34: 7-14 Days | P34: 7-14 Days | R34: 7-14 Days | S34: 7-14 Days | T34: 7-14 Days | V34: 7-14 Days | W34: 7-14 Days | X34: 7-14 Days | Z34: 3-7 Days | AA34: 3-7 Days | AB34: 5-10 Days
A35: XXL | B35: 1-2 Days | C35: 1-2 Days | D35: 2-7 Days | F35: 3-7 Days | J35: 3-7 Days | N35: 7-14 Days | R35: 7-14 Days | V35: 7-14 Days | Z35: 3-7 Days

Sheet Cost model
A1: Key | B1: Delivering to | C1: Ships from | D1: Size | E1: Zone | F1: Expected cost incl. GST | G1: Orders in this cell | H1: Orders on this lane | I1: Lane factor | J1: 2025 Standard | K1: 2025 Priority | L1: Priority ratio | M1: New Standard | N1: New Priority | O1: Standard change | P1: Rule
A2: ACT|QLD|Small|Metro | B2: ACT | C2: QLD | D2: Small | E2: Metro | F2: 14.46 | G2: 23 | H2: 52 | I2: 1.02 | J2: 14.5 | K2: 19.5 | L2: =INDEX('Read me'!$B$10:$B$14,1) -> 1.34 | M2: =IF(F2*(1+'Read me'!$B$5)<='Read me'!$B$7,CEILING(F2*(1+'Read me'!$B$5)+0.5,1)-0.5,CEILING(F2*(1+'Read me'!$B$5),5)) -> 14.5 | N2: =IF(MAX(M2*L2,M2+'Read me'!$B$6)<='Read me'!$B$7,CEILING(MAX(M2*L2,M2+'Read me'!$B$6)+0.5,1)-0.5,CEILING(MAX(M2*L2,M2+'Read me'!$B$6),5)) -> 19.5 | O2: =IF(ISNUMBER(J2),M2-J2,"new") -> 0
A3: ACT|QLD|Small|Metro Outer | B3: ACT | C3: QLD | D3: Small | E3: Metro Outer | F3: 16.43 | G3: 0 | H3: 52 | I3: 1.02 | J3: 14.5 | K3: 19.5 | L3: =INDEX('Read me'!$B$10:$B$14,1) -> 1.34 | M3: =IF(F3*(1+'Read me'!$B$5)<='Read me'!$B$7,CEILING(F3*(1+'Read me'!$B$5)+0.5,1)-0.5,CEILING(F3*(1+'Read me'!$B$5),5)) -> 16.5 | N3: =IF(MAX(M3*L3,M3+'Read me'!$B$6)<='Read me'!$B$7,CEILING(MAX(M3*L3,M3+'Read me'!$B$6)+0.5,1)-0.5,CEILING(MAX(M3*L3,M3+'Read me'!$B$6),5)) -> 22.5 | O3: =IF(ISNUMBER(J3),M3-J3,"new") -> 2
A4: ACT|QLD|Small|Regional | B4: ACT | C4: QLD | D4: Small | E4: Regional | F4: 20.2 | G4: 0 | H4: 52 | I4: 1.02 | J4: 17.5 | K4: 29.5 | L4: =INDEX('Read me'!$B$10:$B$14,1) -> 1.34 | M4: =IF(F4*(1+'Read me'!$B$5)<='Read me'!$B$7,CEILING(F4*(1+'Read me'!$B$5)+0.5,1)-0.5,CEILING(F4*(1+'Read me'!$B$5),5)) -> 20.5 | N4: =IF(MAX(M4*L4,M4+'Read me'!$B$6)<='Read me'!$B$7,CEILING(MAX(M4*L4,M4+'Read me'!$B$6)+0.5,1)-0.5,CEILING(MAX(M4*L4,M4+'Read me'!$B$6),5)) -> 27.5 | O4: =IF(ISNUMBER(J4),M4-J4,"new") -> 3
A5: ACT|QLD|Medium|Metro | B5: ACT | C5: QLD | D5: Medium | E5: Metro | F5: 34.32 | G5: 26 | H5: 52 | I5: 0.82 | J5: 19.5 | K5: 24.5 | L5: =INDEX('Read me'!$B$10:$B$14,2) -> 1.26 | M5: =IF(F5*(1+'Read me'!$B$5)<='Read me'!$B$7,CEILING(F5*(1+'Read me'!$B$5)+0.5,1)-0.5,CEILING(F5*(1+'Read me'!$B$5),5)) -> 35 | N5: =IF(MAX(M5*L5,M5+'Read me'!$B$6)<='Read me'!$B$7,CEILING(MAX(M5*L5,M5+'Read me'!$B$6)+0.5,1)-0.5,CEILING(MAX(M5*L5,M5+'Read me'!$B$6),5)) -> 45 | O5: =IF(ISNUMBER(J5),M5-J5,"new") -> 15.5
A6: ACT|QLD|Medium|Metro Outer | B6: ACT | C6: QLD | D6: Medium | E6: Metro Outer | F6: 39.62 | G6: 0 | H6: 52 | I6: 0.82 | J6: 19.5 | K6: 24.5 | L6: =INDEX('Read me'!$B$10:$B$14,2) -> 1.26 | M6: =IF(F6*(1+'Read me'!$B$5)<='Read me'!$B$7,CEILING(F6*(1+'Read me'!$B$5)+0.5,1)-0.5,CEILING(F6*(1+'Read me'!$B$5),5)) -> 40 | N6: =IF(MAX(M6*L6,M6+'Read me'!$B$6)<='Read me'!$B$7,CEILING(MAX(M6*L6,M6+'Read me'!$B$6)+0.5,1)-0.5,CEILING(MAX(M6*L6,M6+'Read me'!$B$6),5)) -> 55 | O6: =IF(ISNUMBER(J6),M6-J6,"new") -> 20.5
A7: ACT|QLD|Medium|Regional | B7: ACT | C7: QLD | D7: Medium | E7: Regional | F7: 44.27 | G7: 0 | H7: 52 | I7: 0.82 | J7: 19.5 | K7: 34.5 | L7: =INDEX('Read me'!$B$10:$B$14,2) -> 1.26 | M7: =IF(F7*(1+'Read me'!$B$5)<='Read me'!$B$7,CEILING(F7*(1+'Read me'!$B$5)+0.5,1)-0.5,CEILING(F7*(1+'Read me'!$B$5),5)) -> 45 | N7: =IF(MAX(M7*L7,M7+'Read me'!$B$6)<='Read me'!$B$7,CEILING(MAX(M7*L7,M7+'Read me'!$B$6)+0.5,1)-0.5,CEILING(MAX(M7*L7,M7+'Read me'!$B$6),5)) -> 60 | O7: =IF(ISNUMBER(J7),M7-J7,"new") -> 25.5
A8: ACT|QLD|Large|Metro | B8: ACT | C8: QLD | D8: Large | E8: Metro | F8: 72.22 | G8: 1 | H8: 52 | I8: 0.94 | J8: 24.5 | K8: 75 | L8: =INDEX('Read me'!$B$10:$B$14,3) -> 1.35 | M8: =IF(F8*(1+'Read me'!$B$5)<='Read me'!$B$7,CEILING(F8*(1+'Read me'!$B$5)+0.5,1)-0.5,CEILING(F8*(1+'Read me'!$B$5),5)) -> 75 | N8: =IF(MAX(M8*L8,M8+'Read me'!$B$6)<='Read me'!$B$7,CEILING(MAX(M8*L8,M8+'Read me'!$B$6)+0.5,1)-0.5,CEILING(MAX(M8*L8,M8+'Read me'!$B$6),5)) -> 105 | O8: =IF(ISNUMBER(J8),M8-J8,"new") -> 50.5
A9: ACT|QLD|Large|Metro Outer | B9: ACT | C9: QLD | D9: Large | E9: Metro Outer | F9: 80.44 | G9: 0 | H9: 52 | I9: 0.94 | J9: 24.5 | K9: 75 | L9: =INDEX('Read me'!$B$10:$B$14,3) -> 1.35 | M9: =IF(F9*(1+'Read me'!$B$5)<='Read me'!$B$7,CEILING(F9*(1+'Read me'!$B$5)+0.5,1)-0.5,CEILING(F9*(1+'Read me'!$B$5),5)) -> 85 | N9: =IF(MAX(M9*L9,M9+'Read me'!$B$6)<='Read me'!$B$7,CEILING(MAX(M9*L9,M9+'Read me'!$B$6)+0.5,1)-0.5,CEILING(MAX(M9*L9,M9+'Read me'!$B$6),5)) -> 115 | O9: =IF(ISNUMBER(J9),M9-J9,"new") -> 60.5
A10: ACT|QLD|Large|Regional | B10: ACT | C10: QLD | D10: Large | E10: Regional | F10: 109.86 | G10: 0 | H10: 52 | I10: 0.94 | J10: 85 | K10: 125 | L10: =INDEX('Read me'!$B$10:$B$14,3) -> 1.35 | M10: =IF(F10*(1+'Read me'!$B$5)<='Read me'!$B$7,CEILING(F10*(1+'Read me'!$B$5)+0.5,1)-0.5,CEILING(F10*(1+'Read me'!$B$5),5)) -> 110 | N10: =IF(MAX(M10*L10,M10+'Read me'!$B$6)<='Read me'!$B$7,CEILING(MAX(M10*L10,M10+'Read me'!$B$6)+0.5,1)-0.5,CEILING(MAX(M10*L10,M10+'Read me'!$B$6),5)) -> 150 | O10: =IF(ISNUMBER(J10),M10-J10,"new") -> 25
A11: ACT|QLD|XL|Metro | B11: ACT | C11: QLD | D11: XL | E11: Metro | F11: 115.46 | G11: 2 | H11: 52 | I11: 0.94 | J11: 85 | K11: 125 | L11: =INDEX('Read me'!$B$10:$B$14,4) -> 1.2 | M11: =IF(F11*(1+'Read me'!$B$5)<='Read me'!$B$7,CEILING(F11*(1+'Read me'!$B$5)+0.5,1)-0.5,CEILING(F11*(1+'Read me'!$B$5),5)) -> 120 | N11: =IF(MAX(M11*L11,M11+'Read me'!$B$6)<='Read me'!$B$7,CEILING(MAX(M11*L11,M11+'Read me'!$B$6)+0.5,1)-0.5,CEILING(MAX(M11*L11,M11+'Read me'!$B$6),5)) -> 145 | O11: =IF(ISNUMBER(J11),M11-J11,"new") -> 35
A12: ACT|QLD|XL|Metro Outer | B12: ACT | C12: QLD | D12: XL | E12: Metro Outer | F12: 149.91 | G12: 0 | H12: 52 | I12: 0.94 | J12: 125 | K12: 125 | L12: =INDEX('Read me'!$B$10:$B$14,4) -> 1.2 | M12: =IF(F12*(1+'Read me'!$B$5)<='Read me'!$B$7,CEILING(F12*(1+'Read me'!$B$5)+0.5,1)-0.5,CEILING(F12*(1+'Read me'!$B$5),5)) -> 150 | N12: =IF(MAX(M12*L12,M12+'Read me'!$B$6)<='Read me'!$B$7,CEILING(MAX(M12*L12,M12+'Read me'!$B$6)+0.5,1)-0.5,CEILING(MAX(M12*L12,M12+'Read me'!$B$6),5)) -> 180 | O12: =IF(ISNUMBER(J12),M12-J12,"new") -> 25
A13: ACT|QLD|XL|Regional | B13: ACT | C13: QLD | D13: XL | E13: Regional | F13: 190.44 | G13: 0 | H13: 52 | I13: 0.94 | J13: 199 | K13: 175 | L13: =INDEX('Read me'!$B$10:$B$14,4) -> 1.2 | M13: =IF(F13*(1+'Read me'!$B$5)<='Read me'!$B$7,CEILING(F13*(1+'Read me'!$B$5)+0.5,1)-0.5,CEILING(F13*(1+'Read me'!$B$5),5)) -> 195 | N13: =IF(MAX(M13*L13,M13+'Read me'!$B$6)<='Read me'!$B$7,CEILING(MAX(M13*L13,M13+'Read me'!$B$6)+0.5,1)-0.5,CEILING(MAX(M13*L13,M13+'Read me'!$B$6),5)) -> 235 | O13: =IF(ISNUMBER(J13),M13-J13,"new") -> -4
A14: ACT|QLD|XXL|Metro | B14: ACT | C14: QLD | D14: XXL | E14: Metro | F14: 156.62 | G14: 0 | H14: 52 | I14: 0.94 | J14: 250 | K14: 300 | L14: =INDEX('Read me'!$B$10:$B$14,5) -> 1.2 | M14: =IF(F14*(1+'Read me'!$B$5)<='Read me'!$B$7,CEILING(F14*(1+'Read me'!$B$5)+0.5,1)-0.5,CEILING(F14*(1+'Read me'!$B$5),5)) -> 160 | N14: =IF(MAX(M14*L14,M14+'Read me'!$B$6)<='Read me'!$B$7,CEILING(MAX(M14*L14,M14+'Read me'!$B$6)+0.5,1)-0.5,CEILING(MAX(M14*L14,M14+'Read me'!$B$6),5)) -> 195 | O14: =IF(ISNUMBER(J14),M14-J14,"new") -> -90
A15: ACT|QLD|XXL|Metro Outer | B15: ACT | C15: QLD | D15: XXL | E15: Metro Outer | F15: 219.17 | G15: 0 | H15: 52 | I15: 0.94 | J15: 250 | K15: 300 | L15: =INDEX('Read me'!$B$10:$B$14,5) -> 1.2 | M15: =IF(MAX((IF(F15*(1+'Read me'!$B$5)<='Read me'!$B$7,CEILING(F15*(1+'Read me'!$B$5)+0.5,1)-0.5,CEILING(F15*(1+'Read me'!$B$5),5)))*L15,(IF(F15*(1+'Read me'!$B$5)<='Read me'!$B$7,CEILING(F15*(1+'Read me'!$B$5)+0.5,1)-0.5,CEILING(F15*(1+'Read me'!$B$5),5)))+'Read me'!$B$6)<='Read me'!$B$7,CEILING(MAX((IF(F15*(1+'Read me'!$B$5)<='Read me'!$B$7,CEILING(F15*(1+'Read me'!$B$5)+0.5,1)-0.5,CEILING(F15*(1+'Read me'!$B$5),5)))*L15,(IF(F15*(1+'Read me'!$B$5)<='Read me'!$B$7,CEILING(F15*(1+'Read me'!$B$5)+0.5,1)-0.5,CEILING(F15*(1+'Read me'!$B$5),5)))+'Read me'!$B$6)+0.5,1)-0.5,CEILING(MAX((IF(F15*(1+'Read me'!$B$5)<='Read me'!$B$7,CEILING(F15*(1+'Read me'!$B$5)+0.5,1)-0.5,CEILING(F15*(1+'Read me'!$B$5),5)))*L15,(IF(F15*(1+'Read me'!$B$5)<='Read me'!$B$7,CEILING(F15*(1+'Read me'!$B$5)+0.5,1)-0.5,CEILING(F15*(1+'Read me'!$B$5),5)))+'Read me'!$B$6),5)) -> 265 | N15: Not offered | O15: =IF(ISNUMBER(J15),M15-J15,"new") -> 15 | P15: One rate: interstate XXL/Bulky to Metro Outer or Regional. Standard is charged at what Priority would have been; no Priority option
A16: ACT|QLD|XXL|Regional | B16: ACT | C16: QLD | D16: XXL | E16: Regional | F16: 262.42 | G16: 0 | H16: 52 | I16: 0.94 | J16: 300 | K16: 400 | L16: =INDEX('Read me'!$B$10:$B$14,5) -> 1.2 | M16: =IF(MAX((IF(F16*(1+'Read me'!$B$5)<='Read me'!$B$7,CEILING(F16*(1+'Read me'!$B$5)+0.5,1)-0.5,CEILING(F16*(1+'Read me'!$B$5),5)))*L16,(IF(F16*(1+'Read me'!$B$5)<='Read me'!$B$7,CEILING(F16*(1+'Read me'!$B$5)+0.5,1)-0.5,CEILING(F16*(1+'Read me'!$B$5),5)))+'Read me'!$B$6)<='Read me'!$B$7,CEILING(MAX((IF(F16*(1+'Read me'!$B$5)<='Read me'!$B$7,CEILING(F16*(1+'Read me'!$B$5)+0.5,1)-0.5,CEILING(F16*(1+'Read me'!$B$5),5)))*L16,(IF(F16*(1+'Read me'!$B$5)<='Read me'!$B$7,CEILING(F16*(1+'Read me'!$B$5)+0.5,1)-0.5,CEILING(F16*(1+'Read me'!$B$5),5)))+'Read me'!$B$6)+0.5,1)-0.5,CEILING(MAX((IF(F16*(1+'Read me'!$B$5)<='Read me'!$B$7,CEILING(F16*(1+'Read me'!$B$5)+0.5,1)-0.5,CEILING(F16*(1+'Read me'!$B$5),5)))*L16,(IF(F16*(1+'Read me'!$B$5)<='Read me'!$B$7,CEILING(F16*(1+'Read me'!$B$5)+0.5,1)-0.5,CEILING(F16*(1+'Read me'!$B$5),5)))+'Read me'!$B$6),5)) -> 320 | N16: Not offered | O16: =IF(ISNUMBER(J16),M16-J16,"new") -> 20 | P16: One rate: interstate XXL/Bulky to Metro Outer or Regional. Standard is charged at what Priority would have been; no Priority option
A17: ACT|VIC|Small|Metro | B17: ACT | C17: VIC | D17: Small | E17: Metro | F17: 12.21 | G17: 8 | H17: 26 | I17: 0.81 | J17: 14.5 | K17: 19.5 | L17: =INDEX('Read me'!$B$10:$B$14,1) -> 1.34 | M17: =IF(F17*(1+'Read me'!$B$5)<='Read me'!$B$7,CEILING(F17*(1+'Read me'!$B$5)+0.5,1)-0.5,CEILING(F17*(1+'Read me'!$B$5),5)) -> 12.5 | N17: =IF(MAX(M17*L17,M17+'Read me'!$B$6)<='Read me'!$B$7,CEILING(MAX(M17*L17,M17+'Read me'!$B$6)+0.5,1)-0.5,CEILING(MAX(M17*L17,M17+'Read me'!$B$6),5)) -> 17.5 | O17: =IF(ISNUMBER(J17),M17-J17,"new") -> -2
A18: ACT|VIC|Small|Metro Outer | B18: ACT | C18: VIC | D18: Small | E18: Metro Outer | F18: 13.07 | G18: 0 | H18: 26 | I18: 0.81 | J18: 14.5 | K18: 19.5 | L18: =INDEX('Read me'!$B$10:$B$14,1) -> 1.34 | M18: =IF(F18*(1+'Read me'!$B$5)<='Read me'!$B$7,CEILING(F18*(1+'Read me'!$B$5)+0.5,1)-0.5,CEILING(F18*(1+'Read me'!$B$5),5)) -> 13.5 | N18: =IF(MAX(M18*L18,M18+'Read me'!$B$6)<='Read me'!$B$7,CEILING(MAX(M18*L18,M18+'Read me'!$B$6)+0.5,1)-0.5,CEILING(MAX(M18*L18,M18+'Read me'!$B$6),5)) -> 18.5 | O18: =IF(ISNUMBER(J18),M18-J18,"new") -> -1
A19: ACT|VIC|Small|Regional | B19: ACT | C19: VIC | D19: Small | E19: Regional | F19: 16.07 | G19: 0 | H19: 26 | I19: 0.81 | J19: 17.5 | K19: 29.5 | L19: =INDEX('Read me'!$B$10:$B$14,1) -> 1.34 | M19: =IF(F19*(1+'Read me'!$B$5)<='Read me'!$B$7,CEILING(F19*(1+'Read me'!$B$5)+0.5,1)-0.5,CEILING(F19*(1+'Read me'!$B$5),5)) -> 16.5 | N19: =IF(MAX(M19*L19,M19+'Read me'!$B$6)<='Read me'!$B$7,CEILING(MAX(M19*L19,M19+'Read me'!$B$6)+0.5,1)-0.5,CEILING(MAX(M19*L19,M19+'Read me'!$B$6),5)) -> 22.5 | O19: =IF(ISNUMBER(J19),M19-J19,"new") -> -1
A20: ACT|VIC|Medium|Metro | B20: ACT | C20: VIC | D20: Medium | E20: Metro | F20: 34.61 | G20: 16 | H20: 26 | I20: 0.82 | J20: 19.5 | K20: 24.5 | L20: =INDEX('Read me'!$B$10:$B$14,2) -> 1.26 | M20: =IF(F20*(1+'Read me'!$B$5)<='Read me'!$B$7,CEILING(F20*(1+'Read me'!$B$5)+0.5,1)-0.5,CEILING(F20*(1+'Read me'!$B$5),5)) -> 35 | N20: =IF(MAX(M20*L20,M20+'Read me'!$B$6)<='Read me'!$B$7,CEILING(MAX(M20*L20,M20+'Read me'!$B$6)+0.5,1)-0.5,CEILING(MAX(M20*L20,M20+'Read me'!$B$6),5)) -> 45 | O20: =IF(ISNUMBER(J20),M20-J20,"new") -> 15.5
A21: ACT|VIC|Medium|Metro Outer | B21: ACT | C21: VIC | D21: Medium | E21: Metro Outer | F21: 39.64 | G21: 0 | H21: 26 | I21: 0.82 | J21: 19.5 | K21: 24.5 | L21: =INDEX('Read me'!$B$10:$B$14,2) -> 1.26 | M21: =IF(F21*(1+'Read me'!$B$5)<='Read me'!$B$7,CEILING(F21*(1+'Read me'!$B$5)+0.5,1)-0.5,CEILING(F21*(1+'Read me'!$B$5),5)) -> 40 | N21: =IF(MAX(M21*L21,M21+'Read me'!$B$6)<='Read me'!$B$7,CEILING(MAX(M21*L21,M21+'Read me'!$B$6)+0.5,1)-0.5,CEILING(MAX(M21*L21,M21+'Read me'!$B$6),5)) -> 55 | O21: =IF(ISNUMBER(J21),M21-J21,"new") -> 20.5
A22: ACT|VIC|Medium|Regional | B22: ACT | C22: VIC | D22: Medium | E22: Regional | F22: 44.29 | G22: 0 | H22: 26 | I22: 0.82 | J22: 19.5 | K22: 34.5 | L22: =INDEX('Read me'!$B$10:$B$14,2) -> 1.26 | M22: =IF(F22*(1+'Read me'!$B$5)<='Read me'!$B$7,CEILING(F22*(1+'Read me'!$B$5)+0.5,1)-0.5,CEILING(F22*(1+'Read me'!$B$5),5)) -> 45 | N22: =IF(MAX(M22*L22,M22+'Read me'!$B$6)<='Read me'!$B$7,CEILING(MAX(M22*L22,M22+'Read me'!$B$6)+0.5,1)-0.5,CEILING(MAX(M22*L22,M22+'Read me'!$B$6),5)) -> 60 | O22: =IF(ISNUMBER(J22),M22-J22,"new") -> 25.5
A23: ACT|VIC|Large|Metro | B23: ACT | C23: VIC | D23: Large | E23: Metro | F23: 58.91 | G23: 2 | H23: 26 | I23: 0.81 | J23: 24.5 | K23: 75 | L23: =INDEX('Read me'!$B$10:$B$14,3) -> 1.35 | M23: =IF(F23*(1+'Read me'!$B$5)<='Read me'!$B$7,CEILING(F23*(1+'Read me'!$B$5)+0.5,1)-0.5,CEILING(F23*(1+'Read me'!$B$5),5)) -> 60 | N23: =IF(MAX(M23*L23,M23+'Read me'!$B$6)<='Read me'!$B$7,CEILING(MAX(M23*L23,M23+'Read me'!$B$6)+0.5,1)-0.5,CEILING(MAX(M23*L23,M23+'Read me'!$B$6),5)) -> 85 | O23: =IF(ISNUMBER(J23),M23-J23,"new") -> 35.5
A24: ACT|VIC|Large|Metro Outer | B24: ACT | C24: VIC | D24: Large | E24: Metro Outer | F24: 69.11 | G24: 0 | H24: 26 | I24: 0.81 | J24: 24.5 | K24: 75 | L24: =INDEX('Read me'!$B$10:$B$14,3) -> 1.35 | M24: =IF(F24*(1+'Read me'!$B$5)<='Read me'!$B$7,CEILING(F24*(1+'Read me'!$B$5)+0.5,1)-0.5,CEILING(F24*(1+'Read me'!$B$5),5)) -> 70 | N24: =IF(MAX(M24*L24,M24+'Read me'!$B$6)<='Read me'!$B$7,CEILING(MAX(M24*L24,M24+'Read me'!$B$6)+0.5,1)-0.5,CEILING(MAX(M24*L24,M24+'Read me'!$B$6),5)) -> 95 | O24: =IF(ISNUMBER(J24),M24-J24,"new") -> 45.5
A25: ACT|VIC|Large|Regional | B25: ACT | C25: VIC | D25: Large | E25: Regional | F25: 94.38 | G25: 0 | H25: 26 | I25: 0.81 | J25: 85 | K25: 125 | L25: =INDEX('Read me'!$B$10:$B$14,3) -> 1.35 | M25: =IF(F25*(1+'Read me'!$B$5)<='Read me'!$B$7,CEILING(F25*(1+'Read me'!$B$5)+0.5,1)-0.5,CEILING(F25*(1+'Read me'!$B$5),5)) -> 95 | N25: =IF(MAX(M25*L25,M25+'Read me'!$B$6)<='Read me'!$B$7,CEILING(MAX(M25*L25,M25+'Read me'!$B$6)+0.5,1)-0.5,CEILING(MAX(M25*L25,M25+'Read me'!$B$6),5)) -> 130 | O25: =IF(ISNUMBER(J25),M25-J25,"new") -> 10
A26: ACT|VIC|XL|Metro | B26: ACT | C26: VIC | D26: XL | E26: Metro | F26: 100.02 | G26: 0 | H26: 26 | I26: 0.81 | J26: 85 | K26: 125 | L26: =INDEX('Read me'!$B$10:$B$14,4) -> 1.2 | M26: =IF(F26*(1+'Read me'!$B$5)<='Read me'!$B$7,CEILING(F26*(1+'Read me'!$B$5)+0.5,1)-0.5,CEILING(F26*(1+'Read me'!$B$5),5)) -> 105 | N26: =IF(MAX(M26*L26,M26+'Read me'!$B$6)<='Read me'!$B$7,CEILING(MAX(M26*L26,M26+'Read me'!$B$6)+0.5,1)-0.5,CEILING(MAX(M26*L26,M26+'Read me'!$B$6),5)) -> 130 | O26: =IF(ISNUMBER(J26),M26-J26,"new") -> 20
A27: ACT|VIC|XL|Metro Outer | B27: ACT | C27: VIC | D27: XL | E27: Metro Outer | F27: 128.79 | G27: 0 | H27: 26 | I27: 0.81 | J27: 125 | K27: 125 | L27: =INDEX('Read me'!$B$10:$B$14,4) -> 1.2 | M27: =IF(F27*(1+'Read me'!$B$5)<='Read me'!$B$7,CEILING(F27*(1+'Read me'!$B$5)+0.5,1)-0.5,CEILING(F27*(1+'Read me'!$B$5),5)) -> 130 | N27: =IF(MAX(M27*L27,M27+'Read me'!$B$6)<='Read me'!$B$7,CEILING(MAX(M27*L27,M27+'Read me'!$B$6)+0.5,1)-0.5,CEILING(MAX(M27*L27,M27+'Read me'!$B$6),5)) -> 160 | O27: =IF(ISNUMBER(J27),M27-J27,"new") -> 5
A28: ACT|VIC|XL|Regional | B28: ACT | C28: VIC | D28: XL | E28: Regional | F28: 163.61 | G28: 0 | H28: 26 | I28: 0.81 | J28: 199 | K28: 175 | L28: =INDEX('Read me'!$B$10:$B$14,4) -> 1.2 | M28: =IF(F28*(1+'Read me'!$B$5)<='Read me'!$B$7,CEILING(F28*(1+'Read me'!$B$5)+0.5,1)-0.5,CEILING(F28*(1+'Read me'!$B$5),5)) -> 165 | N28: =IF(MAX(M28*L28,M28+'Read me'!$B$6)<='Read me'!$B$7,CEILING(MAX(M28*L28,M28+'Read me'!$B$6)+0.5,1)-0.5,CEILING(MAX(M28*L28,M28+'Read me'!$B$6),5)) -> 200 | O28: =IF(ISNUMBER(J28),M28-J28,"new") -> -34
A29: ACT|VIC|XXL|Metro | B29: ACT | C29: VIC | D29: XXL | E29: Metro | F29: 134.56 | G29: 0 | H29: 26 | I29: 0.81 | J29: 250 | K29: 300 | L29: =INDEX('Read me'!$B$10:$B$14,5) -> 1.2 | M29: =IF(F29*(1+'Read me'!$B$5)<='Read me'!$B$7,CEILING(F29*(1+'Read me'!$B$5)+0.5,1)-0.5,CEILING(F29*(1+'Read me'!$B$5),5)) -> 135 | N29: =IF(MAX(M29*L29,M29+'Read me'!$B$6)<='Read me'!$B$7,CEILING(MAX(M29*L29,M29+'Read me'!$B$6)+0.5,1)-0.5,CEILING(MAX(M29*L29,M29+'Read me'!$B$6),5)) -> 165 | O29: =IF(ISNUMBER(J29),M29-J29,"new") -> -115
A30: ACT|VIC|XXL|Metro Outer | B30: ACT | C30: VIC | D30: XXL | E30: Metro Outer | F30: 188.29 | G30: 0 | H30: 26 | I30: 0.81 | J30: 250 | K30: 300 | L30: =INDEX('Read me'!$B$10:$B$14,5) -> 1.2 | M30: =IF(MAX((IF(F30*(1+'Read me'!$B$5)<='Read me'!$B$7,CEILING(F30*(1+'Read me'!$B$5)+0.5,1)-0.5,CEILING(F30*(1+'Read me'!$B$5),5)))*L30,(IF(F30*(1+'Read me'!$B$5)<='Read me'!$B$7,CEILING(F30*(1+'Read me'!$B$5)+0.5,1)-0.5,CEILING(F30*(1+'Read me'!$B$5),5)))+'Read me'!$B$6)<='Read me'!$B$7,CEILING(MAX((IF(F30*(1+'Read me'!$B$5)<='Read me'!$B$7,CEILING(F30*(1+'Read me'!$B$5)+0.5,1)-0.5,CEILING(F30*(1+'Read me'!$B$5),5)))*L30,(IF(F30*(1+'Read me'!$B$5)<='Read me'!$B$7,CEILING(F30*(1+'Read me'!$B$5)+0.5,1)-0.5,CEILING(F30*(1+'Read me'!$B$5),5)))+'Read me'!$B$6)+0.5,1)-0.5,CEILING(MAX((IF(F30*(1+'Read me'!$B$5)<='Read me'!$B$7,CEILING(F30*(1+'Read me'!$B$5)+0.5,1)-0.5,CEILING(F30*(1+'Read me'!$B$5),5)))*L30,(IF(F30*(1+'Read me'!$B$5)<='Read me'!$B$7,CEILING(F30*(1+'Read me'!$B$5)+0.5,1)-0.5,CEILING(F30*(1+'Read me'!$B$5),5)))+'Read me'!$B$6),5)) -> 230 | N30: Not offered | O30: =IF(ISNUMBER(J30),M30-J30,"new") -> -20 | P30: One rate: interstate XXL/Bulky to Metro Outer or Regional. Standard is charged at what Priority would have been; no Priority option
A31: ACT|VIC|XXL|Regional | B31: ACT | C31: VIC | D31: XXL | E31: Regional | F31: 225.44 | G31: 0 | H31: 26 | I31: 0.81 | J31: 300 | K31: 400 | L31: =INDEX('Read me'!$B$10:$B$14,5) -> 1.2 | M31: =IF(MAX((IF(F31*(1+'Read me'!$B$5)<='Read me'!$B$7,CEILING(F31*(1+'Read me'!$B$5)+0.5,1)-0.5,CEILING(F31*(1+'Read me'!$B$5),5)))*L31,(IF(F31*(1+'Read me'!$B$5)<='Read me'!$B$7,CEILING(F31*(1+'Read me'!$B$5)+0.5,1)-0.5,CEILING(F31*(1+'Read me'!$B$5),5)))+'Read me'!$B$6)<='Read me'!$B$7,CEILING(MAX((IF(F31*(1+'Read me'!$B$5)<='Read me'!$B$7,CEILING(F31*(1+'Read me'!$B$5)+0.5,1)-0.5,CEILING(F31*(1+'Read me'!$B$5),5)))*L31,(IF(F31*(1+'Read me'!$B$5)<='Read me'!$B$7,CEILING(F31*(1+'Read me'!$B$5)+0.5,1)-0.5,CEILING(F31*(1+'Read me'!$B$5),5)))+'Read me'!$B$6)+0.5,1)-0.5,CEILING(MAX((IF(F31*(1+'Read me'!$B$5)<='Read me'!$B$7,CEILING(F31*(1+'Read me'!$B$5)+0.5,1)-0.5,CEILING(F31*(1+'Read me'!$B$5),5)))*L31,(IF(F31*(1+'Read me'!$B$5)<='Read me'!$B$7,CEILING(F31*(1+'Read me'!$B$5)+0.5,1)-0.5,CEILING(F31*(1+'Read me'!$B$5),5)))+'Read me'!$B$6),5)) -> 280 | N31: Not offered | O31: =IF(ISNUMBER(J31),M31-J31,"new") -> -20 | P31: One rate: interstate XXL/Bulky to Metro Outer or Regional. Standard is charged at what Priority would have been; no Priority option
A32: ACT|SA|Small|Metro | B32: ACT | C32: SA | D32: Small | E32: Metro | F32: 15.1 | G32: 10 | H32: 14 | I32: 1.13 | J32: 19.5 | K32: 24.5 | L32: =INDEX('Read me'!$B$10:$B$14,1) -> 1.34 | M32: =IF(F32*(1+'Read me'!$B$5)<='Read me'!$B$7,CEILING(F32*(1+'Read me'!$B$5)+0.5,1)-0.5,CEILING(F32*(1+'Read me'!$B$5),5)) -> 15.5 | N32: =IF(MAX(M32*L32,M32+'Read me'!$B$6)<='Read me'!$B$7,CEILING(MAX(M32*L32,M32+'Read me'!$B$6)+0.5,1)-0.5,CEILING(MAX(M32*L32,M32+'Read me'!$B$6),5)) -> 21.5 | O32: =IF(ISNUMBER(J32),M32-J32,"new") -> -4
A33: ACT|SA|Small|Metro Outer | B33: ACT | C33: SA | D33: Small | E33: Metro Outer | F33: 18.21 | G33: 0 | H33: 14 | I33: 1.13 | J33: 19.5 | K33: 24.5 | L33: =INDEX('Read me'!$B$10:$B$14,1) -> 1.34 | M33: =IF(F33*(1+'Read me'!$B$5)<='Read me'!$B$7,CEILING(F33*(1+'Read me'!$B$5)+0.5,1)-0.5,CEILING(F33*(1+'Read me'!$B$5),5)) -> 18.5 | N33: =IF(MAX(M33*L33,M33+'Read me'!$B$6)<='Read me'!$B$7,CEILING(MAX(M33*L33,M33+'Read me'!$B$6)+0.5,1)-0.5,CEILING(MAX(M33*L33,M33+'Read me'!$B$6),5)) -> 25.5 | O33: =IF(ISNUMBER(J33),M33-J33,"new") -> -1
A34: ACT|SA|Small|Regional | B34: ACT | C34: SA | D34: Small | E34: Regional | F34: 22.39 | G34: 0 | H34: 14 | I34: 1.13 | J34: 19.5 | K34: 34.5 | L34: =INDEX('Read me'!$B$10:$B$14,1) -> 1.34 | M34: =IF(F34*(1+'Read me'!$B$5)<='Read me'!$B$7,CEILING(F34*(1+'Read me'!$B$5)+0.5,1)-0.5,CEILING(F34*(1+'Read me'!$B$5),5)) -> 22.5 | N34: =IF(MAX(M34*L34,M34+'Read me'!$B$6)<='Read me'!$B$7,CEILING(MAX(M34*L34,M34+'Read me'!$B$6)+0.5,1)-0.5,CEILING(MAX(M34*L34,M34+'Read me'!$B$6),5)) -> 35 | O34: =IF(ISNUMBER(J34),M34-J34,"new") -> 3
A35: ACT|SA|Medium|Metro | B35: ACT | C35: SA | D35: Medium | E35: Metro | F35: 40.65 | G35: 2 | H35: 14 | I35: 1.02 | J35: 24.5 | K35: 29.5 | L35: =INDEX('Read me'!$B$10:$B$14,2) -> 1.26 | M35: =IF(F35*(1+'Read me'!$B$5)<='Read me'!$B$7,CEILING(F35*(1+'Read me'!$B$5)+0.5,1)-0.5,CEILING(F35*(1+'Read me'!$B$5),5)) -> 45 | N35: =IF(MAX(M35*L35,M35+'Read me'!$B$6)<='Read me'!$B$7,CEILING(MAX(M35*L35,M35+'Read me'!$B$6)+0.5,1)-0.5,CEILING(MAX(M35*L35,M35+'Read me'!$B$6),5)) -> 60 | O35: =IF(ISNUMBER(J35),M35-J35,"new") -> 20.5
A36: ACT|SA|Medium|Metro Outer | B36: ACT | C36: SA | D36: Medium | E36: Metro Outer | F36: 49 | G36: 0 | H36: 14 | I36: 1.02 | J36: 24.5 | K36: 29.5 | L36: =INDEX('Read me'!$B$10:$B$14,2) -> 1.26 | M36: =IF(F36*(1+'Read me'!$B$5)<='Read me'!$B$7,CEILING(F36*(1+'Read me'!$B$5)+0.5,1)-0.5,CEILING(F36*(1+'Read me'!$B$5),5)) -> 50 | N36: =IF(MAX(M36*L36,M36+'Read me'!$B$6)<='Read me'!$B$7,CEILING(MAX(M36*L36,M36+'Read me'!$B$6)+0.5,1)-0.5,CEILING(MAX(M36*L36,M36+'Read me'!$B$6),5)) -> 65 | O36: =IF(ISNUMBER(J36),M36-J36,"new") -> 25.5
A37: ACT|SA|Medium|Regional | B37: ACT | C37: SA | D37: Medium | E37: Regional | F37: 54.74 | G37: 0 | H37: 14 | I37: 1.02 | J37: 24.5 | K37: 45 | L37: =INDEX('Read me'!$B$10:$B$14,2) -> 1.26 | M37: =IF(F37*(1+'Read me'!$B$5)<='Read me'!$B$7,CEILING(F37*(1+'Read me'!$B$5)+0.5,1)-0.5,CEILING(F37*(1+'Read me'!$B$5),5)) -> 55 | N37: =IF(MAX(M37*L37,M37+'Read me'!$B$6)<='Read me'!$B$7,CEILING(MAX(M37*L37,M37+'Read me'!$B$6)+0.5,1)-0.5,CEILING(MAX(M37*L37,M37+'Read me'!$B$6),5)) -> 70 | O37: =IF(ISNUMBER(J37),M37-J37,"new") -> 30.5
A38: ACT|SA|Large|Metro | B38: ACT | C38: SA | D38: Large | E38: Metro | F38: 76.12 | G38: 1 | H38: 14 | I38: 1.02 | J38: 45 | K38: 95 | L38: =INDEX('Read me'!$B$10:$B$14,3) -> 1.35 | M38: =IF(F38*(1+'Read me'!$B$5)<='Read me'!$B$7,CEILING(F38*(1+'Read me'!$B$5)+0.5,1)-0.5,CEILING(F38*(1+'Read me'!$B$5),5)) -> 80 | N38: =IF(MAX(M38*L38,M38+'Read me'!$B$6)<='Read me'!$B$7,CEILING(MAX(M38*L38,M38+'Read me'!$B$6)+0.5,1)-0.5,CEILING(MAX(M38*L38,M38+'Read me'!$B$6),5)) -> 110 | O38: =IF(ISNUMBER(J38),M38-J38,"new") -> 35
A39: ACT|SA|Large|Metro Outer | B39: ACT | C39: SA | D39: Large | E39: Metro Outer | F39: 86.77 | G39: 0 | H39: 14 | I39: 1.02 | J39: 45 | K39: 95 | L39: =INDEX('Read me'!$B$10:$B$14,3) -> 1.35 | M39: =IF(F39*(1+'Read me'!$B$5)<='Read me'!$B$7,CEILING(F39*(1+'Read me'!$B$5)+0.5,1)-0.5,CEILING(F39*(1+'Read me'!$B$5),5)) -> 90 | N39: =IF(MAX(M39*L39,M39+'Read me'!$B$6)<='Read me'!$B$7,CEILING(MAX(M39*L39,M39+'Read me'!$B$6)+0.5,1)-0.5,CEILING(MAX(M39*L39,M39+'Read me'!$B$6),5)) -> 125 | O39: =IF(ISNUMBER(J39),M39-J39,"new") -> 45
A40: ACT|SA|Large|Regional | B40: ACT | C40: SA | D40: Large | E40: Regional | F40: 118.51 | G40: 0 | H40: 14 | I40: 1.02 | J40: 99 | K40: 150 | L40: =INDEX('Read me'!$B$10:$B$14,3) -> 1.35 | M40: =IF(F40*(1+'Read me'!$B$5)<='Read me'!$B$7,CEILING(F40*(1+'Read me'!$B$5)+0.5,1)-0.5,CEILING(F40*(1+'Read me'!$B$5),5)) -> 120 | N40: =IF(MAX(M40*L40,M40+'Read me'!$B$6)<='Read me'!$B$7,CEILING(MAX(M40*L40,M40+'Read me'!$B$6)+0.5,1)-0.5,CEILING(MAX(M40*L40,M40+'Read me'!$B$6),5)) -> 165 | O40: =IF(ISNUMBER(J40),M40-J40,"new") -> 21
A41: ACT|SA|XL|Metro | B41: ACT | C41: SA | D41: XL | E41: Metro | F41: 121.49 | G41: 1 | H41: 14 | I41: 1.02 | J41: 99 | K41: 150 | L41: =INDEX('Read me'!$B$10:$B$14,4) -> 1.2 | M41: =IF(F41*(1+'Read me'!$B$5)<='Read me'!$B$7,CEILING(F41*(1+'Read me'!$B$5)+0.5,1)-0.5,CEILING(F41*(1+'Read me'!$B$5),5)) -> 125 | N41: =IF(MAX(M41*L41,M41+'Read me'!$B$6)<='Read me'!$B$7,CEILING(MAX(M41*L41,M41+'Read me'!$B$6)+0.5,1)-0.5,CEILING(MAX(M41*L41,M41+'Read me'!$B$6),5)) -> 150 | O41: =IF(ISNUMBER(J41),M41-J41,"new") -> 26
A42: ACT|SA|XL|Metro Outer | B42: ACT | C42: SA | D42: XL | E42: Metro Outer | F42: 161.72 | G42: 0 | H42: 14 | I42: 1.02 | J42: 150 | K42: 150 | L42: =INDEX('Read me'!$B$10:$B$14,4) -> 1.2 | M42: =IF(F42*(1+'Read me'!$B$5)<='Read me'!$B$7,CEILING(F42*(1+'Read me'!$B$5)+0.5,1)-0.5,CEILING(F42*(1+'Read me'!$B$5),5)) -> 165 | N42: =IF(MAX(M42*L42,M42+'Read me'!$B$6)<='Read me'!$B$7,CEILING(MAX(M42*L42,M42+'Read me'!$B$6)+0.5,1)-0.5,CEILING(MAX(M42*L42,M42+'Read me'!$B$6),5)) -> 200 | O42: =IF(ISNUMBER(J42),M42-J42,"new") -> 15
A43: ACT|SA|XL|Regional | B43: ACT | C43: SA | D43: XL | E43: Regional | F43: 205.44 | G43: 0 | H43: 14 | I43: 1.02 | J43: 250 | K43: 195 | L43: =INDEX('Read me'!$B$10:$B$14,4) -> 1.2 | M43: =IF(F43*(1+'Read me'!$B$5)<='Read me'!$B$7,CEILING(F43*(1+'Read me'!$B$5)+0.5,1)-0.5,CEILING(F43*(1+'Read me'!$B$5),5)) -> 210 | N43: =IF(MAX(M43*L43,M43+'Read me'!$B$6)<='Read me'!$B$7,CEILING(MAX(M43*L43,M43+'Read me'!$B$6)+0.5,1)-0.5,CEILING(MAX(M43*L43,M43+'Read me'!$B$6),5)) -> 255 | O43: =IF(ISNUMBER(J43),M43-J43,"new") -> -40
A44: ACT|SA|XXL|Metro | B44: ACT | C44: SA | D44: XXL | E44: Metro | F44: 168.95 | G44: 0 | H44: 14 | I44: 1.02 | J44: 300 | K44: 300 | L44: =INDEX('Read me'!$B$10:$B$14,5) -> 1.2 | M44: =IF(F44*(1+'Read me'!$B$5)<='Read me'!$B$7,CEILING(F44*(1+'Read me'!$B$5)+0.5,1)-0.5,CEILING(F44*(1+'Read me'!$B$5),5)) -> 170 | N44: =IF(MAX(M44*L44,M44+'Read me'!$B$6)<='Read me'!$B$7,CEILING(MAX(M44*L44,M44+'Read me'!$B$6)+0.5,1)-0.5,CEILING(MAX(M44*L44,M44+'Read me'!$B$6),5)) -> 205 | O44: =IF(ISNUMBER(J44),M44-J44,"new") -> -130
A45: ACT|SA|XXL|Metro Outer | B45: ACT | C45: SA | D45: XXL | E45: Metro Outer | F45: 236.42 | G45: 0 | H45: 14 | I45: 1.02 | J45: 300 | K45: 300 | L45: =INDEX('Read me'!$B$10:$B$14,5) -> 1.2 | M45: =IF(MAX((IF(F45*(1+'Read me'!$B$5)<='Read me'!$B$7,CEILING(F45*(1+'Read me'!$B$5)+0.5,1)-0.5,CEILING(F45*(1+'Read me'!$B$5),5)))*L45,(IF(F45*(1+'Read me'!$B$5)<='Read me'!$B$7,CEILING(F45*(1+'Read me'!$B$5)+0.5,1)-0.5,CEILING(F45*(1+'Read me'!$B$5),5)))+'Read me'!$B$6)<='Read me'!$B$7,CEILING(MAX((IF(F45*(1+'Read me'!$B$5)<='Read me'!$B$7,CEILING(F45*(1+'Read me'!$B$5)+0.5,1)-0.5,CEILING(F45*(1+'Read me'!$B$5),5)))*L45,(IF(F45*(1+'Read me'!$B$5)<='Read me'!$B$7,CEILING(F45*(1+'Read me'!$B$5)+0.5,1)-0.5,CEILING(F45*(1+'Read me'!$B$5),5)))+'Read me'!$B$6)+0.5,1)-0.5,CEILING(MAX((IF(F45*(1+'Read me'!$B$5)<='Read me'!$B$7,CEILING(F45*(1+'Read me'!$B$5)+0.5,1)-0.5,CEILING(F45*(1+'Read me'!$B$5),5)))*L45,(IF(F45*(1+'Read me'!$B$5)<='Read me'!$B$7,CEILING(F45*(1+'Read me'!$B$5)+0.5,1)-0.5,CEILING(F45*(1+'Read me'!$B$5),5)))+'Read me'!$B$6),5)) -> 290 | N45: Not offered | O45: =IF(ISNUMBER(J45),M45-J45,"new") -> -10 | P45: One rate: interstate XXL/Bulky to Metro Outer or Regional. Standard is charged at what Priority would have been; no Priority option
A46: ACT|SA|XXL|Regional | B46: ACT | C46: SA | D46: XXL | E46: Regional | F46: 283.08 | G46: 0 | H46: 14 | I46: 1.02 | J46: 350 | K46: 400 | L46: =INDEX('Read me'!$B$10:$B$14,5) -> 1.2 | M46: =IF(MAX((IF(F46*(1+'Read me'!$B$5)<='Read me'!$B$7,CEILING(F46*(1+'Read me'!$B$5)+0.5,1)-0.5,CEILING(F46*(1+'Read me'!$B$5),5)))*L46,(IF(F46*(1+'Read me'!$B$5)<='Read me'!$B$7,CEILING(F46*(1+'Read me'!$B$5)+0.5,1)-0.5,CEILING(F46*(1+'Read me'!$B$5),5)))+'Read me'!$B$6)<='Read me'!$B$7,CEILING(MAX((IF(F46*(1+'Read me'!$B$5)<='Read me'!$B$7,CEILING(F46*(1+'Read me'!$B$5)+0.5,1)-0.5,CEILING(F46*(1+'Read me'!$B$5),5)))*L46,(IF(F46*(1+'Read me'!$B$5)<='Read me'!$B$7,CEILING(F46*(1+'Read me'!$B$5)+0.5,1)-0.5,CEILING(F46*(1+'Read me'!$B$5),5)))+'Read me'!$B$6)+0.5,1)-0.5,CEILING(MAX((IF(F46*(1+'Read me'!$B$5)<='Read me'!$B$7,CEILING(F46*(1+'Read me'!$B$5)+0.5,1)-0.5,CEILING(F46*(1+'Read me'!$B$5),5)))*L46,(IF(F46*(1+'Read me'!$B$5)<='Read me'!$B$7,CEILING(F46*(1+'Read me'!$B$5)+0.5,1)-0.5,CEILING(F46*(1+'Read me'!$B$5),5)))+'Read me'!$B$6),5)) -> 345 | N46: Not offered | O46: =IF(ISNUMBER(J46),M46-J46,"new") -> -5 | P46: One rate: interstate XXL/Bulky to Metro Outer or Regional. Standard is charged at what Priority would have been; no Priority option
A47: ACT|NSW|Small|Metro | B47: ACT | C47: NSW | D47: Small | E47: Metro | F47: 11.93 | G47: 55 | H47: 121 | I47: 0.85 | J47: 14.5 | K47: 19.5 | L47: =INDEX('Read me'!$B$10:$B$14,1) -> 1.34 | M47: =IF(F47*(1+'Read me'!$B$5)<='Read me'!$B$7,CEILING(F47*(1+'Read me'!$B$5)+0.5,1)-0.5,CEILING(F47*(1+'Read me'!$B$5),5)) -> 12.5 | N47: =IF(MAX(M47*L47,M47+'Read me'!$B$6)<='Read me'!$B$7,CEILING(MAX(M47*L47,M47+'Read me'!$B$6)+0.5,1)-0.5,CEILING(MAX(M47*L47,M47+'Read me'!$B$6),5)) -> 17.5 | O47: =IF(ISNUMBER(J47),M47-J47,"new") -> -2
A48: ACT|NSW|Small|Metro Outer | B48: ACT | C48: NSW | D48: Small | E48: Metro Outer | F48: 13.76 | G48: 0 | H48: 121 | I48: 0.85 | J48: 14.5 | K48: 19.5 | L48: =INDEX('Read me'!$B$10:$B$14,1) -> 1.34 | M48: =IF(F48*(1+'Read me'!$B$5)<='Read me'!$B$7,CEILING(F48*(1+'Read me'!$B$5)+0.5,1)-0.5,CEILING(F48*(1+'Read me'!$B$5),5)) -> 14.5 | N48: =IF(MAX(M48*L48,M48+'Read me'!$B$6)<='Read me'!$B$7,CEILING(MAX(M48*L48,M48+'Read me'!$B$6)+0.5,1)-0.5,CEILING(MAX(M48*L48,M48+'Read me'!$B$6),5)) -> 19.5 | O48: =IF(ISNUMBER(J48),M48-J48,"new") -> 0
A49: ACT|NSW|Small|Regional | B49: ACT | C49: NSW | D49: Small | E49: Regional | F49: 16.93 | G49: 0 | H49: 121 | I49: 0.85 | J49: 17.5 | K49: 29.5 | L49: =INDEX('Read me'!$B$10:$B$14,1) -> 1.34 | M49: =IF(F49*(1+'Read me'!$B$5)<='Read me'!$B$7,CEILING(F49*(1+'Read me'!$B$5)+0.5,1)-0.5,CEILING(F49*(1+'Read me'!$B$5),5)) -> 17.5 | N49: =IF(MAX(M49*L49,M49+'Read me'!$B$6)<='Read me'!$B$7,CEILING(MAX(M49*L49,M49+'Read me'!$B$6)+0.5,1)-0.5,CEILING(MAX(M49*L49,M49+'Read me'!$B$6),5)) -> 23.5 | O49: =IF(ISNUMBER(J49),M49-J49,"new") -> 0
A50: ACT|NSW|Medium|Metro | B50: ACT | C50: NSW | D50: Medium | E50: Metro | F50: 35.96 | G50: 53 | H50: 121 | I50: 0.97 | J50: 19.5 | K50: 24.5 | L50: =INDEX('Read me'!$B$10:$B$14,2) -> 1.26 | M50: =IF(F50*(1+'Read me'!$B$5)<='Read me'!$B$7,CEILING(F50*(1+'Read me'!$B$5)+0.5,1)-0.5,CEILING(F50*(1+'Read me'!$B$5),5)) -> 40 | N50: =IF(MAX(M50*L50,M50+'Read me'!$B$6)<='Read me'!$B$7,CEILING(MAX(M50*L50,M50+'Read me'!$B$6)+0.5,1)-0.5,CEILING(MAX(M50*L50,M50+'Read me'!$B$6),5)) -> 55 | O50: =IF(ISNUMBER(J50),M50-J50,"new") -> 20.5
A51: ACT|NSW|Medium|Metro Outer | B51: ACT | C51: NSW | D51: Medium | E51: Metro Outer | F51: 46.43 | G51: 0 | H51: 121 | I51: 0.97 | J51: 19.5 | K51: 24.5 | L51: =INDEX('Read me'!$B$10:$B$14,2) -> 1.26 | M51: =IF(F51*(1+'Read me'!$B$5)<='Read me'!$B$7,CEILING(F51*(1+'Read me'!$B$5)+0.5,1)-0.5,CEILING(F51*(1+'Read me'!$B$5),5)) -> 50 | N51: =IF(MAX(M51*L51,M51+'Read me'!$B$6)<='Read me'!$B$7,CEILING(MAX(M51*L51,M51+'Read me'!$B$6)+0.5,1)-0.5,CEILING(MAX(M51*L51,M51+'Read me'!$B$6),5)) -> 65 | O51: =IF(ISNUMBER(J51),M51-J51,"new") -> 30.5
A52: ACT|NSW|Medium|Regional | B52: ACT | C52: NSW | D52: Medium | E52: Regional | F52: 51.87 | G52: 0 | H52: 121 | I52: 0.97 | J52: 19.5 | K52: 34.5 | L52: =INDEX('Read me'!$B$10:$B$14,2) -> 1.26 | M52: =IF(F52*(1+'Read me'!$B$5)<='Read me'!$B$7,CEILING(F52*(1+'Read me'!$B$5)+0.5,1)-0.5,CEILING(F52*(1+'Read me'!$B$5),5)) -> 55 | N52: =IF(MAX(M52*L52,M52+'Read me'!$B$6)<='Read me'!$B$7,CEILING(MAX(M52*L52,M52+'Read me'!$B$6)+0.5,1)-0.5,CEILING(MAX(M52*L52,M52+'Read me'!$B$6),5)) -> 70 | O52: =IF(ISNUMBER(J52),M52-J52,"new") -> 35.5
A53: ACT|NSW|Large|Metro | B53: ACT | C53: NSW | D53: Large | E53: Metro | F53: 72.84 | G53: 9 | H53: 121 | I53: 0.98 | J53: 24.5 | K53: 75 | L53: =INDEX('Read me'!$B$10:$B$14,3) -> 1.35 | M53: =IF(F53*(1+'Read me'!$B$5)<='Read me'!$B$7,CEILING(F53*(1+'Read me'!$B$5)+0.5,1)-0.5,CEILING(F53*(1+'Read me'!$B$5),5)) -> 75 | N53: =IF(MAX(M53*L53,M53+'Read me'!$B$6)<='Read me'!$B$7,CEILING(MAX(M53*L53,M53+'Read me'!$B$6)+0.5,1)-0.5,CEILING(MAX(M53*L53,M53+'Read me'!$B$6),5)) -> 105 | O53: =IF(ISNUMBER(J53),M53-J53,"new") -> 50.5
A54: ACT|NSW|Large|Metro Outer | B54: ACT | C54: NSW | D54: Large | E54: Metro Outer | F54: 83.4 | G54: 0 | H54: 121 | I54: 0.98 | J54: 24.5 | K54: 75 | L54: =INDEX('Read me'!$B$10:$B$14,3) -> 1.35 | M54: =IF(F54*(1+'Read me'!$B$5)<='Read me'!$B$7,CEILING(F54*(1+'Read me'!$B$5)+0.5,1)-0.5,CEILING(F54*(1+'Read me'!$B$5),5)) -> 85 | N54: =IF(MAX(M54*L54,M54+'Read me'!$B$6)<='Read me'!$B$7,CEILING(MAX(M54*L54,M54+'Read me'!$B$6)+0.5,1)-0.5,CEILING(MAX(M54*L54,M54+'Read me'!$B$6),5)) -> 115 | O54: =IF(ISNUMBER(J54),M54-J54,"new") -> 60.5
A55: ACT|NSW|Large|Regional | B55: ACT | C55: NSW | D55: Large | E55: Regional | F55: 113.9 | G55: 0 | H55: 121 | I55: 0.98 | J55: 85 | K55: 125 | L55: =INDEX('Read me'!$B$10:$B$14,3) -> 1.35 | M55: =IF(F55*(1+'Read me'!$B$5)<='Read me'!$B$7,CEILING(F55*(1+'Read me'!$B$5)+0.5,1)-0.5,CEILING(F55*(1+'Read me'!$B$5),5)) -> 115 | N55: =IF(MAX(M55*L55,M55+'Read me'!$B$6)<='Read me'!$B$7,CEILING(MAX(M55*L55,M55+'Read me'!$B$6)+0.5,1)-0.5,CEILING(MAX(M55*L55,M55+'Read me'!$B$6),5)) -> 160 | O55: =IF(ISNUMBER(J55),M55-J55,"new") -> 30
A56: ACT|NSW|XL|Metro | B56: ACT | C56: NSW | D56: XL | E56: Metro | F56: 125.72 | G56: 3 | H56: 121 | I56: 0.98 | J56: 85 | K56: 125 | L56: =INDEX('Read me'!$B$10:$B$14,4) -> 1.2 | M56: =IF(F56*(1+'Read me'!$B$5)<='Read me'!$B$7,CEILING(F56*(1+'Read me'!$B$5)+0.5,1)-0.5,CEILING(F56*(1+'Read me'!$B$5),5)) -> 130 | N56: =IF(MAX(M56*L56,M56+'Read me'!$B$6)<='Read me'!$B$7,CEILING(MAX(M56*L56,M56+'Read me'!$B$6)+0.5,1)-0.5,CEILING(MAX(M56*L56,M56+'Read me'!$B$6),5)) -> 160 | O56: =IF(ISNUMBER(J56),M56-J56,"new") -> 45
A57: ACT|NSW|XL|Metro Outer | B57: ACT | C57: NSW | D57: XL | E57: Metro Outer | F57: 155.42 | G57: 0 | H57: 121 | I57: 0.98 | J57: 125 | K57: 125 | L57: =INDEX('Read me'!$B$10:$B$14,4) -> 1.2 | M57: =IF(F57*(1+'Read me'!$B$5)<='Read me'!$B$7,CEILING(F57*(1+'Read me'!$B$5)+0.5,1)-0.5,CEILING(F57*(1+'Read me'!$B$5),5)) -> 160 | N57: =IF(MAX(M57*L57,M57+'Read me'!$B$6)<='Read me'!$B$7,CEILING(MAX(M57*L57,M57+'Read me'!$B$6)+0.5,1)-0.5,CEILING(MAX(M57*L57,M57+'Read me'!$B$6),5)) -> 195 | O57: =IF(ISNUMBER(J57),M57-J57,"new") -> 35
A58: ACT|NSW|XL|Regional | B58: ACT | C58: NSW | D58: XL | E58: Regional | F58: 197.44 | G58: 0 | H58: 121 | I58: 0.98 | J58: 199 | K58: 175 | L58: =INDEX('Read me'!$B$10:$B$14,4) -> 1.2 | M58: =IF(F58*(1+'Read me'!$B$5)<='Read me'!$B$7,CEILING(F58*(1+'Read me'!$B$5)+0.5,1)-0.5,CEILING(F58*(1+'Read me'!$B$5),5)) -> 200 | N58: =IF(MAX(M58*L58,M58+'Read me'!$B$6)<='Read me'!$B$7,CEILING(MAX(M58*L58,M58+'Read me'!$B$6)+0.5,1)-0.5,CEILING(MAX(M58*L58,M58+'Read me'!$B$6),5)) -> 240 | O58: =IF(ISNUMBER(J58),M58-J58,"new") -> 1
A59: ACT|NSW|XXL|Metro | B59: ACT | C59: NSW | D59: XXL | E59: Metro | F59: 165.86 | G59: 1 | H59: 121 | I59: 0.98 | J59: 250 | K59: 300 | L59: =INDEX('Read me'!$B$10:$B$14,5) -> 1.2 | M59: =IF(F59*(1+'Read me'!$B$5)<='Read me'!$B$7,CEILING(F59*(1+'Read me'!$B$5)+0.5,1)-0.5,CEILING(F59*(1+'Read me'!$B$5),5)) -> 170 | N59: =IF(MAX(M59*L59,M59+'Read me'!$B$6)<='Read me'!$B$7,CEILING(MAX(M59*L59,M59+'Read me'!$B$6)+0.5,1)-0.5,CEILING(MAX(M59*L59,M59+'Read me'!$B$6),5)) -> 205 | O59: =IF(ISNUMBER(J59),M59-J59,"new") -> -80
A60: ACT|NSW|XXL|Metro Outer | B60: ACT | C60: NSW | D60: XXL | E60: Metro Outer | F60: 227.22 | G60: 0 | H60: 121 | I60: 0.98 | J60: 250 | K60: 300 | L60: =INDEX('Read me'!$B$10:$B$14,5) -> 1.2 | M60: =IF(MAX((IF(F60*(1+'Read me'!$B$5)<='Read me'!$B$7,CEILING(F60*(1+'Read me'!$B$5)+0.5,1)-0.5,CEILING(F60*(1+'Read me'!$B$5),5)))*L60,(IF(F60*(1+'Read me'!$B$5)<='Read me'!$B$7,CEILING(F60*(1+'Read me'!$B$5)+0.5,1)-0.5,CEILING(F60*(1+'Read me'!$B$5),5)))+'Read me'!$B$6)<='Read me'!$B$7,CEILING(MAX((IF(F60*(1+'Read me'!$B$5)<='Read me'!$B$7,CEILING(F60*(1+'Read me'!$B$5)+0.5,1)-0.5,CEILING(F60*(1+'Read me'!$B$5),5)))*L60,(IF(F60*(1+'Read me'!$B$5)<='Read me'!$B$7,CEILING(F60*(1+'Read me'!$B$5)+0.5,1)-0.5,CEILING(F60*(1+'Read me'!$B$5),5)))+'Read me'!$B$6)+0.5,1)-0.5,CEILING(MAX((IF(F60*(1+'Read me'!$B$5)<='Read me'!$B$7,CEILING(F60*(1+'Read me'!$B$5)+0.5,1)-0.5,CEILING(F60*(1+'Read me'!$B$5),5)))*L60,(IF(F60*(1+'Read me'!$B$5)<='Read me'!$B$7,CEILING(F60*(1+'Read me'!$B$5)+0.5,1)-0.5,CEILING(F60*(1+'Read me'!$B$5),5)))+'Read me'!$B$6),5)) -> 280 | N60: Not offered | O60: =IF(ISNUMBER(J60),M60-J60,"new") -> 30 | P60: One rate: interstate XXL/Bulky to Metro Outer or Regional. Standard is charged at what Priority would have been; no Priority option
A61: ACT|NSW|XXL|Regional | B61: ACT | C61: NSW | D61: XXL | E61: Regional | F61: 272.06 | G61: 0 | H61: 121 | I61: 0.98 | J61: 300 | K61: 400 | L61: =INDEX('Read me'!$B$10:$B$14,5) -> 1.2 | M61: =IF(MAX((IF(F61*(1+'Read me'!$B$5)<='Read me'!$B$7,CEILING(F61*(1+'Read me'!$B$5)+0.5,1)-0.5,CEILING(F61*(1+'Read me'!$B$5),5)))*L61,(IF(F61*(1+'Read me'!$B$5)<='Read me'!$B$7,CEILING(F61*(1+'Read me'!$B$5)+0.5,1)-0.5,CEILING(F61*(1+'Read me'!$B$5),5)))+'Read me'!$B$6)<='Read me'!$B$7,CEILING(MAX((IF(F61*(1+'Read me'!$B$5)<='Read me'!$B$7,CEILING(F61*(1+'Read me'!$B$5)+0.5,1)-0.5,CEILING(F61*(1+'Read me'!$B$5),5)))*L61,(IF(F61*(1+'Read me'!$B$5)<='Read me'!$B$7,CEILING(F61*(1+'Read me'!$B$5)+0.5,1)-0.5,CEILING(F61*(1+'Read me'!$B$5),5)))+'Read me'!$B$6)+0.5,1)-0.5,CEILING(MAX((IF(F61*(1+'Read me'!$B$5)<='Read me'!$B$7,CEILING(F61*(1+'Read me'!$B$5)+0.5,1)-0.5,CEILING(F61*(1+'Read me'!$B$5),5)))*L61,(IF(F61*(1+'Read me'!$B$5)<='Read me'!$B$7,CEILING(F61*(1+'Read me'!$B$5)+0.5,1)-0.5,CEILING(F61*(1+'Read me'!$B$5),5)))+'Read me'!$B$6),5)) -> 330 | N61: Not offered | O61: =IF(ISNUMBER(J61),M61-J61,"new") -> 30 | P61: One rate: interstate XXL/Bulky to Metro Outer or Regional. Standard is charged at what Priority would have been; no Priority option
A62: ACT|ACT|Small|Metro | B62: ACT | C62: ACT | D62: Small | E62: Metro | F62: 11.93 | G62: 36 | H62: 68 | I62: 1.6 | J62: 9.5 | K62: 14.5 | L62: =INDEX('Read me'!$B$10:$B$14,1) -> 1.34 | M62: =IF(F62*(1+'Read me'!$B$5)<='Read me'!$B$7,CEILING(F62*(1+'Read me'!$B$5)+0.5,1)-0.5,CEILING(F62*(1+'Read me'!$B$5),5)) -> 12.5 | N62: =IF(MAX(M62*L62,M62+'Read me'!$B$6)<='Read me'!$B$7,CEILING(MAX(M62*L62,M62+'Read me'!$B$6)+0.5,1)-0.5,CEILING(MAX(M62*L62,M62+'Read me'!$B$6),5)) -> 17.5 | O62: =IF(ISNUMBER(J62),M62-J62,"new") -> 3
A63: ACT|ACT|Small|Metro Outer | B63: ACT | C63: ACT | D63: Small | E63: Metro Outer | F63: 13.07 | G63: 0 | H63: 68 | I63: 1.6 | J63: 12.5 | K63: 17.5 | L63: =INDEX('Read me'!$B$10:$B$14,1) -> 1.34 | M63: =IF(F63*(1+'Read me'!$B$5)<='Read me'!$B$7,CEILING(F63*(1+'Read me'!$B$5)+0.5,1)-0.5,CEILING(F63*(1+'Read me'!$B$5),5)) -> 13.5 | N63: =IF(MAX(M63*L63,M63+'Read me'!$B$6)<='Read me'!$B$7,CEILING(MAX(M63*L63,M63+'Read me'!$B$6)+0.5,1)-0.5,CEILING(MAX(M63*L63,M63+'Read me'!$B$6),5)) -> 18.5 | O63: =IF(ISNUMBER(J63),M63-J63,"new") -> 1
A64: ACT|ACT|Small|Regional | B64: ACT | C64: ACT | D64: Small | E64: Regional | F64: 16.07 | G64: 0 | H64: 68 | I64: 1.6 | J64: 17.5 | K64: 24.5 | L64: =INDEX('Read me'!$B$10:$B$14,1) -> 1.34 | M64: =IF(F64*(1+'Read me'!$B$5)<='Read me'!$B$7,CEILING(F64*(1+'Read me'!$B$5)+0.5,1)-0.5,CEILING(F64*(1+'Read me'!$B$5),5)) -> 16.5 | N64: =IF(MAX(M64*L64,M64+'Read me'!$B$6)<='Read me'!$B$7,CEILING(MAX(M64*L64,M64+'Read me'!$B$6)+0.5,1)-0.5,CEILING(MAX(M64*L64,M64+'Read me'!$B$6),5)) -> 22.5 | O64: =IF(ISNUMBER(J64),M64-J64,"new") -> -1
A65: ACT|ACT|Medium|Metro | B65: ACT | C65: ACT | D65: Medium | E65: Metro | F65: 34.32 | G65: 27 | H65: 68 | I65: 1.6 | J65: 9.5 | K65: 19.5 | L65: =INDEX('Read me'!$B$10:$B$14,2) -> 1.26 | M65: =IF(F65*(1+'Read me'!$B$5)<='Read me'!$B$7,CEILING(F65*(1+'Read me'!$B$5)+0.5,1)-0.5,CEILING(F65*(1+'Read me'!$B$5),5)) -> 35 | N65: =IF(MAX(M65*L65,M65+'Read me'!$B$6)<='Read me'!$B$7,CEILING(MAX(M65*L65,M65+'Read me'!$B$6)+0.5,1)-0.5,CEILING(MAX(M65*L65,M65+'Read me'!$B$6),5)) -> 45 | O65: =IF(ISNUMBER(J65),M65-J65,"new") -> 25.5
A66: ACT|ACT|Medium|Metro Outer | B66: ACT | C66: ACT | D66: Medium | E66: Metro Outer | F66: 39.62 | G66: 0 | H66: 68 | I66: 1.6 | J66: 12.5 | K66: 19.5 | L66: =INDEX('Read me'!$B$10:$B$14,2) -> 1.26 | M66: =IF(F66*(1+'Read me'!$B$5)<='Read me'!$B$7,CEILING(F66*(1+'Read me'!$B$5)+0.5,1)-0.5,CEILING(F66*(1+'Read me'!$B$5),5)) -> 40 | N66: =IF(MAX(M66*L66,M66+'Read me'!$B$6)<='Read me'!$B$7,CEILING(MAX(M66*L66,M66+'Read me'!$B$6)+0.5,1)-0.5,CEILING(MAX(M66*L66,M66+'Read me'!$B$6),5)) -> 55 | O66: =IF(ISNUMBER(J66),M66-J66,"new") -> 27.5
A67: ACT|ACT|Medium|Regional | B67: ACT | C67: ACT | D67: Medium | E67: Regional | F67: 44.27 | G67: 0 | H67: 68 | I67: 1.6 | J67: 19.5 | K67: 29.5 | L67: =INDEX('Read me'!$B$10:$B$14,2) -> 1.26 | M67: =IF(F67*(1+'Read me'!$B$5)<='Read me'!$B$7,CEILING(F67*(1+'Read me'!$B$5)+0.5,1)-0.5,CEILING(F67*(1+'Read me'!$B$5),5)) -> 45 | N67: =IF(MAX(M67*L67,M67+'Read me'!$B$6)<='Read me'!$B$7,CEILING(MAX(M67*L67,M67+'Read me'!$B$6)+0.5,1)-0.5,CEILING(MAX(M67*L67,M67+'Read me'!$B$6),5)) -> 60 | O67: =IF(ISNUMBER(J67),M67-J67,"new") -> 25.5
A68: ACT|ACT|Large|Metro | B68: ACT | C68: ACT | D68: Large | E68: Metro | F68: 58.91 | G68: 2 | H68: 68 | I68: 1.59 | J68: 19 | K68: 45 | L68: =INDEX('Read me'!$B$10:$B$14,3) -> 1.35 | M68: =IF(F68*(1+'Read me'!$B$5)<='Read me'!$B$7,CEILING(F68*(1+'Read me'!$B$5)+0.5,1)-0.5,CEILING(F68*(1+'Read me'!$B$5),5)) -> 60 | N68: =IF(MAX(M68*L68,M68+'Read me'!$B$6)<='Read me'!$B$7,CEILING(MAX(M68*L68,M68+'Read me'!$B$6)+0.5,1)-0.5,CEILING(MAX(M68*L68,M68+'Read me'!$B$6),5)) -> 85 | O68: =IF(ISNUMBER(J68),M68-J68,"new") -> 41
A69: ACT|ACT|Large|Metro Outer | B69: ACT | C69: ACT | D69: Large | E69: Metro Outer | F69: 69.11 | G69: 0 | H69: 68 | I69: 1.59 | J69: 24.5 | K69: 45 | L69: =INDEX('Read me'!$B$10:$B$14,3) -> 1.35 | M69: =IF(F69*(1+'Read me'!$B$5)<='Read me'!$B$7,CEILING(F69*(1+'Read me'!$B$5)+0.5,1)-0.5,CEILING(F69*(1+'Read me'!$B$5),5)) -> 70 | N69: =IF(MAX(M69*L69,M69+'Read me'!$B$6)<='Read me'!$B$7,CEILING(MAX(M69*L69,M69+'Read me'!$B$6)+0.5,1)-0.5,CEILING(MAX(M69*L69,M69+'Read me'!$B$6),5)) -> 95 | O69: =IF(ISNUMBER(J69),M69-J69,"new") -> 45.5
A70: ACT|ACT|Large|Regional | B70: ACT | C70: ACT | D70: Large | E70: Regional | F70: 94.38 | G70: 0 | H70: 68 | I70: 1.59 | J70: 50 | K70: 95 | L70: =INDEX('Read me'!$B$10:$B$14,3) -> 1.35 | M70: =IF(F70*(1+'Read me'!$B$5)<='Read me'!$B$7,CEILING(F70*(1+'Read me'!$B$5)+0.5,1)-0.5,CEILING(F70*(1+'Read me'!$B$5),5)) -> 95 | N70: =IF(MAX(M70*L70,M70+'Read me'!$B$6)<='Read me'!$B$7,CEILING(MAX(M70*L70,M70+'Read me'!$B$6)+0.5,1)-0.5,CEILING(MAX(M70*L70,M70+'Read me'!$B$6),5)) -> 130 | O70: =IF(ISNUMBER(J70),M70-J70,"new") -> 45
A71: ACT|ACT|XL|Metro | B71: ACT | C71: ACT | D71: XL | E71: Metro | F71: 100.02 | G71: 3 | H71: 68 | I71: 1.59 | J71: 25 | K71: 85 | L71: =INDEX('Read me'!$B$10:$B$14,4) -> 1.2 | M71: =IF(F71*(1+'Read me'!$B$5)<='Read me'!$B$7,CEILING(F71*(1+'Read me'!$B$5)+0.5,1)-0.5,CEILING(F71*(1+'Read me'!$B$5),5)) -> 105 | N71: =IF(MAX(M71*L71,M71+'Read me'!$B$6)<='Read me'!$B$7,CEILING(MAX(M71*L71,M71+'Read me'!$B$6)+0.5,1)-0.5,CEILING(MAX(M71*L71,M71+'Read me'!$B$6),5)) -> 130 | O71: =IF(ISNUMBER(J71),M71-J71,"new") -> 80
A72: ACT|ACT|XL|Metro Outer | B72: ACT | C72: ACT | D72: XL | E72: Metro Outer | F72: 128.79 | G72: 0 | H72: 68 | I72: 1.59 | J72: 45 | K72: 125 | L72: =INDEX('Read me'!$B$10:$B$14,4) -> 1.2 | M72: =IF(F72*(1+'Read me'!$B$5)<='Read me'!$B$7,CEILING(F72*(1+'Read me'!$B$5)+0.5,1)-0.5,CEILING(F72*(1+'Read me'!$B$5),5)) -> 130 | N72: =IF(MAX(M72*L72,M72+'Read me'!$B$6)<='Read me'!$B$7,CEILING(MAX(M72*L72,M72+'Read me'!$B$6)+0.5,1)-0.5,CEILING(MAX(M72*L72,M72+'Read me'!$B$6),5)) -> 160 | O72: =IF(ISNUMBER(J72),M72-J72,"new") -> 85
A73: ACT|ACT|XL|Regional | B73: ACT | C73: ACT | D73: XL | E73: Regional | F73: 163.61 | G73: 0 | H73: 68 | I73: 1.59 | J73: 85 | K73: 150 | L73: =INDEX('Read me'!$B$10:$B$14,4) -> 1.2 | M73: =IF(F73*(1+'Read me'!$B$5)<='Read me'!$B$7,CEILING(F73*(1+'Read me'!$B$5)+0.5,1)-0.5,CEILING(F73*(1+'Read me'!$B$5),5)) -> 165 | N73: =IF(MAX(M73*L73,M73+'Read me'!$B$6)<='Read me'!$B$7,CEILING(MAX(M73*L73,M73+'Read me'!$B$6)+0.5,1)-0.5,CEILING(MAX(M73*L73,M73+'Read me'!$B$6),5)) -> 200 | O73: =IF(ISNUMBER(J73),M73-J73,"new") -> 80
A74: ACT|ACT|XXL|Metro | B74: ACT | C74: ACT | D74: XXL | E74: Metro | F74: 134.56 | G74: 0 | H74: 68 | I74: 1.59 | J74: 45 | K74: 85 | L74: =INDEX('Read me'!$B$10:$B$14,5) -> 1.2 | M74: =IF(F74*(1+'Read me'!$B$5)<='Read me'!$B$7,CEILING(F74*(1+'Read me'!$B$5)+0.5,1)-0.5,CEILING(F74*(1+'Read me'!$B$5),5)) -> 135 | N74: =IF(MAX(M74*L74,M74+'Read me'!$B$6)<='Read me'!$B$7,CEILING(MAX(M74*L74,M74+'Read me'!$B$6)+0.5,1)-0.5,CEILING(MAX(M74*L74,M74+'Read me'!$B$6),5)) -> 165 | O74: =IF(ISNUMBER(J74),M74-J74,"new") -> 90
A75: ACT|ACT|XXL|Metro Outer | B75: ACT | C75: ACT | D75: XXL | E75: Metro Outer | F75: 188.29 | G75: 0 | H75: 68 | I75: 1.59 | J75: 85 | K75: 125 | L75: =INDEX('Read me'!$B$10:$B$14,5) -> 1.2 | M75: =IF(F75*(1+'Read me'!$B$5)<='Read me'!$B$7,CEILING(F75*(1+'Read me'!$B$5)+0.5,1)-0.5,CEILING(F75*(1+'Read me'!$B$5),5)) -> 190 | N75: =IF(MAX(M75*L75,M75+'Read me'!$B$6)<='Read me'!$B$7,CEILING(MAX(M75*L75,M75+'Read me'!$B$6)+0.5,1)-0.5,CEILING(MAX(M75*L75,M75+'Read me'!$B$6),5)) -> 230 | O75: =IF(ISNUMBER(J75),M75-J75,"new") -> 105
A76: ACT|ACT|XXL|Regional | B76: ACT | C76: ACT | D76: XXL | E76: Regional | F76: 225.44 | G76: 0 | H76: 68 | I76: 1.59 | J76: 250 | K76: 350 | L76: =INDEX('Read me'!$B$10:$B$14,5) -> 1.2 | M76: =IF(F76*(1+'Read me'!$B$5)<='Read me'!$B$7,CEILING(F76*(1+'Read me'!$B$5)+0.5,1)-0.5,CEILING(F76*(1+'Read me'!$B$5),5)) -> 230 | N76: =IF(MAX(M76*L76,M76+'Read me'!$B$6)<='Read me'!$B$7,CEILING(MAX(M76*L76,M76+'Read me'!$B$6)+0.5,1)-0.5,CEILING(MAX(M76*L76,M76+'Read me'!$B$6),5)) -> 280 | O76: =IF(ISNUMBER(J76),M76-J76,"new") -> -20
A77: ACT|TAS|Small|Metro | B77: ACT | C77: TAS | D77: Small | E77: Metro | F77: 12.65 | G77: 3 | H77: 3 | I77: 0.95 | J77: 19.5 | K77: 24.5 | L77: =INDEX('Read me'!$B$10:$B$14,1) -> 1.34 | M77: =IF(F77*(1+'Read me'!$B$5)<='Read me'!$B$7,CEILING(F77*(1+'Read me'!$B$5)+0.5,1)-0.5,CEILING(F77*(1+'Read me'!$B$5),5)) -> 13.5 | N77: =IF(MAX(M77*L77,M77+'Read me'!$B$6)<='Read me'!$B$7,CEILING(MAX(M77*L77,M77+'Read me'!$B$6)+0.5,1)-0.5,CEILING(MAX(M77*L77,M77+'Read me'!$B$6),5)) -> 18.5 | O77: =IF(ISNUMBER(J77),M77-J77,"new") -> -6
A78: ACT|TAS|Small|Metro Outer | B78: ACT | C78: TAS | D78: Small | E78: Metro Outer | F78: 15.35 | G78: 0 | H78: 3 | I78: 0.95 | J78: 19.5 | K78: 24.5 | L78: =INDEX('Read me'!$B$10:$B$14,1) -> 1.34 | M78: =IF(F78*(1+'Read me'!$B$5)<='Read me'!$B$7,CEILING(F78*(1+'Read me'!$B$5)+0.5,1)-0.5,CEILING(F78*(1+'Read me'!$B$5),5)) -> 15.5 | N78: =IF(MAX(M78*L78,M78+'Read me'!$B$6)<='Read me'!$B$7,CEILING(MAX(M78*L78,M78+'Read me'!$B$6)+0.5,1)-0.5,CEILING(MAX(M78*L78,M78+'Read me'!$B$6),5)) -> 21.5 | O78: =IF(ISNUMBER(J78),M78-J78,"new") -> -4
A79: ACT|TAS|Small|Regional | B79: ACT | C79: TAS | D79: Small | E79: Regional | F79: 18.88 | G79: 0 | H79: 3 | I79: 0.95 | J79: 19.5 | K79: 34.5 | L79: =INDEX('Read me'!$B$10:$B$14,1) -> 1.34 | M79: =IF(F79*(1+'Read me'!$B$5)<='Read me'!$B$7,CEILING(F79*(1+'Read me'!$B$5)+0.5,1)-0.5,CEILING(F79*(1+'Read me'!$B$5),5)) -> 19.5 | N79: =IF(MAX(M79*L79,M79+'Read me'!$B$6)<='Read me'!$B$7,CEILING(MAX(M79*L79,M79+'Read me'!$B$6)+0.5,1)-0.5,CEILING(MAX(M79*L79,M79+'Read me'!$B$6),5)) -> 26.5 | O79: =IF(ISNUMBER(J79),M79-J79,"new") -> 0
A80: ACT|TAS|Medium|Metro | B80: ACT | C80: TAS | D80: Medium | E80: Metro | F80: 38.15 | G80: 0 | H80: 3 | I80: 0.94 | J80: 24.5 | K80: 29.5 | L80: =INDEX('Read me'!$B$10:$B$14,2) -> 1.26 | M80: =IF(F80*(1+'Read me'!$B$5)<='Read me'!$B$7,CEILING(F80*(1+'Read me'!$B$5)+0.5,1)-0.5,CEILING(F80*(1+'Read me'!$B$5),5)) -> 40 | N80: =IF(MAX(M80*L80,M80+'Read me'!$B$6)<='Read me'!$B$7,CEILING(MAX(M80*L80,M80+'Read me'!$B$6)+0.5,1)-0.5,CEILING(MAX(M80*L80,M80+'Read me'!$B$6),5)) -> 55 | O80: =IF(ISNUMBER(J80),M80-J80,"new") -> 15.5
A81: ACT|TAS|Medium|Metro Outer | B81: ACT | C81: TAS | D81: Medium | E81: Metro Outer | F81: 45.18 | G81: 0 | H81: 3 | I81: 0.94 | J81: 24.5 | K81: 29.5 | L81: =INDEX('Read me'!$B$10:$B$14,2) -> 1.26 | M81: =IF(F81*(1+'Read me'!$B$5)<='Read me'!$B$7,CEILING(F81*(1+'Read me'!$B$5)+0.5,1)-0.5,CEILING(F81*(1+'Read me'!$B$5),5)) -> 50 | N81: =IF(MAX(M81*L81,M81+'Read me'!$B$6)<='Read me'!$B$7,CEILING(MAX(M81*L81,M81+'Read me'!$B$6)+0.5,1)-0.5,CEILING(MAX(M81*L81,M81+'Read me'!$B$6),5)) -> 65 | O81: =IF(ISNUMBER(J81),M81-J81,"new") -> 25.5
A82: ACT|TAS|Medium|Regional | B82: ACT | C82: TAS | D82: Medium | E82: Regional | F82: 50.47 | G82: 0 | H82: 3 | I82: 0.94 | J82: 24.5 | K82: 45 | L82: =INDEX('Read me'!$B$10:$B$14,2) -> 1.26 | M82: =IF(F82*(1+'Read me'!$B$5)<='Read me'!$B$7,CEILING(F82*(1+'Read me'!$B$5)+0.5,1)-0.5,CEILING(F82*(1+'Read me'!$B$5),5)) -> 55 | N82: =IF(MAX(M82*L82,M82+'Read me'!$B$6)<='Read me'!$B$7,CEILING(MAX(M82*L82,M82+'Read me'!$B$6)+0.5,1)-0.5,CEILING(MAX(M82*L82,M82+'Read me'!$B$6),5)) -> 70 | O82: =IF(ISNUMBER(J82),M82-J82,"new") -> 30.5
A83: ACT|TAS|Large|Metro | B83: ACT | C83: TAS | D83: Large | E83: Metro | F83: 69.39 | G83: 0 | H83: 3 | I83: 0.94 | J83: 45 | K83: 95 | L83: =INDEX('Read me'!$B$10:$B$14,3) -> 1.35 | M83: =IF(F83*(1+'Read me'!$B$5)<='Read me'!$B$7,CEILING(F83*(1+'Read me'!$B$5)+0.5,1)-0.5,CEILING(F83*(1+'Read me'!$B$5),5)) -> 70 | N83: =IF(MAX(M83*L83,M83+'Read me'!$B$6)<='Read me'!$B$7,CEILING(MAX(M83*L83,M83+'Read me'!$B$6)+0.5,1)-0.5,CEILING(MAX(M83*L83,M83+'Read me'!$B$6),5)) -> 95 | O83: =IF(ISNUMBER(J83),M83-J83,"new") -> 25
A84: ACT|TAS|Large|Metro Outer | B84: ACT | C84: TAS | D84: Large | E84: Metro Outer | F84: 80.12 | G84: 0 | H84: 3 | I84: 0.94 | J84: 45 | K84: 95 | L84: =INDEX('Read me'!$B$10:$B$14,3) -> 1.35 | M84: =IF(F84*(1+'Read me'!$B$5)<='Read me'!$B$7,CEILING(F84*(1+'Read me'!$B$5)+0.5,1)-0.5,CEILING(F84*(1+'Read me'!$B$5),5)) -> 85 | N84: =IF(MAX(M84*L84,M84+'Read me'!$B$6)<='Read me'!$B$7,CEILING(MAX(M84*L84,M84+'Read me'!$B$6)+0.5,1)-0.5,CEILING(MAX(M84*L84,M84+'Read me'!$B$6),5)) -> 115 | O84: =IF(ISNUMBER(J84),M84-J84,"new") -> 40
A85: ACT|TAS|Large|Regional | B85: ACT | C85: TAS | D85: Large | E85: Regional | F85: 109.42 | G85: 0 | H85: 3 | I85: 0.94 | J85: 99 | K85: 150 | L85: =INDEX('Read me'!$B$10:$B$14,3) -> 1.35 | M85: =IF(F85*(1+'Read me'!$B$5)<='Read me'!$B$7,CEILING(F85*(1+'Read me'!$B$5)+0.5,1)-0.5,CEILING(F85*(1+'Read me'!$B$5),5)) -> 110 | N85: =IF(MAX(M85*L85,M85+'Read me'!$B$6)<='Read me'!$B$7,CEILING(MAX(M85*L85,M85+'Read me'!$B$6)+0.5,1)-0.5,CEILING(MAX(M85*L85,M85+'Read me'!$B$6),5)) -> 150 | O85: =IF(ISNUMBER(J85),M85-J85,"new") -> 11
A86: ACT|TAS|XL|Metro | B86: ACT | C86: TAS | D86: XL | E86: Metro | F86: 115.96 | G86: 0 | H86: 3 | I86: 0.94 | J86: 99 | K86: 150 | L86: =INDEX('Read me'!$B$10:$B$14,4) -> 1.2 | M86: =IF(F86*(1+'Read me'!$B$5)<='Read me'!$B$7,CEILING(F86*(1+'Read me'!$B$5)+0.5,1)-0.5,CEILING(F86*(1+'Read me'!$B$5),5)) -> 120 | N86: =IF(MAX(M86*L86,M86+'Read me'!$B$6)<='Read me'!$B$7,CEILING(MAX(M86*L86,M86+'Read me'!$B$6)+0.5,1)-0.5,CEILING(MAX(M86*L86,M86+'Read me'!$B$6),5)) -> 145 | O86: =IF(ISNUMBER(J86),M86-J86,"new") -> 21
A87: ACT|TAS|XL|Metro Outer | B87: ACT | C87: TAS | D87: XL | E87: Metro Outer | F87: 149.31 | G87: 0 | H87: 3 | I87: 0.94 | J87: 150 | K87: 150 | L87: =INDEX('Read me'!$B$10:$B$14,4) -> 1.2 | M87: =IF(F87*(1+'Read me'!$B$5)<='Read me'!$B$7,CEILING(F87*(1+'Read me'!$B$5)+0.5,1)-0.5,CEILING(F87*(1+'Read me'!$B$5),5)) -> 150 | N87: =IF(MAX(M87*L87,M87+'Read me'!$B$6)<='Read me'!$B$7,CEILING(MAX(M87*L87,M87+'Read me'!$B$6)+0.5,1)-0.5,CEILING(MAX(M87*L87,M87+'Read me'!$B$6),5)) -> 180 | O87: =IF(ISNUMBER(J87),M87-J87,"new") -> 0
A88: ACT|TAS|XL|Regional | B88: ACT | C88: TAS | D88: XL | E88: Regional | F88: 189.68 | G88: 0 | H88: 3 | I88: 0.94 | J88: 250 | K88: 195 | L88: =INDEX('Read me'!$B$10:$B$14,4) -> 1.2 | M88: =IF(F88*(1+'Read me'!$B$5)<='Read me'!$B$7,CEILING(F88*(1+'Read me'!$B$5)+0.5,1)-0.5,CEILING(F88*(1+'Read me'!$B$5),5)) -> 190 | N88: =IF(MAX(M88*L88,M88+'Read me'!$B$6)<='Read me'!$B$7,CEILING(MAX(M88*L88,M88+'Read me'!$B$6)+0.5,1)-0.5,CEILING(MAX(M88*L88,M88+'Read me'!$B$6),5)) -> 230 | O88: =IF(ISNUMBER(J88),M88-J88,"new") -> -60
A89: ACT|TAS|XXL|Metro | B89: ACT | C89: TAS | D89: XXL | E89: Metro | F89: 156 | G89: 0 | H89: 3 | I89: 0.94 | J89: 300 | K89: 300 | L89: =INDEX('Read me'!$B$10:$B$14,5) -> 1.2 | M89: =IF(F89*(1+'Read me'!$B$5)<='Read me'!$B$7,CEILING(F89*(1+'Read me'!$B$5)+0.5,1)-0.5,CEILING(F89*(1+'Read me'!$B$5),5)) -> 160 | N89: =IF(MAX(M89*L89,M89+'Read me'!$B$6)<='Read me'!$B$7,CEILING(MAX(M89*L89,M89+'Read me'!$B$6)+0.5,1)-0.5,CEILING(MAX(M89*L89,M89+'Read me'!$B$6),5)) -> 195 | O89: =IF(ISNUMBER(J89),M89-J89,"new") -> -140
A90: ACT|TAS|XXL|Metro Outer | B90: ACT | C90: TAS | D90: XXL | E90: Metro Outer | F90: 218.29 | G90: 0 | H90: 3 | I90: 0.94 | J90: 300 | K90: 300 | L90: =INDEX('Read me'!$B$10:$B$14,5) -> 1.2 | M90: =IF(MAX((IF(F90*(1+'Read me'!$B$5)<='Read me'!$B$7,CEILING(F90*(1+'Read me'!$B$5)+0.5,1)-0.5,CEILING(F90*(1+'Read me'!$B$5),5)))*L90,(IF(F90*(1+'Read me'!$B$5)<='Read me'!$B$7,CEILING(F90*(1+'Read me'!$B$5)+0.5,1)-0.5,CEILING(F90*(1+'Read me'!$B$5),5)))+'Read me'!$B$6)<='Read me'!$B$7,CEILING(MAX((IF(F90*(1+'Read me'!$B$5)<='Read me'!$B$7,CEILING(F90*(1+'Read me'!$B$5)+0.5,1)-0.5,CEILING(F90*(1+'Read me'!$B$5),5)))*L90,(IF(F90*(1+'Read me'!$B$5)<='Read me'!$B$7,CEILING(F90*(1+'Read me'!$B$5)+0.5,1)-0.5,CEILING(F90*(1+'Read me'!$B$5),5)))+'Read me'!$B$6)+0.5,1)-0.5,CEILING(MAX((IF(F90*(1+'Read me'!$B$5)<='Read me'!$B$7,CEILING(F90*(1+'Read me'!$B$5)+0.5,1)-0.5,CEILING(F90*(1+'Read me'!$B$5),5)))*L90,(IF(F90*(1+'Read me'!$B$5)<='Read me'!$B$7,CEILING(F90*(1+'Read me'!$B$5)+0.5,1)-0.5,CEILING(F90*(1+'Read me'!$B$5),5)))+'Read me'!$B$6),5)) -> 265 | N90: Not offered | O90: =IF(ISNUMBER(J90),M90-J90,"new") -> -35 | P90: One rate: interstate XXL/Bulky to Metro Outer or Regional. Standard is charged at what Priority would have been; no Priority option
A91: ACT|TAS|XXL|Regional | B91: ACT | C91: TAS | D91: XXL | E91: Regional | F91: 261.37 | G91: 0 | H91: 3 | I91: 0.94 | J91: 350 | K91: 400 | L91: =INDEX('Read me'!$B$10:$B$14,5) -> 1.2 | M91: =IF(MAX((IF(F91*(1+'Read me'!$B$5)<='Read me'!$B$7,CEILING(F91*(1+'Read me'!$B$5)+0.5,1)-0.5,CEILING(F91*(1+'Read me'!$B$5),5)))*L91,(IF(F91*(1+'Read me'!$B$5)<='Read me'!$B$7,CEILING(F91*(1+'Read me'!$B$5)+0.5,1)-0.5,CEILING(F91*(1+'Read me'!$B$5),5)))+'Read me'!$B$6)<='Read me'!$B$7,CEILING(MAX((IF(F91*(1+'Read me'!$B$5)<='Read me'!$B$7,CEILING(F91*(1+'Read me'!$B$5)+0.5,1)-0.5,CEILING(F91*(1+'Read me'!$B$5),5)))*L91,(IF(F91*(1+'Read me'!$B$5)<='Read me'!$B$7,CEILING(F91*(1+'Read me'!$B$5)+0.5,1)-0.5,CEILING(F91*(1+'Read me'!$B$5),5)))+'Read me'!$B$6)+0.5,1)-0.5,CEILING(MAX((IF(F91*(1+'Read me'!$B$5)<='Read me'!$B$7,CEILING(F91*(1+'Read me'!$B$5)+0.5,1)-0.5,CEILING(F91*(1+'Read me'!$B$5),5)))*L91,(IF(F91*(1+'Read me'!$B$5)<='Read me'!$B$7,CEILING(F91*(1+'Read me'!$B$5)+0.5,1)-0.5,CEILING(F91*(1+'Read me'!$B$5),5)))+'Read me'!$B$6),5)) -> 320 | N91: Not offered | O91: =IF(ISNUMBER(J91),M91-J91,"new") -> -30 | P91: One rate: interstate XXL/Bulky to Metro Outer or Regional. Standard is charged at what Priority would have been; no Priority option
A92: ACT|WA|Small|Metro | B92: ACT | C92: WA | D92: Small | E92: Metro | F92: 13.71 | G92: 3 | H92: 6 | I92: 1.06 | J92: 19.5 | K92: 24.5 | L92: =INDEX('Read me'!$B$10:$B$14,1) -> 1.34 | M92: =IF(F92*(1+'Read me'!$B$5)<='Read me'!$B$7,CEILING(F92*(1+'Read me'!$B$5)+0.5,1)-0.5,CEILING(F92*(1+'Read me'!$B$5),5)) -> 14.5 | N92: =IF(MAX(M92*L92,M92+'Read me'!$B$6)<='Read me'!$B$7,CEILING(MAX(M92*L92,M92+'Read me'!$B$6)+0.5,1)-0.5,CEILING(MAX(M92*L92,M92+'Read me'!$B$6),5)) -> 19.5 | O92: =IF(ISNUMBER(J92),M92-J92,"new") -> -5
A93: ACT|WA|Small|Metro Outer | B93: ACT | C93: WA | D93: Small | E93: Metro Outer | F93: 17.06 | G93: 0 | H93: 6 | I93: 1.06 | J93: 19.5 | K93: 24.5 | L93: =INDEX('Read me'!$B$10:$B$14,1) -> 1.34 | M93: =IF(F93*(1+'Read me'!$B$5)<='Read me'!$B$7,CEILING(F93*(1+'Read me'!$B$5)+0.5,1)-0.5,CEILING(F93*(1+'Read me'!$B$5),5)) -> 17.5 | N93: =IF(MAX(M93*L93,M93+'Read me'!$B$6)<='Read me'!$B$7,CEILING(MAX(M93*L93,M93+'Read me'!$B$6)+0.5,1)-0.5,CEILING(MAX(M93*L93,M93+'Read me'!$B$6),5)) -> 23.5 | O93: =IF(ISNUMBER(J93),M93-J93,"new") -> -2
A94: ACT|WA|Small|Regional | B94: ACT | C94: WA | D94: Small | E94: Regional | F94: 20.98 | G94: 0 | H94: 6 | I94: 1.06 | J94: 19.5 | K94: 34.5 | L94: =INDEX('Read me'!$B$10:$B$14,1) -> 1.34 | M94: =IF(F94*(1+'Read me'!$B$5)<='Read me'!$B$7,CEILING(F94*(1+'Read me'!$B$5)+0.5,1)-0.5,CEILING(F94*(1+'Read me'!$B$5),5)) -> 21.5 | N94: =IF(MAX(M94*L94,M94+'Read me'!$B$6)<='Read me'!$B$7,CEILING(MAX(M94*L94,M94+'Read me'!$B$6)+0.5,1)-0.5,CEILING(MAX(M94*L94,M94+'Read me'!$B$6),5)) -> 29.5 | O94: =IF(ISNUMBER(J94),M94-J94,"new") -> 2
A95: ACT|WA|Medium|Metro | B95: ACT | C95: WA | D95: Medium | E95: Metro | F95: 45.5 | G95: 2 | H95: 6 | I95: 1.09 | J95: 24.5 | K95: 29.5 | L95: =INDEX('Read me'!$B$10:$B$14,2) -> 1.26 | M95: =IF(F95*(1+'Read me'!$B$5)<='Read me'!$B$7,CEILING(F95*(1+'Read me'!$B$5)+0.5,1)-0.5,CEILING(F95*(1+'Read me'!$B$5),5)) -> 50 | N95: =IF(MAX(M95*L95,M95+'Read me'!$B$6)<='Read me'!$B$7,CEILING(MAX(M95*L95,M95+'Read me'!$B$6)+0.5,1)-0.5,CEILING(MAX(M95*L95,M95+'Read me'!$B$6),5)) -> 65 | O95: =IF(ISNUMBER(J95),M95-J95,"new") -> 25.5
A96: ACT|WA|Medium|Metro Outer | B96: ACT | C96: WA | D96: Medium | E96: Metro Outer | F96: 52.57 | G96: 0 | H96: 6 | I96: 1.09 | J96: 24.5 | K96: 29.5 | L96: =INDEX('Read me'!$B$10:$B$14,2) -> 1.26 | M96: =IF(F96*(1+'Read me'!$B$5)<='Read me'!$B$7,CEILING(F96*(1+'Read me'!$B$5)+0.5,1)-0.5,CEILING(F96*(1+'Read me'!$B$5),5)) -> 55 | N96: =IF(MAX(M96*L96,M96+'Read me'!$B$6)<='Read me'!$B$7,CEILING(MAX(M96*L96,M96+'Read me'!$B$6)+0.5,1)-0.5,CEILING(MAX(M96*L96,M96+'Read me'!$B$6),5)) -> 70 | O96: =IF(ISNUMBER(J96),M96-J96,"new") -> 30.5
A97: ACT|WA|Medium|Regional | B97: ACT | C97: WA | D97: Medium | E97: Regional | F97: 58.73 | G97: 0 | H97: 6 | I97: 1.09 | J97: 24.5 | K97: 45 | L97: =INDEX('Read me'!$B$10:$B$14,2) -> 1.26 | M97: =IF(F97*(1+'Read me'!$B$5)<='Read me'!$B$7,CEILING(F97*(1+'Read me'!$B$5)+0.5,1)-0.5,CEILING(F97*(1+'Read me'!$B$5),5)) -> 60 | N97: =IF(MAX(M97*L97,M97+'Read me'!$B$6)<='Read me'!$B$7,CEILING(MAX(M97*L97,M97+'Read me'!$B$6)+0.5,1)-0.5,CEILING(MAX(M97*L97,M97+'Read me'!$B$6),5)) -> 80 | O97: =IF(ISNUMBER(J97),M97-J97,"new") -> 35.5
A98: ACT|WA|Large|Metro | B98: ACT | C98: WA | D98: Large | E98: Metro | F98: 72.23 | G98: 1 | H98: 6 | I98: 1.02 | J98: 45 | K98: 95 | L98: =INDEX('Read me'!$B$10:$B$14,3) -> 1.35 | M98: =IF(F98*(1+'Read me'!$B$5)<='Read me'!$B$7,CEILING(F98*(1+'Read me'!$B$5)+0.5,1)-0.5,CEILING(F98*(1+'Read me'!$B$5),5)) -> 75 | N98: =IF(MAX(M98*L98,M98+'Read me'!$B$6)<='Read me'!$B$7,CEILING(MAX(M98*L98,M98+'Read me'!$B$6)+0.5,1)-0.5,CEILING(MAX(M98*L98,M98+'Read me'!$B$6),5)) -> 105 | O98: =IF(ISNUMBER(J98),M98-J98,"new") -> 30
A99: ACT|WA|Large|Metro Outer | B99: ACT | C99: WA | D99: Large | E99: Metro Outer | F99: 86.94 | G99: 0 | H99: 6 | I99: 1.02 | J99: 45 | K99: 95 | L99: =INDEX('Read me'!$B$10:$B$14,3) -> 1.35 | M99: =IF(F99*(1+'Read me'!$B$5)<='Read me'!$B$7,CEILING(F99*(1+'Read me'!$B$5)+0.5,1)-0.5,CEILING(F99*(1+'Read me'!$B$5),5)) -> 90 | N99: =IF(MAX(M99*L99,M99+'Read me'!$B$6)<='Read me'!$B$7,CEILING(MAX(M99*L99,M99+'Read me'!$B$6)+0.5,1)-0.5,CEILING(MAX(M99*L99,M99+'Read me'!$B$6),5)) -> 125 | O99: =IF(ISNUMBER(J99),M99-J99,"new") -> 45
A100: ACT|WA|Large|Regional | B100: ACT | C100: WA | D100: Large | E100: Regional | F100: 118.74 | G100: 0 | H100: 6 | I100: 1.02 | J100: 99 | K100: 150 | L100: =INDEX('Read me'!$B$10:$B$14,3) -> 1.35 | M100: =IF(F100*(1+'Read me'!$B$5)<='Read me'!$B$7,CEILING(F100*(1+'Read me'!$B$5)+0.5,1)-0.5,CEILING(F100*(1+'Read me'!$B$5),5)) -> 120 | N100: =IF(MAX(M100*L100,M100+'Read me'!$B$6)<='Read me'!$B$7,CEILING(MAX(M100*L100,M100+'Read me'!$B$6)+0.5,1)-0.5,CEILING(MAX(M100*L100,M100+'Read me'!$B$6),5)) -> 165 | O100: =IF(ISNUMBER(J100),M100-J100,"new") -> 21
...

Sheet Impact
A1: Delivering to | B1: Ships from | C1: Zone | D1: Size | E1: Service charged | F1: Same state | G1: We charged | H1: Cost us | I1: 2025 sheet price | J1: New price | K1: New − cost | L1: Charged − cost
A2: NSW | B2: VIC | C2: Metro | D2: Small | E2: Priority | F2: No | G2: 14.5 | H2: 9.74 | I2: 14.5 | J2: =IF(AND(E2="Priority",ISNUMBER('Cost model'!N122)),'Cost model'!N122,'Cost model'!M122) -> 18.5 | K2: =J2-H2 -> 8.76 | L2: =G2-H2 -> 4.76
A3: NSW | B3: WA | C3: Regional | D3: Medium | E3: Standard | F3: No | G3: 35 | H3: 59.41 | I3: 24.5 | J3: =IF(AND(E3="Priority",ISNUMBER('Cost model'!N157)),'Cost model'!N157,'Cost model'!M157) -> 65 | K3: =J3-H3 -> 5.59 | L3: =G3-H3 -> -24.41
A4: QLD | B4: NSW | C4: Metro | D4: Small | E4: Standard | F4: No | G4: 24.39 | H4: 26.76 | I4: 14.5 | J4: =IF(AND(E4="Priority",ISNUMBER('Cost model'!N362)),'Cost model'!N362,'Cost model'!M362) -> 10.5 | K4: =J4-H4 -> -16.26 | L4: =G4-H4 -> -2.37
A5: VIC | B5: VIC | C5: Metro Outer | D5: Large | E5: Standard | F5: Yes | G5: 87.48 | H5: 87.48 | I5: 24.5 | J5: =IF(AND(E5="Priority",ISNUMBER('Cost model'!N639)),'Cost model'!N639,'Cost model'!M639) -> 60 | K5: =J5-H5 -> -27.48 | L5: =G5-H5 -> 0
A6: QLD | B6: QLD | C6: Metro | D6: Small | E6: Standard | F6: Yes | G6: 9.5 | H6: 6.57 | I6: 9.5 | J6: =IF(AND(E6="Priority",ISNUMBER('Cost model'!N317)),'Cost model'!N317,'Cost model'!M317) -> 10.5 | K6: =J6-H6 -> 3.93 | L6: =G6-H6 -> 2.93
A7: VIC | B7: VIC | C7: Metro | D7: Small | E7: Standard | F7: Yes | G7: 7.34 | H7: 7.34 | I7: 9.5 | J7: =IF(AND(E7="Priority",ISNUMBER('Cost model'!N632)),'Cost model'!N632,'Cost model'!M632) -> 9.5 | K7: =J7-H7 -> 2.16 | L7: =G7-H7 -> 0
A8: QLD | B8: QLD | C8: Metro Outer | D8: Small | E8: Standard | F8: Yes | G8: 9.5 | H8: 7.82 | I8: 12.5 | J8: =IF(AND(E8="Priority",ISNUMBER('Cost model'!N318)),'Cost model'!N318,'Cost model'!M318) -> 14.5 | K8: =J8-H8 -> 6.68 | L8: =G8-H8 -> 1.68
A9: SA | B9: SA | C9: Regional | D9: Small | E9: Standard | F9: Yes | G9: 27.19 | H9: 29.01 | I9: 17.5 | J9: =IF(AND(E9="Priority",ISNUMBER('Cost model'!N424)),'Cost model'!N424,'Cost model'!M424) -> 16.5 | K9: =J9-H9 -> -12.51 | L9: =G9-H9 -> -1.82
A10: WA | B10: WA | C10: Regional | D10: Small | E10: Standard | F10: Yes | G10: 14.45 | H10: 13.93 | I10: 17.5 | J10: =IF(AND(E10="Priority",ISNUMBER('Cost model'!N739)),'Cost model'!N739,'Cost model'!M739) -> 17.5 | K10: =J10-H10 -> 3.57 | L10: =G10-H10 -> 0.52
A11: WA | B11: QLD | C11: Metro | D11: Small | E11: Standard | F11: No | G11: 7.82 | H11: 12.33 | I11: 19.5 | J11: =IF(AND(E11="Priority",ISNUMBER('Cost model'!N797)),'Cost model'!N797,'Cost model'!M797) -> 14.5 | K11: =J11-H11 -> 2.17 | L11: =G11-H11 -> -4.51
A12: NSW | B12: VIC | C12: Regional | D12: Medium | E12: Standard | F12: No | G12: 35 | H12: 48.31 | I12: 19.5 | J12: =IF(AND(E12="Priority",ISNUMBER('Cost model'!N127)),'Cost model'!N127,'Cost model'!M127) -> 50 | K12: =J12-H12 -> 1.69 | L12: =G12-H12 -> -13.31
A13: QLD | B13: QLD | C13: Metro Outer | D13: Small | E13: Standard | F13: Yes | G13: 9.5 | H13: 8.8 | I13: 12.5 | J13: =IF(AND(E13="Priority",ISNUMBER('Cost model'!N318)),'Cost model'!N318,'Cost model'!M318) -> 14.5 | K13: =J13-H13 -> 5.7 | L13: =G13-H13 -> 0.7
A14: WA | B14: WA | C14: Metro | D14: Small | E14: Standard | F14: Yes | G14: 9.5 | H14: 7.03 | I14: 9.5 | J14: =IF(AND(E14="Priority",ISNUMBER('Cost model'!N737)),'Cost model'!N737,'Cost model'!M737) -> 8.5 | K14: =J14-H14 -> 1.47 | L14: =G14-H14 -> 2.47
A15: QLD | B15: QLD | C15: Metro | D15: Small | E15: Standard | F15: Yes | G15: 7.82 | H15: 6.57 | I15: 9.5 | J15: =IF(AND(E15="Priority",ISNUMBER('Cost model'!N317)),'Cost model'!N317,'Cost model'!M317) -> 10.5 | K15: =J15-H15 -> 3.93 | L15: =G15-H15 -> 1.25
A16: TAS | B16: VIC | C16: Metro Outer | D16: Small | E16: Standard | F16: No | G16: 12.31 | H16: 11.46 | I16: 14.5 | J16: =IF(AND(E16="Priority",ISNUMBER('Cost model'!N543)),'Cost model'!N543,'Cost model'!M543) -> 18.5 | K16: =J16-H16 -> 7.04 | L16: =G16-H16 -> 0.85
A17: NSW | B17: QLD | C17: Metro | D17: Medium | E17: Standard | F17: No | G17: 24.64 | H17: 24.39 | I17: 9.5 | J17: =IF(AND(E17="Priority",ISNUMBER('Cost model'!N110)),'Cost model'!N110,'Cost model'!M110) -> 40 | K17: =J17-H17 -> 15.61 | L17: =G17-H17 -> 0.25
A18: WA | B18: WA | C18: Metro | D18: Small | E18: Standard | F18: Yes | G18: 6.64 | H18: 6.64 | I18: 9.5 | J18: =IF(AND(E18="Priority",ISNUMBER('Cost model'!N737)),'Cost model'!N737,'Cost model'!M737) -> 8.5 | K18: =J18-H18 -> 1.86 | L18: =G18-H18 -> 0
A19: VIC | B19: NSW | C19: Metro Outer | D19: Medium | E19: Standard | F19: No | G19: 8 | H19: 7.78 | I19: 19.5 | J19: =IF(AND(E19="Priority",ISNUMBER('Cost model'!N696)),'Cost model'!N696,'Cost model'!M696) -> 45 | K19: =J19-H19 -> 37.22 | L19: =G19-H19 -> 0.22
A20: NSW | B20: VIC | C20: Metro Outer | D20: Small | E20: Standard | F20: No | G20: 14.5 | H20: 8.81 | I20: 12.5 | J20: =IF(AND(E20="Priority",ISNUMBER('Cost model'!N123)),'Cost model'!N123,'Cost model'!M123) -> 16.5 | K20: =J20-H20 -> 7.69 | L20: =G20-H20 -> 5.69
A21: NSW | B21: VIC | C21: Metro | D21: Medium | E21: Standard | F21: No | G21: 12.33 | H21: 11.52 | I21: 9.5 | J21: =IF(AND(E21="Priority",ISNUMBER('Cost model'!N125)),'Cost model'!N125,'Cost model'!M125) -> 40 | K21: =J21-H21 -> 28.48 | L21: =G21-H21 -> 0.81
A22: VIC | B22: QLD | C22: Metro Outer | D22: Small | E22: Standard | F22: No | G22: 9.92 | H22: 8.97 | I22: 14.5 | J22: =IF(AND(E22="Priority",ISNUMBER('Cost model'!N663)),'Cost model'!N663,'Cost model'!M663) -> 18.5 | K22: =J22-H22 -> 9.53 | L22: =G22-H22 -> 0.95
A23: WA | B23: WA | C23: Regional | D23: Small | E23: Standard | F23: Yes | G23: 14.45 | H23: 13.93 | I23: 17.5 | J23: =IF(AND(E23="Priority",ISNUMBER('Cost model'!N739)),'Cost model'!N739,'Cost model'!M739) -> 17.5 | K23: =J23-H23 -> 3.57 | L23: =G23-H23 -> 0.52
A24: WA | B24: QLD | C24: Metro Outer | D24: Small | E24: Standard | F24: No | G24: 17.5 | H24: 22.75 | I24: 19.5 | J24: =IF(AND(E24="Priority",ISNUMBER('Cost model'!N798)),'Cost model'!N798,'Cost model'!M798) -> 20.5 | K24: =J24-H24 -> -2.25 | L24: =G24-H24 -> -5.25
A25: NSW | B25: VIC | C25: Metro | D25: Small | E25: Standard | F25: No | G25: 15.65 | H25: 14.19 | I25: 9.5 | J25: =IF(AND(E25="Priority",ISNUMBER('Cost model'!N122)),'Cost model'!N122,'Cost model'!M122) -> 13.5 | K25: =J25-H25 -> -0.69 | L25: =G25-H25 -> 1.46
A26: VIC | B26: SA | C26: Regional | D26: Small | E26: Standard | F26: No | G26: 19.5 | H26: 20.05 | I26: 17.5 | J26: =IF(AND(E26="Priority",ISNUMBER('Cost model'!N649)),'Cost model'!N649,'Cost model'!M649) -> 19.5 | K26: =J26-H26 -> -0.55 | L26: =G26-H26 -> -0.55
A27: QLD | B27: QLD | C27: Metro | D27: Small | E27: Standard | F27: Yes | G27: 7.34 | H27: 7.34 | I27: 9.5 | J27: =IF(AND(E27="Priority",ISNUMBER('Cost model'!N317)),'Cost model'!N317,'Cost model'!M317) -> 10.5 | K27: =J27-H27 -> 3.16 | L27: =G27-H27 -> 0
A28: WA | B28: WA | C28: Metro | D28: Small | E28: Standard | F28: Yes | G28: 9.53 | H28: 9.2 | I28: 9.5 | J28: =IF(AND(E28="Priority",ISNUMBER('Cost model'!N737)),'Cost model'!N737,'Cost model'!M737) -> 8.5 | K28: =J28-H28 -> -0.7 | L28: =G28-H28 -> 0.33
A29: WA | B29: WA | C29: Regional | D29: Medium | E29: Standard | F29: Yes | G29: 19.5 | H29: 52.6 | I29: 19.5 | J29: =IF(AND(E29="Priority",ISNUMBER('Cost model'!N742)),'Cost model'!N742,'Cost model'!M742) -> 60 | K29: =J29-H29 -> 7.4 | L29: =G29-H29 -> -33.1
A30: NSW | B30: QLD | C30: Regional | D30: Small | E30: Standard | F30: No | G30: 19.5 | H30: 15.33 | I30: 17.5 | J30: =IF(AND(E30="Priority",ISNUMBER('Cost model'!N109)),'Cost model'!N109,'Cost model'!M109) -> 18.5 | K30: =J30-H30 -> 3.17 | L30: =G30-H30 -> 4.17
A31: NSW | B31: NSW | C31: Metro | D31: Small | E31: Priority | F31: Yes | G31: 14.5 | H31: 7.34 | I31: 14.5 | J31: =IF(AND(E31="Priority",ISNUMBER('Cost model'!N167)),'Cost model'!N167,'Cost model'!M167) -> 13.5 | K31: =J31-H31 -> 6.16 | L31: =G31-H31 -> 7.16
A32: NSW | B32: VIC | C32: Metro | D32: Small | E32: Standard | F32: No | G32: 11.29 | H32: 7.94 | I32: 9.5 | J32: =IF(AND(E32="Priority",ISNUMBER('Cost model'!N122)),'Cost model'!N122,'Cost model'!M122) -> 13.5 | K32: =J32-H32 -> 5.56 | L32: =G32-H32 -> 3.35
A33: QLD | B33: QLD | C33: Metro Outer | D33: Large | E33: Standard | F33: Yes | G33: 85 | H33: 116.26 | I33: 24.5 | J33: =IF(AND(E33="Priority",ISNUMBER('Cost model'!N324)),'Cost model'!N324,'Cost model'!M324) -> 85 | K33: =J33-H33 -> -31.26 | L33: =G33-H33 -> -31.26
A34: NSW | B34: VIC | C34: Metro | D34: Small | E34: Standard | F34: No | G34: 9.5 | H34: 9.5 | I34: 9.5 | J34: =IF(AND(E34="Priority",ISNUMBER('Cost model'!N122)),'Cost model'!N122,'Cost model'!M122) -> 13.5 | K34: =J34-H34 -> 4 | L34: =G34-H34 -> 0
A35: NSW | B35: QLD | C35: Regional | D35: XL | E35: Standard | F35: No | G35: 250 | H35: 264.79 | I35: 85 | J35: =IF(AND(E35="Priority",ISNUMBER('Cost model'!N118)),'Cost model'!N118,'Cost model'!M118) -> 180 | K35: =J35-H35 -> -84.79 | L35: =G35-H35 -> -14.79
A36: WA | B36: SA | C36: Metro | D36: Small | E36: Standard | F36: No | G36: 7.06 | H36: 12.93 | I36: 14.5 | J36: =IF(AND(E36="Priority",ISNUMBER('Cost model'!N752)),'Cost model'!N752,'Cost model'!M752) -> 12.5 | K36: =J36-H36 -> -0.43 | L36: =G36-H36 -> -5.87
A37: QLD | B37: QLD | C37: Metro Outer | D37: Small | E37: Standard | F37: Yes | G37: 10 | H37: 14.97 | I37: 12.5 | J37: =IF(AND(E37="Priority",ISNUMBER('Cost model'!N318)),'Cost model'!N318,'Cost model'!M318) -> 14.5 | K37: =J37-H37 -> -0.47 | L37: =G37-H37 -> -4.97
A38: WA | B38: QLD | C38: Metro | D38: Small | E38: Standard | F38: No | G38: 5.99 | H38: 7.96 | I38: 19.5 | J38: =IF(AND(E38="Priority",ISNUMBER('Cost model'!N797)),'Cost model'!N797,'Cost model'!M797) -> 14.5 | K38: =J38-H38 -> 6.54 | L38: =G38-H38 -> -1.97
A39: VIC | B39: VIC | C39: Metro | D39: Small | E39: Standard | F39: Yes | G39: 20 | H39: 5.8 | I39: 9.5 | J39: =IF(AND(E39="Priority",ISNUMBER('Cost model'!N632)),'Cost model'!N632,'Cost model'!M632) -> 9.5 | K39: =J39-H39 -> 3.7 | L39: =G39-H39 -> 14.2
A40: VIC | B40: VIC | C40: Metro Outer | D40: Small | E40: Standard | F40: Yes | G40: 10.79 | H40: 7.78 | I40: 12.5 | J40: =IF(AND(E40="Priority",ISNUMBER('Cost model'!N633)),'Cost model'!N633,'Cost model'!M633) -> 11.5 | K40: =J40-H40 -> 3.72 | L40: =G40-H40 -> 3.01
A41: ACT | B41: SA | C41: Metro | D41: Small | E41: Standard | F41: No | G41: 9 | H41: 8.79 | I41: 19.5 | J41: =IF(AND(E41="Priority",ISNUMBER('Cost model'!N32)),'Cost model'!N32,'Cost model'!M32) -> 15.5 | K41: =J41-H41 -> 6.71 | L41: =G41-H41 -> 0.21
A42: NSW | B42: NSW | C42: Metro | D42: Small | E42: Standard | F42: Yes | G42: 9.58 | H42: 6.57 | I42: 9.5 | J42: =IF(AND(E42="Priority",ISNUMBER('Cost model'!N167)),'Cost model'!N167,'Cost model'!M167) -> 8.5 | K42: =J42-H42 -> 1.93 | L42: =G42-H42 -> 3.01
A43: NSW | B43: VIC | C43: Metro Outer | D43: Medium | E43: Standard | F43: No | G43: 14.5 | H43: 29.35 | I43: 12.5 | J43: =IF(AND(E43="Priority",ISNUMBER('Cost model'!N126)),'Cost model'!N126,'Cost model'!M126) -> 45 | K43: =J43-H43 -> 15.65 | L43: =G43-H43 -> -14.85
A44: QLD | B44: QLD | C44: Regional | D44: Small | E44: Standard | F44: Yes | G44: 14.5 | H44: 20.05 | I44: 17.5 | J44: =IF(AND(E44="Priority",ISNUMBER('Cost model'!N319)),'Cost model'!N319,'Cost model'!M319) -> 16.5 | K44: =J44-H44 -> -3.55 | L44: =G44-H44 -> -5.55
A45: SA | B45: SA | C45: Regional | D45: Large | E45: Standard | F45: Yes | G45: 68.7 | H45: 19.28 | I45: 50 | J45: =IF(AND(E45="Priority",ISNUMBER('Cost model'!N430)),'Cost model'!N430,'Cost model'!M430) -> 50 | K45: =J45-H45 -> 30.72 | L45: =G45-H45 -> 49.42
A46: NSW | B46: SA | C46: Metro | D46: Small | E46: Standard | F46: No | G46: 12.33 | H46: 10.56 | I46: 14.5 | J46: =IF(AND(E46="Priority",ISNUMBER('Cost model'!N137)),'Cost model'!N137,'Cost model'!M137) -> 13.5 | K46: =J46-H46 -> 2.94 | L46: =G46-H46 -> 1.77
A47: QLD | B47: QLD | C47: Metro Outer | D47: Small | E47: Standard | F47: Yes | G47: 9.5 | H47: 7.82 | I47: 12.5 | J47: =IF(AND(E47="Priority",ISNUMBER('Cost model'!N318)),'Cost model'!N318,'Cost model'!M318) -> 14.5 | K47: =J47-H47 -> 6.68 | L47: =G47-H47 -> 1.68
A48: NSW | B48: VIC | C48: Metro Outer | D48: Small | E48: Standard | F48: No | G48: 15.33 | H48: 18.4 | I48: 12.5 | J48: =IF(AND(E48="Priority",ISNUMBER('Cost model'!N123)),'Cost model'!N123,'Cost model'!M123) -> 16.5 | K48: =J48-H48 -> -1.9 | L48: =G48-H48 -> -3.07
A49: VIC | B49: SA | C49: Regional | D49: Small | E49: Standard | F49: No | G49: 22.28 | H49: 25.45 | I49: 17.5 | J49: =IF(AND(E49="Priority",ISNUMBER('Cost model'!N649)),'Cost model'!N649,'Cost model'!M649) -> 19.5 | K49: =J49-H49 -> -5.95 | L49: =G49-H49 -> -3.17
A50: QLD | B50: QLD | C50: Metro Outer | D50: Small | E50: Standard | F50: Yes | G50: 9.5 | H50: 9.12 | I50: 12.5 | J50: =IF(AND(E50="Priority",ISNUMBER('Cost model'!N318)),'Cost model'!N318,'Cost model'!M318) -> 14.5 | K50: =J50-H50 -> 5.38 | L50: =G50-H50 -> 0.38
A51: NSW | B51: VIC | C51: Regional | D51: Medium | E51: Standard | F51: No | G51: 35 | H51: 56.83 | I51: 19.5 | J51: =IF(AND(E51="Priority",ISNUMBER('Cost model'!N127)),'Cost model'!N127,'Cost model'!M127) -> 50 | K51: =J51-H51 -> -6.83 | L51: =G51-H51 -> -21.83
A52: QLD | B52: QLD | C52: Metro Outer | D52: Small | E52: Standard | F52: Yes | G52: 40.89 | H52: 36.1 | I52: 12.5 | J52: =IF(AND(E52="Priority",ISNUMBER('Cost model'!N318)),'Cost model'!N318,'Cost model'!M318) -> 14.5 | K52: =J52-H52 -> -21.6 | L52: =G52-H52 -> 4.79
A53: NSW | B53: VIC | C53: Metro | D53: Small | E53: Standard | F53: No | G53: 12.33 | H53: 7.94 | I53: 9.5 | J53: =IF(AND(E53="Priority",ISNUMBER('Cost model'!N122)),'Cost model'!N122,'Cost model'!M122) -> 13.5 | K53: =J53-H53 -> 5.56 | L53: =G53-H53 -> 4.39
A54: WA | B54: WA | C54: Metro | D54: Small | E54: Standard | F54: Yes | G54: 7.03 | H54: 7.03 | I54: 9.5 | J54: =IF(AND(E54="Priority",ISNUMBER('Cost model'!N737)),'Cost model'!N737,'Cost model'!M737) -> 8.5 | K54: =J54-H54 -> 1.47 | L54: =G54-H54 -> 0
A55: SA | B55: SA | C55: Metro | D55: Small | E55: Standard | F55: Yes | G55: 8.12 | H55: 8.12 | I55: 9.5 | J55: =IF(AND(E55="Priority",ISNUMBER('Cost model'!N422)),'Cost model'!N422,'Cost model'!M422) -> 8.5 | K55: =J55-H55 -> 0.38 | L55: =G55-H55 -> 0
A56: NSW | B56: VIC | C56: Metro Outer | D56: Small | E56: Standard | F56: No | G56: 19.66 | H56: 10.81 | I56: 12.5 | J56: =IF(AND(E56="Priority",ISNUMBER('Cost model'!N123)),'Cost model'!N123,'Cost model'!M123) -> 16.5 | K56: =J56-H56 -> 5.69 | L56: =G56-H56 -> 8.85
A57: WA | B57: SA | C57: Metro | D57: Small | E57: Standard | F57: No | G57: 7.38 | H57: 10.56 | I57: 14.5 | J57: =IF(AND(E57="Priority",ISNUMBER('Cost model'!N752)),'Cost model'!N752,'Cost model'!M752) -> 12.5 | K57: =J57-H57 -> 1.94 | L57: =G57-H57 -> -3.18
A58: WA | B58: WA | C58: Regional | D58: Small | E58: Standard | F58: Yes | G58: 14.45 | H58: 13.93 | I58: 17.5 | J58: =IF(AND(E58="Priority",ISNUMBER('Cost model'!N739)),'Cost model'!N739,'Cost model'!M739) -> 17.5 | K58: =J58-H58 -> 3.57 | L58: =G58-H58 -> 0.52
A59: NSW | B59: VIC | C59: Regional | D59: Small | E59: Standard | F59: No | G59: 27.03 | H59: 27.14 | I59: 17.5 | J59: =IF(AND(E59="Priority",ISNUMBER('Cost model'!N124)),'Cost model'!N124,'Cost model'!M124) -> 21.5 | K59: =J59-H59 -> -5.64 | L59: =G59-H59 -> -0.11
A60: TAS | B60: VIC | C60: Metro Outer | D60: Medium | E60: Standard | F60: No | G60: 42.5 | H60: 50.34 | I60: 19.5 | J60: =IF(AND(E60="Priority",ISNUMBER('Cost model'!N546)),'Cost model'!N546,'Cost model'!M546) -> 60 | K60: =J60-H60 -> 9.66 | L60: =G60-H60 -> -7.84
A61: VIC | B61: VIC | C61: Metro Outer | D61: Medium | E61: Standard | F61: Yes | G61: 17.27 | H61: 16.65 | I61: 12.5 | J61: =IF(AND(E61="Priority",ISNUMBER('Cost model'!N636)),'Cost model'!N636,'Cost model'!M636) -> 40 | K61: =J61-H61 -> 23.35 | L61: =G61-H61 -> 0.62
A62: QLD | B62: QLD | C62: Regional | D62: XL | E62: Standard | F62: Yes | G62: 85 | H62: 244.82 | I62: 85 | J62: =IF(AND(E62="Priority",ISNUMBER('Cost model'!N328)),'Cost model'!N328,'Cost model'!M328) -> 175 | K62: =J62-H62 -> -69.82 | L62: =G62-H62 -> -159.82
A63: NSW | B63: SA | C63: Metro | D63: Small | E63: Standard | F63: No | G63: 12.33 | H63: 10.56 | I63: 14.5 | J63: =IF(AND(E63="Priority",ISNUMBER('Cost model'!N137)),'Cost model'!N137,'Cost model'!M137) -> 13.5 | K63: =J63-H63 -> 2.94 | L63: =G63-H63 -> 1.77
A64: WA | B64: WA | C64: Metro | D64: Small | E64: Standard | F64: Yes | G64: 7.38 | H64: 7.11 | I64: 9.5 | J64: =IF(AND(E64="Priority",ISNUMBER('Cost model'!N737)),'Cost model'!N737,'Cost model'!M737) -> 8.5 | K64: =J64-H64 -> 1.39 | L64: =G64-H64 -> 0.27
A65: VIC | B65: VIC | C65: Regional | D65: Medium | E65: Standard | F65: Yes | G65: 42.5 | H65: 61.49 | I65: 19.5 | J65: =IF(AND(E65="Priority",ISNUMBER('Cost model'!N637)),'Cost model'!N637,'Cost model'!M637) -> 45 | K65: =J65-H65 -> -16.49 | L65: =G65-H65 -> -18.99
A66: SA | B66: VIC | C66: Regional | D66: XXL | E66: Standard | F66: No | G66: 500 | H66: 730.51 | I66: 300 | J66: =IF(AND(E66="Priority",ISNUMBER('Cost model'!N451)),'Cost model'!N451,'Cost model'!M451) -> 350 | K66: =J66-H66 -> -380.51 | L66: =G66-H66 -> -230.51
A67: QLD | B67: QLD | C67: Metro Outer | D67: Small | E67: Standard | F67: Yes | G67: 14.5 | H67: 10.65 | I67: 12.5 | J67: =IF(AND(E67="Priority",ISNUMBER('Cost model'!N318)),'Cost model'!N318,'Cost model'!M318) -> 14.5 | K67: =J67-H67 -> 3.85 | L67: =G67-H67 -> 3.85
A68: WA | B68: SA | C68: Metro | D68: Small | E68: Standard | F68: No | G68: 7.06 | H68: 11.51 | I68: 14.5 | J68: =IF(AND(E68="Priority",ISNUMBER('Cost model'!N752)),'Cost model'!N752,'Cost model'!M752) -> 12.5 | K68: =J68-H68 -> 0.99 | L68: =G68-H68 -> -4.45
A69: WA | B69: VIC | C69: Metro | D69: Medium | E69: Standard | F69: No | G69: 19.5 | H69: 48.53 | I69: 24.5 | J69: =IF(AND(E69="Priority",ISNUMBER('Cost model'!N770)),'Cost model'!N770,'Cost model'!M770) -> 55 | K69: =J69-H69 -> 6.47 | L69: =G69-H69 -> -29.03
A70: NSW | B70: VIC | C70: Regional | D70: Medium | E70: Standard | F70: No | G70: 36.34 | H70: 32.7 | I70: 19.5 | J70: =IF(AND(E70="Priority",ISNUMBER('Cost model'!N127)),'Cost model'!N127,'Cost model'!M127) -> 50 | K70: =J70-H70 -> 17.3 | L70: =G70-H70 -> 3.64
A71: NSW | B71: VIC | C71: Regional | D71: Small | E71: Standard | F71: No | G71: 10 | H71: 10.99 | I71: 17.5 | J71: =IF(AND(E71="Priority",ISNUMBER('Cost model'!N124)),'Cost model'!N124,'Cost model'!M124) -> 21.5 | K71: =J71-H71 -> 10.51 | L71: =G71-H71 -> -0.99
A72: VIC | B72: VIC | C72: Metro | D72: Small | E72: Standard | F72: Yes | G72: 6.57 | H72: 6.57 | I72: 9.5 | J72: =IF(AND(E72="Priority",ISNUMBER('Cost model'!N632)),'Cost model'!N632,'Cost model'!M632) -> 9.5 | K72: =J72-H72 -> 2.93 | L72: =G72-H72 -> 0
A73: QLD | B73: QLD | C73: Metro | D73: Small | E73: Standard | F73: Yes | G73: 7.81 | H73: 6.03 | I73: 9.5 | J73: =IF(AND(E73="Priority",ISNUMBER('Cost model'!N317)),'Cost model'!N317,'Cost model'!M317) -> 10.5 | K73: =J73-H73 -> 4.47 | L73: =G73-H73 -> 1.78
A74: WA | B74: WA | C74: Metro | D74: Small | E74: Standard | F74: Yes | G74: 7.06 | H74: 5.8 | I74: 9.5 | J74: =IF(AND(E74="Priority",ISNUMBER('Cost model'!N737)),'Cost model'!N737,'Cost model'!M737) -> 8.5 | K74: =J74-H74 -> 2.7 | L74: =G74-H74 -> 1.26
A75: NSW | B75: VIC | C75: Metro | D75: Medium | E75: Standard | F75: No | G75: 36.43 | H75: 33.24 | I75: 9.5 | J75: =IF(AND(E75="Priority",ISNUMBER('Cost model'!N125)),'Cost model'!N125,'Cost model'!M125) -> 40 | K75: =J75-H75 -> 6.76 | L75: =G75-H75 -> 3.19
A76: QLD | B76: QLD | C76: Metro | D76: Small | E76: Standard | F76: Yes | G76: 9.33 | H76: 7.82 | I76: 9.5 | J76: =IF(AND(E76="Priority",ISNUMBER('Cost model'!N317)),'Cost model'!N317,'Cost model'!M317) -> 10.5 | K76: =J76-H76 -> 2.68 | L76: =G76-H76 -> 1.51
A77: NSW | B77: VIC | C77: Metro Outer | D77: Small | E77: Standard | F77: No | G77: 11.28 | H77: 11.46 | I77: 12.5 | J77: =IF(AND(E77="Priority",ISNUMBER('Cost model'!N123)),'Cost model'!N123,'Cost model'!M123) -> 16.5 | K77: =J77-H77 -> 5.04 | L77: =G77-H77 -> -0.18
A78: VIC | B78: NSW | C78: Metro | D78: Medium | E78: Standard | F78: No | G78: 30.67 | H78: 49.08 | I78: 19.5 | J78: =IF(AND(E78="Priority",ISNUMBER('Cost model'!N695)),'Cost model'!N695,'Cost model'!M695) -> 40 | K78: =J78-H78 -> -9.08 | L78: =G78-H78 -> -18.41
A79: NSW | B79: VIC | C79: Regional | D79: Small | E79: Standard | F79: No | G79: 16.25 | H79: 14.91 | I79: 17.5 | J79: =IF(AND(E79="Priority",ISNUMBER('Cost model'!N124)),'Cost model'!N124,'Cost model'!M124) -> 21.5 | K79: =J79-H79 -> 6.59 | L79: =G79-H79 -> 1.34
A80: WA | B80: WA | C80: Metro | D80: Small | E80: Standard | F80: Yes | G80: 6.64 | H80: 6.64 | I80: 9.5 | J80: =IF(AND(E80="Priority",ISNUMBER('Cost model'!N737)),'Cost model'!N737,'Cost model'!M737) -> 8.5 | K80: =J80-H80 -> 1.86 | L80: =G80-H80 -> 0
A81: NSW | B81: NSW | C81: Metro | D81: Small | E81: Standard | F81: Yes | G81: 9.58 | H81: 6.57 | I81: 9.5 | J81: =IF(AND(E81="Priority",ISNUMBER('Cost model'!N167)),'Cost model'!N167,'Cost model'!M167) -> 8.5 | K81: =J81-H81 -> 1.93 | L81: =G81-H81 -> 3.01
A82: NSW | B82: QLD | C82: Metro Outer | D82: Small | E82: Standard | F82: No | G82: 12.9 | H82: 11.87 | I82: 12.5 | J82: =IF(AND(E82="Priority",ISNUMBER('Cost model'!N108)),'Cost model'!N108,'Cost model'!M108) -> 15.5 | K82: =J82-H82 -> 3.63 | L82: =G82-H82 -> 1.03
A83: WA | B83: WA | C83: Metro | D83: XL | E83: Standard | F83: Yes | G83: 19.5 | H83: 86.25 | I83: 25 | J83: =IF(AND(E83="Priority",ISNUMBER('Cost model'!N746)),'Cost model'!N746,'Cost model'!M746) -> 100 | K83: =J83-H83 -> 13.75 | L83: =G83-H83 -> -66.75
A84: QLD | B84: SA | C84: Metro | D84: Medium | E84: Standard | F84: No | G84: 9.5 | H84: 15.93 | I84: 19.5 | J84: =IF(AND(E84="Priority",ISNUMBER('Cost model'!N350)),'Cost model'!N350,'Cost model'!M350) -> 50 | K84: =J84-H84 -> 34.07 | L84: =G84-H84 -> -6.43
A85: VIC | B85: QLD | C85: Regional | D85: Medium | E85: Standard | F85: No | G85: 42.5 | H85: 55.3 | I85: 19.5 | J85: =IF(AND(E85="Priority",ISNUMBER('Cost model'!N667)),'Cost model'!N667,'Cost model'!M667) -> 55 | K85: =J85-H85 -> -0.3 | L85: =G85-H85 -> -12.8
A86: QLD | B86: ACT | C86: Metro | D86: Medium | E86: Standard | F86: No | G86: 29.93 | H86: 47.19 | I86: 24.5 | J86: =IF(AND(E86="Priority",ISNUMBER('Cost model'!N395)),'Cost model'!N395,'Cost model'!M395) -> 50 | K86: =J86-H86 -> 2.81 | L86: =G86-H86 -> -17.26
A87: QLD | B87: QLD | C87: Metro Outer | D87: Small | E87: Standard | F87: Yes | G87: 9.5 | H87: 8.8 | I87: 12.5 | J87: =IF(AND(E87="Priority",ISNUMBER('Cost model'!N318)),'Cost model'!N318,'Cost model'!M318) -> 14.5 | K87: =J87-H87 -> 5.7 | L87: =G87-H87 -> 0.7
A88: WA | B88: SA | C88: Metro | D88: Small | E88: Standard | F88: No | G88: 7.06 | H88: 9.55 | I88: 14.5 | J88: =IF(AND(E88="Priority",ISNUMBER('Cost model'!N752)),'Cost model'!N752,'Cost model'!M752) -> 12.5 | K88: =J88-H88 -> 2.95 | L88: =G88-H88 -> -2.49
A89: QLD | B89: QLD | C89: Metro | D89: Small | E89: Standard | F89: Yes | G89: 6.57 | H89: 6.57 | I89: 9.5 | J89: =IF(AND(E89="Priority",ISNUMBER('Cost model'!N317)),'Cost model'!N317,'Cost model'!M317) -> 10.5 | K89: =J89-H89 -> 3.93 | L89: =G89-H89 -> 0
A90: WA | B90: WA | C90: Metro | D90: Small | E90: Standard | F90: Yes | G90: 7.38 | H90: 7.11 | I90: 9.5 | J90: =IF(AND(E90="Priority",ISNUMBER('Cost model'!N737)),'Cost model'!N737,'Cost model'!M737) -> 8.5 | K90: =J90-H90 -> 1.39 | L90: =G90-H90 -> 0.27
A91: WA | B91: SA | C91: Regional | D91: Small | E91: Standard | F91: No | G91: 17.5 | H91: 14.88 | I91: 17.5 | J91: =IF(AND(E91="Priority",ISNUMBER('Cost model'!N754)),'Cost model'!N754,'Cost model'!M754) -> 23.5 | K91: =J91-H91 -> 8.62 | L91: =G91-H91 -> 2.62
A92: NSW | B92: SA | C92: Metro Outer | D92: Small | E92: Standard | F92: No | G92: 14.32 | H92: 22.75 | I92: 14.5 | J92: =IF(AND(E92="Priority",ISNUMBER('Cost model'!N138)),'Cost model'!N138,'Cost model'!M138) -> 16.5 | K92: =J92-H92 -> -6.25 | L92: =G92-H92 -> -8.43
A93: WA | B93: WA | C93: Regional | D93: XL | E93: Standard | F93: Yes | G93: 50 | H93: 189.2 | I93: 125 | J93: =IF(AND(E93="Priority",ISNUMBER('Cost model'!N748)),'Cost model'!N748,'Cost model'!M748) -> 235 | K93: =J93-H93 -> 45.8 | L93: =G93-H93 -> -139.2
A94: NSW | B94: VIC | C94: Metro | D94: Small | E94: Standard | F94: No | G94: 9.96 | H94: 7.94 | I94: 9.5 | J94: =IF(AND(E94="Priority",ISNUMBER('Cost model'!N122)),'Cost model'!N122,'Cost model'!M122) -> 13.5 | K94: =J94-H94 -> 5.56 | L94: =G94-H94 -> 2.02
A95: QLD | B95: QLD | C95: Metro | D95: Small | E95: Standard | F95: Yes | G95: 9.5 | H95: 7.34 | I95: 9.5 | J95: =IF(AND(E95="Priority",ISNUMBER('Cost model'!N317)),'Cost model'!N317,'Cost model'!M317) -> 10.5 | K95: =J95-H95 -> 3.16 | L95: =G95-H95 -> 2.16
A96: WA | B96: WA | C96: Regional | D96: Small | E96: Standard | F96: Yes | G96: 27.22 | H96: 21.48 | I96: 17.5 | J96: =IF(AND(E96="Priority",ISNUMBER('Cost model'!N739)),'Cost model'!N739,'Cost model'!M739) -> 17.5 | K96: =J96-H96 -> -3.98 | L96: =G96-H96 -> 5.74
A97: VIC | B97: VIC | C97: Metro Outer | D97: Medium | E97: Standard | F97: Yes | G97: 50.19 | H97: 43.77 | I97: 12.5 | J97: =IF(AND(E97="Priority",ISNUMBER('Cost model'!N636)),'Cost model'!N636,'Cost model'!M636) -> 40 | K97: =J97-H97 -> -3.77 | L97: =G97-H97 -> 6.42
A98: VIC | B98: SA | C98: Metro | D98: Small | E98: Standard | F98: No | G98: 14.5 | H98: 9.72 | I98: 14.5 | J98: =IF(AND(E98="Priority",ISNUMBER('Cost model'!N647)),'Cost model'!N647,'Cost model'!M647) -> 13.5 | K98: =J98-H98 -> 3.78 | L98: =G98-H98 -> 4.78
A99: VIC | B99: VIC | C99: Metro | D99: Small | E99: Standard | F99: Yes | G99: 6.57 | H99: 6.57 | I99: 9.5 | J99: =IF(AND(E99="Priority",ISNUMBER('Cost model'!N632)),'Cost model'!N632,'Cost model'!M632) -> 9.5 | K99: =J99-H99 -> 2.93 | L99: =G99-H99 -> 0
A100: NSW | B100: VIC | C100: Metro Outer | D100: Small | E100: Standard | F100: No | G100: 10 | H100: 8.81 | I100: 12.5 | J100: =IF(AND(E100="Priority",ISNUMBER('Cost model'!N123)),'Cost model'!N123,'Cost model'!M123) -> 16.5 | K100: =J100-H100 -> 7.69 | L100: =G100-H100 -> 1.19
...

Sheet Freight SIZE RULES
A1: Freight size rules (how the website scores each product)
A3: Score | B3: Size | C3: Longest side | D3: Cubic weight (L×W×H×250) | E3: Actual weight
A4: 1 | B4: Small | C4: under 0.5 m | D4: under 10 kg | E4: under 5 kg
A5: 2 | B5: Medium | C5: 0.5 to under 1.8 m | D5: 10 to under 25 kg | E5: 5 to under 15 kg
A6: 3 | B6: Large | C6: 1.8 to under 3.5 m | D6: 25 to under 100 kg | E6: 15 to under 22 kg
A7: 4 | B7: XL | C7: 3.5 to under 5 m | D7: 100 to under 180 kg | E7: 22 to under 35 kg
A8: 5 | B8: XXL | C8: 5 m or more | D8: 180 kg or more | E8: 35 kg or more
A10: A product's size is the highest of its three scores. An order takes the size of its biggest product. Products with no dimensions or weight score 1 (Small) on that measure; 15,773 products in the 20 Oct 2026 export have neither, so the website treats them as Small.
A11: The 2025 sheet's version of this tab listed Large 1.8–2.5 m, XL 2.5–3.0 m and XXL 3.0 m+, and no cubic weight. Those aren't the rules the website uses.

Sheet Source Hierarchy
A1: Which warehouse the website ships from first (unchanged from the 2025 sheet; NT from the awaiting-approval version)
A3: Delivering to | B3: 1st | C3: 2nd | D3: 3rd | E3: 4th | F3: 5th
A4: ACT | B4: ACT · Fyshwick | C4: NSW · Moorebank | D4: QLD · Brendale | E4: VIC · Campbellfield | F4: SA · Adelaide
A5: NSW | B5: NSW · Moorebank | C5: QLD · Brendale | D5: VIC · Campbellfield | E5: SA · Adelaide | F5: WA · Wangara
A6: NT | B6: SA · Adelaide | C6: VIC · Campbellfield | D6: NSW · Moorebank | E6: WA · Wangara
A7: QLD | B7: QLD · Brendale | C7: NSW · Moorebank | D7: VIC · Campbellfield | E7: SA · Adelaide
A8: SA | B8: SA · Adelaide | C8: VIC · Campbellfield | D8: NSW · Moorebank | E8: QLD · Brendale | F8: WA · Wangara
A9: TAS | B9: TAS · Moonah | C9: VIC · Campbellfield | D9: NSW · Moorebank | E9: QLD · Brendale | F9: SA · Adelaide
A10: VIC | B10: VIC · Campbellfield | C10: NSW · Moorebank | D10: QLD · Brendale | E10: SA · Adelaide | F10: WA · Wangara
A11: WA | B11: WA · Wangara | C11: SA · Adelaide | D11: VIC · Campbellfield | E11: NSW · Moorebank

Sheet Postcode zones
A1: Postcode | B1: State tab | C1: Website zone name | D1: Zone | E1: Australia Post group | F1: Status | G1: Suburbs
A2: 0200 | B2: ACT | C2: ACT | D2: Metro | E2: Capital City | F2: Same as 2025 | G2: Anu, Australian National University
A3: 0800 | B3: NT | C3: NT | D3: Metro | E3: Capital City | F3: Same as 2025 | G3: Darwin, Darwin City
A4: 0801 | B4: NT | C4: NT | D4: Metro | E4: Capital City | F4: Same as 2025 | G4: Darwin
A5: 0803 | B5: NT | C5: NT - Rural | D5: Regional | E5: Rural | F5: Same as 2025 | G5: Wagait Beach
A6: 0804 | B6: NT | C6: NT | D6: Metro | E6: Capital City | F6: Same as 2025 | G6: Parap
A7: 0810 | B7: NT | C7: NT | D7: Metro | E7: Capital City | F7: Same as 2025 | G7: Alawa, Brinkin, Casuarina, Coconut Grove
A8: 0811 | B8: NT | C8: NT | D8: Metro | E8: Capital City | F8: Same as 2025 | G8: Casuarina
A9: 0812 | B9: NT | C9: NT | D9: Metro | E9: Capital City | F9: Same as 2025 | G9: Anula, Buffalo Creek, Holmes, Karama
A10: 0813 | B10: NT | C10: NT | D10: Metro | E10: Capital City | F10: Same as 2025 | G10: Karama, Sanderson
A11: 0814 | B11: NT | C11: NT | D11: Metro | E11: Capital City | F11: Same as 2025 | G11: Nightcliff
A12: 0815 | B12: NT | C12: NT - Rural | D12: Regional | E12: Rural | F12: Same as 2025 | G12: Charles Darwin University
... A2965: 9999 | B2965: VIC | C2965: VIC - Metro | D2965: Metro | E2965: Capital City | F2965: Same as 2025 | G2965: North Pole
