Workbook

Sheet Read me
A1: RRG Website Shipping · Australia · proposed rates with a Bulky size
A2: Prepared 20 October 2026 from Roof Racks Galore order and carrier data. Same layout as "RRG Website Shipping OCT 2025": one tab per delivery state, a table for each warehouse the order ships from, Standard and Priority, Metro / Metro Outer / Regional.
A4: Settings (change the yellow cells; every price in the workbook updates)
A5: Freight margin on top of expected cost | B5: 0 | C5: 0% = break-even: on average the Standard charge covers what the carrier charges us for that size, zone and warehouse. 10% adds 10% on top of expected cost.
A6: Minimum Priority uplift over Standard ($) | B6: 5 | C6: Priority is at least this much more than Standard.
A7: Round prices up to the next $x.50 up to ($) | B7: 30 | C7: Below this, prices end in .50 (e.g. $12.50). Above it they round up to the next $5.
A9: Priority ÷ Standard ratio by size
A10: Small | B10: 1.34 | C10: Median of Priority ÷ Standard across the 2025 sheet, kept between 1.20 and 1.35 (Large was 2.1 and XL 1.0 in 2025 because those Standard prices were far below cost). Applied to every cell. Change these if you want a different Priority premium.
A11: Medium | B11: 1.26
A12: Large | B12: 1.35
A13: XL | B13: 1.2
A14: XXL | B14: 1.2
A15: Bulky | B15: 1.2
A17: How the prices are set
A18: 1. Each order is sized the way the website does it: every product gets a 1–5 score from its longest side, cubic weight (250 kg/m³) and actual weight, and the order takes its biggest product's size. See the Freight SIZE RULES tab.
A19: 2. Expected cost = what carriers actually charged us (invoiced cost, or the carrier estimate where not yet billed, plus 10% GST) on 5,882 matched orders, June–October 2026, that went as one invoice in one shipment.
A20: 3. Costs are averaged after dropping the top and bottom 10% of orders in each group, so one-off surcharges don't set the price.
A21: 4. Each size × zone gets a national figure, separately for same-state and interstate deliveries. Each warehouse-to-state lane then gets a factor from its own orders (for example WA to VIC costs about 25% more than the interstate average). Lanes with few orders lean on the national figure; lanes with no orders use distance.
A22: 5. Where a lane has its own orders for a size and zone, those orders are blended in. Prices never go down from a smaller size to a larger one, or from Metro to Outer to Regional.
A23: 6. Standard = expected cost × (1 + freight margin), rounded up. Priority = Standard × the Priority ratio for its size (above), at least the minimum uplift, rounded up. We don't yet have enough priority shipments to cost Priority separately.
A24: 7. Delivery time frames are copied from the 2025 sheet, except that there is no 0–1 day Priority any more: those 30 cells (all same-state Metro deliveries) are now Priority 1–2 days and Standard 1–3 days (was 1–2 days).
A25: 8. One rate for interstate XXL and Bulky to Metro Outer and Regional: these have a single price, the Priority price, used for both Standard and Priority. Shown in the state tabs as the same figure in both tables (grey cells), and marked "One rate" on the Cost model tab.
A27: What else changed from the 2025 sheet
A28: • New Bulky size: any product of 0.4 m³ or more (cubic weight 100 kg+), such as roof boxes, rooftop tents, platforms, trays and ladders, is Bulky. Today those are charged as XL or XXL. Taking them out lowers XL and XXL, since Bulky orders cost about $190–$220 to send against about $125 for other XL and XXL orders. Bulky delivery times are copied from XXL.
A29: • The TAS tab now has a From SA table and the WA tab a From TAS table (both were missing).
... A38: • The Impact tab re-prices the same 5,882 orders under these rates so you can see the effect before changing the website.

Sheet Summary
A1: Summary
A2: Re-pricing the 5,882 matched single-shipment orders (Impact tab) under the new rates. Updates when you change the settings on Read me.
B4: Orders | C4: We charged | D4: Cost us | E4: Charged − cost | F4: New rates would charge | G4: New − cost
A5: All orders | B5: =COUNTA(Impact!$A$2:$A$5883) -> 5882 | C5: =SUM(Impact!$G$2:$G$5883) -> 114894.12 | D5: =SUM(Impact!$H$2:$H$5883) -> 240540.63 | E5: =C5-D5 -> -125646.51 | F5: =SUM(Impact!$J$2:$J$5883) -> 243385.5 | G5: =F5-D5 -> 2844.87
A7: By size
A8: Small | B8: =COUNTIF(Impact!$D$2:$D$5883,"Small") -> 2681 | C8: =SUMIF(Impact!$D$2:$D$5883,"Small",Impact!$G$2:$G$5883) -> 37442.65 | D8: =SUMIF(Impact!$D$2:$D$5883,"Small",Impact!$H$2:$H$5883) -> 38519.61 | E8: =C8-D8 -> -1076.96 | F8: =SUMIF(Impact!$D$2:$D$5883,"Small",Impact!$J$2:$J$5883) -> 37854.5 | G8: =F8-D8 -> -665.11
A9: Medium | B9: =COUNTIF(Impact!$D$2:$D$5883,"Medium") -> 2516 | C9: =SUMIF(Impact!$D$2:$D$5883,"Medium",Impact!$G$2:$G$5883) -> 40549.48 | D9: =SUMIF(Impact!$D$2:$D$5883,"Medium",Impact!$H$2:$H$5883) -> 111570.83 | E9: =C9-D9 -> -71021.35 | F9: =SUMIF(Impact!$D$2:$D$5883,"Medium",Impact!$J$2:$J$5883) -> 116496 | G9: =F9-D9 -> 4925.17
A10: Large | B10: =COUNTIF(Impact!$D$2:$D$5883,"Large") -> 346 | C10: =SUMIF(Impact!$D$2:$D$5883,"Large",Impact!$G$2:$G$5883) -> 12563 | D10: =SUMIF(Impact!$D$2:$D$5883,"Large",Impact!$H$2:$H$5883) -> 30449.77 | E10: =C10-D10 -> -17886.77 | F10: =SUMIF(Impact!$D$2:$D$5883,"Large",Impact!$J$2:$J$5883) -> 29545 | G10: =F10-D10 -> -904.77
A11: XL | B11: =COUNTIF(Impact!$D$2:$D$5883,"XL") -> 233 | C11: =SUMIF(Impact!$D$2:$D$5883,"XL",Impact!$G$2:$G$5883) -> 14564.99 | D11: =SUMIF(Impact!$D$2:$D$5883,"XL",Impact!$H$2:$H$5883) -> 36049.21 | E11: =C11-D11 -> -21484.22 | F11: =SUMIF(Impact!$D$2:$D$5883,"XL",Impact!$J$2:$J$5883) -> 35450 | G11: =F11-D11 -> -599.21
A12: XXL | B12: =COUNTIF(Impact!$D$2:$D$5883,"XXL") -> 25 | C12: =SUMIF(Impact!$D$2:$D$5883,"XXL",Impact!$G$2:$G$5883) -> 3130 | D12: =SUMIF(Impact!$D$2:$D$5883,"XXL",Impact!$H$2:$H$5883) -> 4413.05 | E12: =C12-D12 -> -1283.05 | F12: =SUMIF(Impact!$D$2:$D$5883,"XXL",Impact!$J$2:$J$5883) -> 4615 | G12: =F12-D12 -> 201.95
A13: Bulky | B13: =COUNTIF(Impact!$D$2:$D$5883,"Bulky") -> 81 | C13: =SUMIF(Impact!$D$2:$D$5883,"Bulky",Impact!$G$2:$G$5883) -> 6644 | D13: =SUMIF(Impact!$D$2:$D$5883,"Bulky",Impact!$H$2:$H$5883) -> 19538.16 | E13: =C13-D13 -> -12894.16 | F13: =SUMIF(Impact!$D$2:$D$5883,"Bulky",Impact!$J$2:$J$5883) -> 19425 | G13: =F13-D13 -> -113.16
A15: By zone
A16: Metro | B16: =COUNTIF(Impact!$C$2:$C$5883,"Metro") -> 2671 | C16: =SUMIF(Impact!$C$2:$C$5883,"Metro",Impact!$G$2:$G$5883) -> 39188.7 | D16: =SUMIF(Impact!$C$2:$C$5883,"Metro",Impact!$H$2:$H$5883) -> 84408.92 | E16: =C16-D16 -> -45220.22 | F16: =SUMIF(Impact!$C$2:$C$5883,"Metro",Impact!$J$2:$J$5883) -> 84518 | G16: =F16-D16 -> 109.08
A17: Metro Outer | B17: =COUNTIF(Impact!$C$2:$C$5883,"Metro Outer") -> 1750 | C17: =SUMIF(Impact!$C$2:$C$5883,"Metro Outer",Impact!$G$2:$G$5883) -> 32928.98 | D17: =SUMIF(Impact!$C$2:$C$5883,"Metro Outer",Impact!$H$2:$H$5883) -> 77446.75 | E17: =C17-D17 -> -44517.77 | F17: =SUMIF(Impact!$C$2:$C$5883,"Metro Outer",Impact!$J$2:$J$5883) -> 79702.5 | G17: =F17-D17 -> 2255.75
A18: Regional | B18: =COUNTIF(Impact!$C$2:$C$5883,"Regional") -> 1461 | C18: =SUMIF(Impact!$C$2:$C$5883,"Regional",Impact!$G$2:$G$5883) -> 42776.44 | D18: =SUMIF(Impact!$C$2:$C$5883,"Regional",Impact!$H$2:$H$5883) -> 78684.96 | E18: =C18-D18 -> -35908.52 | F18: =SUMIF(Impact!$C$2:$C$5883,"Regional",Impact!$J$2:$J$5883) -> 79165 | G18: =F18-D18 -> 480.04
A20: By warehouse
A21: QLD · Brendale | B21: =COUNTIF(Impact!$B$2:$B$5883,"QLD") -> 1636 | C21: =SUMIF(Impact!$B$2:$B$5883,"QLD",Impact!$G$2:$G$5883) -> 31332.63 | D21: =SUMIF(Impact!$B$2:$B$5883,"QLD",Impact!$H$2:$H$5883) -> 65008.7 | E21: =C21-D21 -> -33676.07 | F21: =SUMIF(Impact!$B$2:$B$5883,"QLD",Impact!$J$2:$J$5883) -> 66398.5 | G21: =F21-D21 -> 1389.8
A22: NSW · Moorebank | B22: =COUNTIF(Impact!$B$2:$B$5883,"NSW") -> 1735 | C22: =SUMIF(Impact!$B$2:$B$5883,"NSW",Impact!$G$2:$G$5883) -> 31503 | D22: =SUMIF(Impact!$B$2:$B$5883,"NSW",Impact!$H$2:$H$5883) -> 63242.37 | E22: =C22-D22 -> -31739.37 | F22: =SUMIF(Impact!$B$2:$B$5883,"NSW",Impact!$J$2:$J$5883) -> 64194 | G22: =F22-D22 -> 951.63
A23: VIC · Campbellfield | B23: =COUNTIF(Impact!$B$2:$B$5883,"VIC") -> 1154 | C23: =SUMIF(Impact!$B$2:$B$5883,"VIC",Impact!$G$2:$G$5883) -> 21504 | D23: =SUMIF(Impact!$B$2:$B$5883,"VIC",Impact!$H$2:$H$5883) -> 49083.33 | E23: =C23-D23 -> -27579.33 | F23: =SUMIF(Impact!$B$2:$B$5883,"VIC",Impact!$J$2:$J$5883) -> 50927.5 | G23: =F23-D23 -> 1844.17
A24: SA · Adelaide | B24: =COUNTIF(Impact!$B$2:$B$5883,"SA") -> 520 | C24: =SUMIF(Impact!$B$2:$B$5883,"SA",Impact!$G$2:$G$5883) -> 12112.99 | D24: =SUMIF(Impact!$B$2:$B$5883,"SA",Impact!$H$2:$H$5883) -> 21825.77 | E24: =C24-D24 -> -9712.78 | F24: =SUMIF(Impact!$B$2:$B$5883,"SA",Impact!$J$2:$J$5883) -> 23232.5 | G24: =F24-D24 -> 1406.73
A25: WA · Wangara | B25: =COUNTIF(Impact!$B$2:$B$5883,"WA") -> 599 | C25: =SUMIF(Impact!$B$2:$B$5883,"WA",Impact!$G$2:$G$5883) -> 13897 | D25: =SUMIF(Impact!$B$2:$B$5883,"WA",Impact!$H$2:$H$5883) -> 29455.45 | E25: =C25-D25 -> -15558.45 | F25: =SUMIF(Impact!$B$2:$B$5883,"WA",Impact!$J$2:$J$5883) -> 26758.5 | G25: =F25-D25 -> -2696.95
A26: TAS · Moonah | B26: =COUNTIF(Impact!$B$2:$B$5883,"TAS") -> 137 | C26: =SUMIF(Impact!$B$2:$B$5883,"TAS",Impact!$G$2:$G$5883) -> 2712 | D26: =SUMIF(Impact!$B$2:$B$5883,"TAS",Impact!$H$2:$H$5883) -> 7001.57 | E26: =C26-D26 -> -4289.57 | F26: =SUMIF(Impact!$B$2:$B$5883,"TAS",Impact!$J$2:$J$5883) -> 6360.5 | G26: =F26-D26 -> -641.07
A27: ACT · Fyshwick | B27: =COUNTIF(Impact!$B$2:$B$5883,"ACT") -> 101 | C27: =SUMIF(Impact!$B$2:$B$5883,"ACT",Impact!$G$2:$G$5883) -> 1832.5 | D27: =SUMIF(Impact!$B$2:$B$5883,"ACT",Impact!$H$2:$H$5883) -> 4923.44 | E27: =C27-D27 -> -3090.94 | F27: =SUMIF(Impact!$B$2:$B$5883,"ACT",Impact!$J$2:$J$5883) -> 5514 | G27: =F27-D27 -> 590.56
A29: Typical price per order, Standard (median of each tab's same-state table)
A30: Size | B30: Metro 2025 | C30: Metro new | D30: Outer 2025 | E30: Outer new | F30: Regional 2025 | G30: Regional new
A31: Small | B31: 9.5 | C31: =MEDIAN('Cost model'!M74,'Cost model'!M200,'Cost model'!M380,'Cost model'!M506,'Cost model'!M632,'Cost model'!M758,'Cost model'!M884) -> 8.5 | D31: 12.5 | E31: =MEDIAN('Cost model'!M75,'Cost model'!M201,'Cost model'!M381,'Cost model'!M507,'Cost model'!M633,'Cost model'!M759,'Cost model'!M885) -> 13.5 | F31: 17.5 | G31: =MEDIAN('Cost model'!M76,'Cost model'!M202,'Cost model'!M382,'Cost model'!M508,'Cost model'!M634,'Cost model'!M760,'Cost model'!M886) -> 18.5
A32: Medium | B32: 9.5 | C32: =MEDIAN('Cost model'!M77,'Cost model'!M203,'Cost model'!M383,'Cost model'!M509,'Cost model'!M635,'Cost model'!M761,'Cost model'!M887) -> 27.5 | D32: 12.5 | E32: =MEDIAN('Cost model'!M78,'Cost model'!M204,'Cost model'!M384,'Cost model'!M510,'Cost model'!M636,'Cost model'!M762,'Cost model'!M888) -> 45 | F32: 19.5 | G32: =MEDIAN('Cost model'!M79,'Cost model'!M205,'Cost model'!M385,'Cost model'!M511,'Cost model'!M637,'Cost model'!M763,'Cost model'!M889) -> 55
A33: Large | B33: 19 | C33: =MEDIAN('Cost model'!M80,'Cost model'!M206,'Cost model'!M386,'Cost model'!M512,'Cost model'!M638,'Cost model'!M764,'Cost model'!M890) -> 55 | D33: 24.5 | E33: =MEDIAN('Cost model'!M81,'Cost model'!M207,'Cost model'!M387,'Cost model'!M513,'Cost model'!M639,'Cost model'!M765,'Cost model'!M891) -> 75 | F33: 50 | G33: =MEDIAN('Cost model'!M82,'Cost model'!M208,'Cost model'!M388,'Cost model'!M514,'Cost model'!M640,'Cost model'!M766,'Cost model'!M892) -> 110
A34: XL | B34: 25 | C34: =MEDIAN('Cost model'!M83,'Cost model'!M209,'Cost model'!M389,'Cost model'!M515,'Cost model'!M641,'Cost model'!M767,'Cost model'!M893) -> 105 | D34: 45 | E34: =MEDIAN('Cost model'!M84,'Cost model'!M210,'Cost model'!M390,'Cost model'!M516,'Cost model'!M642,'Cost model'!M768,'Cost model'!M894) -> 135 | F34: 85 | G34: =MEDIAN('Cost model'!M85,'Cost model'!M211,'Cost model'!M391,'Cost model'!M517,'Cost model'!M643,'Cost model'!M769,'Cost model'!M895) -> 175
A35: XXL | B35: 45 | C35: =MEDIAN('Cost model'!M86,'Cost model'!M212,'Cost model'!M392,'Cost model'!M518,'Cost model'!M644,'Cost model'!M770,'Cost model'!M896) -> 125 | D35: 85 | E35: =MEDIAN('Cost model'!M87,'Cost model'!M213,'Cost model'!M393,'Cost model'!M519,'Cost model'!M645,'Cost model'!M771,'Cost model'!M897) -> 160 | F35: 250 | G35: =MEDIAN('Cost model'!M88,'Cost model'!M214,'Cost model'!M394,'Cost model'!M520,'Cost model'!M646,'Cost model'!M772,'Cost model'!M898) -> 250
A36: Bulky (XXL today) | B36: 45 | C36: =MEDIAN('Cost model'!M89,'Cost model'!M215,'Cost model'!M395,'Cost model'!M521,'Cost model'!M647,'Cost model'!M773,'Cost model'!M899) -> 135 | D36: 85 | E36: =MEDIAN('Cost model'!M90,'Cost model'!M216,'Cost model'!M396,'Cost model'!M522,'Cost model'!M648,'Cost model'!M774,'Cost model'!M900) -> 225 | F36: 250 | G36: =MEDIAN('Cost model'!M91,'Cost model'!M217,'Cost model'!M397,'Cost model'!M523,'Cost model'!M649,'Cost model'!M775,'Cost model'!M901) -> 295
A38: Option: split Medium at 1.05 m (what Medium orders actually cost us, incl. GST, trimmed average)
B39: Orders | C39: Metro | D39: Outer metro | E39: Regional
A40: Medium up to 1.05 m, same state | B40: 437 | C40: 11.22 | D40: 21.12 | E40: 30.7
A41: Medium over 1.05 m, same state | B41: 1356 | C41: 31.31 | D41: 50.16 | E41: 52.68
A42: Medium up to 1.05 m, interstate | B42: 189 | C42: 25.46 | D42: 30.96 | E42: 37.56
A43: Medium over 1.05 m, interstate | B43: 534 | C43: 55.99 | D43: 60.24 | E43: 66.2
A44: Most Medium orders under 1.05 m can go Australia Post. Splitting Medium would let the website keep a low price for those and charge the long ones what StarTrack costs. It needs a 6th size on the website, so it isn't applied in the state tabs.

Sheet ACT
A1: Freight Charges for ACT Orders
A3: Standard | B3: From QLD | F3: From VIC | J3: From SA | N3: From NSW | R3: From ACT | V3: From TAS | Z3: From WA
A4: Freight Size | B4: Metro | C4: Metro Outer | D4: Regional | F4: Metro | G4: Metro Outer | H4: Regional | J4: Metro | K4: Metro Outer | L4: Regional | N4: Metro | O4: Metro Outer | P4: Regional | R4: Metro | S4: Metro Outer | T4: Regional | V4: Metro | W4: Metro Outer | X4: Regional | Z4: Metro | AA4: Metro Outer | AB4: Regional
A5: Small | B5: ='Cost model'!M2 -> 14.5 | C5: ='Cost model'!M3 -> 14.5 | D5: ='Cost model'!M4 -> 19.5 | F5: ='Cost model'!M20 -> 13.5 | G5: ='Cost model'!M21 -> 15.5 | H5: ='Cost model'!M22 -> 19.5 | J5: ='Cost model'!M38 -> 13.5 | K5: ='Cost model'!M39 -> 14.5 | L5: ='Cost model'!M40 -> 19.5 | N5: ='Cost model'!M56 -> 11.5 | O5: ='Cost model'!M57 -> 13.5 | P5: ='Cost model'!M58 -> 18.5 | R5: ='Cost model'!M74 -> 21.5 | S5: ='Cost model'!M75 -> 35 | T5: ='Cost model'!M76 -> 40 | V5: ='Cost model'!M92 -> 13.5 | W5: ='Cost model'!M93 -> 15.5 | X5: ='Cost model'!M94 -> 20.5 | Z5: ='Cost model'!M110 -> 13.5 | AA5: ='Cost model'!M111 -> 16.5 | AB5: ='Cost model'!M112 -> 21.5
A6: Medium | B6: ='Cost model'!M5 -> 50 | C6: ='Cost model'!M6 -> 50 | D6: ='Cost model'!M7 -> 60 | F6: ='Cost model'!M23 -> 55 | G6: ='Cost model'!M24 -> 55 | H6: ='Cost model'!M25 -> 60 | J6: ='Cost model'!M41 -> 45 | K6: ='Cost model'!M42 -> 50 | L6: ='Cost model'!M43 -> 60 | N6: ='Cost model'!M59 -> 45 | O6: ='Cost model'!M60 -> 50 | P6: ='Cost model'!M61 -> 55 | R6: ='Cost model'!M77 -> 50 | S6: ='Cost model'!M78 -> 100 | T6: ='Cost model'!M79 -> 115 | V6: ='Cost model'!M95 -> 50 | W6: ='Cost model'!M96 -> 55 | X6: ='Cost model'!M97 -> 60 | Z6: ='Cost model'!M113 -> 50 | AA6: ='Cost model'!M114 -> 55 | AB6: ='Cost model'!M115 -> 65
A7: Large | B7: ='Cost model'!M8 -> 80 | C7: ='Cost model'!M9 -> 90 | D7: ='Cost model'!M10 -> 120 | F7: ='Cost model'!M26 -> 85 | G7: ='Cost model'!M27 -> 95 | H7: ='Cost model'!M28 -> 125 | J7: ='Cost model'!M44 -> 80 | K7: ='Cost model'!M45 -> 90 | L7: ='Cost model'!M46 -> 120 | N7: ='Cost model'!M62 -> 80 | O7: ='Cost model'!M63 -> 85 | P7: ='Cost model'!M64 -> 115 | R7: ='Cost model'!M80 -> 115 | S7: ='Cost model'!M81 -> 180 | T7: ='Cost model'!M82 -> 225 | V7: ='Cost model'!M98 -> 85 | W7: ='Cost model'!M99 -> 95 | X7: ='Cost model'!M100 -> 125 | Z7: ='Cost model'!M116 -> 90 | AA7: ='Cost model'!M117 -> 100 | AB7: ='Cost model'!M118 -> 130
A8: XL | B8: ='Cost model'!M11 -> 135 | C8: ='Cost model'!M12 -> 165 | D8: ='Cost model'!M13 -> 200 | F8: ='Cost model'!M29 -> 140 | G8: ='Cost model'!M30 -> 170 | H8: ='Cost model'!M31 -> 205 | J8: ='Cost model'!M47 -> 135 | K8: ='Cost model'!M48 -> 165 | L8: ='Cost model'!M49 -> 195 | N8: ='Cost model'!M65 -> 130 | O8: ='Cost model'!M66 -> 155 | P8: ='Cost model'!M67 -> 185 | R8: ='Cost model'!M83 -> 210 | S8: ='Cost model'!M84 -> 295 | T8: ='Cost model'!M85 -> 445 | V8: ='Cost model'!M101 -> 140 | W8: ='Cost model'!M102 -> 170 | X8: ='Cost model'!M103 -> 205 | Z8: ='Cost model'!M119 -> 150 | AA8: ='Cost model'!M120 -> 180 | AB8: ='Cost model'!M121 -> 215
A9: XXL | B9: ='Cost model'!M14 -> 175 | C9: ='Cost model'!M15 -> 260 | D9: ='Cost model'!M16 -> 310 | F9: ='Cost model'!M32 -> 180 | G9: ='Cost model'!M33 -> 265 | H9: ='Cost model'!M34 -> 320 | J9: ='Cost model'!M50 -> 175 | K9: ='Cost model'!M51 -> 260 | L9: ='Cost model'!M52 -> 310 | N9: ='Cost model'!M68 -> 165 | O9: ='Cost model'!M69 -> 240 | P9: ='Cost model'!M70 -> 290 | R9: ='Cost model'!M86 -> 265 | S9: ='Cost model'!M87 -> 380 | T9: ='Cost model'!M88 -> 565 | V9: ='Cost model'!M104 -> 180 | W9: ='Cost model'!M105 -> 265 | X9: ='Cost model'!M106 -> 320 | Z9: ='Cost model'!M122 -> 190 | AA9: ='Cost model'!M123 -> 285 | AB9: ='Cost model'!M124 -> 340
A10: Bulky | B10: ='Cost model'!M17 -> 240 | C10: ='Cost model'!M18 -> 375 | D10: ='Cost model'!M19 -> 435 | F10: ='Cost model'!M35 -> 245 | G10: ='Cost model'!M36 -> 380 | H10: ='Cost model'!M37 -> 445 | J10: ='Cost model'!M53 -> 240 | K10: ='Cost model'!M54 -> 370 | L10: ='Cost model'!M55 -> 435 | N10: ='Cost model'!M71 -> 225 | O10: ='Cost model'!M72 -> 350 | P10: ='Cost model'!M73 -> 410 | R10: ='Cost model'!M89 -> 290 | S10: ='Cost model'!M90 -> 520 | T10: ='Cost model'!M91 -> 680 | V10: ='Cost model'!M107 -> 250 | W10: ='Cost model'!M108 -> 385 | X10: ='Cost model'!M109 -> 450 | Z10: ='Cost model'!M125 -> 265 | AA10: ='Cost model'!M126 -> 410 | AB10: ='Cost model'!M127 -> 475
A12: Priority | B12: From QLD | F12: From VIC | J12: From SA | N12: From NSW | R12: From ACT | V12: From TAS | Z12: From WA
A13: Freight Size | B13: Metro | C13: Metro Outer | D13: Regional | F13: Metro | G13: Metro Outer | H13: Regional | J13: Metro | K13: Metro Outer | L13: Regional | N13: Metro | O13: Metro Outer | P13: Regional | R13: Metro | S13: Metro Outer | T13: Regional | V13: Metro | W13: Metro Outer | X13: Regional | Z13: Metro | AA13: Metro Outer | AB13: Regional
A14: Small | B14: ='Cost model'!N2 -> 19.5 | C14: ='Cost model'!N3 -> 19.5 | D14: ='Cost model'!N4 -> 26.5 | F14: ='Cost model'!N20 -> 18.5 | G14: ='Cost model'!N21 -> 21.5 | H14: ='Cost model'!N22 -> 26.5 | J14: ='Cost model'!N38 -> 18.5 | K14: ='Cost model'!N39 -> 19.5 | L14: ='Cost model'!N40 -> 26.5 | N14: ='Cost model'!N56 -> 16.5 | O14: ='Cost model'!N57 -> 18.5 | P14: ='Cost model'!N58 -> 25.5 | R14: ='Cost model'!N74 -> 29.5 | S14: ='Cost model'!N75 -> 50 | T14: ='Cost model'!N76 -> 55 | V14: ='Cost model'!N92 -> 18.5 | W14: ='Cost model'!N93 -> 21.5 | X14: ='Cost model'!N94 -> 27.5 | Z14: ='Cost model'!N110 -> 18.5 | AA14: ='Cost model'!N111 -> 22.5 | AB14: ='Cost model'!N112 -> 29.5
A15: Medium | B15: ='Cost model'!N5 -> 65 | C15: ='Cost model'!N6 -> 65 | D15: ='Cost model'!N7 -> 80 | F15: ='Cost model'!N23 -> 70 | G15: ='Cost model'!N24 -> 70 | H15: ='Cost model'!N25 -> 80 | J15: ='Cost model'!N41 -> 60 | K15: ='Cost model'!N42 -> 65 | L15: ='Cost model'!N43 -> 80 | N15: ='Cost model'!N59 -> 60 | O15: ='Cost model'!N60 -> 65 | P15: ='Cost model'!N61 -> 70 | R15: ='Cost model'!N77 -> 65 | S15: ='Cost model'!N78 -> 130 | T15: ='Cost model'!N79 -> 145 | V15: ='Cost model'!N95 -> 65 | W15: ='Cost model'!N96 -> 70 | X15: ='Cost model'!N97 -> 80 | Z15: ='Cost model'!N113 -> 65 | AA15: ='Cost model'!N114 -> 70 | AB15: ='Cost model'!N115 -> 85
A16: Large | B16: ='Cost model'!N8 -> 110 | C16: ='Cost model'!N9 -> 125 | D16: ='Cost model'!N10 -> 165 | F16: ='Cost model'!N26 -> 115 | G16: ='Cost model'!N27 -> 130 | H16: ='Cost model'!N28 -> 170 | J16: ='Cost model'!N44 -> 110 | K16: ='Cost model'!N45 -> 125 | L16: ='Cost model'!N46 -> 165 | N16: ='Cost model'!N62 -> 110 | O16: ='Cost model'!N63 -> 115 | P16: ='Cost model'!N64 -> 160 | R16: ='Cost model'!N80 -> 160 | S16: ='Cost model'!N81 -> 245 | T16: ='Cost model'!N82 -> 305 | V16: ='Cost model'!N98 -> 115 | W16: ='Cost model'!N99 -> 130 | X16: ='Cost model'!N100 -> 170 | Z16: ='Cost model'!N116 -> 125 | AA16: ='Cost model'!N117 -> 135 | AB16: ='Cost model'!N118 -> 180
A17: XL | B17: ='Cost model'!N11 -> 165 | C17: ='Cost model'!N12 -> 200 | D17: ='Cost model'!N13 -> 240 | F17: ='Cost model'!N29 -> 170 | G17: ='Cost model'!N30 -> 205 | H17: ='Cost model'!N31 -> 250 | J17: ='Cost model'!N47 -> 165 | K17: ='Cost model'!N48 -> 200 | L17: ='Cost model'!N49 -> 235 | N17: ='Cost model'!N65 -> 160 | O17: ='Cost model'!N66 -> 190 | P17: ='Cost model'!N67 -> 225 | R17: ='Cost model'!N83 -> 255 | S17: ='Cost model'!N84 -> 355 | T17: ='Cost model'!N85 -> 535 | V17: ='Cost model'!N101 -> 170 | W17: ='Cost model'!N102 -> 205 | X17: ='Cost model'!N103 -> 250 | Z17: ='Cost model'!N119 -> 180 | AA17: ='Cost model'!N120 -> 220 | AB17: ='Cost model'!N121 -> 260
A18: XXL | B18: ='Cost model'!N14 -> 210 | C18: ='Cost model'!N15 -> 260 | D18: ='Cost model'!N16 -> 310 | F18: ='Cost model'!N32 -> 220 | G18: ='Cost model'!N33 -> 265 | H18: ='Cost model'!N34 -> 320 | J18: ='Cost model'!N50 -> 210 | K18: ='Cost model'!N51 -> 260 | L18: ='Cost model'!N52 -> 310 | N18: ='Cost model'!N68 -> 200 | O18: ='Cost model'!N69 -> 240 | P18: ='Cost model'!N70 -> 290 | R18: ='Cost model'!N86 -> 320 | S18: ='Cost model'!N87 -> 460 | T18: ='Cost model'!N88 -> 680 | V18: ='Cost model'!N104 -> 220 | W18: ='Cost model'!N105 -> 265 | X18: ='Cost model'!N106 -> 320 | Z18: ='Cost model'!N122 -> 230 | AA18: ='Cost model'!N123 -> 285 | AB18: ='Cost model'!N124 -> 340
A19: Bulky | B19: ='Cost model'!N17 -> 290 | C19: ='Cost model'!N18 -> 375 | D19: ='Cost model'!N19 -> 435 | F19: ='Cost model'!N35 -> 295 | G19: ='Cost model'!N36 -> 380 | H19: ='Cost model'!N37 -> 445 | J19: ='Cost model'!N53 -> 290 | K19: ='Cost model'!N54 -> 370 | L19: ='Cost model'!N55 -> 435 | N19: ='Cost model'!N71 -> 270 | O19: ='Cost model'!N72 -> 350 | P19: ='Cost model'!N73 -> 410 | R19: ='Cost model'!N89 -> 350 | S19: ='Cost model'!N90 -> 625 | T19: ='Cost model'!N91 -> 820 | V19: ='Cost model'!N107 -> 300 | W19: ='Cost model'!N108 -> 385 | X19: ='Cost model'!N109 -> 450 | Z19: ='Cost model'!N125 -> 320 | AA19: ='Cost model'!N126 -> 410 | AB19: ='Cost model'!N127 -> 475
A21: Delivery time frames for ACT Orders
A23: Standard | B23: From QLD | F23: From VIC | J23: From SA | N23: From NSW | R23: From ACT | V23: From TAS | Z23: From WA
A24: Freight Size | B24: Metro | C24: Metro Outer | D24: Regional | F24: Metro | G24: Metro Outer | H24: Regional | J24: Metro | K24: Metro Outer | L24: Regional | N24: Metro | O24: Metro Outer | P24: Regional | R24: Metro | S24: Metro Outer | T24: Regional | V24: Metro | W24: Metro Outer | X24: Regional | Z24: Metro | AA24: Metro Outer | AB24: Regional
A25: Small | B25: 2-5 Days | C25: 2-5 Days | D25: 3-7 Days | F25: 2-5 Days | G25: 2-5 Days | H25: 2-5 Days | J25: 2-5 Days | K25: 2-5 Days | L25: 2-5 Days | N25: 2-5 Days | O25: 2-5 Days | P25: 3-7 Days | R25: 1-3 Days | S25: 1-3 Days | T25: 2-5 Days | V25: 7-14 Days | W25: 7-14 Days | X25: 7-14 Days | Z25: 7-14 Days | AA25: 7-14 Days | AB25: 7-14 Days
A26: Medium | B26: 2-5 Days | C26: 2-5 Days | D26: 3-7 Days | F26: 2-5 Days | G26: 2-5 Days | H26: 2-5 Days | J26: 2-5 Days | K26: 2-5 Days | L26: 2-5 Days | N26: 2-5 Days | O26: 2-5 Days | P26: 3-7 Days | R26: 1-3 Days | S26: 1-3 Days | T26: 2-5 Days | V26: 7-14 Days | W26: 7-14 Days | X26: 7-14 Days | Z26: 7-14 Days | AA26: 7-14 Days | AB26: 7-14 Days
A27: Large | B27: 3-7 Days | C27: 3-7 Days | D27: 5-10 Days | F27: 3-7 Days | G27: 3-7 Days | H27: 5-10 Days | J27: 3-7 Days | K27: 3-7 Days | L27: 5-10 Days | N27: 3-7 Days | O27: 3-7 Days | P27: 5-10 Days | R27: 1-3 Days | S27: 1-3 Days | T27: 3-7 Days | V27: 7-14 Days | W27: 7-14 Days | X27: 7-14 Days | Z27: 7-14 Days | AA27: 7-14 Days | AB27: 7-14 Days
A28: XL | B28: 5-10 Days | C28: 5-10 Days | D28: 5-10 Days | F28: 5-10 Days | G28: 5-10 Days | H28: 5-10 Days | J28: 5-10 Days | K28: 5-10 Days | L28: 5-10 Days | N28: 5-10 Days | O28: 5-10 Days | P28: 5-10 Days | R28: 1-3 Days | S28: 1-3 Days | T28: 5-10 Days | V28: 7-14 Days | W28: 7-14 Days | X28: 7-14 Days | Z28: 7-14 Days | AA28: 7-14 Days | AB28: 7-14 Days
A29: XXL | B29: 5-10 Days | C29: 5-10 Days | D29: 5-10 Days | F29: 5-10 Days | G29: 5-10 Days | H29: 5-10 Days | J29: 5-10 Days | K29: 5-10 Days | L29: 5-10 Days | N29: 5-10 Days | O29: 5-10 Days | P29: 5-10 Days | R29: 1-3 Days | S29: 1-3 Days | T29: 5-10 Days | V29: 7-14 Days | W29: 7-14 Days | X29: 7-14 Days | Z29: 7-14 Days | AA29: 7-14 Days | AB29: 7-14 Days
A30: Bulky | B30: 5-10 Days | C30: 5-10 Days | D30: 5-10 Days | F30: 5-10 Days | G30: 5-10 Days | H30: 5-10 Days | J30: 5-10 Days | K30: 5-10 Days | L30: 5-10 Days | N30: 5-10 Days | O30: 5-10 Days | P30: 5-10 Days | R30: 1-3 Days | S30: 1-3 Days | T30: 5-10 Days | V30: 7-14 Days | W30: 7-14 Days | X30: 7-14 Days | Z30: 7-14 Days | AA30: 7-14 Days | AB30: 7-14 Days
A32: Priority | B32: From QLD | F32: From VIC | J32: From SA | N32: From NSW | R32: From ACT | V32: From TAS | Z32: From WA
A33: Freight Size | B33: Metro | C33: Metro Outer | D33: Regional | F33: Metro | G33: Metro Outer | H33: Regional | J33: Metro | K33: Metro Outer | L33: Regional | N33: Metro | O33: Metro Outer | P33: Regional | R33: Metro | S33: Metro Outer | T33: Regional | V33: Metro | W33: Metro Outer | X33: Regional | Z33: Metro | AA33: Metro Outer | AB33: Regional
A34: Small | B34: 1-2 Days | C34: 1-2 Days | D34: 2-5 Days | F34: 1-2 Days | G34: 1-2 Days | H34: 2-5 Days | J34: 1-2 Days | K34: 1-2 Days | L34: 2-5 Days | N34: 1-2 Days | O34: 1-2 Days | P34: 2-5 Days | R34: 1-2 Days | S34: 1-2 Days | T34: 1-3 Days | V34: 1-2 Days | W34: 1-2 Days | X34: 2-5 Days | Z34: 1-2 Days | AA34: 1-2 Days | AB34: 2-5 Days
A35: Medium | B35: 1-2 Days | C35: 1-2 Days | D35: 2-5 Days | F35: 1-2 Days | G35: 1-2 Days | H35: 2-5 Days | J35: 1-2 Days | K35: 1-2 Days | L35: 2-5 Days | N35: 1-2 Days | O35: 1-2 Days | P35: 2-5 Days | R35: 1-2 Days | S35: 1-2 Days | T35: 1-3 Days | V35: 1-2 Days | W35: 1-2 Days | X35: 2-5 Days | Z35: 1-2 Days | AA35: 1-2 Days | AB35: 2-5 Days
A36: Large | B36: 2-5 Days | C36: 2-5 Days | D36: 5-10 Days | F36: 2-5 Days | G36: 2-5 Days | H36: 5-10 Days | J36: 2-5 Days | K36: 2-5 Days | L36: 5-10 Days | N36: 2-5 Days | O36: 2-5 Days | P36: 5-10 Days | R36: 1-2 Days | S36: 1-2 Days | T36: 2-7 Days | V36: 7-14 Days | W36: 7-14 Days | X36: 7-14 Days | Z36: 7-14 Days | AA36: 7-14 Days | AB36: 7-14 Days
A37: XL | B37: 3-7 Days | C37: 3-7 Days | D37: 5-10 Days | F37: 3-7 Days | G37: 3-7 Days | H37: 5-10 Days | J37: 3-7 Days | K37: 3-7 Days | L37: 5-10 Days | N37: 3-7 Days | O37: 3-7 Days | P37: 5-10 Days | R37: 1-2 Days | S37: 1-2 Days | T37: 2-7 Days | V37: 7-14 Days | W37: 7-14 Days | X37: 7-14 Days | Z37: 7-14 Days | AA37: 7-14 Days | AB37: 7-14 Days
A38: XXL | B38: 3-7 Days | C38: 3-7 Days | D38: 5-10 Days | F38: 3-7 Days | G38: 3-7 Days | H38: 5-10 Days | J38: 3-7 Days | K38: 3-7 Days | L38: 5-10 Days | N38: 3-7 Days | O38: 3-7 Days | P38: 5-10 Days | R38: 1-2 Days | S38: 1-2 Days | T38: 2-7 Days | V38: 7-14 Days | W38: 7-14 Days | X38: 7-14 Days | Z38: 7-14 Days | AA38: 7-14 Days | AB38: 7-14 Days
A39: Bulky | B39: 3-7 Days | C39: 3-7 Days | D39: 5-10 Days | F39: 3-7 Days | G39: 3-7 Days | H39: 5-10 Days | J39: 3-7 Days | K39: 3-7 Days | L39: 5-10 Days | N39: 3-7 Days | O39: 3-7 Days | P39: 5-10 Days | R39: 1-2 Days | S39: 1-2 Days | T39: 2-7 Days | V39: 7-14 Days | W39: 7-14 Days | X39: 7-14 Days | Z39: 7-14 Days | AA39: 7-14 Days | AB39: 7-14 Days

Sheet NSW
A1: Freight Charges for NSW Orders
A3: Standard | B3: From QLD | F3: From VIC | J3: From SA | N3: From WA | R3: From NSW | V3: From TAS | Z3: From ACT
A4: Freight Size | B4: Metro | C4: Metro Outer | D4: Regional | F4: Metro | G4: Metro Outer | H4: Regional | J4: Metro | K4: Metro Outer | L4: Regional | N4: Metro | O4: Metro Outer | P4: Regional | R4: Metro | S4: Metro Outer | T4: Regional | V4: Metro | W4: Metro Outer | X4: Regional | Z4: Metro | AA4: Metro Outer | AB4: Regional
A5: Small | B5: ='Cost model'!M128 -> 10.5 | C5: ='Cost model'!M129 -> 13.5 | D5: ='Cost model'!M130 -> 18.5 | F5: ='Cost model'!M146 -> 12.5 | G5: ='Cost model'!M147 -> 14.5 | H5: ='Cost model'!M148 -> 21.5 | J5: ='Cost model'!M164 -> 11.5 | K5: ='Cost model'!M165 -> 15.5 | L5: ='Cost model'!M166 -> 18.5 | N5: ='Cost model'!M182 -> 15.5 | O5: ='Cost model'!M183 -> 17.5 | P5: ='Cost model'!M184 -> 22.5 | R5: ='Cost model'!M200 -> 7.5 | S5: ='Cost model'!M201 -> 12.5 | T5: ='Cost model'!M202 -> 17.5 | V5: ='Cost model'!M218 -> 12.5 | W5: ='Cost model'!M219 -> 14.5 | X5: ='Cost model'!M220 -> 25.5 | Z5: ='Cost model'!M236 -> 17.5 | AA5: ='Cost model'!M237 -> 18.5 | AB5: ='Cost model'!M238 -> 22.5
A6: Medium | B6: ='Cost model'!M131 -> 40 | C6: ='Cost model'!M132 -> 50 | D6: ='Cost model'!M133 -> 55 | F6: ='Cost model'!M149 -> 45 | G6: ='Cost model'!M150 -> 55 | H6: ='Cost model'!M151 -> 55 | J6: ='Cost model'!M167 -> 60 | K6: ='Cost model'!M168 -> 60 | L6: ='Cost model'!M169 -> 60 | N6: ='Cost model'!M185 -> 55 | O6: ='Cost model'!M186 -> 55 | P6: ='Cost model'!M187 -> 75 | R6: ='Cost model'!M203 -> 26.5 | S6: ='Cost model'!M204 -> 45 | T6: ='Cost model'!M205 -> 50 | V6: ='Cost model'!M221 -> 50 | W6: ='Cost model'!M222 -> 60 | X6: ='Cost model'!M223 -> 70 | Z6: ='Cost model'!M239 -> 55 | AA6: ='Cost model'!M240 -> 55 | AB6: ='Cost model'!M241 -> 75
A7: Large | B7: ='Cost model'!M134 -> 80 | C7: ='Cost model'!M135 -> 80 | D7: ='Cost model'!M136 -> 105 | F7: ='Cost model'!M152 -> 65 | G7: ='Cost model'!M153 -> 100 | H7: ='Cost model'!M154 -> 130 | J7: ='Cost model'!M170 -> 80 | K7: ='Cost model'!M171 -> 90 | L7: ='Cost model'!M172 -> 115 | N7: ='Cost model'!M188 -> 95 | O7: ='Cost model'!M189 -> 105 | P7: ='Cost model'!M190 -> 140 | R7: ='Cost model'!M206 -> 55 | S7: ='Cost model'!M207 -> 75 | T7: ='Cost model'!M208 -> 80 | V7: ='Cost model'!M224 -> 85 | W7: ='Cost model'!M225 -> 95 | X7: ='Cost model'!M226 -> 125 | Z7: ='Cost model'!M242 -> 95 | AA7: ='Cost model'!M243 -> 110 | AB7: ='Cost model'!M244 -> 145
A8: XL | B8: ='Cost model'!M137 -> 120 | C8: ='Cost model'!M138 -> 150 | D8: ='Cost model'!M139 -> 170 | F8: ='Cost model'!M155 -> 125 | G8: ='Cost model'!M156 -> 145 | H8: ='Cost model'!M157 -> 195 | J8: ='Cost model'!M173 -> 125 | K8: ='Cost model'!M174 -> 170 | L8: ='Cost model'!M175 -> 195 | N8: ='Cost model'!M191 -> 160 | O8: ='Cost model'!M192 -> 190 | P8: ='Cost model'!M193 -> 230 | R8: ='Cost model'!M209 -> 105 | S8: ='Cost model'!M210 -> 135 | T8: ='Cost model'!M211 -> 175 | V8: ='Cost model'!M227 -> 145 | W8: ='Cost model'!M228 -> 170 | X8: ='Cost model'!M229 -> 205 | Z8: ='Cost model'!M245 -> 165 | AA8: ='Cost model'!M246 -> 195 | AB8: ='Cost model'!M247 -> 235
A9: XXL | B9: ='Cost model'!M140 -> 155 | C9: ='Cost model'!M141 -> 230 | D9: ='Cost model'!M142 -> 270 | F9: ='Cost model'!M158 -> 175 | G9: ='Cost model'!M159 -> 255 | H9: ='Cost model'!M160 -> 300 | J9: ='Cost model'!M176 -> 170 | K9: ='Cost model'!M177 -> 255 | L9: ='Cost model'!M178 -> 310 | N9: ='Cost model'!M194 -> 200 | O9: ='Cost model'!M195 -> 300 | P9: ='Cost model'!M196 -> 360 | R9: ='Cost model'!M212 -> 120 | S9: ='Cost model'!M213 -> 155 | T9: ='Cost model'!M214 -> 240 | V9: ='Cost model'!M230 -> 180 | W9: ='Cost model'!M231 -> 270 | X9: ='Cost model'!M232 -> 325 | Z9: ='Cost model'!M248 -> 210 | AA9: ='Cost model'!M249 -> 310 | AB9: ='Cost model'!M250 -> 375
A10: Bulky | B10: ='Cost model'!M143 -> 235 | C10: ='Cost model'!M144 -> 330 | D10: ='Cost model'!M145 -> 385 | F10: ='Cost model'!M161 -> 230 | G10: ='Cost model'!M162 -> 355 | H10: ='Cost model'!M163 -> 420 | J10: ='Cost model'!M179 -> 240 | K10: ='Cost model'!M180 -> 385 | L10: ='Cost model'!M181 -> 460 | N10: ='Cost model'!M197 -> 280 | O10: ='Cost model'!M198 -> 465 | P10: ='Cost model'!M199 -> 505 | R10: ='Cost model'!M215 -> 135 | S10: ='Cost model'!M216 -> 215 | T10: ='Cost model'!M217 -> 285 | V10: ='Cost model'!M233 -> 250 | W10: ='Cost model'!M234 -> 390 | X10: ='Cost model'!M235 -> 460 | Z10: ='Cost model'!M251 -> 275 | AA10: ='Cost model'!M252 -> 445 | AB10: ='Cost model'!M253 -> 525
A12: Priority | B12: From QLD | F12: From VIC | J12: From SA | N12: From WA | R12: From NSW | V12: From TAS | Z12: From ACT
A13: Freight Size | B13: Metro | C13: Metro Outer | D13: Regional | F13: Metro | G13: Metro Outer | H13: Regional | J13: Metro | K13: Metro Outer | L13: Regional | N13: Metro | O13: Metro Outer | P13: Regional | R13: Metro | S13: Metro Outer | T13: Regional | V13: Metro | W13: Metro Outer | X13: Regional | Z13: Metro | AA13: Metro Outer | AB13: Regional
A14: Small | B14: ='Cost model'!N128 -> 15.5 | C14: ='Cost model'!N129 -> 18.5 | D14: ='Cost model'!N130 -> 25.5 | F14: ='Cost model'!N146 -> 17.5 | G14: ='Cost model'!N147 -> 19.5 | H14: ='Cost model'!N148 -> 29.5 | J14: ='Cost model'!N164 -> 16.5 | K14: ='Cost model'!N165 -> 21.5 | L14: ='Cost model'!N166 -> 25.5 | N14: ='Cost model'!N182 -> 21.5 | O14: ='Cost model'!N183 -> 23.5 | P14: ='Cost model'!N184 -> 35 | R14: ='Cost model'!N200 -> 12.5 | S14: ='Cost model'!N201 -> 17.5 | T14: ='Cost model'!N202 -> 23.5 | V14: ='Cost model'!N218 -> 17.5 | W14: ='Cost model'!N219 -> 19.5 | X14: ='Cost model'!N220 -> 35 | Z14: ='Cost model'!N236 -> 23.5 | AA14: ='Cost model'!N237 -> 25.5 | AB14: ='Cost model'!N238 -> 35
A15: Medium | B15: ='Cost model'!N131 -> 55 | C15: ='Cost model'!N132 -> 65 | D15: ='Cost model'!N133 -> 70 | F15: ='Cost model'!N149 -> 60 | G15: ='Cost model'!N150 -> 70 | H15: ='Cost model'!N151 -> 70 | J15: ='Cost model'!N167 -> 80 | K15: ='Cost model'!N168 -> 80 | L15: ='Cost model'!N169 -> 80 | N15: ='Cost model'!N185 -> 70 | O15: ='Cost model'!N186 -> 70 | P15: ='Cost model'!N187 -> 95 | R15: ='Cost model'!N203 -> 35 | S15: ='Cost model'!N204 -> 60 | T15: ='Cost model'!N205 -> 65 | V15: ='Cost model'!N221 -> 65 | W15: ='Cost model'!N222 -> 80 | X15: ='Cost model'!N223 -> 90 | Z15: ='Cost model'!N239 -> 70 | AA15: ='Cost model'!N240 -> 70 | AB15: ='Cost model'!N241 -> 95
A16: Large | B16: ='Cost model'!N134 -> 110 | C16: ='Cost model'!N135 -> 110 | D16: ='Cost model'!N136 -> 145 | F16: ='Cost model'!N152 -> 90 | G16: ='Cost model'!N153 -> 135 | H16: ='Cost model'!N154 -> 180 | J16: ='Cost model'!N170 -> 110 | K16: ='Cost model'!N171 -> 125 | L16: ='Cost model'!N172 -> 160 | N16: ='Cost model'!N188 -> 130 | O16: ='Cost model'!N189 -> 145 | P16: ='Cost model'!N190 -> 190 | R16: ='Cost model'!N206 -> 75 | S16: ='Cost model'!N207 -> 105 | T16: ='Cost model'!N208 -> 110 | V16: ='Cost model'!N224 -> 115 | W16: ='Cost model'!N225 -> 130 | X16: ='Cost model'!N226 -> 170 | Z16: ='Cost model'!N242 -> 130 | AA16: ='Cost model'!N243 -> 150 | AB16: ='Cost model'!N244 -> 200
A17: XL | B17: ='Cost model'!N137 -> 145 | C17: ='Cost model'!N138 -> 180 | D17: ='Cost model'!N139 -> 205 | F17: ='Cost model'!N155 -> 150 | G17: ='Cost model'!N156 -> 175 | H17: ='Cost model'!N157 -> 235 | J17: ='Cost model'!N173 -> 150 | K17: ='Cost model'!N174 -> 205 | L17: ='Cost model'!N175 -> 235 | N17: ='Cost model'!N191 -> 195 | O17: ='Cost model'!N192 -> 230 | P17: ='Cost model'!N193 -> 280 | R17: ='Cost model'!N209 -> 130 | S17: ='Cost model'!N210 -> 165 | T17: ='Cost model'!N211 -> 210 | V17: ='Cost model'!N227 -> 175 | W17: ='Cost model'!N228 -> 205 | X17: ='Cost model'!N229 -> 250 | Z17: ='Cost model'!N245 -> 200 | AA17: ='Cost model'!N246 -> 235 | AB17: ='Cost model'!N247 -> 285
A18: XXL | B18: ='Cost model'!N140 -> 190 | C18: ='Cost model'!N141 -> 230 | D18: ='Cost model'!N142 -> 270 | F18: ='Cost model'!N158 -> 210 | G18: ='Cost model'!N159 -> 255 | H18: ='Cost model'!N160 -> 300 | J18: ='Cost model'!N176 -> 205 | K18: ='Cost model'!N177 -> 255 | L18: ='Cost model'!N178 -> 310 | N18: ='Cost model'!N194 -> 240 | O18: ='Cost model'!N195 -> 300 | P18: ='Cost model'!N196 -> 360 | R18: ='Cost model'!N212 -> 145 | S18: ='Cost model'!N213 -> 190 | T18: ='Cost model'!N214 -> 290 | V18: ='Cost model'!N230 -> 220 | W18: ='Cost model'!N231 -> 270 | X18: ='Cost model'!N232 -> 325 | Z18: ='Cost model'!N248 -> 255 | AA18: ='Cost model'!N249 -> 310 | AB18: ='Cost model'!N250 -> 375
A19: Bulky | B19: ='Cost model'!N143 -> 285 | C19: ='Cost model'!N144 -> 330 | D19: ='Cost model'!N145 -> 385 | F19: ='Cost model'!N161 -> 280 | G19: ='Cost model'!N162 -> 355 | H19: ='Cost model'!N163 -> 420 | J19: ='Cost model'!N179 -> 290 | K19: ='Cost model'!N180 -> 385 | L19: ='Cost model'!N181 -> 460 | N19: ='Cost model'!N197 -> 340 | O19: ='Cost model'!N198 -> 465 | P19: ='Cost model'!N199 -> 505 | R19: ='Cost model'!N215 -> 165 | S19: ='Cost model'!N216 -> 260 | T19: ='Cost model'!N217 -> 345 | V19: ='Cost model'!N233 -> 300 | W19: ='Cost model'!N234 -> 390 | X19: ='Cost model'!N235 -> 460 | Z19: ='Cost model'!N251 -> 330 | AA19: ='Cost model'!N252 -> 445 | AB19: ='Cost model'!N253 -> 525
A21: Delivery time frames for NSW Orders
A23: Standard | B23: From QLD | F23: From VIC | J23: From SA | N23: From WA | R23: From NSW | V23: From TAS | Z23: From ACT
A24: Freight Size | B24: Metro | C24: Metro Outer | D24: Regional | F24: Metro | G24: Metro Outer | H24: Regional | J24: Metro | K24: Metro Outer | L24: Regional | N24: Metro | O24: Metro Outer | P24: Regional | R24: Metro | S24: Metro Outer | T24: Regional | V24: Metro | W24: Metro Outer | X24: Regional | Z24: Metro | AA24: Metro Outer | AB24: Regional
A25: Small | B25: 1-2 Days | C25: 1-3 Days | D25: 2-5 Days | F25: 1-2 Days | G25: 1-3 Days | H25: 2-5 Days | J25: 2-5 Days | K25: 2-5 Days | L25: 2-5 Days | N25: 7-10 Days | O25: 7-10 Days | P25: 7-10 Days | R25: 1-2 Days | S25: 1-3 Days | T25: 2-5 Days | V25: 7-14 Days | W25: 7-14 Days | X25: 7-14 Days | Z25: 7-14 Days | AA25: 7-14 Days | AB25: 7-14 Days
A26: Medium | B26: 1-2 Days | C26: 1-3 Days | D26: 2-5 Days | F26: 1-2 Days | G26: 1-3 Days | H26: 2-5 Days | J26: 2-5 Days | K26: 2-5 Days | L26: 2-5 Days | N26: 7-10 Days | O26: 7-10 Days | P26: 7-10 Days | R26: 1-2 Days | S26: 1-3 Days | T26: 2-5 Days | V26: 7-14 Days | W26: 7-14 Days | X26: 7-14 Days | Z26: 7-14 Days | AA26: 7-14 Days | AB26: 7-14 Days
A27: Large | B27: 1-2 Days | C27: 1-3 Days | D27: 3-7 Days | F27: 1-2 Days | G27: 1-3 Days | H27: 3-7 Days | J27: 3-7 Days | K27: 3-7 Days | L27: 5-10 Days | N27: 7-10 Days | O27: 7-10 Days | P27: 7-10 Days | R27: 1-2 Days | S27: 1-3 Days | T27: 3-7 Days | V27: 7-14 Days | W27: 7-14 Days | X27: 7-14 Days | Z27: 7-14 Days | AA27: 7-14 Days | AB27: 7-14 Days
A28: XL | B28: 2-5 Days | C28: 2-5 Days | D28: 5-10 Days | F28: 2-5 Days | G28: 2-5 Days | H28: 5-10 Days | J28: 5-10 Days | K28: 5-10 Days | L28: 5-10 Days | N28: 7-10 Days | O28: 7-10 Days | P28: 7-10 Days | R28: 2-5 Days | S28: 2-5 Days | T28: 5-10 Days | V28: 7-14 Days | W28: 7-14 Days | X28: 7-14 Days | Z28: 7-14 Days | AA28: 7-14 Days | AB28: 7-14 Days
A29: XXL | B29: 2-5 Days | C29: 2-5 Days | D29: 5-10 Days | F29: 2-5 Days | G29: 2-5 Days | H29: 5-10 Days | J29: 5-10 Days | K29: 5-10 Days | L29: 5-10 Days | N29: 7-10 Days | O29: 7-10 Days | P29: 7-10 Days | R29: 2-5 Days | S29: 2-5 Days | T29: 5-10 Days | V29: 7-14 Days | W29: 7-14 Days | X29: 7-14 Days | Z29: 7-14 Days | AA29: 7-14 Days | AB29: 7-14 Days
A30: Bulky | B30: 2-5 Days | C30: 2-5 Days | D30: 5-10 Days | F30: 2-5 Days | G30: 2-5 Days | H30: 5-10 Days | J30: 5-10 Days | K30: 5-10 Days | L30: 5-10 Days | N30: 7-10 Days | O30: 7-10 Days | P30: 7-10 Days | R30: 2-5 Days | S30: 2-5 Days | T30: 5-10 Days | V30: 7-14 Days | W30: 7-14 Days | X30: 7-14 Days | Z30: 7-14 Days | AA30: 7-14 Days | AB30: 7-14 Days
A32: Priority | B32: From QLD | F32: From VIC | J32: From SA | N32: From WA | R32: From NSW | V32: From TAS | Z32: From ACT
A33: Freight Size | B33: Metro | C33: Metro Outer | D33: Regional | F33: Metro | G33: Metro Outer | H33: Regional | J33: Metro | K33: Metro Outer | L33: Regional | N33: Metro | O33: Metro Outer | P33: Regional | R33: Metro | S33: Metro Outer | T33: Regional | V33: Metro | W33: Metro Outer | X33: Regional | Z33: Metro | AA33: Metro Outer | AB33: Regional
A34: Small | B34: 1-2 Days | C34: 1-2 Days | D34: 1-3 Days | F34: 1-2 Days | G34: 1-2 Days | H34: 1-3 Days | J34: 1-2 Days | K34: 1-2 Days | L34: 2-5 Days | N34: 1-2 Days | O34: 1-2 Days | P34: 2-5 Days | R34: 1-2 Days | S34: 1-2 Days | T34: 1-3 Days | V34: 1-2 Days | W34: 1-2 Days | X34: 2-5 Days | Z34: 1-2 Days | AA34: 1-2 Days | AB34: 2-5 Days
A35: Medium | B35: 1-2 Days | C35: 1-2 Days | D35: 1-3 Days | F35: 1-2 Days | G35: 1-2 Days | H35: 1-3 Days | J35: 1-2 Days | K35: 1-2 Days | L35: 2-5 Days | N35: 1-2 Days | O35: 1-2 Days | P35: 2-5 Days | R35: 1-2 Days | S35: 1-2 Days | T35: 1-3 Days | V35: 1-2 Days | W35: 1-2 Days | X35: 2-5 Days | Z35: 1-2 Days | AA35: 1-2 Days | AB35: 2-5 Days
A36: Large | B36: 1-2 Days | C36: 1-2 Days | D36: 2-7 Days | F36: 1-2 Days | G36: 1-2 Days | H36: 2-7 Days | J36: 2-5 Days | K36: 2-5 Days | L36: 5-10 Days | N36: 7-10 Days | O36: 7-10 Days | P36: 7-14 Days | R36: 1-2 Days | S36: 1-2 Days | T36: 2-7 Days | V36: 7-14 Days | W36: 7-14 Days | X36: 7-14 Days | Z36: 7-14 Days | AA36: 7-14 Days | AB36: 7-14 Days
A37: XL | B37: 1-3 Days | C37: 1-3 Days | D37: 2-7 Days | F37: 1-3 Days | G37: 1-3 Days | H37: 2-7 Days | J37: 3-7 Days | K37: 3-7 Days | L37: 5-10 Days | N37: 7-10 Days | O37: 7-10 Days | P37: 7-14 Days | R37: 1-3 Days | S37: 1-3 Days | T37: 2-7 Days | V37: 7-14 Days | W37: 7-14 Days | X37: 7-14 Days | Z37: 7-14 Days | AA37: 7-14 Days | AB37: 7-14 Days
A38: XXL | B38: 1-3 Days | C38: 1-3 Days | D38: 2-7 Days | F38: 1-3 Days | G38: 1-3 Days | H38: 2-7 Days | J38: 3-7 Days | K38: 3-7 Days | L38: 5-10 Days | N38: 7-10 Days | O38: 7-10 Days | P38: 7-14 Days | R38: 1-3 Days | S38: 1-3 Days | T38: 2-7 Days | V38: 7-14 Days | W38: 7-14 Days | X38: 7-14 Days | Z38: 7-14 Days | AA38: 7-14 Days | AB38: 7-14 Days
A39: Bulky | B39: 1-3 Days | C39: 1-3 Days | D39: 2-7 Days | F39: 1-3 Days | G39: 1-3 Days | H39: 2-7 Days | J39: 3-7 Days | K39: 3-7 Days | L39: 5-10 Days | N39: 7-10 Days | O39: 7-10 Days | P39: 7-14 Days | R39: 1-3 Days | S39: 1-3 Days | T39: 2-7 Days | V39: 7-14 Days | W39: 7-14 Days | X39: 7-14 Days | Z39: 7-14 Days | AA39: 7-14 Days | AB39: 7-14 Days

Sheet NT
A1: Freight Charges for NT Orders
A3: Standard | B3: From SA | F3: From VIC | J3: From WA | N3: From QLD | R3: From NSW | V3: From TAS | Z3: From ACT
A4: Freight Size | B4: Metro | C4: Metro Outer | D4: Regional | F4: Metro | G4: Metro Outer | H4: Regional | J4: Metro | K4: Metro Outer | L4: Regional | N4: Metro | O4: Metro Outer | P4: Regional | R4: Metro | S4: Metro Outer | T4: Regional | V4: Metro | W4: Metro Outer | X4: Regional | Z4: Metro | AA4: Metro Outer | AB4: Regional
A5: Small | B5: ='Cost model'!M254 -> 20.5 | C5: ='Cost model'!M255 -> 20.5 | D5: ='Cost model'!M256 -> 25.5 | F5: ='Cost model'!M272 -> 22.5 | G5: ='Cost model'!M273 -> 22.5 | H5: ='Cost model'!M274 -> 26.5 | J5: ='Cost model'!M290 -> 22.5 | K5: ='Cost model'!M291 -> 22.5 | L5: ='Cost model'!M292 -> 24.5 | N5: ='Cost model'!M308 -> 15.5 | O5: ='Cost model'!M309 -> 17.5 | P5: ='Cost model'!M310 -> 21.5 | R5: ='Cost model'!M326 -> 15.5 | S5: ='Cost model'!M327 -> 17.5 | T5: ='Cost model'!M328 -> 23.5 | V5: ='Cost model'!M344 -> 15.5 | W5: ='Cost model'!M345 -> 17.5 | X5: ='Cost model'!M346 -> 23.5 | Z5: ='Cost model'!M362 -> 21.5 | AA5: ='Cost model'!M363 -> 21.5 | AB5: ='Cost model'!M364 -> 27.5
A6: Medium | B6: ='Cost model'!M257 -> 60 | C6: ='Cost model'!M258 -> 70 | D6: ='Cost model'!M259 -> 75 | F6: ='Cost model'!M275 -> 70 | G6: ='Cost model'!M276 -> 70 | H6: ='Cost model'!M277 -> 80 | J6: ='Cost model'!M293 -> 75 | K6: ='Cost model'!M294 -> 75 | L6: ='Cost model'!M295 -> 75 | N6: ='Cost model'!M311 -> 55 | O6: ='Cost model'!M312 -> 60 | P6: ='Cost model'!M313 -> 70 | R6: ='Cost model'!M329 -> 55 | S6: ='Cost model'!M330 -> 60 | T6: ='Cost model'!M331 -> 70 | V6: ='Cost model'!M347 -> 55 | W6: ='Cost model'!M348 -> 60 | X6: ='Cost model'!M349 -> 70 | Z6: ='Cost model'!M365 -> 70 | AA6: ='Cost model'!M366 -> 75 | AB6: ='Cost model'!M367 -> 85
A7: Large | B7: ='Cost model'!M260 -> 115 | C7: ='Cost model'!M261 -> 120 | D7: ='Cost model'!M262 -> 155 | F7: ='Cost model'!M278 -> 110 | G7: ='Cost model'!M279 -> 125 | H7: ='Cost model'!M280 -> 165 | J7: ='Cost model'!M296 -> 105 | K7: ='Cost model'!M297 -> 115 | L7: ='Cost model'!M298 -> 155 | N7: ='Cost model'!M314 -> 95 | O7: ='Cost model'!M315 -> 105 | P7: ='Cost model'!M316 -> 140 | R7: ='Cost model'!M332 -> 95 | S7: ='Cost model'!M333 -> 110 | T7: ='Cost model'!M334 -> 145 | V7: ='Cost model'!M350 -> 95 | W7: ='Cost model'!M351 -> 110 | X7: ='Cost model'!M352 -> 145 | Z7: ='Cost model'!M368 -> 115 | AA7: ='Cost model'!M369 -> 130 | AB7: ='Cost model'!M370 -> 175
A8: XL | B8: ='Cost model'!M263 -> 185 | C8: ='Cost model'!M264 -> 220 | D8: ='Cost model'!M265 -> 265 | F8: ='Cost model'!M281 -> 185 | G8: ='Cost model'!M282 -> 225 | H8: ='Cost model'!M283 -> 270 | J8: ='Cost model'!M299 -> 180 | K8: ='Cost model'!M300 -> 210 | L8: ='Cost model'!M301 -> 245 | N8: ='Cost model'!M317 -> 160 | O8: ='Cost model'!M318 -> 190 | P8: ='Cost model'!M319 -> 230 | R8: ='Cost model'!M335 -> 170 | S8: ='Cost model'!M336 -> 195 | T8: ='Cost model'!M337 -> 235 | V8: ='Cost model'!M353 -> 165 | W8: ='Cost model'!M354 -> 195 | X8: ='Cost model'!M355 -> 235 | Z8: ='Cost model'!M371 -> 200 | AA8: ='Cost model'!M372 -> 235 | AB8: ='Cost model'!M373 -> 285
A9: XXL | B9: ='Cost model'!M266 -> 235 | C9: ='Cost model'!M267 -> 350 | D9: ='Cost model'!M268 -> 415 | F9: ='Cost model'!M284 -> 235 | G9: ='Cost model'!M285 -> 350 | H9: ='Cost model'!M286 -> 420 | J9: ='Cost model'!M302 -> 225 | K9: ='Cost model'!M303 -> 330 | L9: ='Cost model'!M304 -> 400 | N9: ='Cost model'!M320 -> 200 | O9: ='Cost model'!M321 -> 300 | P9: ='Cost model'!M322 -> 355 | R9: ='Cost model'!M338 -> 210 | S9: ='Cost model'!M339 -> 310 | T9: ='Cost model'!M340 -> 375 | V9: ='Cost model'!M356 -> 210 | W9: ='Cost model'!M357 -> 310 | X9: ='Cost model'!M358 -> 370 | Z9: ='Cost model'!M374 -> 250 | AA9: ='Cost model'!M375 -> 375 | AB9: ='Cost model'!M376 -> 445
A10: Bulky | B10: ='Cost model'!M269 -> 325 | C10: ='Cost model'!M270 -> 500 | D10: ='Cost model'!M271 -> 590 | F10: ='Cost model'!M287 -> 330 | G10: ='Cost model'!M288 -> 505 | H10: ='Cost model'!M289 -> 595 | J10: ='Cost model'!M305 -> 310 | K10: ='Cost model'!M306 -> 480 | L10: ='Cost model'!M307 -> 560 | N10: ='Cost model'!M323 -> 280 | O10: ='Cost model'!M324 -> 430 | P10: ='Cost model'!M325 -> 505 | R10: ='Cost model'!M341 -> 290 | S10: ='Cost model'!M342 -> 445 | T10: ='Cost model'!M343 -> 525 | V10: ='Cost model'!M359 -> 290 | W10: ='Cost model'!M360 -> 445 | X10: ='Cost model'!M361 -> 525 | Z10: ='Cost model'!M377 -> 345 | AA10: ='Cost model'!M378 -> 535 | AB10: ='Cost model'!M379 -> 625
A12: Priority | B12: From SA | F12: From VIC | J12: From WA | N12: From QLD | R12: From NSW | V12: From TAS | Z12: From ACT
A13: Freight Size | B13: Metro | C13: Metro Outer | D13: Regional | F13: Metro | G13: Metro Outer | H13: Regional | J13: Metro | K13: Metro Outer | L13: Regional | N13: Metro | O13: Metro Outer | P13: Regional | R13: Metro | S13: Metro Outer | T13: Regional | V13: Metro | W13: Metro Outer | X13: Regional | Z13: Metro | AA13: Metro Outer | AB13: Regional
A14: Small | B14: ='Cost model'!N254 -> 27.5 | C14: ='Cost model'!N255 -> 27.5 | D14: ='Cost model'!N256 -> 35 | F14: ='Cost model'!N272 -> 35 | G14: ='Cost model'!N273 -> 35 | H14: ='Cost model'!N274 -> 40 | J14: ='Cost model'!N290 -> 35 | K14: ='Cost model'!N291 -> 35 | L14: ='Cost model'!N292 -> 35 | N14: ='Cost model'!N308 -> 21.5 | O14: ='Cost model'!N309 -> 23.5 | P14: ='Cost model'!N310 -> 29.5 | R14: ='Cost model'!N326 -> 21.5 | S14: ='Cost model'!N327 -> 23.5 | T14: ='Cost model'!N328 -> 35 | V14: ='Cost model'!N344 -> 21.5 | W14: ='Cost model'!N345 -> 23.5 | X14: ='Cost model'!N346 -> 35 | Z14: ='Cost model'!N362 -> 29.5 | AA14: ='Cost model'!N363 -> 29.5 | AB14: ='Cost model'!N364 -> 40
A15: Medium | B15: ='Cost model'!N257 -> 80 | C15: ='Cost model'!N258 -> 90 | D15: ='Cost model'!N259 -> 95 | F15: ='Cost model'!N275 -> 90 | G15: ='Cost model'!N276 -> 90 | H15: ='Cost model'!N277 -> 105 | J15: ='Cost model'!N293 -> 95 | K15: ='Cost model'!N294 -> 95 | L15: ='Cost model'!N295 -> 95 | N15: ='Cost model'!N311 -> 70 | O15: ='Cost model'!N312 -> 80 | P15: ='Cost model'!N313 -> 90 | R15: ='Cost model'!N329 -> 70 | S15: ='Cost model'!N330 -> 80 | T15: ='Cost model'!N331 -> 90 | V15: ='Cost model'!N347 -> 70 | W15: ='Cost model'!N348 -> 80 | X15: ='Cost model'!N349 -> 90 | Z15: ='Cost model'!N365 -> 90 | AA15: ='Cost model'!N366 -> 95 | AB15: ='Cost model'!N367 -> 110
A16: Large | B16: ='Cost model'!N260 -> 160 | C16: ='Cost model'!N261 -> 165 | D16: ='Cost model'!N262 -> 210 | F16: ='Cost model'!N278 -> 150 | G16: ='Cost model'!N279 -> 170 | H16: ='Cost model'!N280 -> 225 | J16: ='Cost model'!N296 -> 145 | K16: ='Cost model'!N297 -> 160 | L16: ='Cost model'!N298 -> 210 | N16: ='Cost model'!N314 -> 130 | O16: ='Cost model'!N315 -> 145 | P16: ='Cost model'!N316 -> 190 | R16: ='Cost model'!N332 -> 130 | S16: ='Cost model'!N333 -> 150 | T16: ='Cost model'!N334 -> 200 | V16: ='Cost model'!N350 -> 130 | W16: ='Cost model'!N351 -> 150 | X16: ='Cost model'!N352 -> 200 | Z16: ='Cost model'!N368 -> 160 | AA16: ='Cost model'!N369 -> 180 | AB16: ='Cost model'!N370 -> 240
A17: XL | B17: ='Cost model'!N263 -> 225 | C17: ='Cost model'!N264 -> 265 | D17: ='Cost model'!N265 -> 320 | F17: ='Cost model'!N281 -> 225 | G17: ='Cost model'!N282 -> 270 | H17: ='Cost model'!N283 -> 325 | J17: ='Cost model'!N299 -> 220 | K17: ='Cost model'!N300 -> 255 | L17: ='Cost model'!N301 -> 295 | N17: ='Cost model'!N317 -> 195 | O17: ='Cost model'!N318 -> 230 | P17: ='Cost model'!N319 -> 280 | R17: ='Cost model'!N335 -> 205 | S17: ='Cost model'!N336 -> 235 | T17: ='Cost model'!N337 -> 285 | V17: ='Cost model'!N353 -> 200 | W17: ='Cost model'!N354 -> 235 | X17: ='Cost model'!N355 -> 285 | Z17: ='Cost model'!N371 -> 240 | AA17: ='Cost model'!N372 -> 285 | AB17: ='Cost model'!N373 -> 345
A18: XXL | B18: ='Cost model'!N266 -> 285 | C18: ='Cost model'!N267 -> 350 | D18: ='Cost model'!N268 -> 415 | F18: ='Cost model'!N284 -> 285 | G18: ='Cost model'!N285 -> 350 | H18: ='Cost model'!N286 -> 420 | J18: ='Cost model'!N302 -> 270 | K18: ='Cost model'!N303 -> 330 | L18: ='Cost model'!N304 -> 400 | N18: ='Cost model'!N320 -> 240 | O18: ='Cost model'!N321 -> 300 | P18: ='Cost model'!N322 -> 355 | R18: ='Cost model'!N338 -> 255 | S18: ='Cost model'!N339 -> 310 | T18: ='Cost model'!N340 -> 375 | V18: ='Cost model'!N356 -> 255 | W18: ='Cost model'!N357 -> 310 | X18: ='Cost model'!N358 -> 370 | Z18: ='Cost model'!N374 -> 300 | AA18: ='Cost model'!N375 -> 375 | AB18: ='Cost model'!N376 -> 445
A19: Bulky | B19: ='Cost model'!N269 -> 390 | C19: ='Cost model'!N270 -> 500 | D19: ='Cost model'!N271 -> 590 | F19: ='Cost model'!N287 -> 400 | G19: ='Cost model'!N288 -> 505 | H19: ='Cost model'!N289 -> 595 | J19: ='Cost model'!N305 -> 375 | K19: ='Cost model'!N306 -> 480 | L19: ='Cost model'!N307 -> 560 | N19: ='Cost model'!N323 -> 340 | O19: ='Cost model'!N324 -> 430 | P19: ='Cost model'!N325 -> 505 | R19: ='Cost model'!N341 -> 350 | S19: ='Cost model'!N342 -> 445 | T19: ='Cost model'!N343 -> 525 | V19: ='Cost model'!N359 -> 350 | W19: ='Cost model'!N360 -> 445 | X19: ='Cost model'!N361 -> 525 | Z19: ='Cost model'!N377 -> 415 | AA19: ='Cost model'!N378 -> 535 | AB19: ='Cost model'!N379 -> 625
A21: Delivery time frames for NT Orders
A23: Standard | B23: From SA | F23: From VIC | J23: From WA | N23: From QLD | R23: From NSW | V23: From TAS | Z23: From ACT
A24: Freight Size | B24: Metro | C24: Metro Outer | D24: Regional | F24: Metro | G24: Metro Outer | H24: Regional | J24: Metro | K24: Metro Outer | L24: Regional | N24: Metro | O24: Metro Outer | P24: Regional | R24: Metro | S24: Metro Outer | T24: Regional | V24: Metro | W24: Metro Outer | X24: Regional | Z24: Metro | AA24: Metro Outer | AB24: Regional
A25: Small | B25: 1-2 Days | C25: 1-3 Days | D25: 2-5 Days | F25: 2-5 Days | G25: 3-7 Days | H25: 5-10 Days | J25: 2-5 Days | K25: 2-5 Days | L25: 3-7 Days | N25: 2-5 Days | O25: 2-5 Days | P25: 3-7 Days | R25: 2-5 Days | S25: 2-5 Days | T25: 3-7 Days | V25: 7-14 Days | W25: 7-14 Days | X25: 7-14 Days | Z25: 7-14 Days | AA25: 7-14 Days | AB25: 7-14 Days
A26: Medium | B26: 1-2 Days | C26: 1-3 Days | D26: 2-5 Days | F26: 2-5 Days | G26: 3-7 Days | H26: 5-10 Days | J26: 2-5 Days | K26: 2-5 Days | L26: 3-7 Days | N26: 2-5 Days | O26: 2-5 Days | P26: 3-7 Days | R26: 2-5 Days | S26: 2-5 Days | T26: 3-7 Days | V26: 7-14 Days | W26: 7-14 Days | X26: 7-14 Days | Z26: 7-14 Days | AA26: 7-14 Days | AB26: 7-14 Days
A27: Large | B27: 1-2 Days | C27: 1-3 Days | D27: 3-7 Days | F27: 3-7 Days | G27: 3-7 Days | H27: 5-10 Days | J27: 5-10 Days | K27: 5-10 Days | L27: 5-10 Days | N27: 5-10 Days | O27: 5-10 Days | P27: 5-10 Days | R27: 5-10 Days | S27: 5-10 Days | T27: 5-10 Days | V27: 7-14 Days | W27: 7-14 Days | X27: 7-14 Days | Z27: 7-14 Days | AA27: 7-14 Days | AB27: 7-14 Days
A28: XL | B28: 1-2 Days | C28: 1-3 Days | D28: 5-10 Days | F28: 5-10 Days | G28: 5-10 Days | H28: 5-10 Days | J28: 5-10 Days | K28: 5-10 Days | L28: 5-10 Days | N28: 5-10 Days | O28: 5-10 Days | P28: 5-10 Days | R28: 5-10 Days | S28: 5-10 Days | T28: 5-10 Days | V28: 7-14 Days | W28: 7-14 Days | X28: 7-14 Days | Z28: 7-14 Days | AA28: 7-14 Days | AB28: 7-14 Days
A29: XXL | B29: 1-2 Days | C29: 1-3 Days | D29: 5-10 Days | F29: 5-10 Days | G29: 5-10 Days | H29: 5-10 Days | J29: 5-10 Days | K29: 5-10 Days | L29: 5-10 Days | N29: 5-10 Days | O29: 5-10 Days | P29: 5-10 Days | R29: 5-10 Days | S29: 5-10 Days | T29: 5-10 Days | V29: 7-14 Days | W29: 7-14 Days | X29: 7-14 Days | Z29: 7-14 Days | AA29: 7-14 Days | AB29: 7-14 Days
A30: Bulky | B30: 1-2 Days | C30: 1-3 Days | D30: 5-10 Days | F30: 5-10 Days | G30: 5-10 Days | H30: 5-10 Days | J30: 5-10 Days | K30: 5-10 Days | L30: 5-10 Days | N30: 5-10 Days | O30: 5-10 Days | P30: 5-10 Days | R30: 5-10 Days | S30: 5-10 Days | T30: 5-10 Days | V30: 7-14 Days | W30: 7-14 Days | X30: 7-14 Days | Z30: 7-14 Days | AA30: 7-14 Days | AB30: 7-14 Days
A32: Priority | B32: From SA | F32: From VIC | J32: From WA | N32: From QLD | R32: From NSW | V32: From TAS | Z32: From ACT
A33: Freight Size | B33: Metro | C33: Metro Outer | D33: Regional | F33: Metro | G33: Metro Outer | H33: Regional | J33: Metro | K33: Metro Outer | L33: Regional | N33: Metro | O33: Metro Outer | P33: Regional | R33: Metro | S33: Metro Outer | T33: Regional | V33: Metro | W33: Metro Outer | X33: Regional | Z33: Metro | AA33: Metro Outer | AB33: Regional
A34: Small | B34: 1-3 Days | C34: 2-5 Days | D34: 3-7 Days | F34: 1-3 Days | G34: 2-5 Days | H34: 3-7 Days | J34: 1-3 Days | K34: 3-7 Days | L34: 3-7 Days | N34: 1-2 Days | O34: 1-2 Days | P34: 2-5 Days | R34: 1-2 Days | S34: 1-2 Days | T34: 2-5 Days | V34: 1-2 Days | W34: 1-2 Days | X34: 2-5 Days | Z34: 1-2 Days | AA34: 1-2 Days | AB34: 2-5 Days
A35: Medium | B35: 1-3 Days | C35: 2-5 Days | D35: 3-7 Days | F35: 1-3 Days | G35: 2-5 Days | H35: 3-7 Days | J35: 1-3 Days | K35: 3-7 Days | L35: 3-7 Days | N35: 1-2 Days | O35: 1-2 Days | P35: 2-5 Days | R35: 1-2 Days | S35: 1-2 Days | T35: 2-5 Days | V35: 1-2 Days | W35: 1-2 Days | X35: 2-5 Days | Z35: 1-2 Days | AA35: 1-2 Days | AB35: 2-5 Days
A36: Large | B36: 1-3 Days | C36: 2-5 Days | D36: 3-7 Days | F36: 1-3 Days | G36: 2-5 Days | H36: 3-7 Days | J36: 3-7 Days | K36: 3-7 Days | L36: 5-10 Days | N36: 7-14 Days | O36: 7-14 Days | P36: 7-14 Days | R36: 7-14 Days | S36: 7-14 Days | T36: 7-14 Days | V36: 7-14 Days | W36: 7-14 Days | X36: 7-14 Days | Z36: 7-14 Days | AA36: 7-14 Days | AB36: 7-14 Days
A37: XL | V37: 7-14 Days | W37: 7-14 Days | X37: 7-14 Days | Z37: 7-14 Days | AA37: 7-14 Days | AB37: 7-14 Days
A38: XXL | V38: 7-14 Days | W38: 7-14 Days | X38: 7-14 Days | Z38: 7-14 Days | AA38: 7-14 Days | AB38: 7-14 Days
A39: Bulky | V39: 7-14 Days | W39: 7-14 Days | X39: 7-14 Days | Z39: 7-14 Days | AA39: 7-14 Days | AB39: 7-14 Days

Sheet QLD
A1: Freight Charges for QLD Orders
A3: Standard | B3: From QLD | F3: From VIC | J3: From SA | N3: From NSW | R3: From TAS | V3: From ACT | Z3: From WA
A4: Freight Size | B4: Metro | C4: Metro Outer | D4: Regional | F4: Metro | G4: Metro Outer | H4: Regional | J4: Metro | K4: Metro Outer | L4: Regional | N4: Metro | O4: Metro Outer | P4: Regional | R4: Metro | S4: Metro Outer | T4: Regional | V4: Metro | W4: Metro Outer | X4: Regional | Z4: Metro | AA4: Metro Outer | AB4: Regional
A5: Small | B5: ='Cost model'!M380 -> 8.5 | C5: ='Cost model'!M381 -> 14.5 | D5: ='Cost model'!M382 -> 18.5 | F5: ='Cost model'!M398 -> 15.5 | G5: ='Cost model'!M399 -> 17.5 | H5: ='Cost model'!M400 -> 20.5 | J5: ='Cost model'!M416 -> 16.5 | K5: ='Cost model'!M417 -> 18.5 | L5: ='Cost model'!M418 -> 21.5 | N5: ='Cost model'!M434 -> 13.5 | O5: ='Cost model'!M435 -> 15.5 | P5: ='Cost model'!M436 -> 19.5 | R5: ='Cost model'!M452 -> 13.5 | S5: ='Cost model'!M453 -> 16.5 | T5: ='Cost model'!M454 -> 22.5 | V5: ='Cost model'!M470 -> 19.5 | W5: ='Cost model'!M471 -> 35 | X5: ='Cost model'!M472 -> 35 | Z5: ='Cost model'!M488 -> 14.5 | AA5: ='Cost model'!M489 -> 26.5 | AB5: ='Cost model'!M490 -> 26.5
A6: Medium | B6: ='Cost model'!M383 -> 27.5 | C6: ='Cost model'!M384 -> 45 | D6: ='Cost model'!M385 -> 55 | F6: ='Cost model'!M401 -> 60 | G6: ='Cost model'!M402 -> 60 | H6: ='Cost model'!M403 -> 75 | J6: ='Cost model'!M419 -> 55 | K6: ='Cost model'!M420 -> 60 | L6: ='Cost model'!M421 -> 70 | N6: ='Cost model'!M437 -> 50 | O6: ='Cost model'!M438 -> 55 | P6: ='Cost model'!M439 -> 60 | R6: ='Cost model'!M455 -> 60 | S6: ='Cost model'!M456 -> 60 | T6: ='Cost model'!M457 -> 105 | V6: ='Cost model'!M473 -> 65 | W6: ='Cost model'!M474 -> 65 | X6: ='Cost model'!M475 -> 75 | Z6: ='Cost model'!M491 -> 55 | AA6: ='Cost model'!M492 -> 60 | AB6: ='Cost model'!M493 -> 70
A7: Large | B7: ='Cost model'!M386 -> 55 | C7: ='Cost model'!M387 -> 95 | D7: ='Cost model'!M388 -> 110 | F7: ='Cost model'!M404 -> 120 | G7: ='Cost model'!M405 -> 120 | H7: ='Cost model'!M406 -> 140 | J7: ='Cost model'!M422 -> 100 | K7: ='Cost model'!M423 -> 105 | L7: ='Cost model'!M424 -> 140 | N7: ='Cost model'!M440 -> 90 | O7: ='Cost model'!M441 -> 95 | P7: ='Cost model'!M442 -> 140 | R7: ='Cost model'!M458 -> 85 | S7: ='Cost model'!M459 -> 105 | T7: ='Cost model'!M460 -> 140 | V7: ='Cost model'!M476 -> 110 | W7: ='Cost model'!M477 -> 120 | X7: ='Cost model'!M478 -> 155 | Z7: ='Cost model'!M494 -> 95 | AA7: ='Cost model'!M495 -> 105 | AB7: ='Cost model'!M496 -> 140
A8: XL | B8: ='Cost model'!M389 -> 95 | C8: ='Cost model'!M390 -> 115 | D8: ='Cost model'!M391 -> 170 | F8: ='Cost model'!M407 -> 155 | G8: ='Cost model'!M408 -> 180 | H8: ='Cost model'!M409 -> 225 | J8: ='Cost model'!M425 -> 160 | K8: ='Cost model'!M426 -> 220 | L8: ='Cost model'!M427 -> 235 | N8: ='Cost model'!M443 -> 155 | O8: ='Cost model'!M444 -> 185 | P8: ='Cost model'!M445 -> 250 | R8: ='Cost model'!M461 -> 160 | S8: ='Cost model'!M462 -> 190 | T8: ='Cost model'!M463 -> 250 | V8: ='Cost model'!M479 -> 190 | W8: ='Cost model'!M480 -> 220 | X8: ='Cost model'!M481 -> 265 | Z8: ='Cost model'!M497 -> 160 | AA8: ='Cost model'!M498 -> 190 | AB8: ='Cost model'!M499 -> 230
A9: XXL | B9: ='Cost model'!M392 -> 115 | C9: ='Cost model'!M393 -> 160 | D9: ='Cost model'!M394 -> 235 | F9: ='Cost model'!M410 -> 195 | G9: ='Cost model'!M411 -> 310 | H9: ='Cost model'!M412 -> 350 | J9: ='Cost model'!M428 -> 205 | K9: ='Cost model'!M429 -> 300 | L9: ='Cost model'!M430 -> 370 | N9: ='Cost model'!M446 -> 185 | O9: ='Cost model'!M447 -> 280 | P9: ='Cost model'!M448 -> 330 | R9: ='Cost model'!M464 -> 200 | S9: ='Cost model'!M465 -> 295 | T9: ='Cost model'!M466 -> 355 | V9: ='Cost model'!M482 -> 235 | W9: ='Cost model'!M483 -> 350 | X9: ='Cost model'!M484 -> 415 | Z9: ='Cost model'!M500 -> 200 | AA9: ='Cost model'!M501 -> 300 | AB9: ='Cost model'!M502 -> 360
A10: Bulky | B10: ='Cost model'!M395 -> 120 | C10: ='Cost model'!M396 -> 245 | D10: ='Cost model'!M397 -> 295 | F10: ='Cost model'!M413 -> 270 | G10: ='Cost model'!M414 -> 415 | H10: ='Cost model'!M415 -> 490 | J10: ='Cost model'!M431 -> 285 | K10: ='Cost model'!M432 -> 435 | L10: ='Cost model'!M433 -> 510 | N10: ='Cost model'!M449 -> 255 | O10: ='Cost model'!M450 -> 400 | P10: ='Cost model'!M451 -> 465 | R10: ='Cost model'!M467 -> 275 | S10: ='Cost model'!M468 -> 430 | T10: ='Cost model'!M469 -> 500 | V10: ='Cost model'!M485 -> 325 | W10: ='Cost model'!M486 -> 490 | X10: ='Cost model'!M487 -> 590 | Z10: ='Cost model'!M503 -> 280 | AA10: ='Cost model'!M504 -> 435 | AB10: ='Cost model'!M505 -> 505
A12: Priority | B12: From QLD | F12: From VIC | J12: From SA | N12: From NSW | R12: From TAS | V12: From ACT | Z12: From WA
A13: Freight Size | B13: Metro | C13: Metro Outer | D13: Regional | F13: Metro | G13: Metro Outer | H13: Regional | J13: Metro | K13: Metro Outer | L13: Regional | N13: Metro | O13: Metro Outer | P13: Regional | R13: Metro | S13: Metro Outer | T13: Regional | V13: Metro | W13: Metro Outer | X13: Regional | Z13: Metro | AA13: Metro Outer | AB13: Regional
A14: Small | B14: ='Cost model'!N380 -> 13.5 | C14: ='Cost model'!N381 -> 19.5 | D14: ='Cost model'!N382 -> 25.5 | F14: ='Cost model'!N398 -> 21.5 | G14: ='Cost model'!N399 -> 23.5 | H14: ='Cost model'!N400 -> 27.5 | J14: ='Cost model'!N416 -> 22.5 | K14: ='Cost model'!N417 -> 25.5 | L14: ='Cost model'!N418 -> 29.5 | N14: ='Cost model'!N434 -> 18.5 | O14: ='Cost model'!N435 -> 21.5 | P14: ='Cost model'!N436 -> 26.5 | R14: ='Cost model'!N452 -> 18.5 | S14: ='Cost model'!N453 -> 22.5 | T14: ='Cost model'!N454 -> 35 | V14: ='Cost model'!N470 -> 26.5 | W14: ='Cost model'!N471 -> 50 | X14: ='Cost model'!N472 -> 50 | Z14: ='Cost model'!N488 -> 19.5 | AA14: ='Cost model'!N489 -> 40 | AB14: ='Cost model'!N490 -> 40
A15: Medium | B15: ='Cost model'!N383 -> 35 | C15: ='Cost model'!N384 -> 60 | D15: ='Cost model'!N385 -> 70 | F15: ='Cost model'!N401 -> 80 | G15: ='Cost model'!N402 -> 80 | H15: ='Cost model'!N403 -> 95 | J15: ='Cost model'!N419 -> 70 | K15: ='Cost model'!N420 -> 80 | L15: ='Cost model'!N421 -> 90 | N15: ='Cost model'!N437 -> 65 | O15: ='Cost model'!N438 -> 70 | P15: ='Cost model'!N439 -> 80 | R15: ='Cost model'!N455 -> 80 | S15: ='Cost model'!N456 -> 80 | T15: ='Cost model'!N457 -> 135 | V15: ='Cost model'!N473 -> 85 | W15: ='Cost model'!N474 -> 85 | X15: ='Cost model'!N475 -> 95 | Z15: ='Cost model'!N491 -> 70 | AA15: ='Cost model'!N492 -> 80 | AB15: ='Cost model'!N493 -> 90
A16: Large | B16: ='Cost model'!N386 -> 75 | C16: ='Cost model'!N387 -> 130 | D16: ='Cost model'!N388 -> 150 | F16: ='Cost model'!N404 -> 165 | G16: ='Cost model'!N405 -> 165 | H16: ='Cost model'!N406 -> 190 | J16: ='Cost model'!N422 -> 135 | K16: ='Cost model'!N423 -> 145 | L16: ='Cost model'!N424 -> 190 | N16: ='Cost model'!N440 -> 125 | O16: ='Cost model'!N441 -> 130 | P16: ='Cost model'!N442 -> 190 | R16: ='Cost model'!N458 -> 115 | S16: ='Cost model'!N459 -> 145 | T16: ='Cost model'!N460 -> 190 | V16: ='Cost model'!N476 -> 150 | W16: ='Cost model'!N477 -> 165 | X16: ='Cost model'!N478 -> 210 | Z16: ='Cost model'!N494 -> 130 | AA16: ='Cost model'!N495 -> 145 | AB16: ='Cost model'!N496 -> 190
A17: XL | B17: ='Cost model'!N389 -> 115 | C17: ='Cost model'!N390 -> 140 | D17: ='Cost model'!N391 -> 205 | F17: ='Cost model'!N407 -> 190 | G17: ='Cost model'!N408 -> 220 | H17: ='Cost model'!N409 -> 270 | J17: ='Cost model'!N425 -> 195 | K17: ='Cost model'!N426 -> 265 | L17: ='Cost model'!N427 -> 285 | N17: ='Cost model'!N443 -> 190 | O17: ='Cost model'!N444 -> 225 | P17: ='Cost model'!N445 -> 300 | R17: ='Cost model'!N461 -> 195 | S17: ='Cost model'!N462 -> 230 | T17: ='Cost model'!N463 -> 300 | V17: ='Cost model'!N479 -> 230 | W17: ='Cost model'!N480 -> 265 | X17: ='Cost model'!N481 -> 320 | Z17: ='Cost model'!N497 -> 195 | AA17: ='Cost model'!N498 -> 230 | AB17: ='Cost model'!N499 -> 280
A18: XXL | B18: ='Cost model'!N392 -> 140 | C18: ='Cost model'!N393 -> 195 | D18: ='Cost model'!N394 -> 285 | F18: ='Cost model'!N410 -> 235 | G18: ='Cost model'!N411 -> 310 | H18: ='Cost model'!N412 -> 350 | J18: ='Cost model'!N428 -> 250 | K18: ='Cost model'!N429 -> 300 | L18: ='Cost model'!N430 -> 370 | N18: ='Cost model'!N446 -> 225 | O18: ='Cost model'!N447 -> 280 | P18: ='Cost model'!N448 -> 330 | R18: ='Cost model'!N464 -> 240 | S18: ='Cost model'!N465 -> 295 | T18: ='Cost model'!N466 -> 355 | V18: ='Cost model'!N482 -> 285 | W18: ='Cost model'!N483 -> 350 | X18: ='Cost model'!N484 -> 415 | Z18: ='Cost model'!N500 -> 240 | AA18: ='Cost model'!N501 -> 300 | AB18: ='Cost model'!N502 -> 360
A19: Bulky | B19: ='Cost model'!N395 -> 145 | C19: ='Cost model'!N396 -> 295 | D19: ='Cost model'!N397 -> 355 | F19: ='Cost model'!N413 -> 325 | G19: ='Cost model'!N414 -> 415 | H19: ='Cost model'!N415 -> 490 | J19: ='Cost model'!N431 -> 345 | K19: ='Cost model'!N432 -> 435 | L19: ='Cost model'!N433 -> 510 | N19: ='Cost model'!N449 -> 310 | O19: ='Cost model'!N450 -> 400 | P19: ='Cost model'!N451 -> 465 | R19: ='Cost model'!N467 -> 330 | S19: ='Cost model'!N468 -> 430 | T19: ='Cost model'!N469 -> 500 | V19: ='Cost model'!N485 -> 390 | W19: ='Cost model'!N486 -> 490 | X19: ='Cost model'!N487 -> 590 | Z19: ='Cost model'!N503 -> 340 | AA19: ='Cost model'!N504 -> 435 | AB19: ='Cost model'!N505 -> 505
A21: Delivery time frames for QLD Orders
A23: Standard | B23: From QLD | F23: From VIC | J23: From SA | N23: From NSW | R23: From TAS | V23: From ACT | Z23: From WA
A24: Freight Size | B24: Metro | C24: Metro Outer | D24: Regional | F24: Metro | G24: Metro Outer | H24: Regional | J24: Metro | K24: Metro Outer | L24: Regional | N24: Metro | O24: Metro Outer | P24: Regional | R24: Metro | S24: Metro Outer | T24: Regional | V24: Metro | W24: Metro Outer | X24: Regional | Z24: Metro | AA24: Metro Outer | AB24: Regional
A25: Small | B25: 1-3 Days | C25: 1-3 Days | D25: 2-5 Days | F25: 2-5 Days | G25: 2-5 Days | H25: 3-7 Days | J25: 2-5 Days | K25: 2-5 Days | L25: 2-5 Days | N25: 2-5 Days | O25: 2-5 Days | P25: 3-7 Days | R25: 7-14 Days | S25: 7-14 Days | T25: 7-14 Days | V25: 7-14 Days | W25: 7-14 Days | X25: 7-14 Days | Z25: 7-14 Days | AA25: 7-14 Days | AB25: 7-14 Days
A26: Medium | B26: 1-3 Days | C26: 1-3 Days | D26: 2-5 Days | F26: 2-5 Days | G26: 2-5 Days | H26: 3-7 Days | J26: 2-5 Days | K26: 2-5 Days | L26: 2-5 Days | N26: 2-5 Days | O26: 2-5 Days | P26: 3-7 Days | R26: 7-14 Days | S26: 7-14 Days | T26: 7-14 Days | V26: 7-14 Days | W26: 7-14 Days | X26: 7-14 Days | Z26: 7-14 Days | AA26: 7-14 Days | AB26: 7-14 Days
A27: Large | B27: 1-3 Days | C27: 1-3 Days | D27: 3-7 Days | F27: 3-7 Days | G27: 3-7 Days | H27: 5-10 Days | J27: 3-7 Days | K27: 3-7 Days | L27: 5-10 Days | N27: 3-7 Days | O27: 3-7 Days | P27: 5-10 Days | R27: 7-14 Days | S27: 7-14 Days | T27: 7-14 Days | V27: 7-14 Days | W27: 7-14 Days | X27: 7-14 Days | Z27: 7-14 Days | AA27: 7-14 Days | AB27: 7-14 Days
A28: XL | B28: 1-3 Days | C28: 1-3 Days | D28: 5-10 Days | F28: 5-10 Days | G28: 5-10 Days | H28: 5-10 Days | J28: 5-10 Days | K28: 5-10 Days | L28: 5-10 Days | N28: 5-10 Days | O28: 5-10 Days | P28: 5-10 Days | R28: 7-14 Days | S28: 7-14 Days | T28: 7-14 Days | V28: 7-14 Days | W28: 7-14 Days | X28: 7-14 Days | Z28: 7-14 Days | AA28: 7-14 Days | AB28: 7-14 Days
A29: XXL | B29: 1-3 Days | C29: 1-3 Days | D29: 5-10 Days | F29: 5-10 Days | G29: 5-10 Days | H29: 5-10 Days | J29: 5-10 Days | K29: 5-10 Days | L29: 5-10 Days | N29: 5-10 Days | O29: 5-10 Days | P29: 5-10 Days | R29: 7-14 Days | S29: 7-14 Days | T29: 7-14 Days | V29: 7-14 Days | W29: 7-14 Days | X29: 7-14 Days | Z29: 7-14 Days | AA29: 7-14 Days | AB29: 7-14 Days
A30: Bulky | B30: 1-3 Days | C30: 1-3 Days | D30: 5-10 Days | F30: 5-10 Days | G30: 5-10 Days | H30: 5-10 Days | J30: 5-10 Days | K30: 5-10 Days | L30: 5-10 Days | N30: 5-10 Days | O30: 5-10 Days | P30: 5-10 Days | R30: 7-14 Days | S30: 7-14 Days | T30: 7-14 Days | V30: 7-14 Days | W30: 7-14 Days | X30: 7-14 Days | Z30: 7-14 Days | AA30: 7-14 Days | AB30: 7-14 Days
A32: Priority | B32: From QLD | F32: From VIC | J32: From SA | N32: From NSW | R32: From TAS | V32: From ACT | Z32: From WA
A33: Freight Size | B33: Metro | C33: Metro Outer | D33: Regional | F33: Metro | G33: Metro Outer | H33: Regional | J33: Metro | K33: Metro Outer | L33: Regional | N33: Metro | O33: Metro Outer | P33: Regional | R33: Metro | S33: Metro Outer | T33: Regional | V33: Metro | W33: Metro Outer | X33: Regional | Z33: Metro | AA33: Metro Outer | AB33: Regional
A34: Small | B34: 1-2 Days | C34: 1-2 Days | D34: 1-3 Days | F34: 1-2 Days | G34: 1-2 Days | H34: 2-5 Days | J34: 1-2 Days | K34: 1-2 Days | L34: 2-5 Days | N34: 1-2 Days | O34: 1-2 Days | P34: 2-5 Days | R34: 1-2 Days | S34: 1-2 Days | T34: 2-5 Days | V34: 1-2 Days | W34: 1-2 Days | X34: 2-5 Days | Z34: 1-2 Days | AA34: 1-2 Days | AB34: 2-5 Days
A35: Medium | B35: 1-2 Days | C35: 1-2 Days | D35: 1-3 Days | F35: 1-2 Days | G35: 1-2 Days | H35: 2-5 Days | J35: 1-2 Days | K35: 1-2 Days | L35: 2-5 Days | N35: 1-2 Days | O35: 1-2 Days | P35: 2-5 Days | R35: 1-2 Days | S35: 1-2 Days | T35: 2-5 Days | V35: 1-2 Days | W35: 1-2 Days | X35: 2-5 Days | Z35: 1-2 Days | AA35: 1-2 Days | AB35: 2-5 Days
A36: Large | B36: 1-2 Days | C36: 1-2 Days | D36: 2-7 Days | F36: 2-5 Days | G36: 2-5 Days | H36: 5-10 Days | J36: 2-5 Days | K36: 2-5 Days | L36: 5-10 Days | N36: 2-5 Days | O36: 2-5 Days | P36: 5-10 Days | R36: 7-14 Days | S36: 7-14 Days | T36: 7-14 Days | V36: 7-14 Days | W36: 7-14 Days | X36: 7-14 Days | Z36: 7-14 Days | AA36: 7-14 Days | AB36: 7-14 Days
A37: XL | B37: 1-2 Days | C37: 1-2 Days | D37: 2-7 Days | F37: 3-7 Days | G37: 3-7 Days | H37: 5-10 Days | J37: 3-7 Days | K37: 3-7 Days | L37: 5-10 Days | N37: 3-7 Days | O37: 3-7 Days | P37: 5-10 Days | R37: 7-14 Days | S37: 7-14 Days | T37: 7-14 Days | V37: 7-14 Days | W37: 7-14 Days | X37: 7-14 Days | Z37: 7-14 Days | AA37: 7-14 Days | AB37: 7-14 Days
A38: XXL | B38: 1-2 Days | C38: 1-2 Days | D38: 2-7 Days | F38: 3-7 Days | G38: 3-7 Days | H38: 5-10 Days | J38: 3-7 Days | K38: 3-7 Days | L38: 5-10 Days | N38: 3-7 Days | O38: 3-7 Days | P38: 5-10 Days | R38: 7-14 Days | S38: 7-14 Days | T38: 7-14 Days | V38: 7-14 Days | W38: 7-14 Days | X38: 7-14 Days | Z38: 7-14 Days | AA38: 7-14 Days | AB38: 7-14 Days
A39: Bulky | B39: 1-2 Days | C39: 1-2 Days | D39: 2-7 Days | F39: 3-7 Days | G39: 3-7 Days | H39: 5-10 Days | J39: 3-7 Days | K39: 3-7 Days | L39: 5-10 Days | N39: 3-7 Days | O39: 3-7 Days | P39: 5-10 Days | R39: 7-14 Days | S39: 7-14 Days | T39: 7-14 Days | V39: 7-14 Days | W39: 7-14 Days | X39: 7-14 Days | Z39: 7-14 Days | AA39: 7-14 Days | AB39: 7-14 Days

Sheet SA
A1: Freight Charges for SA Orders
A3: Standard | B3: From SA | F3: From VIC | J3: From QLD | N3: From WA | R3: From NSW | V3: From TAS | Z3: From ACT
A4: Freight Size | B4: Metro | C4: Metro Outer | D4: Regional | F4: Metro | G4: Metro Outer | H4: Regional | J4: Metro | K4: Metro Outer | L4: Regional | N4: Metro | O4: Metro Outer | P4: Regional | R4: Metro | S4: Metro Outer | T4: Regional | V4: Metro | W4: Metro Outer | X4: Regional | Z4: Metro | AA4: Metro Outer | AB4: Regional
A5: Small | B5: ='Cost model'!M506 -> 7.5 | C5: ='Cost model'!M507 -> 11.5 | D5: ='Cost model'!M508 -> 17.5 | F5: ='Cost model'!M524 -> 14.5 | G5: ='Cost model'!M525 -> 15.5 | H5: ='Cost model'!M526 -> 20.5 | J5: ='Cost model'!M542 -> 14.5 | K5: ='Cost model'!M543 -> 15.5 | L5: ='Cost model'!M544 -> 21.5 | N5: ='Cost model'!M560 -> 13.5 | O5: ='Cost model'!M561 -> 16.5 | P5: ='Cost model'!M562 -> 23.5 | R5: ='Cost model'!M578 -> 10.5 | S5: ='Cost model'!M579 -> 14.5 | T5: ='Cost model'!M580 -> 18.5 | V5: ='Cost model'!M596 -> 15.5 | W5: ='Cost model'!M597 -> 17.5 | X5: ='Cost model'!M598 -> 23.5 | Z5: ='Cost model'!M614 -> 12.5 | AA5: ='Cost model'!M615 -> 14.5 | AB5: ='Cost model'!M616 -> 19.5
A6: Medium | B6: ='Cost model'!M509 -> 17.5 | C6: ='Cost model'!M510 -> 35 | D6: ='Cost model'!M511 -> 35 | F6: ='Cost model'!M527 -> 55 | G6: ='Cost model'!M528 -> 55 | H6: ='Cost model'!M529 -> 65 | J6: ='Cost model'!M545 -> 50 | K6: ='Cost model'!M546 -> 55 | L6: ='Cost model'!M547 -> 60 | N6: ='Cost model'!M563 -> 55 | O6: ='Cost model'!M564 -> 55 | P6: ='Cost model'!M565 -> 65 | R6: ='Cost model'!M581 -> 45 | S6: ='Cost model'!M582 -> 50 | T6: ='Cost model'!M583 -> 55 | V6: ='Cost model'!M599 -> 60 | W6: ='Cost model'!M600 -> 60 | X6: ='Cost model'!M601 -> 70 | Z6: ='Cost model'!M617 -> 45 | AA6: ='Cost model'!M618 -> 50 | AB6: ='Cost model'!M619 -> 60
A7: Large | B7: ='Cost model'!M512 -> 35 | C7: ='Cost model'!M513 -> 65 | D7: ='Cost model'!M514 -> 70 | F7: ='Cost model'!M530 -> 80 | G7: ='Cost model'!M531 -> 90 | H7: ='Cost model'!M532 -> 120 | J7: ='Cost model'!M548 -> 80 | K7: ='Cost model'!M549 -> 95 | L7: ='Cost model'!M550 -> 125 | N7: ='Cost model'!M566 -> 90 | O7: ='Cost model'!M567 -> 100 | P7: ='Cost model'!M568 -> 130 | R7: ='Cost model'!M584 -> 75 | S7: ='Cost model'!M585 -> 85 | T7: ='Cost model'!M586 -> 115 | V7: ='Cost model'!M602 -> 95 | W7: ='Cost model'!M603 -> 110 | X7: ='Cost model'!M604 -> 145 | Z7: ='Cost model'!M620 -> 80 | AA7: ='Cost model'!M621 -> 90 | AB7: ='Cost model'!M622 -> 120
A8: XL | B8: ='Cost model'!M515 -> 75 | C8: ='Cost model'!M516 -> 105 | D8: ='Cost model'!M517 -> 140 | F8: ='Cost model'!M533 -> 135 | G8: ='Cost model'!M534 -> 170 | H8: ='Cost model'!M535 -> 200 | J8: ='Cost model'!M551 -> 140 | K8: ='Cost model'!M552 -> 170 | L8: ='Cost model'!M553 -> 205 | N8: ='Cost model'!M569 -> 150 | O8: ='Cost model'!M570 -> 180 | P8: ='Cost model'!M571 -> 215 | R8: ='Cost model'!M587 -> 130 | S8: ='Cost model'!M588 -> 155 | T8: ='Cost model'!M589 -> 190 | V8: ='Cost model'!M605 -> 180 | W8: ='Cost model'!M606 -> 195 | X8: ='Cost model'!M607 -> 235 | Z8: ='Cost model'!M623 -> 135 | AA8: ='Cost model'!M624 -> 165 | AB8: ='Cost model'!M625 -> 195
A9: XXL | B9: ='Cost model'!M518 -> 95 | C9: ='Cost model'!M519 -> 135 | D9: ='Cost model'!M520 -> 200 | F9: ='Cost model'!M536 -> 175 | G9: ='Cost model'!M537 -> 265 | H9: ='Cost model'!M538 -> 315 | J9: ='Cost model'!M554 -> 180 | K9: ='Cost model'!M555 -> 265 | L9: ='Cost model'!M556 -> 320 | N9: ='Cost model'!M572 -> 190 | O9: ='Cost model'!M573 -> 285 | P9: ='Cost model'!M574 -> 340 | R9: ='Cost model'!M590 -> 165 | S9: ='Cost model'!M591 -> 250 | T9: ='Cost model'!M592 -> 295 | V9: ='Cost model'!M608 -> 210 | W9: ='Cost model'!M609 -> 310 | X9: ='Cost model'!M610 -> 375 | Z9: ='Cost model'!M626 -> 170 | AA9: ='Cost model'!M627 -> 255 | AB9: ='Cost model'!M628 -> 310
A10: Bulky | B10: ='Cost model'!M521 -> 105 | C10: ='Cost model'!M522 -> 185 | D10: ='Cost model'!M523 -> 250 | F10: ='Cost model'!M539 -> 240 | G10: ='Cost model'!M540 -> 380 | H10: ='Cost model'!M541 -> 445 | J10: ='Cost model'!M557 -> 260 | K10: ='Cost model'!M558 -> 385 | L10: ='Cost model'!M559 -> 450 | N10: ='Cost model'!M575 -> 260 | O10: ='Cost model'!M576 -> 405 | P10: ='Cost model'!M577 -> 475 | R10: ='Cost model'!M593 -> 230 | S10: ='Cost model'!M594 -> 355 | T10: ='Cost model'!M595 -> 415 | V10: ='Cost model'!M611 -> 290 | W10: ='Cost model'!M612 -> 445 | X10: ='Cost model'!M613 -> 525 | Z10: ='Cost model'!M629 -> 240 | AA10: ='Cost model'!M630 -> 370 | AB10: ='Cost model'!M631 -> 435
A12: Priority | B12: From SA | F12: From VIC | J12: From QLD | N12: From WA | R12: From NSW | V12: From TAS | Z12: From ACT
A13: Freight Size | B13: Metro | C13: Metro Outer | D13: Regional | F13: Metro | G13: Metro Outer | H13: Regional | J13: Metro | K13: Metro Outer | L13: Regional | N13: Metro | O13: Metro Outer | P13: Regional | R13: Metro | S13: Metro Outer | T13: Regional | V13: Metro | W13: Metro Outer | X13: Regional | Z13: Metro | AA13: Metro Outer | AB13: Regional
A14: Small | B14: ='Cost model'!N506 -> 12.5 | C14: ='Cost model'!N507 -> 16.5 | D14: ='Cost model'!N508 -> 23.5 | F14: ='Cost model'!N524 -> 19.5 | G14: ='Cost model'!N525 -> 21.5 | H14: ='Cost model'!N526 -> 27.5 | J14: ='Cost model'!N542 -> 19.5 | K14: ='Cost model'!N543 -> 21.5 | L14: ='Cost model'!N544 -> 29.5 | N14: ='Cost model'!N560 -> 18.5 | O14: ='Cost model'!N561 -> 22.5 | P14: ='Cost model'!N562 -> 35 | R14: ='Cost model'!N578 -> 15.5 | S14: ='Cost model'!N579 -> 19.5 | T14: ='Cost model'!N580 -> 25.5 | V14: ='Cost model'!N596 -> 21.5 | W14: ='Cost model'!N597 -> 23.5 | X14: ='Cost model'!N598 -> 35 | Z14: ='Cost model'!N614 -> 17.5 | AA14: ='Cost model'!N615 -> 19.5 | AB14: ='Cost model'!N616 -> 26.5
A15: Medium | B15: ='Cost model'!N509 -> 22.5 | C15: ='Cost model'!N510 -> 45 | D15: ='Cost model'!N511 -> 45 | F15: ='Cost model'!N527 -> 70 | G15: ='Cost model'!N528 -> 70 | H15: ='Cost model'!N529 -> 85 | J15: ='Cost model'!N545 -> 65 | K15: ='Cost model'!N546 -> 70 | L15: ='Cost model'!N547 -> 80 | N15: ='Cost model'!N563 -> 70 | O15: ='Cost model'!N564 -> 70 | P15: ='Cost model'!N565 -> 85 | R15: ='Cost model'!N581 -> 60 | S15: ='Cost model'!N582 -> 65 | T15: ='Cost model'!N583 -> 70 | V15: ='Cost model'!N599 -> 80 | W15: ='Cost model'!N600 -> 80 | X15: ='Cost model'!N601 -> 90 | Z15: ='Cost model'!N617 -> 60 | AA15: ='Cost model'!N618 -> 65 | AB15: ='Cost model'!N619 -> 80
A16: Large | B16: ='Cost model'!N512 -> 50 | C16: ='Cost model'!N513 -> 90 | D16: ='Cost model'!N514 -> 95 | F16: ='Cost model'!N530 -> 110 | G16: ='Cost model'!N531 -> 125 | H16: ='Cost model'!N532 -> 165 | J16: ='Cost model'!N548 -> 110 | K16: ='Cost model'!N549 -> 130 | L16: ='Cost model'!N550 -> 170 | N16: ='Cost model'!N566 -> 125 | O16: ='Cost model'!N567 -> 135 | P16: ='Cost model'!N568 -> 180 | R16: ='Cost model'!N584 -> 105 | S16: ='Cost model'!N585 -> 115 | T16: ='Cost model'!N586 -> 160 | V16: ='Cost model'!N602 -> 130 | W16: ='Cost model'!N603 -> 150 | X16: ='Cost model'!N604 -> 200 | Z16: ='Cost model'!N620 -> 110 | AA16: ='Cost model'!N621 -> 125 | AB16: ='Cost model'!N622 -> 165
A17: XL | B17: ='Cost model'!N515 -> 90 | C17: ='Cost model'!N516 -> 130 | D17: ='Cost model'!N517 -> 170 | F17: ='Cost model'!N533 -> 165 | G17: ='Cost model'!N534 -> 205 | H17: ='Cost model'!N535 -> 240 | J17: ='Cost model'!N551 -> 170 | K17: ='Cost model'!N552 -> 205 | L17: ='Cost model'!N553 -> 250 | N17: ='Cost model'!N569 -> 180 | O17: ='Cost model'!N570 -> 220 | P17: ='Cost model'!N571 -> 260 | R17: ='Cost model'!N587 -> 160 | S17: ='Cost model'!N588 -> 190 | T17: ='Cost model'!N589 -> 230 | V17: ='Cost model'!N605 -> 220 | W17: ='Cost model'!N606 -> 235 | X17: ='Cost model'!N607 -> 285 | Z17: ='Cost model'!N623 -> 165 | AA17: ='Cost model'!N624 -> 200 | AB17: ='Cost model'!N625 -> 235
A18: XXL | B18: ='Cost model'!N518 -> 115 | C18: ='Cost model'!N519 -> 165 | D18: ='Cost model'!N520 -> 240 | F18: ='Cost model'!N536 -> 210 | G18: ='Cost model'!N537 -> 265 | H18: ='Cost model'!N538 -> 315 | J18: ='Cost model'!N554 -> 220 | K18: ='Cost model'!N555 -> 265 | L18: ='Cost model'!N556 -> 320 | N18: ='Cost model'!N572 -> 230 | O18: ='Cost model'!N573 -> 285 | P18: ='Cost model'!N574 -> 340 | R18: ='Cost model'!N590 -> 200 | S18: ='Cost model'!N591 -> 250 | T18: ='Cost model'!N592 -> 295 | V18: ='Cost model'!N608 -> 255 | W18: ='Cost model'!N609 -> 310 | X18: ='Cost model'!N610 -> 375 | Z18: ='Cost model'!N626 -> 205 | AA18: ='Cost model'!N627 -> 255 | AB18: ='Cost model'!N628 -> 310
A19: Bulky | B19: ='Cost model'!N521 -> 130 | C19: ='Cost model'!N522 -> 225 | D19: ='Cost model'!N523 -> 300 | F19: ='Cost model'!N539 -> 290 | G19: ='Cost model'!N540 -> 380 | H19: ='Cost model'!N541 -> 445 | J19: ='Cost model'!N557 -> 315 | K19: ='Cost model'!N558 -> 385 | L19: ='Cost model'!N559 -> 450 | N19: ='Cost model'!N575 -> 315 | O19: ='Cost model'!N576 -> 405 | P19: ='Cost model'!N577 -> 475 | R19: ='Cost model'!N593 -> 280 | S19: ='Cost model'!N594 -> 355 | T19: ='Cost model'!N595 -> 415 | V19: ='Cost model'!N611 -> 350 | W19: ='Cost model'!N612 -> 445 | X19: ='Cost model'!N613 -> 525 | Z19: ='Cost model'!N629 -> 290 | AA19: ='Cost model'!N630 -> 370 | AB19: ='Cost model'!N631 -> 435
A21: Delivery time frames for SA Orders
A23: Standard | B23: From SA | F23: From VIC | J23: From QLD | N23: From WA | R23: From NSW | V23: From TAS | Z23: From ACT
A24: Freight Size | B24: Metro | C24: Metro Outer | D24: Regional | F24: Metro | G24: Metro Outer | H24: Regional | J24: Metro | K24: Metro Outer | L24: Regional | N24: Metro | O24: Metro Outer | P24: Regional | R24: Metro | S24: Metro Outer | T24: Regional | V24: Metro | W24: Metro Outer | X24: Regional | Z24: Metro | AA24: Metro Outer | AB24: Regional
A25: Small | B25: 1-3 Days | C25: 1-3 Days | D25: 2-5 Days | F25: 2-5 Days | G25: 2-5 Days | H25: 3-7 Days | J25: 2-5 Days | K25: 2-5 Days | L25: 2-5 Days | N25: 7-14 Days | O25: 7-14 Days | P25: 7-14 Days | R25: 2-5 Days | S25: 2-5 Days | T25: 3-7 Days | V25: 7-14 Days | W25: 7-14 Days | X25: 7-14 Days | Z25: 7-14 Days | AA25: 7-14 Days | AB25: 7-14 Days
A26: Medium | B26: 1-3 Days | C26: 1-3 Days | D26: 2-5 Days | F26: 2-5 Days | G26: 2-5 Days | H26: 3-7 Days | J26: 2-5 Days | K26: 2-5 Days | L26: 2-5 Days | N26: 7-14 Days | O26: 7-14 Days | P26: 7-14 Days | R26: 2-5 Days | S26: 2-5 Days | T26: 3-7 Days | V26: 7-14 Days | W26: 7-14 Days | X26: 7-14 Days | Z26: 7-14 Days | AA26: 7-14 Days | AB26: 7-14 Days
A27: Large | B27: 1-3 Days | C27: 1-3 Days | D27: 3-7 Days | F27: 3-7 Days | G27: 3-7 Days | H27: 5-10 Days | J27: 3-7 Days | K27: 3-7 Days | L27: 5-10 Days | N27: 7-14 Days | O27: 7-14 Days | P27: 7-14 Days | R27: 3-7 Days | S27: 3-7 Days | T27: 5-10 Days | V27: 7-14 Days | W27: 7-14 Days | X27: 7-14 Days | Z27: 7-14 Days | AA27: 7-14 Days | AB27: 7-14 Days
A28: XL | B28: 1-3 Days | C28: 1-3 Days | D28: 5-10 Days | F28: 5-10 Days | G28: 5-10 Days | H28: 5-10 Days | J28: 5-10 Days | K28: 5-10 Days | L28: 5-10 Days | N28: 7-14 Days | O28: 7-14 Days | P28: 7-14 Days | R28: 5-10 Days | S28: 5-10 Days | T28: 5-10 Days | V28: 7-14 Days | W28: 7-14 Days | X28: 7-14 Days | Z28: 7-14 Days | AA28: 7-14 Days | AB28: 7-14 Days
A29: XXL | B29: 1-3 Days | C29: 1-3 Days | D29: 5-10 Days | F29: 5-10 Days | G29: 5-10 Days | H29: 5-10 Days | J29: 5-10 Days | K29: 5-10 Days | L29: 5-10 Days | N29: 7-14 Days | O29: 7-14 Days | P29: 7-14 Days | R29: 5-10 Days | S29: 5-10 Days | T29: 5-10 Days | V29: 7-14 Days | W29: 7-14 Days | X29: 7-14 Days | Z29: 7-14 Days | AA29: 7-14 Days | AB29: 7-14 Days
A30: Bulky | B30: 1-3 Days | C30: 1-3 Days | D30: 5-10 Days | F30: 5-10 Days | G30: 5-10 Days | H30: 5-10 Days | J30: 5-10 Days | K30: 5-10 Days | L30: 5-10 Days | N30: 7-14 Days | O30: 7-14 Days | P30: 7-14 Days | R30: 5-10 Days | S30: 5-10 Days | T30: 5-10 Days | V30: 7-14 Days | W30: 7-14 Days | X30: 7-14 Days | Z30: 7-14 Days | AA30: 7-14 Days | AB30: 7-14 Days
A32: Priority | B32: From SA | F32: From VIC | J32: From QLD | N32: From WA | R32: From NSW | V32: From TAS | Z32: From ACT
A33: Freight Size | B33: Metro | C33: Metro Outer | D33: Regional | F33: Metro | G33: Metro Outer | H33: Regional | J33: Metro | K33: Metro Outer | L33: Regional | N33: Metro | O33: Metro Outer | P33: Regional | R33: Metro | S33: Metro Outer | T33: Regional | V33: Metro | W33: Metro Outer | X33: Regional | Z33: Metro | AA33: Metro Outer | AB33: Regional
A34: Small | B34: 1-2 Days | C34: 1-2 Days | D34: 1-3 Days | F34: 1-2 Days | G34: 1-2 Days | H34: 2-5 Days | J34: 1-2 Days | K34: 1-2 Days | L34: 2-5 Days | N34: 1-2 Days | O34: 1-2 Days | P34: 2-5 Days | R34: 1-2 Days | S34: 1-2 Days | T34: 2-5 Days | V34: 1-2 Days | W34: 1-2 Days | X34: 2-5 Days | Z34: 1-2 Days | AA34: 1-2 Days | AB34: 2-5 Days
A35: Medium | B35: 1-2 Days | C35: 1-2 Days | D35: 1-3 Days | F35: 1-2 Days | G35: 1-2 Days | H35: 2-5 Days | J35: 1-2 Days | K35: 1-2 Days | L35: 2-5 Days | N35: 1-2 Days | O35: 1-2 Days | P35: 2-5 Days | R35: 1-2 Days | S35: 1-2 Days | T35: 2-5 Days | V35: 1-2 Days | W35: 1-2 Days | X35: 2-5 Days | Z35: 1-2 Days | AA35: 1-2 Days | AB35: 2-5 Days
A36: Large | B36: 1-2 Days | C36: 1-2 Days | D36: 2-7 Days | F36: 2-5 Days | G36: 2-5 Days | H36: 5-10 Days | J36: 2-5 Days | K36: 2-5 Days | L36: 5-10 Days | N36: 7-14 Days | O36: 7-14 Days | P36: 7-14 Days | R36: 2-5 Days | S36: 2-5 Days | T36: 5-10 Days | V36: 7-14 Days | W36: 7-14 Days | X36: 7-14 Days | Z36: 7-14 Days | AA36: 7-14 Days | AB36: 7-14 Days
A37: XL | B37: 1-2 Days | C37: 1-2 Days | D37: 2-7 Days | F37: 3-7 Days | G37: 3-7 Days | H37: 5-10 Days | J37: 3-7 Days | K37: 3-7 Days | L37: 5-10 Days | N37: 7-14 Days | O37: 7-14 Days | P37: 7-14 Days | R37: 3-7 Days | S37: 3-7 Days | T37: 5-10 Days | V37: 7-14 Days | W37: 7-14 Days | X37: 7-14 Days | Z37: 7-14 Days | AA37: 7-14 Days | AB37: 7-14 Days
A38: XXL | B38: 1-2 Days | C38: 1-2 Days | D38: 2-7 Days | F38: 3-7 Days | G38: 3-7 Days | H38: 5-10 Days | J38: 3-7 Days | K38: 3-7 Days | L38: 5-10 Days | N38: 7-14 Days | O38: 7-14 Days | P38: 7-14 Days | R38: 3-7 Days | S38: 3-7 Days | T38: 5-10 Days | V38: 7-14 Days | W38: 7-14 Days | X38: 7-14 Days | Z38: 7-14 Days | AA38: 7-14 Days | AB38: 7-14 Days
A39: Bulky | B39: 1-2 Days | C39: 1-2 Days | D39: 2-7 Days | F39: 3-7 Days | G39: 3-7 Days | H39: 5-10 Days | J39: 3-7 Days | K39: 3-7 Days | L39: 5-10 Days | N39: 7-14 Days | O39: 7-14 Days | P39: 7-14 Days | R39: 3-7 Days | S39: 3-7 Days | T39: 5-10 Days | V39: 7-14 Days | W39: 7-14 Days | X39: 7-14 Days | Z39: 7-14 Days | AA39: 7-14 Days | AB39: 7-14 Days

Sheet TAS
A1: Freight Charges for TAS Orders
A3: Standard | B3: From TAS | F3: From VIC | J3: From NSW | N3: From QLD | R3: From WA | V3: From ACT | Z3: From SA
A4: Freight Size | B4: Metro | C4: Metro Outer | D4: Regional | F4: Metro | G4: Metro Outer | H4: Regional | J4: Metro | K4: Metro Outer | L4: Regional | N4: Metro | O4: Metro Outer | P4: Regional | R4: Metro | S4: Metro Outer | T4: Regional | V4: Metro | W4: Metro Outer | X4: Regional | Z4: Metro | AA4: Metro Outer | AB4: Regional
A5: Small | B5: ='Cost model'!M632 -> 10.5 | C5: ='Cost model'!M633 -> 13.5 | D5: ='Cost model'!M634 -> 19.5 | F5: ='Cost model'!M650 -> 16.5 | G5: ='Cost model'!M651 -> 20.5 | H5: ='Cost model'!M652 -> 25.5 | J5: ='Cost model'!M668 -> 15.5 | K5: ='Cost model'!M669 -> 17.5 | L5: ='Cost model'!M670 -> 22.5 | N5: ='Cost model'!M686 -> 14.5 | O5: ='Cost model'!M687 -> 17.5 | P5: ='Cost model'!M688 -> 22.5 | R5: ='Cost model'!M704 -> 13.5 | S5: ='Cost model'!M705 -> 16.5 | T5: ='Cost model'!M706 -> 21.5 | V5: ='Cost model'!M722 -> 13.5 | W5: ='Cost model'!M723 -> 17.5 | X5: ='Cost model'!M724 -> 21.5 | Z5: ='Cost model'!M740 -> 14.5 | AA5: ='Cost model'!M741 -> 16.5 | AB5: ='Cost model'!M742 -> 21.5
A6: Medium | B6: ='Cost model'!M635 -> 29.5 | C6: ='Cost model'!M636 -> 55 | D6: ='Cost model'!M637 -> 55 | F6: ='Cost model'!M653 -> 65 | G6: ='Cost model'!M654 -> 80 | H6: ='Cost model'!M655 -> 80 | J6: ='Cost model'!M671 -> 55 | K6: ='Cost model'!M672 -> 65 | L6: ='Cost model'!M673 -> 70 | N6: ='Cost model'!M689 -> 55 | O6: ='Cost model'!M690 -> 60 | P6: ='Cost model'!M691 -> 70 | R6: ='Cost model'!M707 -> 50 | S6: ='Cost model'!M708 -> 55 | T6: ='Cost model'!M709 -> 65 | V6: ='Cost model'!M725 -> 50 | W6: ='Cost model'!M726 -> 55 | X6: ='Cost model'!M727 -> 65 | Z6: ='Cost model'!M743 -> 50 | AA6: ='Cost model'!M744 -> 55 | AB6: ='Cost model'!M745 -> 65
A7: Large | B7: ='Cost model'!M638 -> 55 | C7: ='Cost model'!M639 -> 90 | D7: ='Cost model'!M640 -> 110 | F7: ='Cost model'!M656 -> 105 | G7: ='Cost model'!M657 -> 135 | H7: ='Cost model'!M658 -> 160 | J7: ='Cost model'!M674 -> 95 | K7: ='Cost model'!M675 -> 105 | L7: ='Cost model'!M676 -> 145 | N7: ='Cost model'!M692 -> 95 | O7: ='Cost model'!M693 -> 105 | P7: ='Cost model'!M694 -> 140 | R7: ='Cost model'!M710 -> 90 | S7: ='Cost model'!M711 -> 100 | T7: ='Cost model'!M712 -> 130 | V7: ='Cost model'!M728 -> 85 | W7: ='Cost model'!M729 -> 100 | X7: ='Cost model'!M730 -> 130 | Z7: ='Cost model'!M746 -> 85 | AA7: ='Cost model'!M747 -> 100 | AB7: ='Cost model'!M748 -> 130
A8: XL | B8: ='Cost model'!M641 -> 115 | C8: ='Cost model'!M642 -> 150 | D8: ='Cost model'!M643 -> 215 | F8: ='Cost model'!M659 -> 185 | G8: ='Cost model'!M660 -> 210 | H8: ='Cost model'!M661 -> 265 | J8: ='Cost model'!M677 -> 165 | K8: ='Cost model'!M678 -> 195 | L8: ='Cost model'!M679 -> 235 | N8: ='Cost model'!M695 -> 160 | O8: ='Cost model'!M696 -> 195 | P8: ='Cost model'!M697 -> 230 | R8: ='Cost model'!M713 -> 150 | S8: ='Cost model'!M714 -> 180 | T8: ='Cost model'!M715 -> 215 | V8: ='Cost model'!M731 -> 150 | W8: ='Cost model'!M732 -> 180 | X8: ='Cost model'!M733 -> 215 | Z8: ='Cost model'!M749 -> 150 | AA8: ='Cost model'!M750 -> 180 | AB8: ='Cost model'!M751 -> 215
A9: XXL | B9: ='Cost model'!M644 -> 130 | C9: ='Cost model'!M645 -> 185 | D9: ='Cost model'!M646 -> 275 | F9: ='Cost model'!M662 -> 230 | G9: ='Cost model'!M663 -> 345 | H9: ='Cost model'!M664 -> 410 | J9: ='Cost model'!M680 -> 205 | K9: ='Cost model'!M681 -> 310 | L9: ='Cost model'!M682 -> 370 | N9: ='Cost model'!M698 -> 205 | O9: ='Cost model'!M699 -> 300 | P9: ='Cost model'!M700 -> 360 | R9: ='Cost model'!M716 -> 190 | S9: ='Cost model'!M717 -> 285 | T9: ='Cost model'!M718 -> 340 | V9: ='Cost model'!M734 -> 190 | W9: ='Cost model'!M735 -> 285 | X9: ='Cost model'!M736 -> 340 | Z9: ='Cost model'!M752 -> 195 | AA9: ='Cost model'!M753 -> 285 | AB9: ='Cost model'!M754 -> 340
A10: Bulky | B10: ='Cost model'!M647 -> 140 | C10: ='Cost model'!M648 -> 260 | D10: ='Cost model'!M649 -> 330 | F10: ='Cost model'!M665 -> 320 | G10: ='Cost model'!M666 -> 495 | H10: ='Cost model'!M667 -> 585 | J10: ='Cost model'!M683 -> 285 | K10: ='Cost model'!M684 -> 440 | L10: ='Cost model'!M685 -> 520 | N10: ='Cost model'!M701 -> 280 | O10: ='Cost model'!M702 -> 435 | P10: ='Cost model'!M703 -> 510 | R10: ='Cost model'!M719 -> 265 | S10: ='Cost model'!M720 -> 405 | T10: ='Cost model'!M721 -> 475 | V10: ='Cost model'!M737 -> 260 | W10: ='Cost model'!M738 -> 405 | X10: ='Cost model'!M739 -> 475 | Z10: ='Cost model'!M755 -> 260 | AA10: ='Cost model'!M756 -> 405 | AB10: ='Cost model'!M757 -> 475
A12: Priority | B12: From TAS | F12: From VIC | J12: From NSW | N12: From QLD | R12: From WA | V12: From ACT | Z12: From SA
A13: Freight Size | B13: Metro | C13: Metro Outer | D13: Regional | F13: Metro | G13: Metro Outer | H13: Regional | J13: Metro | K13: Metro Outer | L13: Regional | N13: Metro | O13: Metro Outer | P13: Regional | R13: Metro | S13: Metro Outer | T13: Regional | V13: Metro | W13: Metro Outer | X13: Regional | Z13: Metro | AA13: Metro Outer | AB13: Regional
A14: Small | B14: ='Cost model'!N632 -> 15.5 | C14: ='Cost model'!N633 -> 18.5 | D14: ='Cost model'!N634 -> 26.5 | F14: ='Cost model'!N650 -> 22.5 | G14: ='Cost model'!N651 -> 27.5 | H14: ='Cost model'!N652 -> 35 | J14: ='Cost model'!N668 -> 21.5 | K14: ='Cost model'!N669 -> 23.5 | L14: ='Cost model'!N670 -> 35 | N14: ='Cost model'!N686 -> 19.5 | O14: ='Cost model'!N687 -> 23.5 | P14: ='Cost model'!N688 -> 35 | R14: ='Cost model'!N704 -> 18.5 | S14: ='Cost model'!N705 -> 22.5 | T14: ='Cost model'!N706 -> 29.5 | V14: ='Cost model'!N722 -> 18.5 | W14: ='Cost model'!N723 -> 23.5 | X14: ='Cost model'!N724 -> 29.5 | Z14: ='Cost model'!N740 -> 19.5 | AA14: ='Cost model'!N741 -> 22.5 | AB14: ='Cost model'!N742 -> 29.5
A15: Medium | B15: ='Cost model'!N635 -> 40 | C15: ='Cost model'!N636 -> 70 | D15: ='Cost model'!N637 -> 70 | F15: ='Cost model'!N653 -> 85 | G15: ='Cost model'!N654 -> 105 | H15: ='Cost model'!N655 -> 105 | J15: ='Cost model'!N671 -> 70 | K15: ='Cost model'!N672 -> 85 | L15: ='Cost model'!N673 -> 90 | N15: ='Cost model'!N689 -> 70 | O15: ='Cost model'!N690 -> 80 | P15: ='Cost model'!N691 -> 90 | R15: ='Cost model'!N707 -> 65 | S15: ='Cost model'!N708 -> 70 | T15: ='Cost model'!N709 -> 85 | V15: ='Cost model'!N725 -> 65 | W15: ='Cost model'!N726 -> 70 | X15: ='Cost model'!N727 -> 85 | Z15: ='Cost model'!N743 -> 65 | AA15: ='Cost model'!N744 -> 70 | AB15: ='Cost model'!N745 -> 85
A16: Large | B16: ='Cost model'!N638 -> 75 | C16: ='Cost model'!N639 -> 125 | D16: ='Cost model'!N640 -> 150 | F16: ='Cost model'!N656 -> 145 | G16: ='Cost model'!N657 -> 185 | H16: ='Cost model'!N658 -> 220 | J16: ='Cost model'!N674 -> 130 | K16: ='Cost model'!N675 -> 145 | L16: ='Cost model'!N676 -> 200 | N16: ='Cost model'!N692 -> 130 | O16: ='Cost model'!N693 -> 145 | P16: ='Cost model'!N694 -> 190 | R16: ='Cost model'!N710 -> 125 | S16: ='Cost model'!N711 -> 135 | T16: ='Cost model'!N712 -> 180 | V16: ='Cost model'!N728 -> 115 | W16: ='Cost model'!N729 -> 135 | X16: ='Cost model'!N730 -> 180 | Z16: ='Cost model'!N746 -> 115 | AA16: ='Cost model'!N747 -> 135 | AB16: ='Cost model'!N748 -> 180
A17: XL | B17: ='Cost model'!N641 -> 140 | C17: ='Cost model'!N642 -> 180 | D17: ='Cost model'!N643 -> 260 | F17: ='Cost model'!N659 -> 225 | G17: ='Cost model'!N660 -> 255 | H17: ='Cost model'!N661 -> 320 | J17: ='Cost model'!N677 -> 200 | K17: ='Cost model'!N678 -> 235 | L17: ='Cost model'!N679 -> 285 | N17: ='Cost model'!N695 -> 195 | O17: ='Cost model'!N696 -> 235 | P17: ='Cost model'!N697 -> 280 | R17: ='Cost model'!N713 -> 180 | S17: ='Cost model'!N714 -> 220 | T17: ='Cost model'!N715 -> 260 | V17: ='Cost model'!N731 -> 180 | W17: ='Cost model'!N732 -> 220 | X17: ='Cost model'!N733 -> 260 | Z17: ='Cost model'!N749 -> 180 | AA17: ='Cost model'!N750 -> 220 | AB17: ='Cost model'!N751 -> 260
A18: XXL | B18: ='Cost model'!N644 -> 160 | C18: ='Cost model'!N645 -> 225 | D18: ='Cost model'!N646 -> 330 | F18: ='Cost model'!N662 -> 280 | G18: ='Cost model'!N663 -> 345 | H18: ='Cost model'!N664 -> 410 | J18: ='Cost model'!N680 -> 250 | K18: ='Cost model'!N681 -> 310 | L18: ='Cost model'!N682 -> 370 | N18: ='Cost model'!N698 -> 250 | O18: ='Cost model'!N699 -> 300 | P18: ='Cost model'!N700 -> 360 | R18: ='Cost model'!N716 -> 230 | S18: ='Cost model'!N717 -> 285 | T18: ='Cost model'!N718 -> 340 | V18: ='Cost model'!N734 -> 230 | W18: ='Cost model'!N735 -> 285 | X18: ='Cost model'!N736 -> 340 | Z18: ='Cost model'!N752 -> 235 | AA18: ='Cost model'!N753 -> 285 | AB18: ='Cost model'!N754 -> 340
A19: Bulky | B19: ='Cost model'!N647 -> 170 | C19: ='Cost model'!N648 -> 315 | D19: ='Cost model'!N649 -> 400 | F19: ='Cost model'!N665 -> 385 | G19: ='Cost model'!N666 -> 495 | H19: ='Cost model'!N667 -> 585 | J19: ='Cost model'!N683 -> 345 | K19: ='Cost model'!N684 -> 440 | L19: ='Cost model'!N685 -> 520 | N19: ='Cost model'!N701 -> 340 | O19: ='Cost model'!N702 -> 435 | P19: ='Cost model'!N703 -> 510 | R19: ='Cost model'!N719 -> 320 | S19: ='Cost model'!N720 -> 405 | T19: ='Cost model'!N721 -> 475 | V19: ='Cost model'!N737 -> 315 | W19: ='Cost model'!N738 -> 405 | X19: ='Cost model'!N739 -> 475 | Z19: ='Cost model'!N755 -> 315 | AA19: ='Cost model'!N756 -> 405 | AB19: ='Cost model'!N757 -> 475
A21: Delivery time frames for TAS Orders
A23: Standard | B23: From TAS | F23: From VIC | J23: From NSW | N23: From QLD | R23: From WA | V23: From ACT | Z23: From SA
A24: Freight Size | B24: Metro | C24: Metro Outer | D24: Regional | F24: Metro | G24: Metro Outer | H24: Regional | J24: Metro | K24: Metro Outer | L24: Regional | N24: Metro | O24: Metro Outer | P24: Regional | R24: Metro | S24: Metro Outer | T24: Regional | V24: Metro | W24: Metro Outer | X24: Regional | Z24: Metro | AA24: Metro Outer | AB24: Regional
A25: Small | B25: 1-3 Days | C25: 1-3 Days | D25: 2-5 Days | F25: 2-5 Days | G25: 2-5 Days | H25: 3-7 Days | J25: 2-5 Days | K25: 2-5 Days | L25: 2-5 Days | N25: 7-14 Days | O25: 7-14 Days | P25: 7-14 Days | R25: 2-5 Days | S25: 2-5 Days | T25: 3-7 Days | V25: 2-5 Days | W25: 2-5 Days | X25: 3-7 Days | Z25: 2-5 Days | AA25: 2-5 Days | AB25: 3-7 Days
A26: Medium | B26: 1-3 Days | C26: 1-3 Days | D26: 2-5 Days | F26: 2-5 Days | G26: 2-5 Days | H26: 3-7 Days | J26: 2-5 Days | K26: 2-5 Days | L26: 2-5 Days | N26: 7-14 Days | O26: 7-14 Days | P26: 7-14 Days | R26: 2-5 Days | S26: 2-5 Days | T26: 3-7 Days | V26: 2-5 Days | W26: 2-5 Days | X26: 3-7 Days | Z26: 2-5 Days | AA26: 2-5 Days | AB26: 3-7 Days
A27: Large | B27: 1-3 Days | C27: 1-3 Days | D27: 3-7 Days | F27: 3-7 Days | G27: 3-7 Days | H27: 5-10 Days | J27: 3-7 Days | K27: 3-7 Days | L27: 5-10 Days | N27: 7-14 Days | O27: 7-14 Days | P27: 7-14 Days | R27: 3-7 Days | S27: 3-7 Days | T27: 5-10 Days | V27: 3-7 Days | W27: 3-7 Days | X27: 5-10 Days | Z27: 3-7 Days | AA27: 3-7 Days | AB27: 5-10 Days
A28: XL | B28: 1-3 Days | C28: 1-3 Days | D28: 5-10 Days | F28: 5-10 Days | G28: 5-10 Days | H28: 5-10 Days | J28: 5-10 Days | K28: 5-10 Days | L28: 5-10 Days | N28: 7-14 Days | O28: 7-14 Days | P28: 7-14 Days | R28: 5-10 Days | S28: 5-10 Days | T28: 5-10 Days | V28: 5-10 Days | W28: 5-10 Days | X28: 5-10 Days | Z28: 5-10 Days | AA28: 5-10 Days | AB28: 5-10 Days
A29: XXL | B29: 1-3 Days | C29: 1-3 Days | D29: 5-10 Days | F29: 5-10 Days | G29: 5-10 Days | H29: 5-10 Days | J29: 5-10 Days | K29: 5-10 Days | L29: 5-10 Days | N29: 7-14 Days | O29: 7-14 Days | P29: 7-14 Days | R29: 5-10 Days | S29: 5-10 Days | T29: 5-10 Days | V29: 5-10 Days | W29: 5-10 Days | X29: 5-10 Days | Z29: 5-10 Days | AA29: 5-10 Days | AB29: 5-10 Days
A30: Bulky | B30: 1-3 Days | C30: 1-3 Days | D30: 5-10 Days | F30: 5-10 Days | G30: 5-10 Days | H30: 5-10 Days | J30: 5-10 Days | K30: 5-10 Days | L30: 5-10 Days | N30: 7-14 Days | O30: 7-14 Days | P30: 7-14 Days | R30: 5-10 Days | S30: 5-10 Days | T30: 5-10 Days | V30: 5-10 Days | W30: 5-10 Days | X30: 5-10 Days | Z30: 5-10 Days | AA30: 5-10 Days | AB30: 5-10 Days
A32: Priority | B32: From TAS | F32: From VIC | J32: From NSW | N32: From QLD | R32: From WA | V32: From ACT | Z32: From SA
A33: Freight Size | B33: Metro | C33: Metro Outer | D33: Regional | F33: Metro | G33: Metro Outer | H33: Regional | J33: Metro | K33: Metro Outer | L33: Regional | N33: Metro | O33: Metro Outer | P33: Regional | R33: Metro | S33: Metro Outer | T33: Regional | V33: Metro | W33: Metro Outer | X33: Regional | Z33: Metro | AA33: Metro Outer | AB33: Regional
A34: Small | B34: 1-2 Days | C34: 1-2 Days | D34: 1-3 Days | F34: 1-2 Days | G34: 1-2 Days | H34: 2-5 Days | J34: 1-2 Days | K34: 1-2 Days | L34: 2-5 Days | N34: 1-2 Days | O34: 1-2 Days | P34: 2-5 Days | R34: 1-2 Days | S34: 1-2 Days | T34: 2-5 Days | V34: 1-2 Days | W34: 1-2 Days | X34: 2-5 Days | Z34: 1-2 Days | AA34: 1-2 Days | AB34: 2-5 Days
A35: Medium | B35: 1-2 Days | C35: 1-2 Days | D35: 1-3 Days | F35: 1-2 Days | G35: 1-2 Days | H35: 2-5 Days | J35: 1-2 Days | K35: 1-2 Days | L35: 2-5 Days | N35: 1-2 Days | O35: 1-2 Days | P35: 2-5 Days | R35: 1-2 Days | S35: 1-2 Days | T35: 2-5 Days | V35: 1-2 Days | W35: 1-2 Days | X35: 2-5 Days | Z35: 1-2 Days | AA35: 1-2 Days | AB35: 2-5 Days
A36: Large | B36: 1-2 Days | C36: 1-2 Days | D36: 2-7 Days | F36: 2-5 Days | G36: 2-5 Days | H36: 5-10 Days | J36: 2-5 Days | K36: 2-5 Days | L36: 5-10 Days | N36: 7-14 Days | O36: 7-14 Days | P36: 7-14 Days | R36: 2-5 Days | S36: 2-5 Days | T36: 5-10 Days | V36: 2-5 Days | W36: 2-5 Days | X36: 5-10 Days | Z36: 2-5 Days | AA36: 2-5 Days | AB36: 5-10 Days
A37: XL | B37: 1-2 Days | C37: 1-2 Days | D37: 2-7 Days | F37: 3-7 Days | G37: 3-7 Days | H37: 5-10 Days | J37: 3-7 Days | K37: 3-7 Days | L37: 5-10 Days | N37: 7-14 Days | O37: 7-14 Days | P37: 7-14 Days | R37: 3-7 Days | S37: 3-7 Days | T37: 5-10 Days | V37: 3-7 Days | W37: 3-7 Days | X37: 5-10 Days | Z37: 3-7 Days | AA37: 3-7 Days | AB37: 5-10 Days
A38: XXL | B38: 1-2 Days | C38: 1-2 Days | D38: 2-7 Days | F38: 3-7 Days | G38: 3-7 Days | H38: 5-10 Days | J38: 3-7 Days | K38: 3-7 Days | L38: 5-10 Days | N38: 7-14 Days | O38: 7-14 Days | P38: 7-14 Days | R38: 3-7 Days | S38: 3-7 Days | T38: 5-10 Days | V38: 3-7 Days | W38: 3-7 Days | X38: 5-10 Days | Z38: 3-7 Days | AA38: 3-7 Days | AB38: 5-10 Days
A39: Bulky | B39: 1-2 Days | C39: 1-2 Days | D39: 2-7 Days | F39: 3-7 Days | G39: 3-7 Days | H39: 5-10 Days | J39: 3-7 Days | K39: 3-7 Days | L39: 5-10 Days | N39: 7-14 Days | O39: 7-14 Days | P39: 7-14 Days | R39: 3-7 Days | S39: 3-7 Days | T39: 5-10 Days | V39: 3-7 Days | W39: 3-7 Days | X39: 5-10 Days | Z39: 3-7 Days | AA39: 3-7 Days | AB39: 5-10 Days

Sheet VIC
A1: Freight Charges for VIC Orders
A3: Standard | B3: From VIC | F3: From SA | J3: From QLD | N3: From WA | R3: From NSW | V3: From TAS | Z3: From ACT
A4: Freight Size | B4: Metro | C4: Metro Outer | D4: Regional | F4: Metro | G4: Metro Outer | H4: Regional | J4: Metro | K4: Metro Outer | L4: Regional | N4: Metro | O4: Metro Outer | P4: Regional | R4: Metro | S4: Metro Outer | T4: Regional | V4: Metro | W4: Metro Outer | X4: Regional | Z4: Metro | AA4: Metro Outer | AB4: Regional
A5: Small | B5: ='Cost model'!M758 -> 9.5 | C5: ='Cost model'!M759 -> 15.5 | D5: ='Cost model'!M760 -> 18.5 | F5: ='Cost model'!M776 -> 13.5 | G5: ='Cost model'!M777 -> 16.5 | H5: ='Cost model'!M778 -> 19.5 | J5: ='Cost model'!M794 -> 12.5 | K5: ='Cost model'!M795 -> 13.5 | L5: ='Cost model'!M796 -> 17.5 | N5: ='Cost model'!M812 -> 12.5 | O5: ='Cost model'!M813 -> 15.5 | P5: ='Cost model'!M814 -> 20.5 | R5: ='Cost model'!M830 -> 9.5 | S5: ='Cost model'!M831 -> 10.5 | T5: ='Cost model'!M832 -> 15.5 | V5: ='Cost model'!M848 -> 9.5 | W5: ='Cost model'!M849 -> 12.5 | X5: ='Cost model'!M850 -> 15.5 | Z5: ='Cost model'!M866 -> 15.5 | AA5: ='Cost model'!M867 -> 15.5 | AB5: ='Cost model'!M868 -> 19.5
A6: Medium | B6: ='Cost model'!M761 -> 35 | C6: ='Cost model'!M762 -> 45 | D6: ='Cost model'!M763 -> 50 | F6: ='Cost model'!M779 -> 50 | G6: ='Cost model'!M780 -> 60 | H6: ='Cost model'!M781 -> 60 | J6: ='Cost model'!M797 -> 40 | K6: ='Cost model'!M798 -> 45 | L6: ='Cost model'!M799 -> 55 | N6: ='Cost model'!M815 -> 50 | O6: ='Cost model'!M816 -> 55 | P6: ='Cost model'!M817 -> 60 | R6: ='Cost model'!M833 -> 45 | S6: ='Cost model'!M834 -> 45 | T6: ='Cost model'!M835 -> 50 | V6: ='Cost model'!M851 -> 40 | W6: ='Cost model'!M852 -> 45 | X6: ='Cost model'!M853 -> 50 | Z6: ='Cost model'!M869 -> 45 | AA6: ='Cost model'!M870 -> 50 | AB6: ='Cost model'!M871 -> 55
A7: Large | B7: ='Cost model'!M764 -> 55 | C7: ='Cost model'!M765 -> 70 | D7: ='Cost model'!M766 -> 90 | F7: ='Cost model'!M782 -> 85 | G7: ='Cost model'!M783 -> 95 | H7: ='Cost model'!M784 -> 125 | J7: ='Cost model'!M800 -> 70 | K7: ='Cost model'!M801 -> 85 | L7: ='Cost model'!M802 -> 110 | N7: ='Cost model'!M818 -> 80 | O7: ='Cost model'!M819 -> 90 | P7: ='Cost model'!M820 -> 125 | R7: ='Cost model'!M836 -> 75 | S7: ='Cost model'!M837 -> 75 | T7: ='Cost model'!M838 -> 80 | V7: ='Cost model'!M854 -> 65 | W7: ='Cost model'!M855 -> 70 | X7: ='Cost model'!M856 -> 100 | Z7: ='Cost model'!M872 -> 75 | AA7: ='Cost model'!M873 -> 85 | AB7: ='Cost model'!M874 -> 115
A8: XL | B8: ='Cost model'!M767 -> 100 | C8: ='Cost model'!M768 -> 145 | D8: ='Cost model'!M769 -> 160 | F8: ='Cost model'!M785 -> 145 | G8: ='Cost model'!M786 -> 175 | H8: ='Cost model'!M787 -> 200 | J8: ='Cost model'!M803 -> 120 | K8: ='Cost model'!M804 -> 150 | L8: ='Cost model'!M805 -> 180 | N8: ='Cost model'!M821 -> 140 | O8: ='Cost model'!M822 -> 170 | P8: ='Cost model'!M823 -> 200 | R8: ='Cost model'!M839 -> 95 | S8: ='Cost model'!M840 -> 115 | T8: ='Cost model'!M841 -> 140 | V8: ='Cost model'!M857 -> 115 | W8: ='Cost model'!M858 -> 135 | X8: ='Cost model'!M859 -> 160 | Z8: ='Cost model'!M875 -> 130 | AA8: ='Cost model'!M876 -> 155 | AB8: ='Cost model'!M877 -> 185
A9: XXL | B9: ='Cost model'!M770 -> 125 | C9: ='Cost model'!M771 -> 170 | D9: ='Cost model'!M772 -> 250 | F9: ='Cost model'!M788 -> 185 | G9: ='Cost model'!M789 -> 270 | H9: ='Cost model'!M790 -> 325 | J9: ='Cost model'!M806 -> 150 | K9: ='Cost model'!M807 -> 235 | L9: ='Cost model'!M808 -> 280 | N9: ='Cost model'!M824 -> 180 | O9: ='Cost model'!M825 -> 265 | P9: ='Cost model'!M826 -> 315 | R9: ='Cost model'!M842 -> 125 | S9: ='Cost model'!M843 -> 180 | T9: ='Cost model'!M844 -> 220 | V9: ='Cost model'!M860 -> 145 | W9: ='Cost model'!M861 -> 210 | X9: ='Cost model'!M862 -> 255 | Z9: ='Cost model'!M878 -> 165 | AA9: ='Cost model'!M879 -> 240 | AB9: ='Cost model'!M880 -> 290
A10: Bulky | B10: ='Cost model'!M773 -> 125 | C10: ='Cost model'!M774 -> 225 | D10: ='Cost model'!M775 -> 285 | F10: ='Cost model'!M791 -> 260 | G10: ='Cost model'!M792 -> 385 | H10: ='Cost model'!M793 -> 460 | J10: ='Cost model'!M809 -> 225 | K10: ='Cost model'!M810 -> 355 | L10: ='Cost model'!M811 -> 390 | N10: ='Cost model'!M827 -> 245 | O10: ='Cost model'!M828 -> 380 | P10: ='Cost model'!M829 -> 445 | R10: ='Cost model'!M845 -> 160 | S10: ='Cost model'!M846 -> 260 | T10: ='Cost model'!M847 -> 300 | V10: ='Cost model'!M863 -> 205 | W10: ='Cost model'!M864 -> 300 | X10: ='Cost model'!M865 -> 355 | Z10: ='Cost model'!M881 -> 225 | AA10: ='Cost model'!M882 -> 350 | AB10: ='Cost model'!M883 -> 410
A12: Priority | B12: From VIC | F12: From SA | J12: From QLD | N12: From WA | R12: From NSW | V12: From TAS | Z12: From ACT
A13: Freight Size | B13: Metro | C13: Metro Outer | D13: Regional | F13: Metro | G13: Metro Outer | H13: Regional | J13: Metro | K13: Metro Outer | L13: Regional | N13: Metro | O13: Metro Outer | P13: Regional | R13: Metro | S13: Metro Outer | T13: Regional | V13: Metro | W13: Metro Outer | X13: Regional | Z13: Metro | AA13: Metro Outer | AB13: Regional
A14: Small | B14: ='Cost model'!N758 -> 14.5 | C14: ='Cost model'!N759 -> 21.5 | D14: ='Cost model'!N760 -> 25.5 | F14: ='Cost model'!N776 -> 18.5 | G14: ='Cost model'!N777 -> 22.5 | H14: ='Cost model'!N778 -> 26.5 | J14: ='Cost model'!N794 -> 17.5 | K14: ='Cost model'!N795 -> 18.5 | L14: ='Cost model'!N796 -> 23.5 | N14: ='Cost model'!N812 -> 17.5 | O14: ='Cost model'!N813 -> 21.5 | P14: ='Cost model'!N814 -> 27.5 | R14: ='Cost model'!N830 -> 14.5 | S14: ='Cost model'!N831 -> 15.5 | T14: ='Cost model'!N832 -> 21.5 | V14: ='Cost model'!N848 -> 14.5 | W14: ='Cost model'!N849 -> 17.5 | X14: ='Cost model'!N850 -> 21.5 | Z14: ='Cost model'!N866 -> 21.5 | AA14: ='Cost model'!N867 -> 21.5 | AB14: ='Cost model'!N868 -> 26.5
A15: Medium | B15: ='Cost model'!N761 -> 45 | C15: ='Cost model'!N762 -> 60 | D15: ='Cost model'!N763 -> 65 | F15: ='Cost model'!N779 -> 65 | G15: ='Cost model'!N780 -> 80 | H15: ='Cost model'!N781 -> 80 | J15: ='Cost model'!N797 -> 55 | K15: ='Cost model'!N798 -> 60 | L15: ='Cost model'!N799 -> 70 | N15: ='Cost model'!N815 -> 65 | O15: ='Cost model'!N816 -> 70 | P15: ='Cost model'!N817 -> 80 | R15: ='Cost model'!N833 -> 60 | S15: ='Cost model'!N834 -> 60 | T15: ='Cost model'!N835 -> 65 | V15: ='Cost model'!N851 -> 55 | W15: ='Cost model'!N852 -> 60 | X15: ='Cost model'!N853 -> 65 | Z15: ='Cost model'!N869 -> 60 | AA15: ='Cost model'!N870 -> 65 | AB15: ='Cost model'!N871 -> 70
A16: Large | B16: ='Cost model'!N764 -> 75 | C16: ='Cost model'!N765 -> 95 | D16: ='Cost model'!N766 -> 125 | F16: ='Cost model'!N782 -> 115 | G16: ='Cost model'!N783 -> 130 | H16: ='Cost model'!N784 -> 170 | J16: ='Cost model'!N800 -> 95 | K16: ='Cost model'!N801 -> 115 | L16: ='Cost model'!N802 -> 150 | N16: ='Cost model'!N818 -> 110 | O16: ='Cost model'!N819 -> 125 | P16: ='Cost model'!N820 -> 170 | R16: ='Cost model'!N836 -> 105 | S16: ='Cost model'!N837 -> 105 | T16: ='Cost model'!N838 -> 110 | V16: ='Cost model'!N854 -> 90 | W16: ='Cost model'!N855 -> 95 | X16: ='Cost model'!N856 -> 135 | Z16: ='Cost model'!N872 -> 105 | AA16: ='Cost model'!N873 -> 115 | AB16: ='Cost model'!N874 -> 160
A17: XL | B17: ='Cost model'!N767 -> 120 | C17: ='Cost model'!N768 -> 175 | D17: ='Cost model'!N769 -> 195 | F17: ='Cost model'!N785 -> 175 | G17: ='Cost model'!N786 -> 210 | H17: ='Cost model'!N787 -> 240 | J17: ='Cost model'!N803 -> 145 | K17: ='Cost model'!N804 -> 180 | L17: ='Cost model'!N805 -> 220 | N17: ='Cost model'!N821 -> 170 | O17: ='Cost model'!N822 -> 205 | P17: ='Cost model'!N823 -> 240 | R17: ='Cost model'!N839 -> 115 | S17: ='Cost model'!N840 -> 140 | T17: ='Cost model'!N841 -> 170 | V17: ='Cost model'!N857 -> 140 | W17: ='Cost model'!N858 -> 165 | X17: ='Cost model'!N859 -> 195 | Z17: ='Cost model'!N875 -> 160 | AA17: ='Cost model'!N876 -> 190 | AB17: ='Cost model'!N877 -> 225
A18: XXL | B18: ='Cost model'!N770 -> 150 | C18: ='Cost model'!N771 -> 205 | D18: ='Cost model'!N772 -> 300 | F18: ='Cost model'!N788 -> 225 | G18: ='Cost model'!N789 -> 270 | H18: ='Cost model'!N790 -> 325 | J18: ='Cost model'!N806 -> 180 | K18: ='Cost model'!N807 -> 235 | L18: ='Cost model'!N808 -> 280 | N18: ='Cost model'!N824 -> 220 | O18: ='Cost model'!N825 -> 265 | P18: ='Cost model'!N826 -> 315 | R18: ='Cost model'!N842 -> 150 | S18: ='Cost model'!N843 -> 180 | T18: ='Cost model'!N844 -> 220 | V18: ='Cost model'!N860 -> 175 | W18: ='Cost model'!N861 -> 210 | X18: ='Cost model'!N862 -> 255 | Z18: ='Cost model'!N878 -> 200 | AA18: ='Cost model'!N879 -> 240 | AB18: ='Cost model'!N880 -> 290
A19: Bulky | B19: ='Cost model'!N773 -> 150 | C19: ='Cost model'!N774 -> 270 | D19: ='Cost model'!N775 -> 345 | F19: ='Cost model'!N791 -> 315 | G19: ='Cost model'!N792 -> 385 | H19: ='Cost model'!N793 -> 460 | J19: ='Cost model'!N809 -> 270 | K19: ='Cost model'!N810 -> 355 | L19: ='Cost model'!N811 -> 390 | N19: ='Cost model'!N827 -> 295 | O19: ='Cost model'!N828 -> 380 | P19: ='Cost model'!N829 -> 445 | R19: ='Cost model'!N845 -> 195 | S19: ='Cost model'!N846 -> 260 | T19: ='Cost model'!N847 -> 300 | V19: ='Cost model'!N863 -> 250 | W19: ='Cost model'!N864 -> 300 | X19: ='Cost model'!N865 -> 355 | Z19: ='Cost model'!N881 -> 270 | AA19: ='Cost model'!N882 -> 350 | AB19: ='Cost model'!N883 -> 410
A21: Delivery time frames for VIC Orders
A23: Standard | B23: From VIC | F23: From SA | J23: From QLD | N23: From WA | R23: From NSW | V23: From TAS | Z23: From ACT
A24: Freight Size | B24: Metro | C24: Metro Outer | D24: Regional | F24: Metro | G24: Metro Outer | H24: Regional | J24: Metro | K24: Metro Outer | L24: Regional | N24: Metro | O24: Metro Outer | P24: Regional | R24: Metro | S24: Metro Outer | T24: Regional | V24: Metro | W24: Metro Outer | X24: Regional | Z24: Metro | AA24: Metro Outer | AB24: Regional
A25: Small | B25: 1-3 Days | C25: 1-3 Days | D25: 2-5 Days | F25: 2-5 Days | G25: 2-5 Days | H25: 3-7 Days | J25: 2-5 Days | K25: 2-5 Days | L25: 2-5 Days | N25: 7-14 Days | O25: 7-14 Days | P25: 7-14 Days | R25: 2-5 Days | S25: 2-5 Days | T25: 2-5 Days | V25: 7-14 Days | W25: 7-14 Days | X25: 7-14 Days | Z25: 7-14 Days | AA25: 7-14 Days | AB25: 7-14 Days
A26: Medium | B26: 1-3 Days | C26: 1-3 Days | D26: 2-5 Days | F26: 2-5 Days | G26: 2-5 Days | H26: 3-7 Days | J26: 2-5 Days | K26: 2-5 Days | L26: 2-5 Days | N26: 7-14 Days | O26: 7-14 Days | P26: 7-14 Days | R26: 2-5 Days | S26: 2-5 Days | T26: 2-5 Days | V26: 7-14 Days | W26: 7-14 Days | X26: 7-14 Days | Z26: 7-14 Days | AA26: 7-14 Days | AB26: 7-14 Days
A27: Large | B27: 1-3 Days | C27: 1-3 Days | D27: 3-7 Days | F27: 3-7 Days | G27: 3-7 Days | H27: 5-10 Days | J27: 3-7 Days | K27: 3-7 Days | L27: 5-10 Days | N27: 7-14 Days | O27: 7-14 Days | P27: 7-14 Days | R27: 3-7 Days | S27: 3-7 Days | T27: 5-10 Days | V27: 7-14 Days | W27: 7-14 Days | X27: 7-14 Days | Z27: 7-14 Days | AA27: 7-14 Days | AB27: 7-14 Days
A28: XL | B28: 1-3 Days | C28: 1-3 Days | D28: 5-10 Days | F28: 5-10 Days | G28: 5-10 Days | H28: 5-10 Days | J28: 5-10 Days | K28: 5-10 Days | L28: 5-10 Days | N28: 7-14 Days | O28: 7-14 Days | P28: 7-14 Days | R28: 5-10 Days | S28: 5-10 Days | T28: 5-10 Days | V28: 7-14 Days | W28: 7-14 Days | X28: 7-14 Days | Z28: 7-14 Days | AA28: 7-14 Days | AB28: 7-14 Days
A29: XXL | B29: 1-3 Days | C29: 1-3 Days | D29: 5-10 Days | F29: 5-10 Days | G29: 5-10 Days | H29: 5-10 Days | J29: 5-10 Days | K29: 5-10 Days | L29: 5-10 Days | N29: 7-14 Days | O29: 7-14 Days | P29: 7-14 Days | R29: 5-10 Days | S29: 5-10 Days | T29: 5-10 Days | V29: 7-14 Days | W29: 7-14 Days | X29: 7-14 Days | Z29: 7-14 Days | AA29: 7-14 Days | AB29: 7-14 Days
A30: Bulky | B30: 1-3 Days | C30: 1-3 Days | D30: 5-10 Days | F30: 5-10 Days | G30: 5-10 Days | H30: 5-10 Days | J30: 5-10 Days | K30: 5-10 Days | L30: 5-10 Days | N30: 7-14 Days | O30: 7-14 Days | P30: 7-14 Days | R30: 5-10 Days | S30: 5-10 Days | T30: 5-10 Days | V30: 7-14 Days | W30: 7-14 Days | X30: 7-14 Days | Z30: 7-14 Days | AA30: 7-14 Days | AB30: 7-14 Days
A32: Priority | B32: From VIC | F32: From SA | J32: From QLD | N32: From WA | R32: From NSW | V32: From TAS | Z32: From ACT
A33: Freight Size | B33: Metro | C33: Metro Outer | D33: Regional | F33: Metro | G33: Metro Outer | H33: Regional | J33: Metro | K33: Metro Outer | L33: Regional | N33: Metro | O33: Metro Outer | P33: Regional | R33: Metro | S33: Metro Outer | T33: Regional | V33: Metro | W33: Metro Outer | X33: Regional | Z33: Metro | AA33: Metro Outer | AB33: Regional
A34: Small | B34: 1-2 Days | C34: 1-2 Days | D34: 1-3 Days | F34: 1-2 Days | G34: 1-2 Days | H34: 2-5 Days | J34: 1-2 Days | K34: 1-2 Days | L34: 2-5 Days | N34: 1-2 Days | O34: 1-2 Days | P34: 2-5 Days | R34: 1-2 Days | S34: 1-2 Days | T34: 2-5 Days | V34: 1-2 Days | W34: 1-2 Days | X34: 2-5 Days | Z34: 1-2 Days | AA34: 1-2 Days | AB34: 2-5 Days
A35: Medium | B35: 1-2 Days | C35: 1-2 Days | D35: 1-3 Days | F35: 1-2 Days | G35: 1-2 Days | H35: 2-5 Days | J35: 1-2 Days | K35: 1-2 Days | L35: 2-5 Days | N35: 1-2 Days | O35: 1-2 Days | P35: 2-5 Days | R35: 1-2 Days | S35: 1-2 Days | T35: 2-5 Days | V35: 1-2 Days | W35: 1-2 Days | X35: 2-5 Days | Z35: 1-2 Days | AA35: 1-2 Days | AB35: 2-5 Days
A36: Large | B36: 1-2 Days | C36: 1-2 Days | D36: 2-7 Days | F36: 2-5 Days | G36: 2-5 Days | H36: 5-10 Days | J36: 2-5 Days | K36: 2-5 Days | L36: 5-10 Days | N36: 7-14 Days | O36: 7-14 Days | P36: 7-14 Days | R36: 2-5 Days | S36: 2-5 Days | T36: 5-10 Days | V36: 7-14 Days | W36: 7-14 Days | X36: 7-14 Days | Z36: 7-14 Days | AA36: 7-14 Days | AB36: 7-14 Days
A37: XL | B37: 1-2 Days | C37: 1-2 Days | D37: 2-7 Days | F37: 3-7 Days | G37: 3-7 Days | H37: 5-10 Days | J37: 3-7 Days | K37: 3-7 Days | L37: 5-10 Days | N37: 7-14 Days | O37: 7-14 Days | P37: 7-14 Days | R37: 3-7 Days | S37: 3-7 Days | T37: 5-10 Days | V37: 7-14 Days | W37: 7-14 Days | X37: 7-14 Days | Z37: 7-14 Days | AA37: 7-14 Days | AB37: 7-14 Days
A38: XXL | B38: 1-2 Days | C38: 1-2 Days | D38: 2-7 Days | F38: 3-7 Days | G38: 3-7 Days | H38: 5-10 Days | J38: 3-7 Days | K38: 3-7 Days | L38: 5-10 Days | N38: 7-14 Days | O38: 7-14 Days | P38: 7-14 Days | R38: 3-7 Days | S38: 3-7 Days | T38: 5-10 Days | V38: 7-14 Days | W38: 7-14 Days | X38: 7-14 Days | Z38: 7-14 Days | AA38: 7-14 Days | AB38: 7-14 Days
A39: Bulky | B39: 1-2 Days | C39: 1-2 Days | D39: 2-7 Days | F39: 3-7 Days | G39: 3-7 Days | H39: 5-10 Days | J39: 3-7 Days | K39: 3-7 Days | L39: 5-10 Days | N39: 7-14 Days | O39: 7-14 Days | P39: 7-14 Days | R39: 3-7 Days | S39: 3-7 Days | T39: 5-10 Days | V39: 7-14 Days | W39: 7-14 Days | X39: 7-14 Days | Z39: 7-14 Days | AA39: 7-14 Days | AB39: 7-14 Days

Sheet WA
A1: Freight Charges for WA Orders
A3: Standard | B3: From WA | F3: From SA | J3: From VIC | N3: From NSW | R3: From QLD | V3: From ACT | Z3: From TAS
A4: Freight Size | B4: Metro | C4: Metro Outer | D4: Regional | F4: Metro | G4: Metro Outer | H4: Regional | J4: Metro | K4: Metro Outer | L4: Regional | N4: Metro | O4: Metro Outer | P4: Regional | R4: Metro | S4: Metro Outer | T4: Regional | V4: Metro | W4: Metro Outer | X4: Regional | Z4: Metro | AA4: Metro Outer | AB4: Regional
A5: Small | B5: ='Cost model'!M884 -> 7.5 | C5: ='Cost model'!M885 -> 13.5 | D5: ='Cost model'!M886 -> 17.5 | F5: ='Cost model'!M902 -> 13.5 | G5: ='Cost model'!M903 -> 16.5 | H5: ='Cost model'!M904 -> 24.5 | J5: ='Cost model'!M920 -> 16.5 | K5: ='Cost model'!M921 -> 24.5 | L5: ='Cost model'!M922 -> 35 | N5: ='Cost model'!M938 -> 16.5 | O5: ='Cost model'!M939 -> 17.5 | P5: ='Cost model'!M940 -> 23.5 | R5: ='Cost model'!M956 -> 15.5 | S5: ='Cost model'!M957 -> 18.5 | T5: ='Cost model'!M958 -> 24.5 | V5: ='Cost model'!M974 -> 22.5 | W5: ='Cost model'!M975 -> 22.5 | X5: ='Cost model'!M976 -> 27.5 | Z5: ='Cost model'!M992 -> 11.5 | AA5: ='Cost model'!M993 -> 15.5 | AB5: ='Cost model'!M994 -> 18.5
A6: Medium | B6: ='Cost model'!M887 -> 21.5 | C6: ='Cost model'!M888 -> 50 | D6: ='Cost model'!M889 -> 60 | F6: ='Cost model'!M905 -> 50 | G6: ='Cost model'!M906 -> 55 | H6: ='Cost model'!M907 -> 70 | J6: ='Cost model'!M923 -> 65 | K6: ='Cost model'!M924 -> 70 | L6: ='Cost model'!M925 -> 80 | N6: ='Cost model'!M941 -> 70 | O6: ='Cost model'!M942 -> 70 | P6: ='Cost model'!M943 -> 75 | R6: ='Cost model'!M959 -> 55 | S6: ='Cost model'!M960 -> 65 | T6: ='Cost model'!M961 -> 75 | V6: ='Cost model'!M977 -> 85 | W6: ='Cost model'!M978 -> 85 | X6: ='Cost model'!M979 -> 85 | Z6: ='Cost model'!M995 -> 45 | AA6: ='Cost model'!M996 -> 50 | AB6: ='Cost model'!M997 -> 60
A7: Large | B7: ='Cost model'!M890 -> 45 | C7: ='Cost model'!M891 -> 75 | D7: ='Cost model'!M892 -> 130 | F7: ='Cost model'!M908 -> 85 | G7: ='Cost model'!M909 -> 105 | H7: ='Cost model'!M910 -> 145 | J7: ='Cost model'!M926 -> 105 | K7: ='Cost model'!M927 -> 120 | L7: ='Cost model'!M928 -> 155 | N7: ='Cost model'!M944 -> 95 | O7: ='Cost model'!M945 -> 110 | P7: ='Cost model'!M946 -> 145 | R7: ='Cost model'!M962 -> 120 | S7: ='Cost model'!M963 -> 120 | T7: ='Cost model'!M964 -> 150 | V7: ='Cost model'!M980 -> 115 | W7: ='Cost model'!M981 -> 130 | X7: ='Cost model'!M982 -> 175 | Z7: ='Cost model'!M998 -> 80 | AA7: ='Cost model'!M999 -> 90 | AB7: ='Cost model'!M1000 -> 120
A8: XL | B8: ='Cost model'!M893 -> 135 | C8: ='Cost model'!M894 -> 135 | D8: ='Cost model'!M895 -> 320 | F8: ='Cost model'!M911 -> 155 | G8: ='Cost model'!M912 -> 180 | H8: ='Cost model'!M913 -> 220 | J8: ='Cost model'!M929 -> 180 | K8: ='Cost model'!M930 -> 215 | L8: ='Cost model'!M931 -> 260 | N8: ='Cost model'!M947 -> 165 | O8: ='Cost model'!M948 -> 200 | P8: ='Cost model'!M949 -> 240 | R8: ='Cost model'!M965 -> 170 | S8: ='Cost model'!M966 -> 205 | T8: ='Cost model'!M967 -> 240 | V8: ='Cost model'!M983 -> 195 | W8: ='Cost model'!M984 -> 235 | X8: ='Cost model'!M985 -> 285 | Z8: ='Cost model'!M1001 -> 135 | AA8: ='Cost model'!M1002 -> 160 | AB8: ='Cost model'!M1003 -> 195
A9: XXL | B9: ='Cost model'!M896 -> 135 | C9: ='Cost model'!M897 -> 160 | D9: ='Cost model'!M898 -> 320 | F9: ='Cost model'!M914 -> 185 | G9: ='Cost model'!M915 -> 285 | H9: ='Cost model'!M916 -> 340 | J9: ='Cost model'!M932 -> 230 | K9: ='Cost model'!M933 -> 345 | L9: ='Cost model'!M934 -> 410 | N9: ='Cost model'!M950 -> 210 | O9: ='Cost model'!M951 -> 315 | P9: ='Cost model'!M952 -> 375 | R9: ='Cost model'!M968 -> 215 | S9: ='Cost model'!M969 -> 320 | T9: ='Cost model'!M970 -> 380 | V9: ='Cost model'!M986 -> 250 | W9: ='Cost model'!M987 -> 375 | X9: ='Cost model'!M988 -> 445 | Z9: ='Cost model'!M1004 -> 170 | AA9: ='Cost model'!M1005 -> 255 | AB9: ='Cost model'!M1006 -> 300
A10: Bulky | B10: ='Cost model'!M899 -> 135 | C10: ='Cost model'!M900 -> 215 | D10: ='Cost model'!M901 -> 330 | F10: ='Cost model'!M917 -> 265 | G10: ='Cost model'!M918 -> 410 | H10: ='Cost model'!M919 -> 480 | J10: ='Cost model'!M935 -> 320 | K10: ='Cost model'!M936 -> 495 | L10: ='Cost model'!M937 -> 580 | N10: ='Cost model'!M953 -> 290 | O10: ='Cost model'!M954 -> 445 | P10: ='Cost model'!M955 -> 525 | R10: ='Cost model'!M971 -> 295 | S10: ='Cost model'!M972 -> 460 | T10: ='Cost model'!M973 -> 535 | V10: ='Cost model'!M989 -> 345 | W10: ='Cost model'!M990 -> 535 | X10: ='Cost model'!M991 -> 625 | Z10: ='Cost model'!M1007 -> 235 | AA10: ='Cost model'!M1008 -> 370 | AB10: ='Cost model'!M1009 -> 430
A12: Priority | B12: From WA | F12: From SA | J12: From VIC | N12: From NSW | R12: From QLD | V12: From ACT | Z12: From TAS
A13: Freight Size | B13: Metro | C13: Metro Outer | D13: Regional | F13: Metro | G13: Metro Outer | H13: Regional | J13: Metro | K13: Metro Outer | L13: Regional | N13: Metro | O13: Metro Outer | P13: Regional | R13: Metro | S13: Metro Outer | T13: Regional | V13: Metro | W13: Metro Outer | X13: Regional | Z13: Metro | AA13: Metro Outer | AB13: Regional
A14: Small | B14: ='Cost model'!N884 -> 12.5 | C14: ='Cost model'!N885 -> 18.5 | D14: ='Cost model'!N886 -> 23.5 | F14: ='Cost model'!N902 -> 18.5 | G14: ='Cost model'!N903 -> 22.5 | H14: ='Cost model'!N904 -> 35 | J14: ='Cost model'!N920 -> 22.5 | K14: ='Cost model'!N921 -> 35 | L14: ='Cost model'!N922 -> 50 | N14: ='Cost model'!N938 -> 22.5 | O14: ='Cost model'!N939 -> 23.5 | P14: ='Cost model'!N940 -> 35 | R14: ='Cost model'!N956 -> 21.5 | S14: ='Cost model'!N957 -> 25.5 | T14: ='Cost model'!N958 -> 35 | V14: ='Cost model'!N974 -> 35 | W14: ='Cost model'!N975 -> 35 | X14: ='Cost model'!N976 -> 40 | Z14: ='Cost model'!N992 -> 16.5 | AA14: ='Cost model'!N993 -> 21.5 | AB14: ='Cost model'!N994 -> 25.5
A15: Medium | B15: ='Cost model'!N887 -> 27.5 | C15: ='Cost model'!N888 -> 65 | D15: ='Cost model'!N889 -> 80 | F15: ='Cost model'!N905 -> 65 | G15: ='Cost model'!N906 -> 70 | H15: ='Cost model'!N907 -> 90 | J15: ='Cost model'!N923 -> 85 | K15: ='Cost model'!N924 -> 90 | L15: ='Cost model'!N925 -> 105 | N15: ='Cost model'!N941 -> 90 | O15: ='Cost model'!N942 -> 90 | P15: ='Cost model'!N943 -> 95 | R15: ='Cost model'!N959 -> 70 | S15: ='Cost model'!N960 -> 85 | T15: ='Cost model'!N961 -> 95 | V15: ='Cost model'!N977 -> 110 | W15: ='Cost model'!N978 -> 110 | X15: ='Cost model'!N979 -> 110 | Z15: ='Cost model'!N995 -> 60 | AA15: ='Cost model'!N996 -> 65 | AB15: ='Cost model'!N997 -> 80
A16: Large | B16: ='Cost model'!N890 -> 65 | C16: ='Cost model'!N891 -> 105 | D16: ='Cost model'!N892 -> 180 | F16: ='Cost model'!N908 -> 115 | G16: ='Cost model'!N909 -> 145 | H16: ='Cost model'!N910 -> 200 | J16: ='Cost model'!N926 -> 145 | K16: ='Cost model'!N927 -> 165 | L16: ='Cost model'!N928 -> 210 | N16: ='Cost model'!N944 -> 130 | O16: ='Cost model'!N945 -> 150 | P16: ='Cost model'!N946 -> 200 | R16: ='Cost model'!N962 -> 165 | S16: ='Cost model'!N963 -> 165 | T16: ='Cost model'!N964 -> 205 | V16: ='Cost model'!N980 -> 160 | W16: ='Cost model'!N981 -> 180 | X16: ='Cost model'!N982 -> 240 | Z16: ='Cost model'!N998 -> 110 | AA16: ='Cost model'!N999 -> 125 | AB16: ='Cost model'!N1000 -> 165
A17: XL | B17: ='Cost model'!N893 -> 165 | C17: ='Cost model'!N894 -> 165 | D17: ='Cost model'!N895 -> 385 | F17: ='Cost model'!N911 -> 190 | G17: ='Cost model'!N912 -> 220 | H17: ='Cost model'!N913 -> 265 | J17: ='Cost model'!N929 -> 220 | K17: ='Cost model'!N930 -> 260 | L17: ='Cost model'!N931 -> 315 | N17: ='Cost model'!N947 -> 200 | O17: ='Cost model'!N948 -> 240 | P17: ='Cost model'!N949 -> 290 | R17: ='Cost model'!N965 -> 205 | S17: ='Cost model'!N966 -> 250 | T17: ='Cost model'!N967 -> 290 | V17: ='Cost model'!N983 -> 235 | W17: ='Cost model'!N984 -> 285 | X17: ='Cost model'!N985 -> 345 | Z17: ='Cost model'!N1001 -> 165 | AA17: ='Cost model'!N1002 -> 195 | AB17: ='Cost model'!N1003 -> 235
A18: XXL | B18: ='Cost model'!N896 -> 165 | C18: ='Cost model'!N897 -> 195 | D18: ='Cost model'!N898 -> 385 | F18: ='Cost model'!N914 -> 225 | G18: ='Cost model'!N915 -> 285 | H18: ='Cost model'!N916 -> 340 | J18: ='Cost model'!N932 -> 280 | K18: ='Cost model'!N933 -> 345 | L18: ='Cost model'!N934 -> 410 | N18: ='Cost model'!N950 -> 255 | O18: ='Cost model'!N951 -> 315 | P18: ='Cost model'!N952 -> 375 | R18: ='Cost model'!N968 -> 260 | S18: ='Cost model'!N969 -> 320 | T18: ='Cost model'!N970 -> 380 | V18: ='Cost model'!N986 -> 300 | W18: ='Cost model'!N987 -> 375 | X18: ='Cost model'!N988 -> 445 | Z18: ='Cost model'!N1004 -> 205 | AA18: ='Cost model'!N1005 -> 255 | AB18: ='Cost model'!N1006 -> 300
A19: Bulky | B19: ='Cost model'!N899 -> 165 | C19: ='Cost model'!N900 -> 260 | D19: ='Cost model'!N901 -> 400 | F19: ='Cost model'!N917 -> 320 | G19: ='Cost model'!N918 -> 410 | H19: ='Cost model'!N919 -> 480 | J19: ='Cost model'!N935 -> 385 | K19: ='Cost model'!N936 -> 495 | L19: ='Cost model'!N937 -> 580 | N19: ='Cost model'!N953 -> 350 | O19: ='Cost model'!N954 -> 445 | P19: ='Cost model'!N955 -> 525 | R19: ='Cost model'!N971 -> 355 | S19: ='Cost model'!N972 -> 460 | T19: ='Cost model'!N973 -> 535 | V19: ='Cost model'!N989 -> 415 | W19: ='Cost model'!N990 -> 535 | X19: ='Cost model'!N991 -> 625 | Z19: ='Cost model'!N1007 -> 285 | AA19: ='Cost model'!N1008 -> 370 | AB19: ='Cost model'!N1009 -> 430
A21: Delivery time frames for WA Orders
A23: Standard | B23: From WA | F23: From SA | J23: From VIC | N23: From NSW | R23: From QLD | V23: From ACT | Z23: From TAS
A24: Freight Size | B24: Metro | C24: Metro Outer | D24: Regional | F24: Metro | G24: Metro Outer | H24: Regional | J24: Metro | K24: Metro Outer | L24: Regional | N24: Metro | O24: Metro Outer | P24: Regional | R24: Metro | S24: Metro Outer | T24: Regional | V24: Metro | W24: Metro Outer | X24: Regional | Z24: Metro | AA24: Metro Outer | AB24: Regional
A25: Small | B25: 1-3 Days | C25: 1-3 Days | D25: 2-5 Days | F25: 2-5 Days | G25: 2-5 Days | H25: 3-7 Days | J25: 2-5 Days | K25: 2-5 Days | L25: 2-5 Days | N25: 7-14 Days | O25: 7-14 Days | P25: 7-14 Days | R25: 7-14 Days | S25: 7-14 Days | T25: 7-14 Days | V25: 7-14 Days | W25: 7-14 Days | X25: 7-14 Days | Z25: 2-5 Days | AA25: 2-5 Days | AB25: 2-5 Days
A26: Medium | B26: 1-3 Days | C26: 1-3 Days | D26: 2-5 Days | F26: 2-5 Days | G26: 2-5 Days | H26: 3-7 Days | J26: 2-5 Days | K26: 2-5 Days | L26: 2-5 Days | N26: 7-14 Days | O26: 7-14 Days | P26: 7-14 Days | R26: 7-14 Days | S26: 7-14 Days | T26: 7-14 Days | V26: 7-14 Days | W26: 7-14 Days | X26: 7-14 Days | Z26: 2-5 Days | AA26: 2-5 Days | AB26: 2-5 Days
A27: Large | B27: 1-3 Days | C27: 1-3 Days | D27: 3-7 Days | F27: 3-7 Days | G27: 3-7 Days | H27: 5-10 Days | J27: 3-7 Days | K27: 3-7 Days | L27: 5-10 Days | N27: 7-14 Days | O27: 7-14 Days | P27: 7-14 Days | R27: 7-14 Days | S27: 7-14 Days | T27: 7-14 Days | V27: 7-14 Days | W27: 7-14 Days | X27: 7-14 Days | Z27: 3-7 Days | AA27: 3-7 Days | AB27: 5-10 Days
A28: XL | B28: 1-3 Days | C28: 1-3 Days | D28: 5-10 Days | F28: 5-10 Days | G28: 5-10 Days | H28: 5-10 Days | J28: 5-10 Days | K28: 5-10 Days | L28: 5-10 Days | N28: 7-14 Days | O28: 7-14 Days | P28: 7-14 Days | R28: 7-14 Days | S28: 7-14 Days | T28: 7-14 Days | V28: 7-14 Days | W28: 7-14 Days | X28: 7-14 Days | Z28: 5-10 Days | AA28: 5-10 Days | AB28: 5-10 Days
A29: XXL | B29: 1-3 Days | C29: 1-3 Days | D29: 5-10 Days | F29: 5-10 Days | G29: 5-10 Days | H29: 5-10 Days | J29: 5-10 Days | K29: 5-10 Days | L29: 5-10 Days | N29: 7-14 Days | O29: 7-14 Days | P29: 7-14 Days | R29: 7-14 Days | S29: 7-14 Days | T29: 7-14 Days | V29: 7-14 Days | W29: 7-14 Days | X29: 7-14 Days | Z29: 5-10 Days | AA29: 5-10 Days | AB29: 5-10 Days
A30: Bulky | B30: 1-3 Days | C30: 1-3 Days | D30: 5-10 Days | F30: 5-10 Days | G30: 5-10 Days | H30: 5-10 Days | J30: 5-10 Days | K30: 5-10 Days | L30: 5-10 Days | N30: 7-14 Days | O30: 7-14 Days | P30: 7-14 Days | R30: 7-14 Days | S30: 7-14 Days | T30: 7-14 Days | V30: 7-14 Days | W30: 7-14 Days | X30: 7-14 Days | Z30: 5-10 Days | AA30: 5-10 Days | AB30: 5-10 Days
A32: Priority | B32: From WA | F32: From SA | J32: From VIC | N32: From NSW | R32: From QLD | V32: From ACT | Z32: From TAS
A33: Freight Size | B33: Metro | C33: Metro Outer | D33: Regional | F33: Metro | G33: Metro Outer | H33: Regional | J33: Metro | K33: Metro Outer | L33: Regional | N33: Metro | O33: Metro Outer | P33: Regional | R33: Metro | S33: Metro Outer | T33: Regional | V33: Metro | W33: Metro Outer | X33: Regional | Z33: Metro | AA33: Metro Outer | AB33: Regional
A34: Small | B34: 1-2 Days | C34: 1-2 Days | D34: 1-3 Days | F34: 1-2 Days | G34: 1-2 Days | H34: 2-5 Days | J34: 1-2 Days | K34: 1-2 Days | L34: 2-5 Days | N34: 1-2 Days | O34: 1-2 Days | P34: 2-5 Days | R34: 1-2 Days | S34: 1-2 Days | T34: 2-5 Days | V34: 1-2 Days | W34: 1-2 Days | X34: 2-5 Days | Z34: 1-2 Days | AA34: 1-2 Days | AB34: 2-5 Days
A35: Medium | B35: 1-2 Days | C35: 1-2 Days | D35: 1-3 Days | F35: 1-2 Days | G35: 1-2 Days | H35: 2-5 Days | J35: 1-2 Days | K35: 1-2 Days | L35: 2-5 Days | N35: 1-2 Days | O35: 1-2 Days | P35: 2-5 Days | R35: 1-2 Days | S35: 1-2 Days | T35: 2-5 Days | V35: 1-2 Days | W35: 1-2 Days | X35: 2-5 Days | Z35: 1-2 Days | AA35: 1-2 Days | AB35: 2-5 Days
A36: Large | B36: 1-2 Days | C36: 1-2 Days | D36: 2-7 Days | F36: 2-5 Days | G36: 2-5 Days | H36: 5-10 Days | J36: 2-5 Days | K36: 2-5 Days | L36: 5-10 Days | N36: 7-14 Days | O36: 7-14 Days | P36: 7-14 Days | R36: 7-14 Days | S36: 7-14 Days | T36: 7-14 Days | V36: 7-14 Days | W36: 7-14 Days | X36: 7-14 Days | Z36: 2-5 Days | AA36: 2-5 Days | AB36: 5-10 Days
A37: XL | B37: 1-2 Days | C37: 1-2 Days | D37: 2-7 Days | F37: 3-7 Days | G37: 3-7 Days | H37: 5-10 Days | J37: 3-7 Days | K37: 3-7 Days | L37: 5-10 Days | N37: 7-14 Days | O37: 7-14 Days | P37: 7-14 Days | R37: 7-14 Days | S37: 7-14 Days | T37: 7-14 Days | V37: 7-14 Days | W37: 7-14 Days | X37: 7-14 Days | Z37: 3-7 Days | AA37: 3-7 Days | AB37: 5-10 Days
A38: XXL | B38: 1-2 Days | C38: 1-2 Days | D38: 2-7 Days | F38: 3-7 Days | G38: 3-7 Days | H38: 5-10 Days | J38: 3-7 Days | K38: 3-7 Days | L38: 5-10 Days | N38: 7-14 Days | O38: 7-14 Days | P38: 7-14 Days | R38: 7-14 Days | S38: 7-14 Days | T38: 7-14 Days | V38: 7-14 Days | W38: 7-14 Days | X38: 7-14 Days | Z38: 3-7 Days | AA38: 3-7 Days | AB38: 5-10 Days
A39: Bulky | B39: 1-2 Days | C39: 1-2 Days | D39: 2-7 Days | F39: 3-7 Days | G39: 3-7 Days | H39: 5-10 Days | J39: 3-7 Days | K39: 3-7 Days | L39: 5-10 Days | N39: 7-14 Days | O39: 7-14 Days | P39: 7-14 Days | R39: 7-14 Days | S39: 7-14 Days | T39: 7-14 Days | V39: 7-14 Days | W39: 7-14 Days | X39: 7-14 Days | Z39: 3-7 Days | AA39: 3-7 Days | AB39: 5-10 Days

Sheet Cost model
A1: Key | B1: Delivering to | C1: Ships from | D1: Size | E1: Zone | F1: Expected cost incl. GST | G1: Orders in this cell | H1: Orders on this lane | I1: Lane factor | J1: 2025 Standard | K1: 2025 Priority | L1: Priority ratio | M1: New Standard | N1: New Priority | O1: Standard change | P1: Rule
A2: ACT|QLD|Small|Metro | B2: ACT | C2: QLD | D2: Small | E2: Metro | F2: 13.93 | G2: 7 | H2: 19 | I2: 0.94 | J2: 14.5 | K2: 19.5 | L2: =INDEX('Read me'!$B$10:$B$15,1) -> 1.34 | M2: =IF(F2*(1+'Read me'!$B$5)<='Read me'!$B$7,CEILING(F2*(1+'Read me'!$B$5)+0.5,1)-0.5,CEILING(F2*(1+'Read me'!$B$5),5)) -> 14.5 | N2: =IF(MAX(M2*L2,M2+'Read me'!$B$6)<='Read me'!$B$7,CEILING(MAX(M2*L2,M2+'Read me'!$B$6)+0.5,1)-0.5,CEILING(MAX(M2*L2,M2+'Read me'!$B$6),5)) -> 19.5 | O2: =IF(ISNUMBER(J2),M2-J2,"new") -> 0
A3: ACT|QLD|Small|Metro Outer | B3: ACT | C3: QLD | D3: Small | E3: Metro Outer | F3: 14.35 | G3: 0 | H3: 19 | I3: 0.94 | J3: 14.5 | K3: 19.5 | L3: =INDEX('Read me'!$B$10:$B$15,1) -> 1.34 | M3: =IF(F3*(1+'Read me'!$B$5)<='Read me'!$B$7,CEILING(F3*(1+'Read me'!$B$5)+0.5,1)-0.5,CEILING(F3*(1+'Read me'!$B$5),5)) -> 14.5 | N3: =IF(MAX(M3*L3,M3+'Read me'!$B$6)<='Read me'!$B$7,CEILING(MAX(M3*L3,M3+'Read me'!$B$6)+0.5,1)-0.5,CEILING(MAX(M3*L3,M3+'Read me'!$B$6),5)) -> 19.5 | O3: =IF(ISNUMBER(J3),M3-J3,"new") -> 0
A4: ACT|QLD|Small|Regional | B4: ACT | C4: QLD | D4: Small | E4: Regional | F4: 18.93 | G4: 0 | H4: 19 | I4: 0.94 | J4: 17.5 | K4: 29.5 | L4: =INDEX('Read me'!$B$10:$B$15,1) -> 1.34 | M4: =IF(F4*(1+'Read me'!$B$5)<='Read me'!$B$7,CEILING(F4*(1+'Read me'!$B$5)+0.5,1)-0.5,CEILING(F4*(1+'Read me'!$B$5),5)) -> 19.5 | N4: =IF(MAX(M4*L4,M4+'Read me'!$B$6)<='Read me'!$B$7,CEILING(MAX(M4*L4,M4+'Read me'!$B$6)+0.5,1)-0.5,CEILING(MAX(M4*L4,M4+'Read me'!$B$6),5)) -> 26.5 | O4: =IF(ISNUMBER(J4),M4-J4,"new") -> 2
A5: ACT|QLD|Medium|Metro | B5: ACT | C5: QLD | D5: Medium | E5: Metro | F5: 45.11 | G5: 10 | H5: 19 | I5: 0.94 | J5: 19.5 | K5: 24.5 | L5: =INDEX('Read me'!$B$10:$B$15,2) -> 1.26 | M5: =IF(F5*(1+'Read me'!$B$5)<='Read me'!$B$7,CEILING(F5*(1+'Read me'!$B$5)+0.5,1)-0.5,CEILING(F5*(1+'Read me'!$B$5),5)) -> 50 | N5: =IF(MAX(M5*L5,M5+'Read me'!$B$6)<='Read me'!$B$7,CEILING(MAX(M5*L5,M5+'Read me'!$B$6)+0.5,1)-0.5,CEILING(MAX(M5*L5,M5+'Read me'!$B$6),5)) -> 65 | O5: =IF(ISNUMBER(J5),M5-J5,"new") -> 30.5
A6: ACT|QLD|Medium|Metro Outer | B6: ACT | C6: QLD | D6: Medium | E6: Metro Outer | F6: 49.5 | G6: 0 | H6: 19 | I6: 0.94 | J6: 19.5 | K6: 24.5 | L6: =INDEX('Read me'!$B$10:$B$15,2) -> 1.26 | M6: =IF(F6*(1+'Read me'!$B$5)<='Read me'!$B$7,CEILING(F6*(1+'Read me'!$B$5)+0.5,1)-0.5,CEILING(F6*(1+'Read me'!$B$5),5)) -> 50 | N6: =IF(MAX(M6*L6,M6+'Read me'!$B$6)<='Read me'!$B$7,CEILING(MAX(M6*L6,M6+'Read me'!$B$6)+0.5,1)-0.5,CEILING(MAX(M6*L6,M6+'Read me'!$B$6),5)) -> 65 | O6: =IF(ISNUMBER(J6),M6-J6,"new") -> 30.5
A7: ACT|QLD|Medium|Regional | B7: ACT | C7: QLD | D7: Medium | E7: Regional | F7: 57.79 | G7: 0 | H7: 19 | I7: 0.94 | J7: 19.5 | K7: 34.5 | L7: =INDEX('Read me'!$B$10:$B$15,2) -> 1.26 | M7: =IF(F7*(1+'Read me'!$B$5)<='Read me'!$B$7,CEILING(F7*(1+'Read me'!$B$5)+0.5,1)-0.5,CEILING(F7*(1+'Read me'!$B$5),5)) -> 60 | N7: =IF(MAX(M7*L7,M7+'Read me'!$B$6)<='Read me'!$B$7,CEILING(MAX(M7*L7,M7+'Read me'!$B$6)+0.5,1)-0.5,CEILING(MAX(M7*L7,M7+'Read me'!$B$6),5)) -> 80 | O7: =IF(ISNUMBER(J7),M7-J7,"new") -> 40.5
A8: ACT|QLD|Large|Metro | B8: ACT | C8: QLD | D8: Large | E8: Metro | F8: 76.91 | G8: 1 | H8: 19 | I8: 0.94 | J8: 24.5 | K8: 75 | L8: =INDEX('Read me'!$B$10:$B$15,3) -> 1.35 | M8: =IF(F8*(1+'Read me'!$B$5)<='Read me'!$B$7,CEILING(F8*(1+'Read me'!$B$5)+0.5,1)-0.5,CEILING(F8*(1+'Read me'!$B$5),5)) -> 80 | N8: =IF(MAX(M8*L8,M8+'Read me'!$B$6)<='Read me'!$B$7,CEILING(MAX(M8*L8,M8+'Read me'!$B$6)+0.5,1)-0.5,CEILING(MAX(M8*L8,M8+'Read me'!$B$6),5)) -> 110 | O8: =IF(ISNUMBER(J8),M8-J8,"new") -> 55.5
A9: ACT|QLD|Large|Metro Outer | B9: ACT | C9: QLD | D9: Large | E9: Metro Outer | F9: 87.75 | G9: 0 | H9: 19 | I9: 0.94 | J9: 24.5 | K9: 75 | L9: =INDEX('Read me'!$B$10:$B$15,3) -> 1.35 | M9: =IF(F9*(1+'Read me'!$B$5)<='Read me'!$B$7,CEILING(F9*(1+'Read me'!$B$5)+0.5,1)-0.5,CEILING(F9*(1+'Read me'!$B$5),5)) -> 90 | N9: =IF(MAX(M9*L9,M9+'Read me'!$B$6)<='Read me'!$B$7,CEILING(MAX(M9*L9,M9+'Read me'!$B$6)+0.5,1)-0.5,CEILING(MAX(M9*L9,M9+'Read me'!$B$6),5)) -> 125 | O9: =IF(ISNUMBER(J9),M9-J9,"new") -> 65.5
A10: ACT|QLD|Large|Regional | B10: ACT | C10: QLD | D10: Large | E10: Regional | F10: 118.01 | G10: 0 | H10: 19 | I10: 0.94 | J10: 85 | K10: 125 | L10: =INDEX('Read me'!$B$10:$B$15,3) -> 1.35 | M10: =IF(F10*(1+'Read me'!$B$5)<='Read me'!$B$7,CEILING(F10*(1+'Read me'!$B$5)+0.5,1)-0.5,CEILING(F10*(1+'Read me'!$B$5),5)) -> 120 | N10: =IF(MAX(M10*L10,M10+'Read me'!$B$6)<='Read me'!$B$7,CEILING(MAX(M10*L10,M10+'Read me'!$B$6)+0.5,1)-0.5,CEILING(MAX(M10*L10,M10+'Read me'!$B$6),5)) -> 165 | O10: =IF(ISNUMBER(J10),M10-J10,"new") -> 35
A11: ACT|QLD|XL|Metro | B11: ACT | C11: QLD | D11: XL | E11: Metro | F11: 132.85 | G11: 1 | H11: 19 | I11: 0.94 | J11: 85 | K11: 125 | L11: =INDEX('Read me'!$B$10:$B$15,4) -> 1.2 | M11: =IF(F11*(1+'Read me'!$B$5)<='Read me'!$B$7,CEILING(F11*(1+'Read me'!$B$5)+0.5,1)-0.5,CEILING(F11*(1+'Read me'!$B$5),5)) -> 135 | N11: =IF(MAX(M11*L11,M11+'Read me'!$B$6)<='Read me'!$B$7,CEILING(MAX(M11*L11,M11+'Read me'!$B$6)+0.5,1)-0.5,CEILING(MAX(M11*L11,M11+'Read me'!$B$6),5)) -> 165 | O11: =IF(ISNUMBER(J11),M11-J11,"new") -> 50
A12: ACT|QLD|XL|Metro Outer | B12: ACT | C12: QLD | D12: XL | E12: Metro Outer | F12: 162.18 | G12: 0 | H12: 19 | I12: 0.94 | J12: 125 | K12: 125 | L12: =INDEX('Read me'!$B$10:$B$15,4) -> 1.2 | M12: =IF(F12*(1+'Read me'!$B$5)<='Read me'!$B$7,CEILING(F12*(1+'Read me'!$B$5)+0.5,1)-0.5,CEILING(F12*(1+'Read me'!$B$5),5)) -> 165 | N12: =IF(MAX(M12*L12,M12+'Read me'!$B$6)<='Read me'!$B$7,CEILING(MAX(M12*L12,M12+'Read me'!$B$6)+0.5,1)-0.5,CEILING(MAX(M12*L12,M12+'Read me'!$B$6),5)) -> 200 | O12: =IF(ISNUMBER(J12),M12-J12,"new") -> 40
A13: ACT|QLD|XL|Regional | B13: ACT | C13: QLD | D13: XL | E13: Regional | F13: 195.44 | G13: 0 | H13: 19 | I13: 0.94 | J13: 199 | K13: 175 | L13: =INDEX('Read me'!$B$10:$B$15,4) -> 1.2 | M13: =IF(F13*(1+'Read me'!$B$5)<='Read me'!$B$7,CEILING(F13*(1+'Read me'!$B$5)+0.5,1)-0.5,CEILING(F13*(1+'Read me'!$B$5),5)) -> 200 | N13: =IF(MAX(M13*L13,M13+'Read me'!$B$6)<='Read me'!$B$7,CEILING(MAX(M13*L13,M13+'Read me'!$B$6)+0.5,1)-0.5,CEILING(MAX(M13*L13,M13+'Read me'!$B$6),5)) -> 240 | O13: =IF(ISNUMBER(J13),M13-J13,"new") -> 1
A14: ACT|QLD|XXL|Metro | B14: ACT | C14: QLD | D14: XXL | E14: Metro | F14: 171.44 | G14: 0 | H14: 19 | I14: 0.94 | J14: 250 | K14: 300 | L14: =INDEX('Read me'!$B$10:$B$15,5) -> 1.2 | M14: =IF(F14*(1+'Read me'!$B$5)<='Read me'!$B$7,CEILING(F14*(1+'Read me'!$B$5)+0.5,1)-0.5,CEILING(F14*(1+'Read me'!$B$5),5)) -> 175 | N14: =IF(MAX(M14*L14,M14+'Read me'!$B$6)<='Read me'!$B$7,CEILING(MAX(M14*L14,M14+'Read me'!$B$6)+0.5,1)-0.5,CEILING(MAX(M14*L14,M14+'Read me'!$B$6),5)) -> 210 | O14: =IF(ISNUMBER(J14),M14-J14,"new") -> -75
A15: ACT|QLD|XXL|Metro Outer | B15: ACT | C15: QLD | D15: XXL | E15: Metro Outer | F15: 211.51 | G15: 0 | H15: 19 | I15: 0.94 | J15: 250 | K15: 300 | L15: =INDEX('Read me'!$B$10:$B$15,5) -> 1.2 | M15: =N15 -> 260 | N15: =IF(MAX((IF(F15*(1+'Read me'!$B$5)<='Read me'!$B$7,CEILING(F15*(1+'Read me'!$B$5)+0.5,1)-0.5,CEILING(F15*(1+'Read me'!$B$5),5)))*L15,(IF(F15*(1+'Read me'!$B$5)<='Read me'!$B$7,CEILING(F15*(1+'Read me'!$B$5)+0.5,1)-0.5,CEILING(F15*(1+'Read me'!$B$5),5)))+'Read me'!$B$6)<='Read me'!$B$7,CEILING(MAX((IF(F15*(1+'Read me'!$B$5)<='Read me'!$B$7,CEILING(F15*(1+'Read me'!$B$5)+0.5,1)-0.5,CEILING(F15*(1+'Read me'!$B$5),5)))*L15,(IF(F15*(1+'Read me'!$B$5)<='Read me'!$B$7,CEILING(F15*(1+'Read me'!$B$5)+0.5,1)-0.5,CEILING(F15*(1+'Read me'!$B$5),5)))+'Read me'!$B$6)+0.5,1)-0.5,CEILING(MAX((IF(F15*(1+'Read me'!$B$5)<='Read me'!$B$7,CEILING(F15*(1+'Read me'!$B$5)+0.5,1)-0.5,CEILING(F15*(1+'Read me'!$B$5),5)))*L15,(IF(F15*(1+'Read me'!$B$5)<='Read me'!$B$7,CEILING(F15*(1+'Read me'!$B$5)+0.5,1)-0.5,CEILING(F15*(1+'Read me'!$B$5),5)))+'Read me'!$B$6),5)) -> 260 | O15: =IF(ISNUMBER(J15),M15-J15,"new") -> 10 | P15: One rate: interstate XXL/Bulky to Metro Outer or Regional is charged at the Priority price for both services
A16: ACT|QLD|XXL|Regional | B16: ACT | C16: QLD | D16: XXL | E16: Regional | F16: 254.14 | G16: 0 | H16: 19 | I16: 0.94 | J16: 300 | K16: 400 | L16: =INDEX('Read me'!$B$10:$B$15,5) -> 1.2 | M16: =N16 -> 310 | N16: =IF(MAX((IF(F16*(1+'Read me'!$B$5)<='Read me'!$B$7,CEILING(F16*(1+'Read me'!$B$5)+0.5,1)-0.5,CEILING(F16*(1+'Read me'!$B$5),5)))*L16,(IF(F16*(1+'Read me'!$B$5)<='Read me'!$B$7,CEILING(F16*(1+'Read me'!$B$5)+0.5,1)-0.5,CEILING(F16*(1+'Read me'!$B$5),5)))+'Read me'!$B$6)<='Read me'!$B$7,CEILING(MAX((IF(F16*(1+'Read me'!$B$5)<='Read me'!$B$7,CEILING(F16*(1+'Read me'!$B$5)+0.5,1)-0.5,CEILING(F16*(1+'Read me'!$B$5),5)))*L16,(IF(F16*(1+'Read me'!$B$5)<='Read me'!$B$7,CEILING(F16*(1+'Read me'!$B$5)+0.5,1)-0.5,CEILING(F16*(1+'Read me'!$B$5),5)))+'Read me'!$B$6)+0.5,1)-0.5,CEILING(MAX((IF(F16*(1+'Read me'!$B$5)<='Read me'!$B$7,CEILING(F16*(1+'Read me'!$B$5)+0.5,1)-0.5,CEILING(F16*(1+'Read me'!$B$5),5)))*L16,(IF(F16*(1+'Read me'!$B$5)<='Read me'!$B$7,CEILING(F16*(1+'Read me'!$B$5)+0.5,1)-0.5,CEILING(F16*(1+'Read me'!$B$5),5)))+'Read me'!$B$6),5)) -> 310 | O16: =IF(ISNUMBER(J16),M16-J16,"new") -> 10 | P16: One rate: interstate XXL/Bulky to Metro Outer or Regional is charged at the Priority price for both services
A17: ACT|QLD|Bulky|Metro | B17: ACT | C17: QLD | D17: Bulky | E17: Metro | F17: 238.05 | G17: 0 | H17: 19 | I17: 0.94 | L17: =INDEX('Read me'!$B$10:$B$15,6) -> 1.2 | M17: =IF(F17*(1+'Read me'!$B$5)<='Read me'!$B$7,CEILING(F17*(1+'Read me'!$B$5)+0.5,1)-0.5,CEILING(F17*(1+'Read me'!$B$5),5)) -> 240 | N17: =IF(MAX(M17*L17,M17+'Read me'!$B$6)<='Read me'!$B$7,CEILING(MAX(M17*L17,M17+'Read me'!$B$6)+0.5,1)-0.5,CEILING(MAX(M17*L17,M17+'Read me'!$B$6),5)) -> 290 | O17: =IF(ISNUMBER(J17),M17-J17,"new") -> new
A18: ACT|QLD|Bulky|Metro Outer | B18: ACT | C18: QLD | D18: Bulky | E18: Metro Outer | F18: 305.89 | G18: 0 | H18: 19 | I18: 0.94 | L18: =INDEX('Read me'!$B$10:$B$15,6) -> 1.2 | M18: =N18 -> 375 | N18: =IF(MAX((IF(F18*(1+'Read me'!$B$5)<='Read me'!$B$7,CEILING(F18*(1+'Read me'!$B$5)+0.5,1)-0.5,CEILING(F18*(1+'Read me'!$B$5),5)))*L18,(IF(F18*(1+'Read me'!$B$5)<='Read me'!$B$7,CEILING(F18*(1+'Read me'!$B$5)+0.5,1)-0.5,CEILING(F18*(1+'Read me'!$B$5),5)))+'Read me'!$B$6)<='Read me'!$B$7,CEILING(MAX((IF(F18*(1+'Read me'!$B$5)<='Read me'!$B$7,CEILING(F18*(1+'Read me'!$B$5)+0.5,1)-0.5,CEILING(F18*(1+'Read me'!$B$5),5)))*L18,(IF(F18*(1+'Read me'!$B$5)<='Read me'!$B$7,CEILING(F18*(1+'Read me'!$B$5)+0.5,1)-0.5,CEILING(F18*(1+'Read me'!$B$5),5)))+'Read me'!$B$6)+0.5,1)-0.5,CEILING(MAX((IF(F18*(1+'Read me'!$B$5)<='Read me'!$B$7,CEILING(F18*(1+'Read me'!$B$5)+0.5,1)-0.5,CEILING(F18*(1+'Read me'!$B$5),5)))*L18,(IF(F18*(1+'Read me'!$B$5)<='Read me'!$B$7,CEILING(F18*(1+'Read me'!$B$5)+0.5,1)-0.5,CEILING(F18*(1+'Read me'!$B$5),5)))+'Read me'!$B$6),5)) -> 375 | O18: =IF(ISNUMBER(J18),M18-J18,"new") -> new | P18: One rate: interstate XXL/Bulky to Metro Outer or Regional is charged at the Priority price for both services
A19: ACT|QLD|Bulky|Regional | B19: ACT | C19: QLD | D19: Bulky | E19: Regional | F19: 359.53 | G19: 0 | H19: 19 | I19: 0.94 | L19: =INDEX('Read me'!$B$10:$B$15,6) -> 1.2 | M19: =N19 -> 435 | N19: =IF(MAX((IF(F19*(1+'Read me'!$B$5)<='Read me'!$B$7,CEILING(F19*(1+'Read me'!$B$5)+0.5,1)-0.5,CEILING(F19*(1+'Read me'!$B$5),5)))*L19,(IF(F19*(1+'Read me'!$B$5)<='Read me'!$B$7,CEILING(F19*(1+'Read me'!$B$5)+0.5,1)-0.5,CEILING(F19*(1+'Read me'!$B$5),5)))+'Read me'!$B$6)<='Read me'!$B$7,CEILING(MAX((IF(F19*(1+'Read me'!$B$5)<='Read me'!$B$7,CEILING(F19*(1+'Read me'!$B$5)+0.5,1)-0.5,CEILING(F19*(1+'Read me'!$B$5),5)))*L19,(IF(F19*(1+'Read me'!$B$5)<='Read me'!$B$7,CEILING(F19*(1+'Read me'!$B$5)+0.5,1)-0.5,CEILING(F19*(1+'Read me'!$B$5),5)))+'Read me'!$B$6)+0.5,1)-0.5,CEILING(MAX((IF(F19*(1+'Read me'!$B$5)<='Read me'!$B$7,CEILING(F19*(1+'Read me'!$B$5)+0.5,1)-0.5,CEILING(F19*(1+'Read me'!$B$5),5)))*L19,(IF(F19*(1+'Read me'!$B$5)<='Read me'!$B$7,CEILING(F19*(1+'Read me'!$B$5)+0.5,1)-0.5,CEILING(F19*(1+'Read me'!$B$5),5)))+'Read me'!$B$6),5)) -> 435 | O19: =IF(ISNUMBER(J19),M19-J19,"new") -> new | P19: One rate: interstate XXL/Bulky to Metro Outer or Regional is charged at the Priority price for both services
A20: ACT|VIC|Small|Metro | B20: ACT | C20: VIC | D20: Small | E20: Metro | F20: 13.44 | G20: 7 | H20: 13 | I20: 0.97 | J20: 14.5 | K20: 19.5 | L20: =INDEX('Read me'!$B$10:$B$15,1) -> 1.34 | M20: =IF(F20*(1+'Read me'!$B$5)<='Read me'!$B$7,CEILING(F20*(1+'Read me'!$B$5)+0.5,1)-0.5,CEILING(F20*(1+'Read me'!$B$5),5)) -> 13.5 | N20: =IF(MAX(M20*L20,M20+'Read me'!$B$6)<='Read me'!$B$7,CEILING(MAX(M20*L20,M20+'Read me'!$B$6)+0.5,1)-0.5,CEILING(MAX(M20*L20,M20+'Read me'!$B$6),5)) -> 18.5 | O20: =IF(ISNUMBER(J20),M20-J20,"new") -> -1
A21: ACT|VIC|Small|Metro Outer | B21: ACT | C21: VIC | D21: Small | E21: Metro Outer | F21: 14.76 | G21: 0 | H21: 13 | I21: 0.97 | J21: 14.5 | K21: 19.5 | L21: =INDEX('Read me'!$B$10:$B$15,1) -> 1.34 | M21: =IF(F21*(1+'Read me'!$B$5)<='Read me'!$B$7,CEILING(F21*(1+'Read me'!$B$5)+0.5,1)-0.5,CEILING(F21*(1+'Read me'!$B$5),5)) -> 15.5 | N21: =IF(MAX(M21*L21,M21+'Read me'!$B$6)<='Read me'!$B$7,CEILING(MAX(M21*L21,M21+'Read me'!$B$6)+0.5,1)-0.5,CEILING(MAX(M21*L21,M21+'Read me'!$B$6),5)) -> 21.5 | O21: =IF(ISNUMBER(J21),M21-J21,"new") -> 1
A22: ACT|VIC|Small|Regional | B22: ACT | C22: VIC | D22: Small | E22: Regional | F22: 19.47 | G22: 0 | H22: 13 | I22: 0.97 | J22: 17.5 | K22: 29.5 | L22: =INDEX('Read me'!$B$10:$B$15,1) -> 1.34 | M22: =IF(F22*(1+'Read me'!$B$5)<='Read me'!$B$7,CEILING(F22*(1+'Read me'!$B$5)+0.5,1)-0.5,CEILING(F22*(1+'Read me'!$B$5),5)) -> 19.5 | N22: =IF(MAX(M22*L22,M22+'Read me'!$B$6)<='Read me'!$B$7,CEILING(MAX(M22*L22,M22+'Read me'!$B$6)+0.5,1)-0.5,CEILING(MAX(M22*L22,M22+'Read me'!$B$6),5)) -> 26.5 | O22: =IF(ISNUMBER(J22),M22-J22,"new") -> 2
A23: ACT|VIC|Medium|Metro | B23: ACT | C23: VIC | D23: Medium | E23: Metro | F23: 53.82 | G23: 5 | H23: 13 | I23: 0.97 | J23: 19.5 | K23: 24.5 | L23: =INDEX('Read me'!$B$10:$B$15,2) -> 1.26 | M23: =IF(F23*(1+'Read me'!$B$5)<='Read me'!$B$7,CEILING(F23*(1+'Read me'!$B$5)+0.5,1)-0.5,CEILING(F23*(1+'Read me'!$B$5),5)) -> 55 | N23: =IF(MAX(M23*L23,M23+'Read me'!$B$6)<='Read me'!$B$7,CEILING(MAX(M23*L23,M23+'Read me'!$B$6)+0.5,1)-0.5,CEILING(MAX(M23*L23,M23+'Read me'!$B$6),5)) -> 70 | O23: =IF(ISNUMBER(J23),M23-J23,"new") -> 35.5
A24: ACT|VIC|Medium|Metro Outer | B24: ACT | C24: VIC | D24: Medium | E24: Metro Outer | F24: 53.82 | G24: 0 | H24: 13 | I24: 0.97 | J24: 19.5 | K24: 24.5 | L24: =INDEX('Read me'!$B$10:$B$15,2) -> 1.26 | M24: =IF(F24*(1+'Read me'!$B$5)<='Read me'!$B$7,CEILING(F24*(1+'Read me'!$B$5)+0.5,1)-0.5,CEILING(F24*(1+'Read me'!$B$5),5)) -> 55 | N24: =IF(MAX(M24*L24,M24+'Read me'!$B$6)<='Read me'!$B$7,CEILING(MAX(M24*L24,M24+'Read me'!$B$6)+0.5,1)-0.5,CEILING(MAX(M24*L24,M24+'Read me'!$B$6),5)) -> 70 | O24: =IF(ISNUMBER(J24),M24-J24,"new") -> 35.5
A25: ACT|VIC|Medium|Regional | B25: ACT | C25: VIC | D25: Medium | E25: Regional | F25: 59.42 | G25: 0 | H25: 13 | I25: 0.97 | J25: 19.5 | K25: 34.5 | L25: =INDEX('Read me'!$B$10:$B$15,2) -> 1.26 | M25: =IF(F25*(1+'Read me'!$B$5)<='Read me'!$B$7,CEILING(F25*(1+'Read me'!$B$5)+0.5,1)-0.5,CEILING(F25*(1+'Read me'!$B$5),5)) -> 60 | N25: =IF(MAX(M25*L25,M25+'Read me'!$B$6)<='Read me'!$B$7,CEILING(MAX(M25*L25,M25+'Read me'!$B$6)+0.5,1)-0.5,CEILING(MAX(M25*L25,M25+'Read me'!$B$6),5)) -> 80 | O25: =IF(ISNUMBER(J25),M25-J25,"new") -> 40.5
A26: ACT|VIC|Large|Metro | B26: ACT | C26: VIC | D26: Large | E26: Metro | F26: 80.34 | G26: 1 | H26: 13 | I26: 0.97 | J26: 24.5 | K26: 75 | L26: =INDEX('Read me'!$B$10:$B$15,3) -> 1.35 | M26: =IF(F26*(1+'Read me'!$B$5)<='Read me'!$B$7,CEILING(F26*(1+'Read me'!$B$5)+0.5,1)-0.5,CEILING(F26*(1+'Read me'!$B$5),5)) -> 85 | N26: =IF(MAX(M26*L26,M26+'Read me'!$B$6)<='Read me'!$B$7,CEILING(MAX(M26*L26,M26+'Read me'!$B$6)+0.5,1)-0.5,CEILING(MAX(M26*L26,M26+'Read me'!$B$6),5)) -> 115 | O26: =IF(ISNUMBER(J26),M26-J26,"new") -> 60.5
A27: ACT|VIC|Large|Metro Outer | B27: ACT | C27: VIC | D27: Large | E27: Metro Outer | F27: 90.23 | G27: 0 | H27: 13 | I27: 0.97 | J27: 24.5 | K27: 75 | L27: =INDEX('Read me'!$B$10:$B$15,3) -> 1.35 | M27: =IF(F27*(1+'Read me'!$B$5)<='Read me'!$B$7,CEILING(F27*(1+'Read me'!$B$5)+0.5,1)-0.5,CEILING(F27*(1+'Read me'!$B$5),5)) -> 95 | N27: =IF(MAX(M27*L27,M27+'Read me'!$B$6)<='Read me'!$B$7,CEILING(MAX(M27*L27,M27+'Read me'!$B$6)+0.5,1)-0.5,CEILING(MAX(M27*L27,M27+'Read me'!$B$6),5)) -> 130 | O27: =IF(ISNUMBER(J27),M27-J27,"new") -> 70.5
A28: ACT|VIC|Large|Regional | B28: ACT | C28: VIC | D28: Large | E28: Regional | F28: 121.34 | G28: 0 | H28: 13 | I28: 0.97 | J28: 85 | K28: 125 | L28: =INDEX('Read me'!$B$10:$B$15,3) -> 1.35 | M28: =IF(F28*(1+'Read me'!$B$5)<='Read me'!$B$7,CEILING(F28*(1+'Read me'!$B$5)+0.5,1)-0.5,CEILING(F28*(1+'Read me'!$B$5),5)) -> 125 | N28: =IF(MAX(M28*L28,M28+'Read me'!$B$6)<='Read me'!$B$7,CEILING(MAX(M28*L28,M28+'Read me'!$B$6)+0.5,1)-0.5,CEILING(MAX(M28*L28,M28+'Read me'!$B$6),5)) -> 170 | O28: =IF(ISNUMBER(J28),M28-J28,"new") -> 40
A29: ACT|VIC|XL|Metro | B29: ACT | C29: VIC | D29: XL | E29: Metro | F29: 138.88 | G29: 0 | H29: 13 | I29: 0.97 | J29: 85 | K29: 125 | L29: =INDEX('Read me'!$B$10:$B$15,4) -> 1.2 | M29: =IF(F29*(1+'Read me'!$B$5)<='Read me'!$B$7,CEILING(F29*(1+'Read me'!$B$5)+0.5,1)-0.5,CEILING(F29*(1+'Read me'!$B$5),5)) -> 140 | N29: =IF(MAX(M29*L29,M29+'Read me'!$B$6)<='Read me'!$B$7,CEILING(MAX(M29*L29,M29+'Read me'!$B$6)+0.5,1)-0.5,CEILING(MAX(M29*L29,M29+'Read me'!$B$6),5)) -> 170 | O29: =IF(ISNUMBER(J29),M29-J29,"new") -> 55
A30: ACT|VIC|XL|Metro Outer | B30: ACT | C30: VIC | D30: XL | E30: Metro Outer | F30: 166.75 | G30: 0 | H30: 13 | I30: 0.97 | J30: 125 | K30: 125 | L30: =INDEX('Read me'!$B$10:$B$15,4) -> 1.2 | M30: =IF(F30*(1+'Read me'!$B$5)<='Read me'!$B$7,CEILING(F30*(1+'Read me'!$B$5)+0.5,1)-0.5,CEILING(F30*(1+'Read me'!$B$5),5)) -> 170 | N30: =IF(MAX(M30*L30,M30+'Read me'!$B$6)<='Read me'!$B$7,CEILING(MAX(M30*L30,M30+'Read me'!$B$6)+0.5,1)-0.5,CEILING(MAX(M30*L30,M30+'Read me'!$B$6),5)) -> 205 | O30: =IF(ISNUMBER(J30),M30-J30,"new") -> 45
A31: ACT|VIC|XL|Regional | B31: ACT | C31: VIC | D31: XL | E31: Regional | F31: 200.96 | G31: 0 | H31: 13 | I31: 0.97 | J31: 199 | K31: 175 | L31: =INDEX('Read me'!$B$10:$B$15,4) -> 1.2 | M31: =IF(F31*(1+'Read me'!$B$5)<='Read me'!$B$7,CEILING(F31*(1+'Read me'!$B$5)+0.5,1)-0.5,CEILING(F31*(1+'Read me'!$B$5),5)) -> 205 | N31: =IF(MAX(M31*L31,M31+'Read me'!$B$6)<='Read me'!$B$7,CEILING(MAX(M31*L31,M31+'Read me'!$B$6)+0.5,1)-0.5,CEILING(MAX(M31*L31,M31+'Read me'!$B$6),5)) -> 250 | O31: =IF(ISNUMBER(J31),M31-J31,"new") -> 6
A32: ACT|VIC|XXL|Metro | B32: ACT | C32: VIC | D32: XXL | E32: Metro | F32: 176.28 | G32: 0 | H32: 13 | I32: 0.97 | J32: 250 | K32: 300 | L32: =INDEX('Read me'!$B$10:$B$15,5) -> 1.2 | M32: =IF(F32*(1+'Read me'!$B$5)<='Read me'!$B$7,CEILING(F32*(1+'Read me'!$B$5)+0.5,1)-0.5,CEILING(F32*(1+'Read me'!$B$5),5)) -> 180 | N32: =IF(MAX(M32*L32,M32+'Read me'!$B$6)<='Read me'!$B$7,CEILING(MAX(M32*L32,M32+'Read me'!$B$6)+0.5,1)-0.5,CEILING(MAX(M32*L32,M32+'Read me'!$B$6),5)) -> 220 | O32: =IF(ISNUMBER(J32),M32-J32,"new") -> -70
A33: ACT|VIC|XXL|Metro Outer | B33: ACT | C33: VIC | D33: XXL | E33: Metro Outer | F33: 217.48 | G33: 0 | H33: 13 | I33: 0.97 | J33: 250 | K33: 300 | L33: =INDEX('Read me'!$B$10:$B$15,5) -> 1.2 | M33: =N33 -> 265 | N33: =IF(MAX((IF(F33*(1+'Read me'!$B$5)<='Read me'!$B$7,CEILING(F33*(1+'Read me'!$B$5)+0.5,1)-0.5,CEILING(F33*(1+'Read me'!$B$5),5)))*L33,(IF(F33*(1+'Read me'!$B$5)<='Read me'!$B$7,CEILING(F33*(1+'Read me'!$B$5)+0.5,1)-0.5,CEILING(F33*(1+'Read me'!$B$5),5)))+'Read me'!$B$6)<='Read me'!$B$7,CEILING(MAX((IF(F33*(1+'Read me'!$B$5)<='Read me'!$B$7,CEILING(F33*(1+'Read me'!$B$5)+0.5,1)-0.5,CEILING(F33*(1+'Read me'!$B$5),5)))*L33,(IF(F33*(1+'Read me'!$B$5)<='Read me'!$B$7,CEILING(F33*(1+'Read me'!$B$5)+0.5,1)-0.5,CEILING(F33*(1+'Read me'!$B$5),5)))+'Read me'!$B$6)+0.5,1)-0.5,CEILING(MAX((IF(F33*(1+'Read me'!$B$5)<='Read me'!$B$7,CEILING(F33*(1+'Read me'!$B$5)+0.5,1)-0.5,CEILING(F33*(1+'Read me'!$B$5),5)))*L33,(IF(F33*(1+'Read me'!$B$5)<='Read me'!$B$7,CEILING(F33*(1+'Read me'!$B$5)+0.5,1)-0.5,CEILING(F33*(1+'Read me'!$B$5),5)))+'Read me'!$B$6),5)) -> 265 | O33: =IF(ISNUMBER(J33),M33-J33,"new") -> 15 | P33: One rate: interstate XXL/Bulky to Metro Outer or Regional is charged at the Priority price for both services
A34: ACT|VIC|XXL|Regional | B34: ACT | C34: VIC | D34: XXL | E34: Regional | F34: 261.31 | G34: 0 | H34: 13 | I34: 0.97 | J34: 300 | K34: 400 | L34: =INDEX('Read me'!$B$10:$B$15,5) -> 1.2 | M34: =N34 -> 320 | N34: =IF(MAX((IF(F34*(1+'Read me'!$B$5)<='Read me'!$B$7,CEILING(F34*(1+'Read me'!$B$5)+0.5,1)-0.5,CEILING(F34*(1+'Read me'!$B$5),5)))*L34,(IF(F34*(1+'Read me'!$B$5)<='Read me'!$B$7,CEILING(F34*(1+'Read me'!$B$5)+0.5,1)-0.5,CEILING(F34*(1+'Read me'!$B$5),5)))+'Read me'!$B$6)<='Read me'!$B$7,CEILING(MAX((IF(F34*(1+'Read me'!$B$5)<='Read me'!$B$7,CEILING(F34*(1+'Read me'!$B$5)+0.5,1)-0.5,CEILING(F34*(1+'Read me'!$B$5),5)))*L34,(IF(F34*(1+'Read me'!$B$5)<='Read me'!$B$7,CEILING(F34*(1+'Read me'!$B$5)+0.5,1)-0.5,CEILING(F34*(1+'Read me'!$B$5),5)))+'Read me'!$B$6)+0.5,1)-0.5,CEILING(MAX((IF(F34*(1+'Read me'!$B$5)<='Read me'!$B$7,CEILING(F34*(1+'Read me'!$B$5)+0.5,1)-0.5,CEILING(F34*(1+'Read me'!$B$5),5)))*L34,(IF(F34*(1+'Read me'!$B$5)<='Read me'!$B$7,CEILING(F34*(1+'Read me'!$B$5)+0.5,1)-0.5,CEILING(F34*(1+'Read me'!$B$5),5)))+'Read me'!$B$6),5)) -> 320 | O34: =IF(ISNUMBER(J34),M34-J34,"new") -> 20 | P34: One rate: interstate XXL/Bulky to Metro Outer or Regional is charged at the Priority price for both services
A35: ACT|VIC|Bulky|Metro | B35: ACT | C35: VIC | D35: Bulky | E35: Metro | F35: 244.77 | G35: 0 | H35: 13 | I35: 0.97 | L35: =INDEX('Read me'!$B$10:$B$15,6) -> 1.2 | M35: =IF(F35*(1+'Read me'!$B$5)<='Read me'!$B$7,CEILING(F35*(1+'Read me'!$B$5)+0.5,1)-0.5,CEILING(F35*(1+'Read me'!$B$5),5)) -> 245 | N35: =IF(MAX(M35*L35,M35+'Read me'!$B$6)<='Read me'!$B$7,CEILING(MAX(M35*L35,M35+'Read me'!$B$6)+0.5,1)-0.5,CEILING(MAX(M35*L35,M35+'Read me'!$B$6),5)) -> 295 | O35: =IF(ISNUMBER(J35),M35-J35,"new") -> new
A36: ACT|VIC|Bulky|Metro Outer | B36: ACT | C36: VIC | D36: Bulky | E36: Metro Outer | F36: 314.52 | G36: 0 | H36: 13 | I36: 0.97 | L36: =INDEX('Read me'!$B$10:$B$15,6) -> 1.2 | M36: =N36 -> 380 | N36: =IF(MAX((IF(F36*(1+'Read me'!$B$5)<='Read me'!$B$7,CEILING(F36*(1+'Read me'!$B$5)+0.5,1)-0.5,CEILING(F36*(1+'Read me'!$B$5),5)))*L36,(IF(F36*(1+'Read me'!$B$5)<='Read me'!$B$7,CEILING(F36*(1+'Read me'!$B$5)+0.5,1)-0.5,CEILING(F36*(1+'Read me'!$B$5),5)))+'Read me'!$B$6)<='Read me'!$B$7,CEILING(MAX((IF(F36*(1+'Read me'!$B$5)<='Read me'!$B$7,CEILING(F36*(1+'Read me'!$B$5)+0.5,1)-0.5,CEILING(F36*(1+'Read me'!$B$5),5)))*L36,(IF(F36*(1+'Read me'!$B$5)<='Read me'!$B$7,CEILING(F36*(1+'Read me'!$B$5)+0.5,1)-0.5,CEILING(F36*(1+'Read me'!$B$5),5)))+'Read me'!$B$6)+0.5,1)-0.5,CEILING(MAX((IF(F36*(1+'Read me'!$B$5)<='Read me'!$B$7,CEILING(F36*(1+'Read me'!$B$5)+0.5,1)-0.5,CEILING(F36*(1+'Read me'!$B$5),5)))*L36,(IF(F36*(1+'Read me'!$B$5)<='Read me'!$B$7,CEILING(F36*(1+'Read me'!$B$5)+0.5,1)-0.5,CEILING(F36*(1+'Read me'!$B$5),5)))+'Read me'!$B$6),5)) -> 380 | O36: =IF(ISNUMBER(J36),M36-J36,"new") -> new | P36: One rate: interstate XXL/Bulky to Metro Outer or Regional is charged at the Priority price for both services
A37: ACT|VIC|Bulky|Regional | B37: ACT | C37: VIC | D37: Bulky | E37: Regional | F37: 369.67 | G37: 0 | H37: 13 | I37: 0.97 | L37: =INDEX('Read me'!$B$10:$B$15,6) -> 1.2 | M37: =N37 -> 445 | N37: =IF(MAX((IF(F37*(1+'Read me'!$B$5)<='Read me'!$B$7,CEILING(F37*(1+'Read me'!$B$5)+0.5,1)-0.5,CEILING(F37*(1+'Read me'!$B$5),5)))*L37,(IF(F37*(1+'Read me'!$B$5)<='Read me'!$B$7,CEILING(F37*(1+'Read me'!$B$5)+0.5,1)-0.5,CEILING(F37*(1+'Read me'!$B$5),5)))+'Read me'!$B$6)<='Read me'!$B$7,CEILING(MAX((IF(F37*(1+'Read me'!$B$5)<='Read me'!$B$7,CEILING(F37*(1+'Read me'!$B$5)+0.5,1)-0.5,CEILING(F37*(1+'Read me'!$B$5),5)))*L37,(IF(F37*(1+'Read me'!$B$5)<='Read me'!$B$7,CEILING(F37*(1+'Read me'!$B$5)+0.5,1)-0.5,CEILING(F37*(1+'Read me'!$B$5),5)))+'Read me'!$B$6)+0.5,1)-0.5,CEILING(MAX((IF(F37*(1+'Read me'!$B$5)<='Read me'!$B$7,CEILING(F37*(1+'Read me'!$B$5)+0.5,1)-0.5,CEILING(F37*(1+'Read me'!$B$5),5)))*L37,(IF(F37*(1+'Read me'!$B$5)<='Read me'!$B$7,CEILING(F37*(1+'Read me'!$B$5)+0.5,1)-0.5,CEILING(F37*(1+'Read me'!$B$5),5)))+'Read me'!$B$6),5)) -> 445 | O37: =IF(ISNUMBER(J37),M37-J37,"new") -> new | P37: One rate: interstate XXL/Bulky to Metro Outer or Regional is charged at the Priority price for both services
A38: ACT|SA|Small|Metro | B38: ACT | C38: SA | D38: Small | E38: Metro | F38: 12.81 | G38: 3 | H38: 5 | I38: 0.94 | J38: 19.5 | K38: 24.5 | L38: =INDEX('Read me'!$B$10:$B$15,1) -> 1.34 | M38: =IF(F38*(1+'Read me'!$B$5)<='Read me'!$B$7,CEILING(F38*(1+'Read me'!$B$5)+0.5,1)-0.5,CEILING(F38*(1+'Read me'!$B$5),5)) -> 13.5 | N38: =IF(MAX(M38*L38,M38+'Read me'!$B$6)<='Read me'!$B$7,CEILING(MAX(M38*L38,M38+'Read me'!$B$6)+0.5,1)-0.5,CEILING(MAX(M38*L38,M38+'Read me'!$B$6),5)) -> 18.5 | O38: =IF(ISNUMBER(J38),M38-J38,"new") -> -6
A39: ACT|SA|Small|Metro Outer | B39: ACT | C39: SA | D39: Small | E39: Metro Outer | F39: 14.27 | G39: 0 | H39: 5 | I39: 0.94 | J39: 19.5 | K39: 24.5 | L39: =INDEX('Read me'!$B$10:$B$15,1) -> 1.34 | M39: =IF(F39*(1+'Read me'!$B$5)<='Read me'!$B$7,CEILING(F39*(1+'Read me'!$B$5)+0.5,1)-0.5,CEILING(F39*(1+'Read me'!$B$5),5)) -> 14.5 | N39: =IF(MAX(M39*L39,M39+'Read me'!$B$6)<='Read me'!$B$7,CEILING(MAX(M39*L39,M39+'Read me'!$B$6)+0.5,1)-0.5,CEILING(MAX(M39*L39,M39+'Read me'!$B$6),5)) -> 19.5 | O39: =IF(ISNUMBER(J39),M39-J39,"new") -> -5
A40: ACT|SA|Small|Regional | B40: ACT | C40: SA | D40: Small | E40: Regional | F40: 18.83 | G40: 0 | H40: 5 | I40: 0.94 | J40: 19.5 | K40: 34.5 | L40: =INDEX('Read me'!$B$10:$B$15,1) -> 1.34 | M40: =IF(F40*(1+'Read me'!$B$5)<='Read me'!$B$7,CEILING(F40*(1+'Read me'!$B$5)+0.5,1)-0.5,CEILING(F40*(1+'Read me'!$B$5),5)) -> 19.5 | N40: =IF(MAX(M40*L40,M40+'Read me'!$B$6)<='Read me'!$B$7,CEILING(MAX(M40*L40,M40+'Read me'!$B$6)+0.5,1)-0.5,CEILING(MAX(M40*L40,M40+'Read me'!$B$6),5)) -> 26.5 | O40: =IF(ISNUMBER(J40),M40-J40,"new") -> 0
A41: ACT|SA|Medium|Metro | B41: ACT | C41: SA | D41: Medium | E41: Metro | F41: 44.28 | G41: 2 | H41: 5 | I41: 0.94 | J41: 24.5 | K41: 29.5 | L41: =INDEX('Read me'!$B$10:$B$15,2) -> 1.26 | M41: =IF(F41*(1+'Read me'!$B$5)<='Read me'!$B$7,CEILING(F41*(1+'Read me'!$B$5)+0.5,1)-0.5,CEILING(F41*(1+'Read me'!$B$5),5)) -> 45 | N41: =IF(MAX(M41*L41,M41+'Read me'!$B$6)<='Read me'!$B$7,CEILING(MAX(M41*L41,M41+'Read me'!$B$6)+0.5,1)-0.5,CEILING(MAX(M41*L41,M41+'Read me'!$B$6),5)) -> 60 | O41: =IF(ISNUMBER(J41),M41-J41,"new") -> 20.5
A42: ACT|SA|Medium|Metro Outer | B42: ACT | C42: SA | D42: Medium | E42: Metro Outer | F42: 49.21 | G42: 0 | H42: 5 | I42: 0.94 | J42: 24.5 | K42: 29.5 | L42: =INDEX('Read me'!$B$10:$B$15,2) -> 1.26 | M42: =IF(F42*(1+'Read me'!$B$5)<='Read me'!$B$7,CEILING(F42*(1+'Read me'!$B$5)+0.5,1)-0.5,CEILING(F42*(1+'Read me'!$B$5),5)) -> 50 | N42: =IF(MAX(M42*L42,M42+'Read me'!$B$6)<='Read me'!$B$7,CEILING(MAX(M42*L42,M42+'Read me'!$B$6)+0.5,1)-0.5,CEILING(MAX(M42*L42,M42+'Read me'!$B$6),5)) -> 65 | O42: =IF(ISNUMBER(J42),M42-J42,"new") -> 25.5
A43: ACT|SA|Medium|Regional | B43: ACT | C43: SA | D43: Medium | E43: Regional | F43: 57.45 | G43: 0 | H43: 5 | I43: 0.94 | J43: 24.5 | K43: 45 | L43: =INDEX('Read me'!$B$10:$B$15,2) -> 1.26 | M43: =IF(F43*(1+'Read me'!$B$5)<='Read me'!$B$7,CEILING(F43*(1+'Read me'!$B$5)+0.5,1)-0.5,CEILING(F43*(1+'Read me'!$B$5),5)) -> 60 | N43: =IF(MAX(M43*L43,M43+'Read me'!$B$6)<='Read me'!$B$7,CEILING(MAX(M43*L43,M43+'Read me'!$B$6)+0.5,1)-0.5,CEILING(MAX(M43*L43,M43+'Read me'!$B$6),5)) -> 80 | O43: =IF(ISNUMBER(J43),M43-J43,"new") -> 35.5
A44: ACT|SA|Large|Metro | B44: ACT | C44: SA | D44: Large | E44: Metro | F44: 77.56 | G44: 0 | H44: 5 | I44: 0.94 | J44: 45 | K44: 95 | L44: =INDEX('Read me'!$B$10:$B$15,3) -> 1.35 | M44: =IF(F44*(1+'Read me'!$B$5)<='Read me'!$B$7,CEILING(F44*(1+'Read me'!$B$5)+0.5,1)-0.5,CEILING(F44*(1+'Read me'!$B$5),5)) -> 80 | N44: =IF(MAX(M44*L44,M44+'Read me'!$B$6)<='Read me'!$B$7,CEILING(MAX(M44*L44,M44+'Read me'!$B$6)+0.5,1)-0.5,CEILING(MAX(M44*L44,M44+'Read me'!$B$6),5)) -> 110 | O44: =IF(ISNUMBER(J44),M44-J44,"new") -> 35
A45: ACT|SA|Large|Metro Outer | B45: ACT | C45: SA | D45: Large | E45: Metro Outer | F45: 87.25 | G45: 0 | H45: 5 | I45: 0.94 | J45: 45 | K45: 95 | L45: =INDEX('Read me'!$B$10:$B$15,3) -> 1.35 | M45: =IF(F45*(1+'Read me'!$B$5)<='Read me'!$B$7,CEILING(F45*(1+'Read me'!$B$5)+0.5,1)-0.5,CEILING(F45*(1+'Read me'!$B$5),5)) -> 90 | N45: =IF(MAX(M45*L45,M45+'Read me'!$B$6)<='Read me'!$B$7,CEILING(MAX(M45*L45,M45+'Read me'!$B$6)+0.5,1)-0.5,CEILING(MAX(M45*L45,M45+'Read me'!$B$6),5)) -> 125 | O45: =IF(ISNUMBER(J45),M45-J45,"new") -> 45
A46: ACT|SA|Large|Regional | B46: ACT | C46: SA | D46: Large | E46: Regional | F46: 117.33 | G46: 0 | H46: 5 | I46: 0.94 | J46: 99 | K46: 150 | L46: =INDEX('Read me'!$B$10:$B$15,3) -> 1.35 | M46: =IF(F46*(1+'Read me'!$B$5)<='Read me'!$B$7,CEILING(F46*(1+'Read me'!$B$5)+0.5,1)-0.5,CEILING(F46*(1+'Read me'!$B$5),5)) -> 120 | N46: =IF(MAX(M46*L46,M46+'Read me'!$B$6)<='Read me'!$B$7,CEILING(MAX(M46*L46,M46+'Read me'!$B$6)+0.5,1)-0.5,CEILING(MAX(M46*L46,M46+'Read me'!$B$6),5)) -> 165 | O46: =IF(ISNUMBER(J46),M46-J46,"new") -> 21
A47: ACT|SA|XL|Metro | B47: ACT | C47: SA | D47: XL | E47: Metro | F47: 134.3 | G47: 0 | H47: 5 | I47: 0.94 | J47: 99 | K47: 150 | L47: =INDEX('Read me'!$B$10:$B$15,4) -> 1.2 | M47: =IF(F47*(1+'Read me'!$B$5)<='Read me'!$B$7,CEILING(F47*(1+'Read me'!$B$5)+0.5,1)-0.5,CEILING(F47*(1+'Read me'!$B$5),5)) -> 135 | N47: =IF(MAX(M47*L47,M47+'Read me'!$B$6)<='Read me'!$B$7,CEILING(MAX(M47*L47,M47+'Read me'!$B$6)+0.5,1)-0.5,CEILING(MAX(M47*L47,M47+'Read me'!$B$6),5)) -> 165 | O47: =IF(ISNUMBER(J47),M47-J47,"new") -> 36
A48: ACT|SA|XL|Metro Outer | B48: ACT | C48: SA | D48: XL | E48: Metro Outer | F48: 161.25 | G48: 0 | H48: 5 | I48: 0.94 | J48: 150 | K48: 150 | L48: =INDEX('Read me'!$B$10:$B$15,4) -> 1.2 | M48: =IF(F48*(1+'Read me'!$B$5)<='Read me'!$B$7,CEILING(F48*(1+'Read me'!$B$5)+0.5,1)-0.5,CEILING(F48*(1+'Read me'!$B$5),5)) -> 165 | N48: =IF(MAX(M48*L48,M48+'Read me'!$B$6)<='Read me'!$B$7,CEILING(MAX(M48*L48,M48+'Read me'!$B$6)+0.5,1)-0.5,CEILING(MAX(M48*L48,M48+'Read me'!$B$6),5)) -> 200 | O48: =IF(ISNUMBER(J48),M48-J48,"new") -> 15
A49: ACT|SA|XL|Regional | B49: ACT | C49: SA | D49: XL | E49: Regional | F49: 194.32 | G49: 0 | H49: 5 | I49: 0.94 | J49: 250 | K49: 195 | L49: =INDEX('Read me'!$B$10:$B$15,4) -> 1.2 | M49: =IF(F49*(1+'Read me'!$B$5)<='Read me'!$B$7,CEILING(F49*(1+'Read me'!$B$5)+0.5,1)-0.5,CEILING(F49*(1+'Read me'!$B$5),5)) -> 195 | N49: =IF(MAX(M49*L49,M49+'Read me'!$B$6)<='Read me'!$B$7,CEILING(MAX(M49*L49,M49+'Read me'!$B$6)+0.5,1)-0.5,CEILING(MAX(M49*L49,M49+'Read me'!$B$6),5)) -> 235 | O49: =IF(ISNUMBER(J49),M49-J49,"new") -> -55
A50: ACT|SA|XXL|Metro | B50: ACT | C50: SA | D50: XXL | E50: Metro | F50: 170.46 | G50: 0 | H50: 5 | I50: 0.94 | J50: 300 | K50: 300 | L50: =INDEX('Read me'!$B$10:$B$15,5) -> 1.2 | M50: =IF(F50*(1+'Read me'!$B$5)<='Read me'!$B$7,CEILING(F50*(1+'Read me'!$B$5)+0.5,1)-0.5,CEILING(F50*(1+'Read me'!$B$5),5)) -> 175 | N50: =IF(MAX(M50*L50,M50+'Read me'!$B$6)<='Read me'!$B$7,CEILING(MAX(M50*L50,M50+'Read me'!$B$6)+0.5,1)-0.5,CEILING(MAX(M50*L50,M50+'Read me'!$B$6),5)) -> 210 | O50: =IF(ISNUMBER(J50),M50-J50,"new") -> -125
A51: ACT|SA|XXL|Metro Outer | B51: ACT | C51: SA | D51: XXL | E51: Metro Outer | F51: 210.3 | G51: 0 | H51: 5 | I51: 0.94 | J51: 300 | K51: 300 | L51: =INDEX('Read me'!$B$10:$B$15,5) -> 1.2 | M51: =N51 -> 260 | N51: =IF(MAX((IF(F51*(1+'Read me'!$B$5)<='Read me'!$B$7,CEILING(F51*(1+'Read me'!$B$5)+0.5,1)-0.5,CEILING(F51*(1+'Read me'!$B$5),5)))*L51,(IF(F51*(1+'Read me'!$B$5)<='Read me'!$B$7,CEILING(F51*(1+'Read me'!$B$5)+0.5,1)-0.5,CEILING(F51*(1+'Read me'!$B$5),5)))+'Read me'!$B$6)<='Read me'!$B$7,CEILING(MAX((IF(F51*(1+'Read me'!$B$5)<='Read me'!$B$7,CEILING(F51*(1+'Read me'!$B$5)+0.5,1)-0.5,CEILING(F51*(1+'Read me'!$B$5),5)))*L51,(IF(F51*(1+'Read me'!$B$5)<='Read me'!$B$7,CEILING(F51*(1+'Read me'!$B$5)+0.5,1)-0.5,CEILING(F51*(1+'Read me'!$B$5),5)))+'Read me'!$B$6)+0.5,1)-0.5,CEILING(MAX((IF(F51*(1+'Read me'!$B$5)<='Read me'!$B$7,CEILING(F51*(1+'Read me'!$B$5)+0.5,1)-0.5,CEILING(F51*(1+'Read me'!$B$5),5)))*L51,(IF(F51*(1+'Read me'!$B$5)<='Read me'!$B$7,CEILING(F51*(1+'Read me'!$B$5)+0.5,1)-0.5,CEILING(F51*(1+'Read me'!$B$5),5)))+'Read me'!$B$6),5)) -> 260 | O51: =IF(ISNUMBER(J51),M51-J51,"new") -> -40 | P51: One rate: interstate XXL/Bulky to Metro Outer or Regional is charged at the Priority price for both services
A52: ACT|SA|XXL|Regional | B52: ACT | C52: SA | D52: XXL | E52: Regional | F52: 252.68 | G52: 0 | H52: 5 | I52: 0.94 | J52: 350 | K52: 400 | L52: =INDEX('Read me'!$B$10:$B$15,5) -> 1.2 | M52: =N52 -> 310 | N52: =IF(MAX((IF(F52*(1+'Read me'!$B$5)<='Read me'!$B$7,CEILING(F52*(1+'Read me'!$B$5)+0.5,1)-0.5,CEILING(F52*(1+'Read me'!$B$5),5)))*L52,(IF(F52*(1+'Read me'!$B$5)<='Read me'!$B$7,CEILING(F52*(1+'Read me'!$B$5)+0.5,1)-0.5,CEILING(F52*(1+'Read me'!$B$5),5)))+'Read me'!$B$6)<='Read me'!$B$7,CEILING(MAX((IF(F52*(1+'Read me'!$B$5)<='Read me'!$B$7,CEILING(F52*(1+'Read me'!$B$5)+0.5,1)-0.5,CEILING(F52*(1+'Read me'!$B$5),5)))*L52,(IF(F52*(1+'Read me'!$B$5)<='Read me'!$B$7,CEILING(F52*(1+'Read me'!$B$5)+0.5,1)-0.5,CEILING(F52*(1+'Read me'!$B$5),5)))+'Read me'!$B$6)+0.5,1)-0.5,CEILING(MAX((IF(F52*(1+'Read me'!$B$5)<='Read me'!$B$7,CEILING(F52*(1+'Read me'!$B$5)+0.5,1)-0.5,CEILING(F52*(1+'Read me'!$B$5),5)))*L52,(IF(F52*(1+'Read me'!$B$5)<='Read me'!$B$7,CEILING(F52*(1+'Read me'!$B$5)+0.5,1)-0.5,CEILING(F52*(1+'Read me'!$B$5),5)))+'Read me'!$B$6),5)) -> 310 | O52: =IF(ISNUMBER(J52),M52-J52,"new") -> -40 | P52: One rate: interstate XXL/Bulky to Metro Outer or Regional is charged at the Priority price for both services
A53: ACT|SA|Bulky|Metro | B53: ACT | C53: SA | D53: Bulky | E53: Metro | F53: 236.69 | G53: 0 | H53: 5 | I53: 0.94 | L53: =INDEX('Read me'!$B$10:$B$15,6) -> 1.2 | M53: =IF(F53*(1+'Read me'!$B$5)<='Read me'!$B$7,CEILING(F53*(1+'Read me'!$B$5)+0.5,1)-0.5,CEILING(F53*(1+'Read me'!$B$5),5)) -> 240 | N53: =IF(MAX(M53*L53,M53+'Read me'!$B$6)<='Read me'!$B$7,CEILING(MAX(M53*L53,M53+'Read me'!$B$6)+0.5,1)-0.5,CEILING(MAX(M53*L53,M53+'Read me'!$B$6),5)) -> 290 | O53: =IF(ISNUMBER(J53),M53-J53,"new") -> new
A54: ACT|SA|Bulky|Metro Outer | B54: ACT | C54: SA | D54: Bulky | E54: Metro Outer | F54: 304.14 | G54: 0 | H54: 5 | I54: 0.94 | L54: =INDEX('Read me'!$B$10:$B$15,6) -> 1.2 | M54: =N54 -> 370 | N54: =IF(MAX((IF(F54*(1+'Read me'!$B$5)<='Read me'!$B$7,CEILING(F54*(1+'Read me'!$B$5)+0.5,1)-0.5,CEILING(F54*(1+'Read me'!$B$5),5)))*L54,(IF(F54*(1+'Read me'!$B$5)<='Read me'!$B$7,CEILING(F54*(1+'Read me'!$B$5)+0.5,1)-0.5,CEILING(F54*(1+'Read me'!$B$5),5)))+'Read me'!$B$6)<='Read me'!$B$7,CEILING(MAX((IF(F54*(1+'Read me'!$B$5)<='Read me'!$B$7,CEILING(F54*(1+'Read me'!$B$5)+0.5,1)-0.5,CEILING(F54*(1+'Read me'!$B$5),5)))*L54,(IF(F54*(1+'Read me'!$B$5)<='Read me'!$B$7,CEILING(F54*(1+'Read me'!$B$5)+0.5,1)-0.5,CEILING(F54*(1+'Read me'!$B$5),5)))+'Read me'!$B$6)+0.5,1)-0.5,CEILING(MAX((IF(F54*(1+'Read me'!$B$5)<='Read me'!$B$7,CEILING(F54*(1+'Read me'!$B$5)+0.5,1)-0.5,CEILING(F54*(1+'Read me'!$B$5),5)))*L54,(IF(F54*(1+'Read me'!$B$5)<='Read me'!$B$7,CEILING(F54*(1+'Read me'!$B$5)+0.5,1)-0.5,CEILING(F54*(1+'Read me'!$B$5),5)))+'Read me'!$B$6),5)) -> 370 | O54: =IF(ISNUMBER(J54),M54-J54,"new") -> new | P54: One rate: interstate XXL/Bulky to Metro Outer or Regional is charged at the Priority price for both services
A55: ACT|SA|Bulky|Regional | B55: ACT | C55: SA | D55: Bulky | E55: Regional | F55: 357.47 | G55: 0 | H55: 5 | I55: 0.94 | L55: =INDEX('Read me'!$B$10:$B$15,6) -> 1.2 | M55: =N55 -> 435 | N55: =IF(MAX((IF(F55*(1+'Read me'!$B$5)<='Read me'!$B$7,CEILING(F55*(1+'Read me'!$B$5)+0.5,1)-0.5,CEILING(F55*(1+'Read me'!$B$5),5)))*L55,(IF(F55*(1+'Read me'!$B$5)<='Read me'!$B$7,CEILING(F55*(1+'Read me'!$B$5)+0.5,1)-0.5,CEILING(F55*(1+'Read me'!$B$5),5)))+'Read me'!$B$6)<='Read me'!$B$7,CEILING(MAX((IF(F55*(1+'Read me'!$B$5)<='Read me'!$B$7,CEILING(F55*(1+'Read me'!$B$5)+0.5,1)-0.5,CEILING(F55*(1+'Read me'!$B$5),5)))*L55,(IF(F55*(1+'Read me'!$B$5)<='Read me'!$B$7,CEILING(F55*(1+'Read me'!$B$5)+0.5,1)-0.5,CEILING(F55*(1+'Read me'!$B$5),5)))+'Read me'!$B$6)+0.5,1)-0.5,CEILING(MAX((IF(F55*(1+'Read me'!$B$5)<='Read me'!$B$7,CEILING(F55*(1+'Read me'!$B$5)+0.5,1)-0.5,CEILING(F55*(1+'Read me'!$B$5),5)))*L55,(IF(F55*(1+'Read me'!$B$5)<='Read me'!$B$7,CEILING(F55*(1+'Read me'!$B$5)+0.5,1)-0.5,CEILING(F55*(1+'Read me'!$B$5),5)))+'Read me'!$B$6),5)) -> 435 | O55: =IF(ISNUMBER(J55),M55-J55,"new") -> new | P55: One rate: interstate XXL/Bulky to Metro Outer or Regional is charged at the Priority price for both services
A56: ACT|NSW|Small|Metro | B56: ACT | C56: NSW | D56: Small | E56: Metro | F56: 11.46 | G56: 20 | H56: 42 | I56: 0.88 | J56: 14.5 | K56: 19.5 | L56: =INDEX('Read me'!$B$10:$B$15,1) -> 1.34 | M56: =IF(F56*(1+'Read me'!$B$5)<='Read me'!$B$7,CEILING(F56*(1+'Read me'!$B$5)+0.5,1)-0.5,CEILING(F56*(1+'Read me'!$B$5),5)) -> 11.5 | N56: =IF(MAX(M56*L56,M56+'Read me'!$B$6)<='Read me'!$B$7,CEILING(MAX(M56*L56,M56+'Read me'!$B$6)+0.5,1)-0.5,CEILING(MAX(M56*L56,M56+'Read me'!$B$6),5)) -> 16.5 | O56: =IF(ISNUMBER(J56),M56-J56,"new") -> -3
A57: ACT|NSW|Small|Metro Outer | B57: ACT | C57: NSW | D57: Small | E57: Metro Outer | F57: 13.43 | G57: 0 | H57: 42 | I57: 0.88 | J57: 14.5 | K57: 19.5 | L57: =INDEX('Read me'!$B$10:$B$15,1) -> 1.34 | M57: =IF(F57*(1+'Read me'!$B$5)<='Read me'!$B$7,CEILING(F57*(1+'Read me'!$B$5)+0.5,1)-0.5,CEILING(F57*(1+'Read me'!$B$5),5)) -> 13.5 | N57: =IF(MAX(M57*L57,M57+'Read me'!$B$6)<='Read me'!$B$7,CEILING(MAX(M57*L57,M57+'Read me'!$B$6)+0.5,1)-0.5,CEILING(MAX(M57*L57,M57+'Read me'!$B$6),5)) -> 18.5 | O57: =IF(ISNUMBER(J57),M57-J57,"new") -> -1
A58: ACT|NSW|Small|Regional | B58: ACT | C58: NSW | D58: Small | E58: Regional | F58: 17.72 | G58: 0 | H58: 42 | I58: 0.88 | J58: 17.5 | K58: 29.5 | L58: =INDEX('Read me'!$B$10:$B$15,1) -> 1.34 | M58: =IF(F58*(1+'Read me'!$B$5)<='Read me'!$B$7,CEILING(F58*(1+'Read me'!$B$5)+0.5,1)-0.5,CEILING(F58*(1+'Read me'!$B$5),5)) -> 18.5 | N58: =IF(MAX(M58*L58,M58+'Read me'!$B$6)<='Read me'!$B$7,CEILING(MAX(M58*L58,M58+'Read me'!$B$6)+0.5,1)-0.5,CEILING(MAX(M58*L58,M58+'Read me'!$B$6),5)) -> 25.5 | O58: =IF(ISNUMBER(J58),M58-J58,"new") -> 1
A59: ACT|NSW|Medium|Metro | B59: ACT | C59: NSW | D59: Medium | E59: Metro | F59: 40.9 | G59: 16 | H59: 42 | I59: 0.88 | J59: 19.5 | K59: 24.5 | L59: =INDEX('Read me'!$B$10:$B$15,2) -> 1.26 | M59: =IF(F59*(1+'Read me'!$B$5)<='Read me'!$B$7,CEILING(F59*(1+'Read me'!$B$5)+0.5,1)-0.5,CEILING(F59*(1+'Read me'!$B$5),5)) -> 45 | N59: =IF(MAX(M59*L59,M59+'Read me'!$B$6)<='Read me'!$B$7,CEILING(MAX(M59*L59,M59+'Read me'!$B$6)+0.5,1)-0.5,CEILING(MAX(M59*L59,M59+'Read me'!$B$6),5)) -> 60 | O59: =IF(ISNUMBER(J59),M59-J59,"new") -> 25.5
A60: ACT|NSW|Medium|Metro Outer | B60: ACT | C60: NSW | D60: Medium | E60: Metro Outer | F60: 46.33 | G60: 0 | H60: 42 | I60: 0.88 | J60: 19.5 | K60: 24.5 | L60: =INDEX('Read me'!$B$10:$B$15,2) -> 1.26 | M60: =IF(F60*(1+'Read me'!$B$5)<='Read me'!$B$7,CEILING(F60*(1+'Read me'!$B$5)+0.5,1)-0.5,CEILING(F60*(1+'Read me'!$B$5),5)) -> 50 | N60: =IF(MAX(M60*L60,M60+'Read me'!$B$6)<='Read me'!$B$7,CEILING(MAX(M60*L60,M60+'Read me'!$B$6)+0.5,1)-0.5,CEILING(MAX(M60*L60,M60+'Read me'!$B$6),5)) -> 65 | O60: =IF(ISNUMBER(J60),M60-J60,"new") -> 30.5
A61: ACT|NSW|Medium|Regional | B61: ACT | C61: NSW | D61: Medium | E61: Regional | F61: 54.09 | G61: 0 | H61: 42 | I61: 0.88 | J61: 19.5 | K61: 34.5 | L61: =INDEX('Read me'!$B$10:$B$15,2) -> 1.26 | M61: =IF(F61*(1+'Read me'!$B$5)<='Read me'!$B$7,CEILING(F61*(1+'Read me'!$B$5)+0.5,1)-0.5,CEILING(F61*(1+'Read me'!$B$5),5)) -> 55 | N61: =IF(MAX(M61*L61,M61+'Read me'!$B$6)<='Read me'!$B$7,CEILING(MAX(M61*L61,M61+'Read me'!$B$6)+0.5,1)-0.5,CEILING(MAX(M61*L61,M61+'Read me'!$B$6),5)) -> 70 | O61: =IF(ISNUMBER(J61),M61-J61,"new") -> 35.5
A62: ACT|NSW|Large|Metro | B62: ACT | C62: NSW | D62: Large | E62: Metro | F62: 75.16 | G62: 3 | H62: 42 | I62: 0.88 | J62: 24.5 | K62: 75 | L62: =INDEX('Read me'!$B$10:$B$15,3) -> 1.35 | M62: =IF(F62*(1+'Read me'!$B$5)<='Read me'!$B$7,CEILING(F62*(1+'Read me'!$B$5)+0.5,1)-0.5,CEILING(F62*(1+'Read me'!$B$5),5)) -> 80 | N62: =IF(MAX(M62*L62,M62+'Read me'!$B$6)<='Read me'!$B$7,CEILING(MAX(M62*L62,M62+'Read me'!$B$6)+0.5,1)-0.5,CEILING(MAX(M62*L62,M62+'Read me'!$B$6),5)) -> 110 | O62: =IF(ISNUMBER(J62),M62-J62,"new") -> 55.5
A63: ACT|NSW|Large|Metro Outer | B63: ACT | C63: NSW | D63: Large | E63: Metro Outer | F63: 82.14 | G63: 0 | H63: 42 | I63: 0.88 | J63: 24.5 | K63: 75 | L63: =INDEX('Read me'!$B$10:$B$15,3) -> 1.35 | M63: =IF(F63*(1+'Read me'!$B$5)<='Read me'!$B$7,CEILING(F63*(1+'Read me'!$B$5)+0.5,1)-0.5,CEILING(F63*(1+'Read me'!$B$5),5)) -> 85 | N63: =IF(MAX(M63*L63,M63+'Read me'!$B$6)<='Read me'!$B$7,CEILING(MAX(M63*L63,M63+'Read me'!$B$6)+0.5,1)-0.5,CEILING(MAX(M63*L63,M63+'Read me'!$B$6),5)) -> 115 | O63: =IF(ISNUMBER(J63),M63-J63,"new") -> 60.5
A64: ACT|NSW|Large|Regional | B64: ACT | C64: NSW | D64: Large | E64: Regional | F64: 110.46 | G64: 0 | H64: 42 | I64: 0.88 | J64: 85 | K64: 125 | L64: =INDEX('Read me'!$B$10:$B$15,3) -> 1.35 | M64: =IF(F64*(1+'Read me'!$B$5)<='Read me'!$B$7,CEILING(F64*(1+'Read me'!$B$5)+0.5,1)-0.5,CEILING(F64*(1+'Read me'!$B$5),5)) -> 115 | N64: =IF(MAX(M64*L64,M64+'Read me'!$B$6)<='Read me'!$B$7,CEILING(MAX(M64*L64,M64+'Read me'!$B$6)+0.5,1)-0.5,CEILING(MAX(M64*L64,M64+'Read me'!$B$6),5)) -> 160 | O64: =IF(ISNUMBER(J64),M64-J64,"new") -> 30
A65: ACT|NSW|XL|Metro | B65: ACT | C65: NSW | D65: XL | E65: Metro | F65: 129.74 | G65: 2 | H65: 42 | I65: 0.88 | J65: 85 | K65: 125 | L65: =INDEX('Read me'!$B$10:$B$15,4) -> 1.2 | M65: =IF(F65*(1+'Read me'!$B$5)<='Read me'!$B$7,CEILING(F65*(1+'Read me'!$B$5)+0.5,1)-0.5,CEILING(F65*(1+'Read me'!$B$5),5)) -> 130 | N65: =IF(MAX(M65*L65,M65+'Read me'!$B$6)<='Read me'!$B$7,CEILING(MAX(M65*L65,M65+'Read me'!$B$6)+0.5,1)-0.5,CEILING(MAX(M65*L65,M65+'Read me'!$B$6),5)) -> 160 | O65: =IF(ISNUMBER(J65),M65-J65,"new") -> 45
A66: ACT|NSW|XL|Metro Outer | B66: ACT | C66: NSW | D66: XL | E66: Metro Outer | F66: 151.8 | G66: 0 | H66: 42 | I66: 0.88 | J66: 125 | K66: 125 | L66: =INDEX('Read me'!$B$10:$B$15,4) -> 1.2 | M66: =IF(F66*(1+'Read me'!$B$5)<='Read me'!$B$7,CEILING(F66*(1+'Read me'!$B$5)+0.5,1)-0.5,CEILING(F66*(1+'Read me'!$B$5),5)) -> 155 | N66: =IF(MAX(M66*L66,M66+'Read me'!$B$6)<='Read me'!$B$7,CEILING(MAX(M66*L66,M66+'Read me'!$B$6)+0.5,1)-0.5,CEILING(MAX(M66*L66,M66+'Read me'!$B$6),5)) -> 190 | O66: =IF(ISNUMBER(J66),M66-J66,"new") -> 30
A67: ACT|NSW|XL|Regional | B67: ACT | C67: NSW | D67: XL | E67: Regional | F67: 182.94 | G67: 0 | H67: 42 | I67: 0.88 | J67: 199 | K67: 175 | L67: =INDEX('Read me'!$B$10:$B$15,4) -> 1.2 | M67: =IF(F67*(1+'Read me'!$B$5)<='Read me'!$B$7,CEILING(F67*(1+'Read me'!$B$5)+0.5,1)-0.5,CEILING(F67*(1+'Read me'!$B$5),5)) -> 185 | N67: =IF(MAX(M67*L67,M67+'Read me'!$B$6)<='Read me'!$B$7,CEILING(MAX(M67*L67,M67+'Read me'!$B$6)+0.5,1)-0.5,CEILING(MAX(M67*L67,M67+'Read me'!$B$6),5)) -> 225 | O67: =IF(ISNUMBER(J67),M67-J67,"new") -> -14
A68: ACT|NSW|XXL|Metro | B68: ACT | C68: NSW | D68: XXL | E68: Metro | F68: 163.03 | G68: 1 | H68: 42 | I68: 0.88 | J68: 250 | K68: 300 | L68: =INDEX('Read me'!$B$10:$B$15,5) -> 1.2 | M68: =IF(F68*(1+'Read me'!$B$5)<='Read me'!$B$7,CEILING(F68*(1+'Read me'!$B$5)+0.5,1)-0.5,CEILING(F68*(1+'Read me'!$B$5),5)) -> 165 | N68: =IF(MAX(M68*L68,M68+'Read me'!$B$6)<='Read me'!$B$7,CEILING(MAX(M68*L68,M68+'Read me'!$B$6)+0.5,1)-0.5,CEILING(MAX(M68*L68,M68+'Read me'!$B$6),5)) -> 200 | O68: =IF(ISNUMBER(J68),M68-J68,"new") -> -85
A69: ACT|NSW|XXL|Metro Outer | B69: ACT | C69: NSW | D69: XXL | E69: Metro Outer | F69: 197.98 | G69: 0 | H69: 42 | I69: 0.88 | J69: 250 | K69: 300 | L69: =INDEX('Read me'!$B$10:$B$15,5) -> 1.2 | M69: =N69 -> 240 | N69: =IF(MAX((IF(F69*(1+'Read me'!$B$5)<='Read me'!$B$7,CEILING(F69*(1+'Read me'!$B$5)+0.5,1)-0.5,CEILING(F69*(1+'Read me'!$B$5),5)))*L69,(IF(F69*(1+'Read me'!$B$5)<='Read me'!$B$7,CEILING(F69*(1+'Read me'!$B$5)+0.5,1)-0.5,CEILING(F69*(1+'Read me'!$B$5),5)))+'Read me'!$B$6)<='Read me'!$B$7,CEILING(MAX((IF(F69*(1+'Read me'!$B$5)<='Read me'!$B$7,CEILING(F69*(1+'Read me'!$B$5)+0.5,1)-0.5,CEILING(F69*(1+'Read me'!$B$5),5)))*L69,(IF(F69*(1+'Read me'!$B$5)<='Read me'!$B$7,CEILING(F69*(1+'Read me'!$B$5)+0.5,1)-0.5,CEILING(F69*(1+'Read me'!$B$5),5)))+'Read me'!$B$6)+0.5,1)-0.5,CEILING(MAX((IF(F69*(1+'Read me'!$B$5)<='Read me'!$B$7,CEILING(F69*(1+'Read me'!$B$5)+0.5,1)-0.5,CEILING(F69*(1+'Read me'!$B$5),5)))*L69,(IF(F69*(1+'Read me'!$B$5)<='Read me'!$B$7,CEILING(F69*(1+'Read me'!$B$5)+0.5,1)-0.5,CEILING(F69*(1+'Read me'!$B$5),5)))+'Read me'!$B$6),5)) -> 240 | O69: =IF(ISNUMBER(J69),M69-J69,"new") -> -10 | P69: One rate: interstate XXL/Bulky to Metro Outer or Regional is charged at the Priority price for both services
A70: ACT|NSW|XXL|Regional | B70: ACT | C70: NSW | D70: XXL | E70: Regional | F70: 237.88 | G70: 0 | H70: 42 | I70: 0.88 | J70: 300 | K70: 400 | L70: =INDEX('Read me'!$B$10:$B$15,5) -> 1.2 | M70: =N70 -> 290 | N70: =IF(MAX((IF(F70*(1+'Read me'!$B$5)<='Read me'!$B$7,CEILING(F70*(1+'Read me'!$B$5)+0.5,1)-0.5,CEILING(F70*(1+'Read me'!$B$5),5)))*L70,(IF(F70*(1+'Read me'!$B$5)<='Read me'!$B$7,CEILING(F70*(1+'Read me'!$B$5)+0.5,1)-0.5,CEILING(F70*(1+'Read me'!$B$5),5)))+'Read me'!$B$6)<='Read me'!$B$7,CEILING(MAX((IF(F70*(1+'Read me'!$B$5)<='Read me'!$B$7,CEILING(F70*(1+'Read me'!$B$5)+0.5,1)-0.5,CEILING(F70*(1+'Read me'!$B$5),5)))*L70,(IF(F70*(1+'Read me'!$B$5)<='Read me'!$B$7,CEILING(F70*(1+'Read me'!$B$5)+0.5,1)-0.5,CEILING(F70*(1+'Read me'!$B$5),5)))+'Read me'!$B$6)+0.5,1)-0.5,CEILING(MAX((IF(F70*(1+'Read me'!$B$5)<='Read me'!$B$7,CEILING(F70*(1+'Read me'!$B$5)+0.5,1)-0.5,CEILING(F70*(1+'Read me'!$B$5),5)))*L70,(IF(F70*(1+'Read me'!$B$5)<='Read me'!$B$7,CEILING(F70*(1+'Read me'!$B$5)+0.5,1)-0.5,CEILING(F70*(1+'Read me'!$B$5),5)))+'Read me'!$B$6),5)) -> 290 | O70: =IF(ISNUMBER(J70),M70-J70,"new") -> -10 | P70: One rate: interstate XXL/Bulky to Metro Outer or Regional is charged at the Priority price for both services
A71: ACT|NSW|Bulky|Metro | B71: ACT | C71: NSW | D71: Bulky | E71: Metro | F71: 222.83 | G71: 0 | H71: 42 | I71: 0.88 | L71: =INDEX('Read me'!$B$10:$B$15,6) -> 1.2 | M71: =IF(F71*(1+'Read me'!$B$5)<='Read me'!$B$7,CEILING(F71*(1+'Read me'!$B$5)+0.5,1)-0.5,CEILING(F71*(1+'Read me'!$B$5),5)) -> 225 | N71: =IF(MAX(M71*L71,M71+'Read me'!$B$6)<='Read me'!$B$7,CEILING(MAX(M71*L71,M71+'Read me'!$B$6)+0.5,1)-0.5,CEILING(MAX(M71*L71,M71+'Read me'!$B$6),5)) -> 270 | O71: =IF(ISNUMBER(J71),M71-J71,"new") -> new
A72: ACT|NSW|Bulky|Metro Outer | B72: ACT | C72: NSW | D72: Bulky | E72: Metro Outer | F72: 286.33 | G72: 0 | H72: 42 | I72: 0.88 | L72: =INDEX('Read me'!$B$10:$B$15,6) -> 1.2 | M72: =N72 -> 350 | N72: =IF(MAX((IF(F72*(1+'Read me'!$B$5)<='Read me'!$B$7,CEILING(F72*(1+'Read me'!$B$5)+0.5,1)-0.5,CEILING(F72*(1+'Read me'!$B$5),5)))*L72,(IF(F72*(1+'Read me'!$B$5)<='Read me'!$B$7,CEILING(F72*(1+'Read me'!$B$5)+0.5,1)-0.5,CEILING(F72*(1+'Read me'!$B$5),5)))+'Read me'!$B$6)<='Read me'!$B$7,CEILING(MAX((IF(F72*(1+'Read me'!$B$5)<='Read me'!$B$7,CEILING(F72*(1+'Read me'!$B$5)+0.5,1)-0.5,CEILING(F72*(1+'Read me'!$B$5),5)))*L72,(IF(F72*(1+'Read me'!$B$5)<='Read me'!$B$7,CEILING(F72*(1+'Read me'!$B$5)+0.5,1)-0.5,CEILING(F72*(1+'Read me'!$B$5),5)))+'Read me'!$B$6)+0.5,1)-0.5,CEILING(MAX((IF(F72*(1+'Read me'!$B$5)<='Read me'!$B$7,CEILING(F72*(1+'Read me'!$B$5)+0.5,1)-0.5,CEILING(F72*(1+'Read me'!$B$5),5)))*L72,(IF(F72*(1+'Read me'!$B$5)<='Read me'!$B$7,CEILING(F72*(1+'Read me'!$B$5)+0.5,1)-0.5,CEILING(F72*(1+'Read me'!$B$5),5)))+'Read me'!$B$6),5)) -> 350 | O72: =IF(ISNUMBER(J72),M72-J72,"new") -> new | P72: One rate: interstate XXL/Bulky to Metro Outer or Regional is charged at the Priority price for both services
A73: ACT|NSW|Bulky|Regional | B73: ACT | C73: NSW | D73: Bulky | E73: Regional | F73: 336.54 | G73: 0 | H73: 42 | I73: 0.88 | L73: =INDEX('Read me'!$B$10:$B$15,6) -> 1.2 | M73: =N73 -> 410 | N73: =IF(MAX((IF(F73*(1+'Read me'!$B$5)<='Read me'!$B$7,CEILING(F73*(1+'Read me'!$B$5)+0.5,1)-0.5,CEILING(F73*(1+'Read me'!$B$5),5)))*L73,(IF(F73*(1+'Read me'!$B$5)<='Read me'!$B$7,CEILING(F73*(1+'Read me'!$B$5)+0.5,1)-0.5,CEILING(F73*(1+'Read me'!$B$5),5)))+'Read me'!$B$6)<='Read me'!$B$7,CEILING(MAX((IF(F73*(1+'Read me'!$B$5)<='Read me'!$B$7,CEILING(F73*(1+'Read me'!$B$5)+0.5,1)-0.5,CEILING(F73*(1+'Read me'!$B$5),5)))*L73,(IF(F73*(1+'Read me'!$B$5)<='Read me'!$B$7,CEILING(F73*(1+'Read me'!$B$5)+0.5,1)-0.5,CEILING(F73*(1+'Read me'!$B$5),5)))+'Read me'!$B$6)+0.5,1)-0.5,CEILING(MAX((IF(F73*(1+'Read me'!$B$5)<='Read me'!$B$7,CEILING(F73*(1+'Read me'!$B$5)+0.5,1)-0.5,CEILING(F73*(1+'Read me'!$B$5),5)))*L73,(IF(F73*(1+'Read me'!$B$5)<='Read me'!$B$7,CEILING(F73*(1+'Read me'!$B$5)+0.5,1)-0.5,CEILING(F73*(1+'Read me'!$B$5),5)))+'Read me'!$B$6),5)) -> 410 | O73: =IF(ISNUMBER(J73),M73-J73,"new") -> new | P73: One rate: interstate XXL/Bulky to Metro Outer or Regional is charged at the Priority price for both services
A74: ACT|ACT|Small|Metro | B74: ACT | C74: ACT | D74: Small | E74: Metro | F74: 20.61 | G74: 22 | H74: 38 | I74: 2.3 | J74: 9.5 | K74: 14.5 | L74: =INDEX('Read me'!$B$10:$B$15,1) -> 1.34 | M74: =IF(F74*(1+'Read me'!$B$5)<='Read me'!$B$7,CEILING(F74*(1+'Read me'!$B$5)+0.5,1)-0.5,CEILING(F74*(1+'Read me'!$B$5),5)) -> 21.5 | N74: =IF(MAX(M74*L74,M74+'Read me'!$B$6)<='Read me'!$B$7,CEILING(MAX(M74*L74,M74+'Read me'!$B$6)+0.5,1)-0.5,CEILING(MAX(M74*L74,M74+'Read me'!$B$6),5)) -> 29.5 | O74: =IF(ISNUMBER(J74),M74-J74,"new") -> 12
A75: ACT|ACT|Small|Metro Outer | B75: ACT | C75: ACT | D75: Small | E75: Metro Outer | F75: 30.3 | G75: 0 | H75: 38 | I75: 2.3 | J75: 12.5 | K75: 17.5 | L75: =INDEX('Read me'!$B$10:$B$15,1) -> 1.34 | M75: =IF(F75*(1+'Read me'!$B$5)<='Read me'!$B$7,CEILING(F75*(1+'Read me'!$B$5)+0.5,1)-0.5,CEILING(F75*(1+'Read me'!$B$5),5)) -> 35 | N75: =IF(MAX(M75*L75,M75+'Read me'!$B$6)<='Read me'!$B$7,CEILING(MAX(M75*L75,M75+'Read me'!$B$6)+0.5,1)-0.5,CEILING(MAX(M75*L75,M75+'Read me'!$B$6),5)) -> 50 | O75: =IF(ISNUMBER(J75),M75-J75,"new") -> 22.5
A76: ACT|ACT|Small|Regional | B76: ACT | C76: ACT | D76: Small | E76: Regional | F76: 39.86 | G76: 0 | H76: 38 | I76: 2.3 | J76: 17.5 | K76: 24.5 | L76: =INDEX('Read me'!$B$10:$B$15,1) -> 1.34 | M76: =IF(F76*(1+'Read me'!$B$5)<='Read me'!$B$7,CEILING(F76*(1+'Read me'!$B$5)+0.5,1)-0.5,CEILING(F76*(1+'Read me'!$B$5),5)) -> 40 | N76: =IF(MAX(M76*L76,M76+'Read me'!$B$6)<='Read me'!$B$7,CEILING(MAX(M76*L76,M76+'Read me'!$B$6)+0.5,1)-0.5,CEILING(MAX(M76*L76,M76+'Read me'!$B$6),5)) -> 55 | O76: =IF(ISNUMBER(J76),M76-J76,"new") -> 22.5
A77: ACT|ACT|Medium|Metro | B77: ACT | C77: ACT | D77: Medium | E77: Metro | F77: 48.08 | G77: 12 | H77: 38 | I77: 2.3 | J77: 9.5 | K77: 19.5 | L77: =INDEX('Read me'!$B$10:$B$15,2) -> 1.26 | M77: =IF(F77*(1+'Read me'!$B$5)<='Read me'!$B$7,CEILING(F77*(1+'Read me'!$B$5)+0.5,1)-0.5,CEILING(F77*(1+'Read me'!$B$5),5)) -> 50 | N77: =IF(MAX(M77*L77,M77+'Read me'!$B$6)<='Read me'!$B$7,CEILING(MAX(M77*L77,M77+'Read me'!$B$6)+0.5,1)-0.5,CEILING(MAX(M77*L77,M77+'Read me'!$B$6),5)) -> 65 | O77: =IF(ISNUMBER(J77),M77-J77,"new") -> 40.5
A78: ACT|ACT|Medium|Metro Outer | B78: ACT | C78: ACT | D78: Medium | E78: Metro Outer | F78: 99.91 | G78: 0 | H78: 38 | I78: 2.3 | J78: 12.5 | K78: 19.5 | L78: =INDEX('Read me'!$B$10:$B$15,2) -> 1.26 | M78: =IF(F78*(1+'Read me'!$B$5)<='Read me'!$B$7,CEILING(F78*(1+'Read me'!$B$5)+0.5,1)-0.5,CEILING(F78*(1+'Read me'!$B$5),5)) -> 100 | N78: =IF(MAX(M78*L78,M78+'Read me'!$B$6)<='Read me'!$B$7,CEILING(MAX(M78*L78,M78+'Read me'!$B$6)+0.5,1)-0.5,CEILING(MAX(M78*L78,M78+'Read me'!$B$6),5)) -> 130 | O78: =IF(ISNUMBER(J78),M78-J78,"new") -> 87.5
A79: ACT|ACT|Medium|Regional | B79: ACT | C79: ACT | D79: Medium | E79: Regional | F79: 111.38 | G79: 0 | H79: 38 | I79: 2.3 | J79: 19.5 | K79: 29.5 | L79: =INDEX('Read me'!$B$10:$B$15,2) -> 1.26 | M79: =IF(F79*(1+'Read me'!$B$5)<='Read me'!$B$7,CEILING(F79*(1+'Read me'!$B$5)+0.5,1)-0.5,CEILING(F79*(1+'Read me'!$B$5),5)) -> 115 | N79: =IF(MAX(M79*L79,M79+'Read me'!$B$6)<='Read me'!$B$7,CEILING(MAX(M79*L79,M79+'Read me'!$B$6)+0.5,1)-0.5,CEILING(MAX(M79*L79,M79+'Read me'!$B$6),5)) -> 145 | O79: =IF(ISNUMBER(J79),M79-J79,"new") -> 95.5
A80: ACT|ACT|Large|Metro | B80: ACT | C80: ACT | D80: Large | E80: Metro | F80: 114.01 | G80: 2 | H80: 38 | I80: 2.3 | J80: 19 | K80: 45 | L80: =INDEX('Read me'!$B$10:$B$15,3) -> 1.35 | M80: =IF(F80*(1+'Read me'!$B$5)<='Read me'!$B$7,CEILING(F80*(1+'Read me'!$B$5)+0.5,1)-0.5,CEILING(F80*(1+'Read me'!$B$5),5)) -> 115 | N80: =IF(MAX(M80*L80,M80+'Read me'!$B$6)<='Read me'!$B$7,CEILING(MAX(M80*L80,M80+'Read me'!$B$6)+0.5,1)-0.5,CEILING(MAX(M80*L80,M80+'Read me'!$B$6),5)) -> 160 | O80: =IF(ISNUMBER(J80),M80-J80,"new") -> 96
A81: ACT|ACT|Large|Metro Outer | B81: ACT | C81: ACT | D81: Large | E81: Metro Outer | F81: 179.74 | G81: 0 | H81: 38 | I81: 2.3 | J81: 24.5 | K81: 45 | L81: =INDEX('Read me'!$B$10:$B$15,3) -> 1.35 | M81: =IF(F81*(1+'Read me'!$B$5)<='Read me'!$B$7,CEILING(F81*(1+'Read me'!$B$5)+0.5,1)-0.5,CEILING(F81*(1+'Read me'!$B$5),5)) -> 180 | N81: =IF(MAX(M81*L81,M81+'Read me'!$B$6)<='Read me'!$B$7,CEILING(MAX(M81*L81,M81+'Read me'!$B$6)+0.5,1)-0.5,CEILING(MAX(M81*L81,M81+'Read me'!$B$6),5)) -> 245 | O81: =IF(ISNUMBER(J81),M81-J81,"new") -> 155.5
A82: ACT|ACT|Large|Regional | B82: ACT | C82: ACT | D82: Large | E82: Regional | F82: 220.97 | G82: 0 | H82: 38 | I82: 2.3 | J82: 50 | K82: 95 | L82: =INDEX('Read me'!$B$10:$B$15,3) -> 1.35 | M82: =IF(F82*(1+'Read me'!$B$5)<='Read me'!$B$7,CEILING(F82*(1+'Read me'!$B$5)+0.5,1)-0.5,CEILING(F82*(1+'Read me'!$B$5),5)) -> 225 | N82: =IF(MAX(M82*L82,M82+'Read me'!$B$6)<='Read me'!$B$7,CEILING(MAX(M82*L82,M82+'Read me'!$B$6)+0.5,1)-0.5,CEILING(MAX(M82*L82,M82+'Read me'!$B$6),5)) -> 305 | O82: =IF(ISNUMBER(J82),M82-J82,"new") -> 175
A83: ACT|ACT|XL|Metro | B83: ACT | C83: ACT | D83: XL | E83: Metro | F83: 206.16 | G83: 2 | H83: 38 | I83: 2.3 | J83: 25 | K83: 85 | L83: =INDEX('Read me'!$B$10:$B$15,4) -> 1.2 | M83: =IF(F83*(1+'Read me'!$B$5)<='Read me'!$B$7,CEILING(F83*(1+'Read me'!$B$5)+0.5,1)-0.5,CEILING(F83*(1+'Read me'!$B$5),5)) -> 210 | N83: =IF(MAX(M83*L83,M83+'Read me'!$B$6)<='Read me'!$B$7,CEILING(MAX(M83*L83,M83+'Read me'!$B$6)+0.5,1)-0.5,CEILING(MAX(M83*L83,M83+'Read me'!$B$6),5)) -> 255 | O83: =IF(ISNUMBER(J83),M83-J83,"new") -> 185
A84: ACT|ACT|XL|Metro Outer | B84: ACT | C84: ACT | D84: XL | E84: Metro Outer | F84: 293.71 | G84: 0 | H84: 38 | I84: 2.3 | J84: 45 | K84: 125 | L84: =INDEX('Read me'!$B$10:$B$15,4) -> 1.2 | M84: =IF(F84*(1+'Read me'!$B$5)<='Read me'!$B$7,CEILING(F84*(1+'Read me'!$B$5)+0.5,1)-0.5,CEILING(F84*(1+'Read me'!$B$5),5)) -> 295 | N84: =IF(MAX(M84*L84,M84+'Read me'!$B$6)<='Read me'!$B$7,CEILING(MAX(M84*L84,M84+'Read me'!$B$6)+0.5,1)-0.5,CEILING(MAX(M84*L84,M84+'Read me'!$B$6),5)) -> 355 | O84: =IF(ISNUMBER(J84),M84-J84,"new") -> 250
A85: ACT|ACT|XL|Regional | B85: ACT | C85: ACT | D85: XL | E85: Regional | F85: 441.44 | G85: 0 | H85: 38 | I85: 2.3 | J85: 85 | K85: 150 | L85: =INDEX('Read me'!$B$10:$B$15,4) -> 1.2 | M85: =IF(F85*(1+'Read me'!$B$5)<='Read me'!$B$7,CEILING(F85*(1+'Read me'!$B$5)+0.5,1)-0.5,CEILING(F85*(1+'Read me'!$B$5),5)) -> 445 | N85: =IF(MAX(M85*L85,M85+'Read me'!$B$6)<='Read me'!$B$7,CEILING(MAX(M85*L85,M85+'Read me'!$B$6)+0.5,1)-0.5,CEILING(MAX(M85*L85,M85+'Read me'!$B$6),5)) -> 535 | O85: =IF(ISNUMBER(J85),M85-J85,"new") -> 360
A86: ACT|ACT|XXL|Metro | B86: ACT | C86: ACT | D86: XXL | E86: Metro | F86: 263.33 | G86: 0 | H86: 38 | I86: 2.3 | J86: 45 | K86: 85 | L86: =INDEX('Read me'!$B$10:$B$15,5) -> 1.2 | M86: =IF(F86*(1+'Read me'!$B$5)<='Read me'!$B$7,CEILING(F86*(1+'Read me'!$B$5)+0.5,1)-0.5,CEILING(F86*(1+'Read me'!$B$5),5)) -> 265 | N86: =IF(MAX(M86*L86,M86+'Read me'!$B$6)<='Read me'!$B$7,CEILING(MAX(M86*L86,M86+'Read me'!$B$6)+0.5,1)-0.5,CEILING(MAX(M86*L86,M86+'Read me'!$B$6),5)) -> 320 | O86: =IF(ISNUMBER(J86),M86-J86,"new") -> 220
A87: ACT|ACT|XXL|Metro Outer | B87: ACT | C87: ACT | D87: XXL | E87: Metro Outer | F87: 379.67 | G87: 0 | H87: 38 | I87: 2.3 | J87: 85 | K87: 125 | L87: =INDEX('Read me'!$B$10:$B$15,5) -> 1.2 | M87: =IF(F87*(1+'Read me'!$B$5)<='Read me'!$B$7,CEILING(F87*(1+'Read me'!$B$5)+0.5,1)-0.5,CEILING(F87*(1+'Read me'!$B$5),5)) -> 380 | N87: =IF(MAX(M87*L87,M87+'Read me'!$B$6)<='Read me'!$B$7,CEILING(MAX(M87*L87,M87+'Read me'!$B$6)+0.5,1)-0.5,CEILING(MAX(M87*L87,M87+'Read me'!$B$6),5)) -> 460 | O87: =IF(ISNUMBER(J87),M87-J87,"new") -> 295
A88: ACT|ACT|XXL|Regional | B88: ACT | C88: ACT | D88: XXL | E88: Regional | F88: 562.64 | G88: 0 | H88: 38 | I88: 2.3 | J88: 250 | K88: 350 | L88: =INDEX('Read me'!$B$10:$B$15,5) -> 1.2 | M88: =IF(F88*(1+'Read me'!$B$5)<='Read me'!$B$7,CEILING(F88*(1+'Read me'!$B$5)+0.5,1)-0.5,CEILING(F88*(1+'Read me'!$B$5),5)) -> 565 | N88: =IF(MAX(M88*L88,M88+'Read me'!$B$6)<='Read me'!$B$7,CEILING(MAX(M88*L88,M88+'Read me'!$B$6)+0.5,1)-0.5,CEILING(MAX(M88*L88,M88+'Read me'!$B$6),5)) -> 680 | O88: =IF(ISNUMBER(J88),M88-J88,"new") -> 315
A89: ACT|ACT|Bulky|Metro | B89: ACT | C89: ACT | D89: Bulky | E89: Metro | F89: 287.18 | G89: 0 | H89: 38 | I89: 2.3 | L89: =INDEX('Read me'!$B$10:$B$15,6) -> 1.2 | M89: =IF(F89*(1+'Read me'!$B$5)<='Read me'!$B$7,CEILING(F89*(1+'Read me'!$B$5)+0.5,1)-0.5,CEILING(F89*(1+'Read me'!$B$5),5)) -> 290 | N89: =IF(MAX(M89*L89,M89+'Read me'!$B$6)<='Read me'!$B$7,CEILING(MAX(M89*L89,M89+'Read me'!$B$6)+0.5,1)-0.5,CEILING(MAX(M89*L89,M89+'Read me'!$B$6),5)) -> 350 | O89: =IF(ISNUMBER(J89),M89-J89,"new") -> new
A90: ACT|ACT|Bulky|Metro Outer | B90: ACT | C90: ACT | D90: Bulky | E90: Metro Outer | F90: 517.22 | G90: 0 | H90: 38 | I90: 2.3 | L90: =INDEX('Read me'!$B$10:$B$15,6) -> 1.2 | M90: =IF(F90*(1+'Read me'!$B$5)<='Read me'!$B$7,CEILING(F90*(1+'Read me'!$B$5)+0.5,1)-0.5,CEILING(F90*(1+'Read me'!$B$5),5)) -> 520 | N90: =IF(MAX(M90*L90,M90+'Read me'!$B$6)<='Read me'!$B$7,CEILING(MAX(M90*L90,M90+'Read me'!$B$6)+0.5,1)-0.5,CEILING(MAX(M90*L90,M90+'Read me'!$B$6),5)) -> 625 | O90: =IF(ISNUMBER(J90),M90-J90,"new") -> new
A91: ACT|ACT|Bulky|Regional | B91: ACT | C91: ACT | D91: Bulky | E91: Regional | F91: 677.72 | G91: 0 | H91: 38 | I91: 2.3 | L91: =INDEX('Read me'!$B$10:$B$15,6) -> 1.2 | M91: =IF(F91*(1+'Read me'!$B$5)<='Read me'!$B$7,CEILING(F91*(1+'Read me'!$B$5)+0.5,1)-0.5,CEILING(F91*(1+'Read me'!$B$5),5)) -> 680 | N91: =IF(MAX(M91*L91,M91+'Read me'!$B$6)<='Read me'!$B$7,CEILING(MAX(M91*L91,M91+'Read me'!$B$6)+0.5,1)-0.5,CEILING(MAX(M91*L91,M91+'Read me'!$B$6),5)) -> 820 | O91: =IF(ISNUMBER(J91),M91-J91,"new") -> new
A92: ACT|TAS|Small|Metro | B92: ACT | C92: TAS | D92: Small | E92: Metro | F92: 13.16 | G92: 2 | H92: 2 | I92: 0.98 | J92: 19.5 | K92: 24.5 | L92: =INDEX('Read me'!$B$10:$B$15,1) -> 1.34 | M92: =IF(F92*(1+'Read me'!$B$5)<='Read me'!$B$7,CEILING(F92*(1+'Read me'!$B$5)+0.5,1)-0.5,CEILING(F92*(1+'Read me'!$B$5),5)) -> 13.5 | N92: =IF(MAX(M92*L92,M92+'Read me'!$B$6)<='Read me'!$B$7,CEILING(MAX(M92*L92,M92+'Read me'!$B$6)+0.5,1)-0.5,CEILING(MAX(M92*L92,M92+'Read me'!$B$6),5)) -> 18.5 | O92: =IF(ISNUMBER(J92),M92-J92,"new") -> -6
A93: ACT|TAS|Small|Metro Outer | B93: ACT | C93: TAS | D93: Small | E93: Metro Outer | F93: 14.85 | G93: 0 | H93: 2 | I93: 0.98 | J93: 19.5 | K93: 24.5 | L93: =INDEX('Read me'!$B$10:$B$15,1) -> 1.34 | M93: =IF(F93*(1+'Read me'!$B$5)<='Read me'!$B$7,CEILING(F93*(1+'Read me'!$B$5)+0.5,1)-0.5,CEILING(F93*(1+'Read me'!$B$5),5)) -> 15.5 | N93: =IF(MAX(M93*L93,M93+'Read me'!$B$6)<='Read me'!$B$7,CEILING(MAX(M93*L93,M93+'Read me'!$B$6)+0.5,1)-0.5,CEILING(MAX(M93*L93,M93+'Read me'!$B$6),5)) -> 21.5 | O93: =IF(ISNUMBER(J93),M93-J93,"new") -> -4
A94: ACT|TAS|Small|Regional | B94: ACT | C94: TAS | D94: Small | E94: Regional | F94: 19.59 | G94: 0 | H94: 2 | I94: 0.98 | J94: 19.5 | K94: 34.5 | L94: =INDEX('Read me'!$B$10:$B$15,1) -> 1.34 | M94: =IF(F94*(1+'Read me'!$B$5)<='Read me'!$B$7,CEILING(F94*(1+'Read me'!$B$5)+0.5,1)-0.5,CEILING(F94*(1+'Read me'!$B$5),5)) -> 20.5 | N94: =IF(MAX(M94*L94,M94+'Read me'!$B$6)<='Read me'!$B$7,CEILING(MAX(M94*L94,M94+'Read me'!$B$6)+0.5,1)-0.5,CEILING(MAX(M94*L94,M94+'Read me'!$B$6),5)) -> 27.5 | O94: =IF(ISNUMBER(J94),M94-J94,"new") -> 1
A95: ACT|TAS|Medium|Metro | B95: ACT | C95: TAS | D95: Medium | E95: Metro | F95: 46.88 | G95: 0 | H95: 2 | I95: 0.98 | J95: 24.5 | K95: 29.5 | L95: =INDEX('Read me'!$B$10:$B$15,2) -> 1.26 | M95: =IF(F95*(1+'Read me'!$B$5)<='Read me'!$B$7,CEILING(F95*(1+'Read me'!$B$5)+0.5,1)-0.5,CEILING(F95*(1+'Read me'!$B$5),5)) -> 50 | N95: =IF(MAX(M95*L95,M95+'Read me'!$B$6)<='Read me'!$B$7,CEILING(MAX(M95*L95,M95+'Read me'!$B$6)+0.5,1)-0.5,CEILING(MAX(M95*L95,M95+'Read me'!$B$6),5)) -> 65 | O95: =IF(ISNUMBER(J95),M95-J95,"new") -> 25.5
A96: ACT|TAS|Medium|Metro Outer | B96: ACT | C96: TAS | D96: Medium | E96: Metro Outer | F96: 51.2 | G96: 0 | H96: 2 | I96: 0.98 | J96: 24.5 | K96: 29.5 | L96: =INDEX('Read me'!$B$10:$B$15,2) -> 1.26 | M96: =IF(F96*(1+'Read me'!$B$5)<='Read me'!$B$7,CEILING(F96*(1+'Read me'!$B$5)+0.5,1)-0.5,CEILING(F96*(1+'Read me'!$B$5),5)) -> 55 | N96: =IF(MAX(M96*L96,M96+'Read me'!$B$6)<='Read me'!$B$7,CEILING(MAX(M96*L96,M96+'Read me'!$B$6)+0.5,1)-0.5,CEILING(MAX(M96*L96,M96+'Read me'!$B$6),5)) -> 70 | O96: =IF(ISNUMBER(J96),M96-J96,"new") -> 30.5
A97: ACT|TAS|Medium|Regional | B97: ACT | C97: TAS | D97: Medium | E97: Regional | F97: 59.78 | G97: 0 | H97: 2 | I97: 0.98 | J97: 24.5 | K97: 45 | L97: =INDEX('Read me'!$B$10:$B$15,2) -> 1.26 | M97: =IF(F97*(1+'Read me'!$B$5)<='Read me'!$B$7,CEILING(F97*(1+'Read me'!$B$5)+0.5,1)-0.5,CEILING(F97*(1+'Read me'!$B$5),5)) -> 60 | N97: =IF(MAX(M97*L97,M97+'Read me'!$B$6)<='Read me'!$B$7,CEILING(MAX(M97*L97,M97+'Read me'!$B$6)+0.5,1)-0.5,CEILING(MAX(M97*L97,M97+'Read me'!$B$6),5)) -> 80 | O97: =IF(ISNUMBER(J97),M97-J97,"new") -> 35.5
A98: ACT|TAS|Large|Metro | B98: ACT | C98: TAS | D98: Large | E98: Metro | F98: 80.69 | G98: 0 | H98: 2 | I98: 0.98 | J98: 45 | K98: 95 | L98: =INDEX('Read me'!$B$10:$B$15,3) -> 1.35 | M98: =IF(F98*(1+'Read me'!$B$5)<='Read me'!$B$7,CEILING(F98*(1+'Read me'!$B$5)+0.5,1)-0.5,CEILING(F98*(1+'Read me'!$B$5),5)) -> 85 | N98: =IF(MAX(M98*L98,M98+'Read me'!$B$6)<='Read me'!$B$7,CEILING(MAX(M98*L98,M98+'Read me'!$B$6)+0.5,1)-0.5,CEILING(MAX(M98*L98,M98+'Read me'!$B$6),5)) -> 115 | O98: =IF(ISNUMBER(J98),M98-J98,"new") -> 40
A99: ACT|TAS|Large|Metro Outer | B99: ACT | C99: TAS | D99: Large | E99: Metro Outer | F99: 90.77 | G99: 0 | H99: 2 | I99: 0.98 | J99: 45 | K99: 95 | L99: =INDEX('Read me'!$B$10:$B$15,3) -> 1.35 | M99: =IF(F99*(1+'Read me'!$B$5)<='Read me'!$B$7,CEILING(F99*(1+'Read me'!$B$5)+0.5,1)-0.5,CEILING(F99*(1+'Read me'!$B$5),5)) -> 95 | N99: =IF(MAX(M99*L99,M99+'Read me'!$B$6)<='Read me'!$B$7,CEILING(MAX(M99*L99,M99+'Read me'!$B$6)+0.5,1)-0.5,CEILING(MAX(M99*L99,M99+'Read me'!$B$6),5)) -> 130 | O99: =IF(ISNUMBER(J99),M99-J99,"new") -> 50
A100: ACT|TAS|Large|Regional | B100: ACT | C100: TAS | D100: Large | E100: Regional | F100: 122.08 | G100: 0 | H100: 2 | I100: 0.98 | J100: 99 | K100: 150 | L100: =INDEX('Read me'!$B$10:$B$15,3) -> 1.35 | M100: =IF(F100*(1+'Read me'!$B$5)<='Read me'!$B$7,CEILING(F100*(1+'Read me'!$B$5)+0.5,1)-0.5,CEILING(F100*(1+'Read me'!$B$5),5)) -> 125 | N100: =IF(MAX(M100*L100,M100+'Read me'!$B$6)<='Read me'!$B$7,CEILING(MAX(M100*L100,M100+'Read me'!$B$6)+0.5,1)-0.5,CEILING(MAX(M100*L100,M100+'Read me'!$B$6),5)) -> 170 | O100: =IF(ISNUMBER(J100),M100-J100,"new") -> 26
...

Sheet Impact
A1: Delivering to | B1: Ships from | C1: Zone | D1: Size | E1: Service charged | F1: Same state | G1: We charged | H1: Cost us | I1: 2025 sheet price | J1: New price | K1: New − cost | L1: Charged − cost
A2: VIC | B2: VIC | C2: Metro | D2: Medium | E2: Standard | F2: Yes | G2: 14.5 | H2: 58.86 | I2: 9.5 | J2: =IF(E2="Priority",'Cost model'!N761,'Cost model'!M761) -> 35 | K2: =J2-H2 -> -23.86 | L2: =G2-H2 -> -44.36
A3: QLD | B3: QLD | C3: Metro Outer | D3: Small | E3: Priority | F3: Yes | G3: 17.5 | H3: 20.83 | I3: 17.5 | J3: =IF(E3="Priority",'Cost model'!N381,'Cost model'!M381) -> 19.5 | K3: =J3-H3 -> -1.33 | L3: =G3-H3 -> -3.33
A4: QLD | B4: QLD | C4: Metro Outer | D4: Small | E4: Standard | F4: Yes | G4: 12.5 | H4: 7.72 | I4: 12.5 | J4: =IF(E4="Priority",'Cost model'!N381,'Cost model'!M381) -> 14.5 | K4: =J4-H4 -> 6.78 | L4: =G4-H4 -> 4.78
A5: TAS | B5: TAS | C5: Metro Outer | D5: Small | E5: Standard | F5: Yes | G5: 14.5 | H5: 24.61 | I5: 12.5 | J5: =IF(E5="Priority",'Cost model'!N633,'Cost model'!M633) -> 13.5 | K5: =J5-H5 -> -11.11 | L5: =G5-H5 -> -10.11
A6: VIC | B6: QLD | C6: Metro | D6: Small | E6: Standard | F6: No | G6: 14.5 | H6: 9.64 | I6: 14.5 | J6: =IF(E6="Priority",'Cost model'!N794,'Cost model'!M794) -> 12.5 | K6: =J6-H6 -> 2.86 | L6: =G6-H6 -> 4.86
A7: TAS | B7: TAS | C7: Metro Outer | D7: Medium | E7: Standard | F7: Yes | G7: 12.5 | H7: 83.06 | I7: 12.5 | J7: =IF(E7="Priority",'Cost model'!N636,'Cost model'!M636) -> 55 | K7: =J7-H7 -> -28.06 | L7: =G7-H7 -> -70.56
A8: NSW | B8: NSW | C8: Metro Outer | D8: Small | E8: Standard | F8: Yes | G8: 12.5 | H8: 16.01 | J8: =IF(E8="Priority",'Cost model'!N201,'Cost model'!M201) -> 12.5 | K8: =J8-H8 -> -3.51 | L8: =G8-H8 -> -3.51
A9: NSW | B9: VIC | C9: Metro | D9: Medium | E9: Standard | F9: No | G9: 9.5 | H9: 48.16 | I9: 9.5 | J9: =IF(E9="Priority",'Cost model'!N149,'Cost model'!M149) -> 45 | K9: =J9-H9 -> -3.16 | L9: =G9-H9 -> -38.66
A10: ACT | B10: NSW | C10: Metro | D10: Small | E10: Standard | F10: No | G10: 14.5 | H10: 12.27 | I10: 14.5 | J10: =IF(E10="Priority",'Cost model'!N56,'Cost model'!M56) -> 11.5 | K10: =J10-H10 -> -0.77 | L10: =G10-H10 -> 2.23
A11: NSW | B11: NSW | C11: Metro | D11: Medium | E11: Standard | F11: Yes | G11: 9.5 | H11: 27.76 | I11: 9.5 | J11: =IF(E11="Priority",'Cost model'!N203,'Cost model'!M203) -> 26.5 | K11: =J11-H11 -> -1.26 | L11: =G11-H11 -> -18.26
A12: QLD | B12: QLD | C12: Regional | D12: Medium | E12: Standard | F12: Yes | G12: 19.5 | H12: 59.1 | I12: 19.5 | J12: =IF(E12="Priority",'Cost model'!N385,'Cost model'!M385) -> 55 | K12: =J12-H12 -> -4.1 | L12: =G12-H12 -> -39.6
A13: QLD | B13: QLD | C13: Metro Outer | D13: Medium | E13: Priority | F13: Yes | G13: 19.5 | H13: 62.85 | I13: 19.5 | J13: =IF(E13="Priority",'Cost model'!N384,'Cost model'!M384) -> 60 | K13: =J13-H13 -> -2.85 | L13: =G13-H13 -> -43.35
A14: WA | B14: WA | C14: Metro | D14: Small | E14: Standard | F14: Yes | G14: 9.5 | H14: 8.13 | I14: 9.5 | J14: =IF(E14="Priority",'Cost model'!N884,'Cost model'!M884) -> 7.5 | K14: =J14-H14 -> -0.63 | L14: =G14-H14 -> 1.37
A15: NSW | B15: NSW | C15: Metro | D15: Medium | E15: Standard | F15: Yes | G15: 9.5 | H15: 27.4 | I15: 9.5 | J15: =IF(E15="Priority",'Cost model'!N203,'Cost model'!M203) -> 26.5 | K15: =J15-H15 -> -0.9 | L15: =G15-H15 -> -17.9
A16: WA | B16: WA | C16: Regional | D16: Small | E16: Standard | F16: Yes | G16: 17.5 | H16: 11.58 | I16: 17.5 | J16: =IF(E16="Priority",'Cost model'!N886,'Cost model'!M886) -> 17.5 | K16: =J16-H16 -> 5.92 | L16: =G16-H16 -> 5.92
A17: QLD | B17: QLD | C17: Metro | D17: Medium | E17: Standard | F17: Yes | G17: 24.5 | H17: 41.77 | I17: 9.5 | J17: =IF(E17="Priority",'Cost model'!N383,'Cost model'!M383) -> 27.5 | K17: =J17-H17 -> -14.27 | L17: =G17-H17 -> -17.27
A18: WA | B18: SA | C18: Regional | D18: Medium | E18: Priority | F18: No | G18: 34.5 | H18: 72.82 | I18: 34.5 | J18: =IF(E18="Priority",'Cost model'!N907,'Cost model'!M907) -> 90 | K18: =J18-H18 -> 17.18 | L18: =G18-H18 -> -38.32
A19: VIC | B19: VIC | C19: Metro | D19: Medium | E19: Standard | F19: Yes | G19: 9.5 | H19: 27.7 | I19: 9.5 | J19: =IF(E19="Priority",'Cost model'!N761,'Cost model'!M761) -> 35 | K19: =J19-H19 -> 7.3 | L19: =G19-H19 -> -18.2
A20: ACT | B20: ACT | C20: Metro | D20: Medium | E20: Standard | F20: Yes | G20: 29.5 | H20: 42.23 | I20: 9.5 | J20: =IF(E20="Priority",'Cost model'!N77,'Cost model'!M77) -> 50 | K20: =J20-H20 -> 7.77 | L20: =G20-H20 -> -12.73
A21: NT | B21: ACT | C21: Metro | D21: Small | E21: Priority | F21: No | G21: 24.5 | H21: 51.6 | I21: 24.5 | J21: =IF(E21="Priority",'Cost model'!N362,'Cost model'!M362) -> 29.5 | K21: =J21-H21 -> -22.1 | L21: =G21-H21 -> -27.1
A22: VIC | B22: VIC | C22: Regional | D22: Medium | E22: Standard | F22: Yes | G22: 19.5 | H22: 60.83 | I22: 19.5 | J22: =IF(E22="Priority",'Cost model'!N763,'Cost model'!M763) -> 50 | K22: =J22-H22 -> -10.83 | L22: =G22-H22 -> -41.33
A23: VIC | B23: VIC | C23: Regional | D23: Small | E23: Standard | F23: Yes | G23: 17.5 | H23: 14.32 | I23: 17.5 | J23: =IF(E23="Priority",'Cost model'!N760,'Cost model'!M760) -> 18.5 | K23: =J23-H23 -> 4.18 | L23: =G23-H23 -> 3.18
A24: TAS | B24: VIC | C24: Metro Outer | D24: XL | E24: Standard | F24: No | G24: 125 | H24: 139.41 | I24: 125 | J24: =IF(E24="Priority",'Cost model'!N660,'Cost model'!M660) -> 210 | K24: =J24-H24 -> 70.59 | L24: =G24-H24 -> -14.41
A25: NSW | B25: NSW | C25: Metro | D25: Small | E25: Standard | F25: Yes | G25: 9.5 | H25: 6.11 | I25: 9.5 | J25: =IF(E25="Priority",'Cost model'!N200,'Cost model'!M200) -> 7.5 | K25: =J25-H25 -> 1.39 | L25: =G25-H25 -> 3.39
A26: QLD | B26: QLD | C26: Metro | D26: Small | E26: Standard | F26: Yes | G26: 9.5 | H26: 6.12 | I26: 9.5 | J26: =IF(E26="Priority",'Cost model'!N380,'Cost model'!M380) -> 8.5 | K26: =J26-H26 -> 2.38 | L26: =G26-H26 -> 3.38
A27: WA | B27: WA | C27: Regional | D27: Small | E27: Priority | F27: Yes | G27: 24.5 | H27: 16.16 | I27: 24.5 | J27: =IF(E27="Priority",'Cost model'!N886,'Cost model'!M886) -> 23.5 | K27: =J27-H27 -> 7.34 | L27: =G27-H27 -> 8.34
A28: SA | B28: QLD | C28: Metro | D28: Small | E28: Standard | F28: No | G28: 9.5 | H28: 12.57 | I28: 14.5 | J28: =IF(E28="Priority",'Cost model'!N542,'Cost model'!M542) -> 14.5 | K28: =J28-H28 -> 1.93 | L28: =G28-H28 -> -3.07
A29: NSW | B29: QLD | C29: Regional | D29: Large | E29: Standard | F29: No | G29: 50 | H29: 182.57 | I29: 50 | J29: =IF(E29="Priority",'Cost model'!N136,'Cost model'!M136) -> 105 | K29: =J29-H29 -> -77.57 | L29: =G29-H29 -> -132.57
